Workbook
Name features: '[1]BASE GHI TP'!$B$1:$BS$1
Name GPA_features: '[1]GPA DB'!$G$3:$P$3
Name GPA_Insurers: '[1]GPA DB'!$A$4:$A$12
Name GPA_number_of_lives_expiring: '[1]High Level Quotes - Working'!$T$22
Name GPA_opt1_number_of_employees_expiring: '[1]High Level Quotes - Working'!$T$22
Name GPA_opt1_number_of_employees_renewal: '[1]High Level Quotes - Working'!$R$22
Name GPA_opt2_number_of_employees_renewal: '[1]High Level Quotes - Working'!$R$24
Name GTLI_Features: '[2]GTLI DB'!$E$7:$K$7
Name GTLI_number_of_employees_expiring: '[1]High Level Quotes - Working'!$T$32
Name GTLI_opt1_number_of_employees_renewal: '[1]High Level Quotes - Working'!$R$32
Name GTLI_opt2_number_of_employees_renewal: '[1]High Level Quotes - Working'!$R$34
Name number_of_employees_expiring: '[1]High Level Quotes - Slide 1'!$U$6
Name number_of_lives_expiring: '[1]High Level Quotes - Slide 1'!$V$6
Name opt1_number_of_employees_renewal: '[1]High Level Quotes - Slide 1'!$R$6
Name opt1_number_of_lives_renewal: '[1]High Level Quotes - Slide 1'!$S$6
Name opt2_number_of_lives_renewal: '[1]High Level Quotes - Slide 1'!$S$7
Name opt3_number_of_lives_renewal: '[1]High Level Quotes - Slide 1'!$S$8
Name opt4_number_of_lives_renewal: '[1]High Level Quotes - Slide 1'!$S$9
Name opt5_number_of_lives_renewal: '[1]High Level Quotes - Slide 1'!$S$10
Name policy_features_custom: 'GHI Policy Features'!$C$17:$C$62

Sheet Final Sheet
A2: Organization Name | B2: Neotel | C2: =IF(B2="","Please fill Organization Name","Good to proceed") -> Good to proceed | E2: Employees | F2: 21 | G2: =IF(F2="","",IF(F2>100,"Rater cannot be used for more than 100 employees",IF(F2<7,"Rater cannot be used for less than 7 employees",IF(AND(F2>=7,F2<=10),"PED and SD waiting period will apply","Good to proceed")))) -> Good to proceed
A4: GST Number | C4: =IF(B4="","Please fill GST Number","Good to proceed") -> Please fill GST Number | E4: Spouse | F4: 15
A6: Location | B6: Bengaluru | C6: =IF(B6="","",VLOOKUP(B6,'Drop Down Options'!A:B,2,0)) -> Zone B | E6: Child | F6: 17
A8: Industry | B8: Agricultural commodity trading | C8: =IF(B8="","",VLOOKUP(B8,'Drop Down Options'!D2:E56,2,0)) -> Good to proceed | E8: Total Lives | F8: =SUM(F2:F6) -> 53
A10: Policy Type | B10: Fresh | E10: Sum Insured | F10: 3 Lac
A12: PY Insurer | C12: =IF(B12="","",IF(B12="Bajaj General Insurance","Rater cannot be used for Bajaj Renewals","Good to Proceed")) | E12: Family Definition | F12: ESC
A14: PY Broker | E14: Policy Start Date DD-MM-YYYY | F14: 46172 | G14: =IF(F14="","",IF(F14<'Age Band Raters'!O7,"Policy start date cannot be in the past","Good to proceed")) -> Good to proceed
A16: Broker Name | E16: Room Rent | F16: =IF(F10="","",IF(F10="5 Lac",'Drop Down Options'!O3,'Drop Down Options'!O2)) -> Normal - 2% of SI (Max 7.5K), ICU - No Limit
A18: Expiring Earned Premium | E18: Maternity | F18: Normal - 50K, C Section - 50K | G18: =IF(OR(F18="",F18="No"),"",IF(F2<10,"Maternity cannot be provided. Minimum 11 employees required","Good to proceed")) -> Good to proceed
A20: Claims (Settled + OS) | E20: Brokerage | F20: 0.25 | G20: Default brokerage is 15%
A22: Loss Ratio (LR) | B22: =IF(OR(B18="",B20=""),"",B20/B18) | C22: =IF(B22="","",IF(B22>=75%,"Rater cannot be used for policies with LR more than 75%","Good to proceed"))
A25: Age Band | B25: Upto 20 Yrs | C25: 21-25 | D25: 26-30 | E25: 31-35 | F25: 36-40 | G25: 41-45 | H25: 46-50 | I25: 51-55 | J25: 56-60 | K25: 61-65 | L25: TOTAL LIVES
A26: 1 Lac | L26: =SUM(B26:K26) -> 0 | M26: =IF(L26=0,"",IF(L26<>$F$8,"Number of lives is different",""))
A27: 2 Lacs | L27: =SUM(B27:K27) -> 0 | M27: =IF(L27=0,"",IF(L27<>$F$8,"Number of lives is different",""))
A28: 3 Lacs | B28: 17 | C28: 0 | D28: 10 | E28: 4 | F28: 10 | G28: 5 | H28: 3 | I28: 4 | L28: =SUM(B28:K28) -> 53 | M28: =IF(L28=0,"",IF(L28<>$F$8,"Number of lives is different",""))
A29: 5 Lacs | L29: =SUM(B29:K29) -> 0 | M29: =IF(L29=0,"",IF(L29<>$F$8,"Number of lives is different",""))
A31: Zone Discount/Loading | B31: =IF(C6="Zone A",0%,IF(C6="Zone B",-16.52%,"")) -> -0.1652
A32: Brokerage Discount/Loading | B32: =IF(F20=7.5%,"-10%",IF(F20=10%,"-7%",IF(F20=15%,"0%",IF(F20=20%,"+6.25%",IF(F20=25%,"+13.33%",""))))) -> +13.33% | E32: Final Premium | F32: =IF(AND($C$6="Zone A",$F$20=7.5%),($B$33+($B$33*(-0.1))),IF(AND($C$6="Zone A",$F$20=10%),($B$33+($B$33*(-0.07))),IF(AND($C$6="Zone A",$F$20=15%),($B$33+($B$33*(0))),IF(AND($C$6="Zone A",$F$20=20%),($B$33+($B$33*(0.0625))),IF(AND($C$6="Zone A",$F$20=25%),($B$33+($B$33*(0.1333))),IF(AND($C$6="Zone B",$F$20=7.5%),($B$33+($B$33*(-0.2652))),IF(AND($C$6="Zone B",$F$20=10%),($B$33+($B$33*(-0.2352))),IF(AND($C$6="Zone B",$F$20=15%),($B$33+($B$33*(-0.1652))),IF(AND($C$6="Zone B",$F$20=20%),($B$33+($B$33*(-0.1027))),IF(AND($C$6="Zone B",$F$20=25%),($B$33+($B$33*(-0.0319))),"")))))))))) -> 217338.45
A33: Pre-Discount Premium | B33: =IF(AND('Final Sheet'!$F$12=Calculations!A2,'Final Sheet'!$F$18=Calculations!B2,'Final Sheet'!$F$10=Calculations!D2,'Final Sheet'!$F$2<10),Calculations!E2,IF(AND('Final Sheet'!$F$12=Calculations!A3,'Final Sheet'!$F$18=Calculations!B3,'Final Sheet'!$F$10=Calculations!D3,'Final Sheet'!$F$2>=10),Calculations!E3,IF(AND('Final Sheet'!$F$12=Calculations!A4,'Final Sheet'!$F$18=Calculations!B4,'Final Sheet'!$F$10=Calculations!D4,'Final Sheet'!$F$2>=10),Calculations!E4,IF(AND('Final Sheet'!$F$12=Calculations!A5,'Final Sheet'!$F$18=Calculations!B5,'Final Sheet'!$F$10=Calculations!D5,'Final Sheet'!$F$2>=10),Calculations!E5,IF(AND('Final Sheet'!$F$12=Calculations!A6,'Final Sheet'!$F$18=Calculations!B6,'Final Sheet'!$F$10=Calculations!D6,'Final Sheet'!$F$2>=10),Calculations!E6,IF(AND('Final Sheet'!$F$12=Calculations!A7,'Final Sheet'!$F$18=Calculations!B7,'Final Sheet'!$F$10=Calculations!D7,'Final Sheet'!$F$2<10),Calculations!E7,IF(AND('Final Sheet'!$F$12=Calculations!A8,'Final Sheet'!$F$18=Calculations!B8,'Final Sheet'!$F$10=Calculations!D8,'Final Sheet'!$F$2>=10),Calculations!E8,IF(AND('Final Sheet'!$F$12=Calculations!A9,'Final Sheet'!$F$18=Calculations!B9,'Final Sheet'!$F$10=Calculations!D9,'Final Sheet'!$F$2>=10),Calculations!E10,IF(AND('Final Sheet'!$F$12=Calculations!A11,'Final Sheet'!$F$18=Calculations!B11,'Final Sheet'!$F$10=Calculations!D11,'Final Sheet'!$F$2>=10),Calculations!E11,IF(AND('Final Sheet'!$F$12=Calculations!A12,'Final Sheet'!$F$18=Calculations!B12,'Final Sheet'!$F$10=Calculations!D12,'Final Sheet'!$F$2<10),Calculations!E12,IF(AND('Final Sheet'!$F$12=Calculations!A13,'Final Sheet'!$F$18=Calculations!B13,'Final Sheet'!$F$10=Calculations!D13,'Final Sheet'!$F$2>=10),Calculations!E13,IF(AND('Final Sheet'!$F$12=Calculations!A14,'Final Sheet'!$F$18=Calculations!B14,'Final Sheet'!$F$10=Calculations!D14,'Final Sheet'!$F$2>=10),Calculations!E14,IF(AND('Final Sheet'!$F$12=Calculations!A15,'Final Sheet'!$F$18=Calculations!B15,'Final Sheet'!$F$10=Calculations!D15,'Final Sheet'!$F$2>=10),Calculations!E15,IF(AND('Final Sheet'!$F$12=Calculations!A16,'Final Sheet'!$F$18=Calculations!B16,'Final Sheet'!$F$10=Calculations!D16,'Final Sheet'!$F$2>=10),Calculations!E16,IF(AND('Final Sheet'!$F$12=Calculations!A17,'Final Sheet'!$F$18=Calculations!B17,'Final Sheet'!$F$10=Calculations!D17,'Final Sheet'!$F$2<10),Calculations!E17,IF(AND('Final Sheet'!$F$12=Calculations!A18,'Final Sheet'!$F$18=Calculations!B18,'Final Sheet'!$F$10=Calculations!D18,'Final Sheet'!$F$2>=10),Calculations!E18,IF(AND('Final Sheet'!$F$12=Calculations!A19,'Final Sheet'!$F$18=Calculations!B19,'Final Sheet'!$F$10=Calculations!D19,'Final Sheet'!$F$2>=10),Calculations!E19,IF(AND('Final Sheet'!$F$12=Calculations!A20,'Final Sheet'!$F$18=Calculations!B20,'Final Sheet'!$F$10=Calculations!D20,'Final Sheet'!$F$2>=10),Calculations!E20,IF(AND('Final Sheet'!$F$12=Calculations!A21,'Final Sheet'!$F$18=Calculations!B21,'Final Sheet'!$F$10=Calculations!D21,'Final Sheet'!$F$2>=10),Calculations!E21,IF(AND('Final Sheet'!$F$12=Calculations!A22,'Final Sheet'!$F$18=Calculations!B22,'Final Sheet'!$F$10=Calculations!D22,'Final Sheet'!$F$2<10),Calculations!E22,IF(AND('Final Sheet'!$F$12=Calculations!A23,'Final Sheet'!$F$18=Calculations!B23,'Final Sheet'!$F$10=Calculations!D23,'Final Sheet'!$F$2>=10),Calculations!E23,IF(AND('Final Sheet'!$F$12=Calculations!A24,'Final Sheet'!$F$18=Calculations!B24,'Final Sheet'!$F$10=Calculations!D24,'Final Sheet'!$F$2>=10),Calculations!E24,IF(AND('Final Sheet'!$F$12=Calculations!A25,'Final Sheet'!$F$18=Calculations!B25,'Final Sheet'!$F$10=Calculations!D25,'Final Sheet'!$F$2>=10),Calculations!E25,IF(AND('Final Sheet'!$F$12=Calculations!A26,'Final Sheet'!$F$18=Calculations!B26,'Final Sheet'!$F$10=Calculations!D26,'Final Sheet'!$F$2>=10),Calculations!E26,IF(AND('Final Sheet'!$F$12=Calculations!A27,'Final Sheet'!$F$18=Calculations!B27,'Final Sheet'!$F$10=Calculations!D27,'Final Sheet'!$F$2<10),Calculations!E27,IF(AND('Final Sheet'!$F$12=Calculations!A28,'Final Sheet'!$F$18=Calculations!B28,'Final Sheet'!$F$10=Calculations!D28,'Final Sheet'!$F$2>=10),Calculations!E28,IF(AND('Final Sheet'!$F$12=Calculations!A29,'Final Sheet'!$F$18=Calculations!B29,'Final Sheet'!$F$10=Calculations!D29,'Final Sheet'!$F$2>=10),Calculations!E29,IF(AND('Final Sheet'!$F$12=Calculations!A30,'Final Sheet'!$F$18=Calculations!B30,'Final Sheet'!$F$10=Calculations!D30,'Final Sheet'!$F$2>=10),Calculations!E30,IF(AND('Final Sheet'!$F$12=Calculations!A31,'Final Sheet'!$F$18=Calculations!B31,'Final Sheet'!$F$10=Calculations!D31,'Final Sheet'!$F$2>=10),Calculations!E31,IF(AND('Final Sheet'!$F$12=Calculations!A32,'Final Sheet'!$F$18=Calculations!B32,'Final Sheet'!$F$10=Calculations!D32,'Final Sheet'!$F$2<10),Calculations!E32,IF(AND('Final Sheet'!$F$12=Calculations!A33,'Final Sheet'!$F$18=Calculations!B33,'Final Sheet'!$F$10=Calculations!D33,'Final Sheet'!$F$2>=10),Calculations!E33,IF(AND('Final Sheet'!$F$12=Calculations!A34,'Final Sheet'!$F$18=Calculations!B34,'Final Sheet'!$F$10=Calculations!D34,'Final Sheet'!$F$2>=10),Calculations!E34,IF(AND('Final Sheet'!$F$12=Calculations!A35,'Final Sheet'!$F$18=Calculations!B35,'Final Sheet'!$F$10=Calculations!D35,'Final Sheet'!$F$2>=10),Calculations!E35,IF(AND('Final Sheet'!$F$12=Calculations!A36,'Final Sheet'!$F$18=Calculations!B36,'Final Sheet'!$F$10=Calculations!D36,'Final Sheet'!$F$2>=10),Calculations!E36,IF(AND('Final Sheet'!$F$12=Calculations!A37,'Final Sheet'!$F$18=Calculations!B37,'Final Sheet'!$F$10=Calculations!D37,'Final Sheet'!$F$2<10),Calculations!E37,IF(AND('Final Sheet'!$F$12=Calculations!A38,'Final Sheet'!$F$18=Calculations!B38,'Final Sheet'!$F$10=Calculations!D38,'Final Sheet'!$F$2>=10),Calculations!E38,IF(AND('Final Sheet'!$F$12=Calculations!A39,'Final Sheet'!$F$18=Calculations!B39,'Final Sheet'!$F$10=Calculations!D39,'Final Sheet'!$F$2>=10),Calculations!E39,IF(AND('Final Sheet'!$F$12=Calculations!A40,'Final Sheet'!$F$18=Calculations!B40,'Final Sheet'!$F$10=Calculations!D40,'Final Sheet'!$F$2>=10),Calculations!E40,IF(AND('Final Sheet'!$F$12=Calculations!A41,'Final Sheet'!$F$18=Calculations!B41,'Final Sheet'!$F$10=Calculations!D41,'Final Sheet'!$F$2>=10),Calculations!E41,""))))))))))))))))))))))))))))))))))))))) -> 224500

Sheet GHI Policy Features
A1: Loco
A2: 45289 | C2: Group Health Insurance
C3: Client Name | G3: ='Final Sheet'!B2 -> Neotel
C4: Type of Policy | G4: Group Health Insurance
C5: Policy Period
C6: Sum Insured | G6: ='Final Sheet'!F10 -> 3 Lac
G8: PROPOSED INSURERS
G9: Bajaj General | H9: ICICI Lombard | I9: Bajaj General | J9: ICICI Lombard
C10: Premium Details
C11: Sum Insured | E11: In INR | G11: ='Final Sheet'!F10 -> 3 Lac | H11: 5 Lac | I11: 3 lac | J11: 3 lac
C12: Net Premium | E12: In INR | G12: ='Final Sheet'!F32 -> 217338.45 | H12: 130000 | I12: 80000 | J12: 100000
C13: Total Number Of Lives | G13: ='Final Sheet'!F8 -> 53 | H13: 17 | I13: 17 | J13: 17
C14: Premium Per Life | E14: In INR | G14: =G12/G13 -> 4100.7255 | H14: =H12/H13 -> 7647.0588 | I14: =I12/I13 -> 4705.8824 | J14: =J12/J13 -> 5882.3529
C15: Policy Features - Group Health Insurance
G16: Go Digit | H16: Care Health | I16: Aditya Birla Health | J16: Care Health
B17: Members Covered | C17: Family Definition | D17: FamilyDefinition | E17: Self | G17: =IF('Final Sheet'!F12<>"","✔","") -> ✔ | H17: ✔ | I17: ✔ | J17: ✔
D18: FamilyDefinition | E18: Spouse | G18: =IF('Final Sheet'!F12="ESC","✔","✖") -> ✔ | H18: ✖ | I18: ✖ | J18: ✖
D19: FamilyDefinition | E19: Children - upto 25 yrs of age | G19: =IF('Final Sheet'!F12="ESC","✔","✖") -> ✔ | H19: ✖ | I19: ✖ | J19: ✖
D20: FamilyDefinition | E20: 2 Parents/PIL - upto 80 yrs of age | G20: ✖ | H20: ✖ | I20: ✖ | J20: ✖
B22: Policy Type | C22: Type of Cover | D22: TypeofCover | E22: Family Floater | G22: ✔ | H22: ✔ | I22: ✔ | J22: ✔
C23: Room Rent Restriction | D23: RoomRentRestriction | E23: =IF('Final Sheet'!F10="5 Lac","Normal - No Limit, ICU - No Limit","Normal - 2% of SI (Max 7.5K), ICU - No Limit") -> Normal - 2% of SI (Max 7.5K), ICU - No Limit | G23: ✔ | H23: ✔ | I23: Normal : 2% max Rs.7.5k and ICU - No Limit | J23: ✔
C24: Co Pay | D24: CoPay | E24: No Co Pay | G24: ✔ | H24: ✔ | I24: ✔ | J24: ✔
C25: Corporate Buffer | D25: CorporateBuffer | E25: Not Covered | G25: Not Covered | H25: Not Covered | I25: Not Covered | J25: Not Covered
B27: Hospitalization Coverage | C27: Inpatient Hospitalization | D27: InpatientHospitalization | E27: Hospitalization > 24 hours | G27: ✔ | H27: ✔ | I27: ✔ | J27: ✔
C28: Day Care Treatments | D28: DayCareTreatments | E28: Hospitalization < 24 hours | G28: All procedures | H28: All procedures | I28: All procedures | J28: All procedures
C29: Disease Capping | D29: DiseaseCapping | E29: No disease capping | G29: ✔ | H29: ✔ | I29: ✔ | J29: ✔
C30: COVID 19 Coverage | D30: COVID19Coverage | E30: Hospitalization > 24 hours | G30: ✔ | H30: ✔ | I30: ✔ | J30: ✔
C31: Domicillary Hospitalization | D31: DomicillaryHospitalization | E31: Home hospitalization > 3 days + Patient unable to move OR hospital bed not available | G31: ✔ | H31: ✔ | I31: ✔ | J31: ✔
B33: Pre and Post Hospitalization Coverage (medicines, lab tests and consultations for IPD treatments) | C33: Pre and Post Hospitalization Coverage | D33: PreandPostHospitalizationCoverage | E33: Covered | G33: 60/90 days | H33: 60/90 days | I33: 60/90 days | J33: 60/90 days
B35: Maternity Coverage | C35: Maternity Cover | D35: MaternityCover | E35: ='Final Sheet'!F18 -> Normal - 50K, C Section - 50K | G35: ✔ | H35: ✔ | I35: ✔ | J35: ✔
C36: Maternity Waiting Period | D36: MaternityWaitingPeriod | E36: Waived Off | G36: ✔ | H36: ✔ | I36: ✔ | J36: ✔
C37: Pre and Post Natal Expenses | D37: PreandPostNatalExpenses | E37: Upto Maternity Limit | G37: ✔ | H37: ✔ | I37: ✔ | J37: ✔
B39: Waiting Period Benefits | C39: Initial Waiting Period | D39: InitialWaitingPeriod | E39: =IF(AND('Final Sheet'!F2>=7,'Final Sheet'!F2<=10),"Waiting period is applicable","Waived off") -> Waived off | G39: ✔ | H39: ✔ | I39: ✔ | J39: ✔
C40: Specific Diseases Waiting Period | D40: SpecificDiseasesWaitingPeriod | E40: =IF(AND('Final Sheet'!F2>=7,'Final Sheet'!F2<=10),"Waiting period is applicable","Waived off") -> Waived off | G40: ✔ | H40: ✔ | I40: ✔ | J40: ✔
C41: PreExisting Diseases Waiting Period | D41: PreExistingDiseasesWaitingPeriod | E41: =IF(AND('Final Sheet'!F2>=7,'Final Sheet'!F2<=10),"Waiting period is applicable","Waived off") -> Waived off | G41: ✔ | H41: ✔ | I41: ✔ | J41: ✔
B43: Hospital Transportation Benefits | C43: Emergency Ambulance | D43: EmergencyAmbulance | E43: Coverage per event | G43: Rs. 2.5k | H43: Rs. 2.5k | I43: Rs. 2.5k | J43: Rs. 2.5k
C44: Emergency Air Ambulance | D44: EmergencyAirAmbulance | E44: Coverage per event | G44: ✖ | H44: ✖ | I44: ✖ | J44: ✖
B46: Other Benefits | C46: Modern Treatments and Robotic Surgeries | D46: ModernTreatmentsandRoboticSurgeries | E46: As per Regulatory Guidelines | G46: Upto 50% Co-Pay | H46: Upto 50% Co-Pay | I46: Upto 50% Co-Pay | J46: Upto 50% Co-Pay
C47: Psychiatric Illness | D47: PsychiatricIllness | E47: Hospitalization > 24 hours | G47: Upto Rs.50K | H47: Upto Rs.50K | I47: Upto Rs.50K | J47: Upto Rs.50K
C48: AYUSH Treatments | D48: AYUSHTreatments | E48: Hospitallization > 24 hours in Govt Approved Hospitals | G48: ✔ | H48: ✔ | I48: ✔ | J48: ✔
C49: Organ Donor Expenses | D49: OrganDonorExpenses | E49: Covered upto 100% of SI | G49: ✔ | H49: ✖ | I49: ✔ | J49: ✖
C50: Lasik Eye Surgery | D50: LasikEyeSurgery | E50: Eye power correction | G50: If eye power +/- 6.5 | H50: If eye power +/- 6.5 | I50: If eye power +/- 6.5 | J50: If eye power +/- 6.5
C51: Terrorism | D51: Terrorism | E51: Terrorism | G51: ✔ | H51: ✔ | I51: ✔ | J51: ✔
B53: Mid-Term Policy Changes | C53: Additions and Deletions | D53: AdditionsandDeletions | E53: On pro-rata basis | G53: ✔
C54: Mid term Increase in Sum Insured | D54: MidtermIncreaseinSumInsured | E54: Only for employee promotion | G54: ✖
C55: Mid term Addition of Dependents | D55: MidtermAdditionofDependents | E55: Day 1 coverage of new borns and spouses of newly weds | G55: =IF('Final Sheet'!F12="ESC","✔","✖") -> ✔
C56: Mid term addition of parents | D56: Midtermadditionofparents | E56: Only for new joinees | G56: ✖
B58: The Healthysure Advantage | C58: Upgrade Option | D58: UpgradeOption | E58: Flexi Top-up Insurance of Rs 30 Lacs with continuity option | G58: ✔
C59: Doctor Teleconsultations | D59: DoctorTeleconsultations | E59: Unlimited with General Physicians | G59: ✔
C60: Health Checkups | D60: HealthCheckups | E60: Full body checkup upto 70% off | G60: ✔
C61: Gym Memberships | E61: Gym Membership Discount upto 50% | G61: ✔
C62: Medicines Delivery | D62: MedicinesDelivery | E62: Prescribed medicines upto 20% off | G62: ✔
E145: STELLAPPS
E146: Vhire4u

Sheet Calculations
A1: Family definition | B1: Maternity | C1: Employees | D1: Sum Insured | E1: Premium | K1: Zone | L1: Disc/Load | M1: Brokerage | N1: Disc/Load | O1: TOTAL Disc/Load
A2: E Only | B2: No | C2: <10 | D2: 1 Lac | E2: =IF(AND('Final Sheet'!$F$12=Calculations!A2,'Final Sheet'!$F$18=Calculations!B2,'Final Sheet'!$F$10=Calculations!D2,'Final Sheet'!$F$2<10),(B44*B52)+(C44*B53)+(D44*B54)+(E44*B55)+(F44*B56)+(G44*B57)+(H44*B58)+(I44*B59)+(J44*B60)+(K44*B61),0) -> 0 | K2: A | L2: 0 | M2: 0.075 | N2: -0.1 | O2: -0.1 | P2: =O2 -> -0.1
A3: E Only | B3: No | C3: >=10 | D3: 1 Lac | E3: =IF(AND('Final Sheet'!$F$12=Calculations!A3,'Final Sheet'!$F$18=Calculations!B3,'Final Sheet'!$F$10=Calculations!D3,'Final Sheet'!$F$2>=10),(B44*H52)+(C44*H53)+(D44*H54)+(E44*H55)+(F44*H56)+(G44*H57)+(H44*H58)+(I44*H59)+(J44*H60)+(K44*H61),0) -> 0 | K3: A | L3: 0 | M3: 0.1 | N3: -0.07 | O3: -0.07 | P3: =O3 -> -0.07
A4: E Only | B4: Normal - 30K, C Section - 30K | C4: >=10 | D4: 1 Lac | E4: =IF(AND('Final Sheet'!$F$12=Calculations!A4,'Final Sheet'!$F$18='Drop Down Options'!Q3,'Final Sheet'!$F$10=Calculations!D4,'Final Sheet'!$F$2>=10),(B44*H79)+(C44*H80)+(D44*H81)+(E44*H82)+(F44*H83)+(G44*H84)+(H44*H85)+(I44*H86)+(J44*H87)+(K44*H88),0) -> 0 | K4: A | L4: 0 | M4: 0.15 | N4: 0 | O4: 0 | P4: =O4 -> 0
A5: E Only | B5: Normal - 50K, C Section - 50K | C5: >=10 | D5: 1 Lac | E5: =IF(AND('Final Sheet'!$F$12=Calculations!A5,'Final Sheet'!$F$18='Drop Down Options'!Q4,'Final Sheet'!$F$10=Calculations!D5,'Final Sheet'!$F$2>=10),(B44*H106)+(C44*H107)+(D44*H108)+(E44*H109)+(F44*H110)+(G44*H111)+(H44*H112)+(I44*H113)+(J44*H114)+(K44*H115),0) -> 0 | K5: A | L5: 0 | M5: 0.2 | N5: 0.0625 | O5: 0.0625 | P5: =O5 -> 0.0625
A6: E Only | B6: Normal - 75K, C Section - 75K | C6: >=10 | D6: 1 Lac | E6: =IF(AND('Final Sheet'!$F$12=Calculations!A6,'Final Sheet'!$F$18='Drop Down Options'!Q5,'Final Sheet'!$F$10=Calculations!D6,'Final Sheet'!$F$2>=10),(B44*H133)+(C44*H134)+(D44*H135)+(E44*H136)+(F44*H137)+(G44*H138)+(H44*H139)+(I44*H140)+(J44*H141)+(K44*H142),0) -> 0 | K6: A | L6: 0 | M6: 0.25 | N6: 0.1333 | O6: 0.1333 | P6: =O6 -> 0.1333
A7: ESC | B7: No | C7: <10 | D7: 1 Lac | E7: =IF(AND('Final Sheet'!$F$12=Calculations!A7,'Final Sheet'!$F$18=Calculations!B7,'Final Sheet'!$F$10=Calculations!D7,'Final Sheet'!$F$2<10),(B44*B65)+(C44*B66)+(D44*B67)+(E44*B68)+(F44*B69)+(G44*B70)+(H44*B71)+(I44*B72)+(J44*B73)+(K44*B74),0) -> 0 | K7: B/C/D | L7: -0.1652 | M7: 0.075 | N7: -0.1 | O7: -0.2652 | P7: =O7 -> -0.2652
A8: ESC | B8: No | C8: >=10 | D8: 1 Lac | E8: =IF(AND('Final Sheet'!$F$12=Calculations!A8,'Final Sheet'!$F$18=Calculations!B8,'Final Sheet'!$F$10=Calculations!D8,'Final Sheet'!$F$2>=10),(B44*H65)+(C44*H66)+(D44*H67)+(E44*H68)+(F44*H69)+(G44*H70)+(H44*H71)+(I44*H72)+(J44*H73)+(K44*H74),0) -> 0 | K8: B/C/D | L8: -0.1652 | M8: 0.1 | N8: -0.07 | O8: =N8+L8 -> -0.2352 | P8: =O8 -> -0.2352
A9: ESC | B9: Normal - 30K, C Section - 30K | C9: >=10 | D9: 1 Lac | E9: =IF(AND('Final Sheet'!$F$12=Calculations!A9,'Final Sheet'!$F$18='Drop Down Options'!Q3,'Final Sheet'!$F$10=Calculations!D9,'Final Sheet'!$F$2>=10),(B44*H92)+(C44*H93)+(D44*H94)+(E44*H95)+(F44*H96)+(G44*H97)+(H44*H98)+(I44*H99)+(J44*H100)+(K44*H101),0) -> 0 | K9: B/C/D | L9: -0.1652 | M9: 0.15 | N9: 0 | O9: =N9+L9 -> -0.1652 | P9: =O9 -> -0.1652
A10: ESC | B10: Normal - 50K, C Section - 50K | C10: >=10 | D10: 1 Lac | E10: =IF(AND('Final Sheet'!$F$12=Calculations!A10,'Final Sheet'!$F$18='Drop Down Options'!Q4,'Final Sheet'!$F$10=Calculations!D10,'Final Sheet'!$F$2>=10),(B44*H119)+(C44*H120)+(D44*H121)+(E44*H122)+(F44*H123)+(G44*H124)+(H44*H125)+(I44*H126)+(J44*H127)+(K44*H128),0) -> 0 | K10: B/C/D | L10: -0.1652 | M10: 0.2 | N10: 0.0625 | O10: =N10+L10 -> -0.1027 | P10: =O10 -> -0.1027
A11: ESC | B11: Normal - 75K, C Section - 75K | C11: >=10 | D11: 1 Lac | E11: =IF(AND('Final Sheet'!$F$12=Calculations!A11,'Final Sheet'!$F$18='Drop Down Options'!Q5,'Final Sheet'!$F$10=Calculations!D11,'Final Sheet'!$F$2>=10),(B44*H146)+(C44*H147)+(D44*H148)+(E44*H149)+(F44*H150)+(G44*H151)+(H44*H152)+(I44*H153)+(J44*H154)+(K44*H155),0) -> 0 | K11: B/C/D | L11: -0.1652 | M11: 0.25 | N11: 0.1333 | O11: =N11+L11 -> -0.0319 | P11: =O11 -> -0.0319
A12: E Only | B12: No | C12: <10 | D12: 2 Lac | E12: =IF(AND('Final Sheet'!$F$12=Calculations!A12,'Final Sheet'!$F$18=Calculations!B12,'Final Sheet'!$F$10=Calculations!D12,'Final Sheet'!$F$2<10),(B45*C52)+(C45*C53)+(D45*C54)+(E45*C55)+(F45*C56)+(G45*C57)+(H45*C58)+(I45*C59)+(J45*C60)+(K45*C61),0) -> 0
A13: E Only | B13: No | C13: >=10 | D13: 2 Lac | E13: =IF(AND('Final Sheet'!$F$12=Calculations!A13,'Final Sheet'!$F$18=Calculations!B13,'Final Sheet'!$F$10=Calculations!D13,'Final Sheet'!$F$2>=10),(B45*I52)+(C45*I53)+(D45*I54)+(E45*I55)+(F45*I56)+(G45*I57)+(H45*I58)+(I45*I59)+(J45*I60)+(K45*I61),0) -> 0
A14: E Only | B14: Normal - 30K, C Section - 30K | C14: >=10 | D14: 2 Lac | E14: =IF(AND('Final Sheet'!$F$12=Calculations!A14,'Final Sheet'!$F$18='Drop Down Options'!Q3,'Final Sheet'!$F$10=Calculations!D14,'Final Sheet'!$F$2>=10),(B45*I79)+(C45*I80)+(D45*I81)+(E45*I82)+(F45*I83)+(G45*I84)+(H45*I85)+(I45*I86)+(J45*I87)+(K45*I88),0) -> 0
A15: E Only | B15: Normal - 50K, C Section - 50K | C15: >=10 | D15: 2 Lac | E15: =IF(AND('Final Sheet'!$F$12=Calculations!A15,'Final Sheet'!$F$18='Drop Down Options'!Q4,'Final Sheet'!$F$10=Calculations!D15,'Final Sheet'!$F$2>=10),(B45*I106)+(C45*I107)+(D45*I108)+(E45*I109)+(F45*I110)+(G45*I111)+(H45*I112)+(I45*I113)+(J45*I114)+(K45*I115),0) -> 0
A16: E Only | B16: Normal - 75K, C Section - 75K | C16: >=10 | D16: 2 Lac | E16: =IF(AND('Final Sheet'!$F$12=Calculations!A16,'Final Sheet'!$F$18='Drop Down Options'!Q5,'Final Sheet'!$F$10=Calculations!D16,'Final Sheet'!$F$2>=10),(B45*I133)+(C45*I134)+(D45*I135)+(E45*I136)+(F45*I137)+(G45*I138)+(H45*I139)+(I45*I140)+(J45*I141)+(K45*I142),0) -> 0
A17: ESC | B17: No | C17: <10 | D17: 2 Lac | E17: =IF(AND('Final Sheet'!$F$12=Calculations!A17,'Final Sheet'!$F$18=Calculations!B17,'Final Sheet'!$F$10=Calculations!D17,'Final Sheet'!$F$2<10),(B45*C65)+(C45*C66)+(D45*C67)+(E45*C68)+(F45*C69)+(G45*C70)+(H45*C71)+(I45*C72)+(J45*C73)+(K45*C74),0) -> 0
A18: ESC | B18: No | C18: >=10 | D18: 2 Lac | E18: =IF(AND('Final Sheet'!$F$12=Calculations!A18,'Final Sheet'!$F$18=Calculations!B18,'Final Sheet'!$F$10=Calculations!D18,'Final Sheet'!$F$2>=10),(B45*I65)+(C45*I66)+(D45*I67)+(E45*I68)+(F45*I69)+(G45*I70)+(H45*I71)+(I45*I72)+(J45*I73)+(K45*I74),0) -> 0
A19: ESC | B19: Normal - 30K, C Section - 30K | C19: >=10 | D19: 2 Lac | E19: =IF(AND('Final Sheet'!$F$12=Calculations!A19,'Final Sheet'!$F$18='Drop Down Options'!Q3,'Final Sheet'!$F$10=Calculations!D19,'Final Sheet'!$F$2>=10),(B45*I92)+(C45*I93)+(D45*I94)+(E45*I95)+(F45*I96)+(G45*I97)+(H45*I98)+(I45*I99)+(J45*I100)+(K45*I101),0) -> 0
A20: ESC | B20: Normal - 50K, C Section - 50K | C20: >=10 | D20: 2 Lac | E20: =IF(AND('Final Sheet'!$F$12=Calculations!A20,'Final Sheet'!$F$18='Drop Down Options'!Q4,'Final Sheet'!$F$10=Calculations!D20,'Final Sheet'!$F$2>=10),(B45*I119)+(C45*I120)+(D45*I121)+(E45*I122)+(F45*I123)+(G45*I124)+(H45*I125)+(I45*I126)+(J45*I127)+(K45*I128),0) -> 0
A21: ESC | B21: Normal - 75K, C Section - 75K | C21: >=10 | D21: 2 Lac | E21: =IF(AND('Final Sheet'!$F$12=Calculations!A21,'Final Sheet'!$F$18='Drop Down Options'!Q5,'Final Sheet'!$F$10=Calculations!D21,'Final Sheet'!$F$2>=10),(B45*I146)+(C45*I147)+(D45*I148)+(E45*I149)+(F45*I150)+(G45*I151)+(H45*I152)+(I45*I153)+(J45*I154)+(K45*I155),0) -> 0
A22: E Only | B22: No | C22: <10 | D22: 3 Lac | E22: =IF(AND('Final Sheet'!$F$12=Calculations!A22,'Final Sheet'!$F$18=Calculations!B22,'Final Sheet'!$F$10=Calculations!D22,'Final Sheet'!$F$2<10),(B46*D52)+(C46*D53)+(D46*D54)+(E46*D55)+(F46*D56)+(G46*D57)+(H46*D58)+(I46*D59)+(J46*D60)+(K46*D61),0) -> 0
A23: E Only | B23: No | C23: >=10 | D23: 3 Lac | E23: =IF(AND('Final Sheet'!$F$12=Calculations!A23,'Final Sheet'!$F$18=Calculations!B23,'Final Sheet'!$F$10=Calculations!D23,'Final Sheet'!$F$2>=10),(B46*J52)+(C46*J53)+(D46*J54)+(E46*J55)+(F46*J56)+(G46*J57)+(H46*J58)+(I46*J59)+(J46*J60)+(K46*J61),0) -> 0
A24: E Only | B24: Normal - 30K, C Section - 30K | C24: >=10 | D24: 3 Lac | E24: =IF(AND('Final Sheet'!$F$12=Calculations!A24,'Final Sheet'!$F$18='Drop Down Options'!Q3,'Final Sheet'!$F$10=Calculations!D24,'Final Sheet'!$F$2>=10),(B46*J79)+(C46*J80)+(D46*J81)+(E46*J82)+(F46*J83)+(G46*J84)+(H46*J85)+(I46*J86)+(J46*J87)+(K46*J88),0) -> 0
A25: E Only | B25: Normal - 50K, C Section - 50K | C25: >=10 | D25: 3 Lac | E25: =IF(AND('Final Sheet'!$F$12=Calculations!A25,'Final Sheet'!$F$18='Drop Down Options'!Q4,'Final Sheet'!$F$10=Calculations!D25,'Final Sheet'!$F$2>=10),(B46*J106)+(C46*J107)+(D46*J108)+(E46*J109)+(F46*J110)+(G46*J111)+(H46*J112)+(I46*J113)+(J46*J114)+(K46*J115),0) -> 0
A26: E Only | B26: Normal - 75K, C Section - 75K | C26: >=10 | D26: 3 Lac | E26: =IF(AND('Final Sheet'!$F$12=Calculations!A26,'Final Sheet'!$F$18='Drop Down Options'!Q5,'Final Sheet'!$F$10=Calculations!D26,'Final Sheet'!$F$2>=10),(B46*J133)+(C46*J134)+(D46*J135)+(E46*J136)+(F46*J137)+(G46*J138)+(H46*J139)+(I46*J140)+(J46*J141)+(K46*J142),0) -> 0
A27: ESC | B27: No | C27: <10 | D27: 3 Lac | E27: =IF(AND('Final Sheet'!$F$12=Calculations!A27,'Final Sheet'!$F$18=Calculations!B27,'Final Sheet'!$F$10=Calculations!D27,'Final Sheet'!$F$2<10),(B46*D65)+(C46*D66)+(D46*D67)+(E46*D68)+(F46*D69)+(G46*D70)+(H46*D71)+(I46*D72)+(J46*D73)+(K46*D74),0) -> 0
A28: ESC | B28: No | C28: >=10 | D28: 3 Lac | E28: =IF(AND('Final Sheet'!$F$12=Calculations!A28,'Final Sheet'!$F$18=Calculations!B28,'Final Sheet'!$F$10=Calculations!D28,'Final Sheet'!$F$2>=10),(B46*J65)+(C46*J66)+(D46*J67)+(E46*J68)+(F46*J69)+(G46*J70)+(H46*J71)+(I46*J72)+(J46*J73)+(K46*J74),0) -> 0
A29: ESC | B29: Normal - 30K, C Section - 30K | C29: >=10 | D29: 3 Lac | E29: =IF(AND('Final Sheet'!$F$12=Calculations!A29,'Final Sheet'!$F$18='Drop Down Options'!Q3,'Final Sheet'!$F$10=Calculations!D29,'Final Sheet'!$F$2>=10),(B46*J92)+(C46*J93)+(D46*J94)+(E46*J95)+(F46*J96)+(G46*J97)+(H46*J98)+(I46*J99)+(J46*J100)+(K46*J101),0) -> 0
A30: ESC | B30: Normal - 50K, C Section - 50K | C30: >=10 | D30: 3 Lac | E30: =IF(AND('Final Sheet'!$F$12=Calculations!A30,'Final Sheet'!$F$18='Drop Down Options'!Q4,'Final Sheet'!$F$10=Calculations!D30,'Final Sheet'!$F$2>=10),(B46*J119)+(C46*J120)+(D46*J121)+(E46*J122)+(F46*J123)+(G46*J124)+(H46*J125)+(I46*J126)+(J46*J127)+(K46*J128),0) -> 224500
A31: ESC | B31: Normal - 75K, C Section - 75K | C31: >=10 | D31: 3 Lac | E31: =IF(AND('Final Sheet'!$F$12=Calculations!A31,'Final Sheet'!$F$18='Drop Down Options'!Q5,'Final Sheet'!$F$10=Calculations!D31,'Final Sheet'!$F$2>=10),(B46*J146)+(C46*J147)+(D46*J148)+(E46*J149)+(F46*J150)+(G46*J151)+(H46*J152)+(I46*J153)+(J46*J154)+(K46*J155),0) -> 0
A32: E Only | B32: No | C32: <10 | D32: 5 Lac | E32: =IF(AND('Final Sheet'!$F$12=Calculations!A32,'Final Sheet'!$F$18=Calculations!B32,'Final Sheet'!$F$10=Calculations!D32,'Final Sheet'!$F$2<10),(B47*E52)+(C47*E53)+(D47*E54)+(E47*E55)+(F47*E56)+(G47*E57)+(H47*E58)+(I47*E59)+(J47*E60)+(K47*E61),0) -> 0
A33: E Only | B33: No | C33: >=10 | D33: 5 Lac | E33: =IF(AND('Final Sheet'!$F$12=Calculations!A33,'Final Sheet'!$F$18=Calculations!B33,'Final Sheet'!$F$10=Calculations!D33,'Final Sheet'!$F$2>=10),(B47*K52)+(C47*K53)+(D47*K54)+(E47*K55)+(F47*K56)+(G47*K57)+(H47*K58)+(I47*K59)+(J47*K60)+(K47*K61),0) -> 0
A34: E Only | B34: Normal - 30K, C Section - 30K | C34: >=10 | D34: 5 Lac | E34: =IF(AND('Final Sheet'!$F$12=Calculations!A34,'Final Sheet'!$F$18='Drop Down Options'!Q3,'Final Sheet'!$F$10=Calculations!D34,'Final Sheet'!$F$2>=10),(B47*K79)+(C47*K80)+(D47*K81)+(E47*K82)+(F47*K83)+(G47*K84)+(H47*K85)+(I47*K86)+(J47*K87)+(K47*K88),0) -> 0
A35: E Only | B35: Normal - 50K, C Section - 50K | C35: >=10 | D35: 5 Lac | E35: =IF(AND('Final Sheet'!$F$12=Calculations!A35,'Final Sheet'!$F$18='Drop Down Options'!Q4,'Final Sheet'!$F$10=Calculations!D35,'Final Sheet'!$F$2>=10),(B47*K106)+(C47*K107)+(D47*K108)+(E47*K109)+(F47*K110)+(G47*K111)+(H47*K112)+(I47*K113)+(J47*K114)+(K47*K115),0) -> 0
A36: E Only | B36: Normal - 75K, C Section - 75K | C36: >=10 | D36: 5 Lac | E36: =IF(AND('Final Sheet'!$F$12=Calculations!A36,'Final Sheet'!$F$18='Drop Down Options'!Q5,'Final Sheet'!$F$10=Calculations!D36,'Final Sheet'!$F$2>=10),(B47*K133)+(C47*K134)+(D47*K135)+(E47*K136)+(F47*K137)+(G47*K138)+(H47*K139)+(I47*K140)+(J47*K141)+(K47*K142),0) -> 0
A37: ESC | B37: No | C37: <10 | D37: 5 Lac | E37: =IF(AND('Final Sheet'!$F$12=Calculations!A37,'Final Sheet'!$F$18=Calculations!B37,'Final Sheet'!$F$10=Calculations!D37,'Final Sheet'!$F$2<10),(B47*E65)+(C47*E66)+(D47*E67)+(E47*E68)+(F47*E69)+(G47*E70)+(H47*E71)+(I47*E72)+(J47*E73)+(K47*E74),0) -> 0
A38: ESC | B38: No | C38: >=10 | D38: 5 Lac | E38: =IF(AND('Final Sheet'!$F$12=Calculations!A38,'Final Sheet'!$F$18=Calculations!B38,'Final Sheet'!$F$10=Calculations!D38,'Final Sheet'!$F$2>=10),(B47*K65)+(C47*K66)+(D47*K67)+(E47*K68)+(F47*K69)+(G47*K70)+(H47*K71)+(I47*K72)+(J47*K73)+(K47*K74),0) -> 0
A39: ESC | B39: Normal - 30K, C Section - 30K | C39: >=10 | D39: 5 Lac | E39: =IF(AND('Final Sheet'!$F$12=Calculations!A39,'Final Sheet'!$F$18='Drop Down Options'!Q3,'Final Sheet'!$F$10=Calculations!D39,'Final Sheet'!$F$2>=10),(B47*K92)+(C47*K93)+(D47*K94)+(E47*K95)+(F47*K96)+(G47*K97)+(H47*K98)+(I47*K99)+(J47*K100)+(K47*K101),0) -> 0
A40: ESC | B40: Normal - 50K, C Section - 50K | C40: >=10 | D40: 5 Lac | E40: =IF(AND('Final Sheet'!$F$12=Calculations!A40,'Final Sheet'!$F$18='Drop Down Options'!Q4,'Final Sheet'!$F$10=Calculations!D40,'Final Sheet'!$F$2>=10),(B47*K119)+(C47*K120)+(D47*K121)+(E47*K122)+(F47*K123)+(G47*K124)+(H47*K125)+(I47*K126)+(J47*K127)+(K47*K128),0) -> 0
A41: ESC | B41: Normal - 75K, C Section - 75K | C41: >=10 | D41: 5 Lac | E41: =IF(AND('Final Sheet'!$F$12=Calculations!A41,'Final Sheet'!$F$18='Drop Down Options'!Q5,'Final Sheet'!$F$10=Calculations!D41,'Final Sheet'!$F$2>=10),(B47*K146)+(C47*K147)+(D47*K148)+(E47*K149)+(F47*K150)+(G47*K151)+(H47*K152)+(I47*K153)+(J47*K154)+(K47*K155),0) -> 0
A43: ='Final Sheet'!A25 -> Age Band | B43: ='Final Sheet'!B25 -> Upto 20 Yrs | C43: ='Final Sheet'!C25 -> 21-25 | D43: ='Final Sheet'!D25 -> 26-30 | E43: ='Final Sheet'!E25 -> 31-35 | F43: ='Final Sheet'!F25 -> 36-40 | G43: ='Final Sheet'!G25 -> 41-45 | H43: ='Final Sheet'!H25 -> 46-50 | ... K43: ='Final Sheet'!K25 -> 61-65
A44: ='Final Sheet'!A26 -> 1 Lac | B44: ='Final Sheet'!B26 -> 0 | C44: ='Final Sheet'!C26 -> 0 | D44: ='Final Sheet'!D26 -> 0 | E44: ='Final Sheet'!E26 -> 0 | F44: ='Final Sheet'!F26 -> 0 | G44: ='Final Sheet'!G26 -> 0 | H44: ='Final Sheet'!H26 -> 0 | ... K44: ='Final Sheet'!K26 -> 0 | L44: =SUM(B44:K44) -> 0
A45: ='Final Sheet'!A27 -> 2 Lacs | B45: ='Final Sheet'!B27 -> 0 | C45: ='Final Sheet'!C27 -> 0 | D45: ='Final Sheet'!D27 -> 0 | E45: ='Final Sheet'!E27 -> 0 | F45: ='Final Sheet'!F27 -> 0 | G45: ='Final Sheet'!G27 -> 0 | H45: ='Final Sheet'!H27 -> 0 | ... K45: ='Final Sheet'!K27 -> 0 | L45: =SUM(B45:K45) -> 0
A46: ='Final Sheet'!A28 -> 3 Lacs | B46: ='Final Sheet'!B28 -> 17 | C46: ='Final Sheet'!C28 -> 0 | D46: ='Final Sheet'!D28 -> 10 | E46: ='Final Sheet'!E28 -> 4 | F46: ='Final Sheet'!F28 -> 10 | G46: ='Final Sheet'!G28 -> 5 | H46: ='Final Sheet'!H28 -> 3 | ... K46: ='Final Sheet'!K28 -> 0 | L46: =SUM(B46:K46) -> 53
A47: ='Final Sheet'!A29 -> 5 Lacs | B47: ='Final Sheet'!B29 -> 0 | C47: ='Final Sheet'!C29 -> 0 | D47: ='Final Sheet'!D29 -> 0 | E47: ='Final Sheet'!E29 -> 0 | F47: ='Final Sheet'!F29 -> 0 | G47: ='Final Sheet'!G29 -> 0 | H47: ='Final Sheet'!H29 -> 0 | ... K47: ='Final Sheet'!K29 -> 0 | L47: =SUM(B47:K47) -> 0
A49: No Maternity
A50: E Only (With PED & SD Waiting periods) | G50: E Only (No PED & SD Waiting periods)
B51: 1 Lac | C51: 2 Lacs | D51: 3 Lacs | E51: 5 Lacs | H51: 1 Lac | I51: 2 Lacs | J51: 3 Lacs | K51: 5 Lacs
A52: Upto 20 Yrs | B52: ='Age Band Raters'!C4 -> 1086 | C52: ='Age Band Raters'!D4 -> 1270 | D52: ='Age Band Raters'!E4 -> 1392 | E52: ='Age Band Raters'!F4 -> 1562 | G52: Upto 20 Yrs | H52: ='Age Band Raters'!I4 -> 1587 | I52: ='Age Band Raters'!J4 -> 1857 | J52: ='Age Band Raters'!K4 -> 2035 | K52: ='Age Band Raters'!L4 -> 2283
A53: 21-25 | B53: ='Age Band Raters'!C5 -> 1710 | C53: ='Age Band Raters'!D5 -> 2000 | D53: ='Age Band Raters'!E5 -> 2192 | E53: ='Age Band Raters'!F5 -> 2460 | G53: 21-25 | H53: ='Age Band Raters'!I5 -> 2500 | I53: ='Age Band Raters'!J5 -> 2924 | J53: ='Age Band Raters'!K5 -> 3204 | K53: ='Age Band Raters'!L5 -> 3596
A54: 26-30 | B54: ='Age Band Raters'!C6 -> 1802 | C54: ='Age Band Raters'!D6 -> 2107 | D54: ='Age Band Raters'!E6 -> 2309 | E54: ='Age Band Raters'!F6 -> 2592 | G54: 26-30 | H54: ='Age Band Raters'!I6 -> 2634 | I54: ='Age Band Raters'!J6 -> 3080 | J54: ='Age Band Raters'!K6 -> 3376 | K54: ='Age Band Raters'!L6 -> 3788
A55: 31-35 | B55: ='Age Band Raters'!C7 -> 1959 | C55: ='Age Band Raters'!D7 -> 2291 | D55: ='Age Band Raters'!E7 -> 2511 | E55: ='Age Band Raters'!F7 -> 2818 | G55: 31-35 | H55: ='Age Band Raters'!I7 -> 2864 | I55: ='Age Band Raters'!J7 -> 3350 | J55: ='Age Band Raters'!K7 -> 3671 | K55: ='Age Band Raters'!L7 -> 4120
A56: 36-40 | B56: ='Age Band Raters'!C8 -> 2209 | C56: ='Age Band Raters'!D8 -> 2583 | D56: ='Age Band Raters'!E8 -> 2831 | E56: ='Age Band Raters'!F8 -> 3177 | G56: 36-40 | H56: ='Age Band Raters'!I8 -> 3229 | I56: ='Age Band Raters'!J8 -> 3777 | J56: ='Age Band Raters'!K8 -> 4139 | K56: ='Age Band Raters'!L8 -> 4645
A57: 41-45 | B57: ='Age Band Raters'!C9 -> 2673 | C57: ='Age Band Raters'!D9 -> 3126 | D57: ='Age Band Raters'!E9 -> 3426 | E57: ='Age Band Raters'!F9 -> 3845 | G57: 41-45 | H57: ='Age Band Raters'!I9 -> 3907 | I57: ='Age Band Raters'!J9 -> 4570 | J57: ='Age Band Raters'!K9 -> 5009 | K57: ='Age Band Raters'!L9 -> 5621
A58: 46-50 | B58: ='Age Band Raters'!C10 -> 3273 | C58: ='Age Band Raters'!D10 -> 3828 | D58: ='Age Band Raters'!E10 -> 4196 | E58: ='Age Band Raters'!F10 -> 4708 | G58: 46-50 | H58: ='Age Band Raters'!I10 -> 4785 | I58: ='Age Band Raters'!J10 -> 5597 | J58: ='Age Band Raters'!K10 -> 6133 | K58: ='Age Band Raters'!L10 -> 6883
A59: 51-55 | B59: ='Age Band Raters'!C11 -> 4172 | C59: ='Age Band Raters'!D11 -> 4880 | D59: ='Age Band Raters'!E11 -> 5348 | E59: ='Age Band Raters'!F11 -> 6001 | G59: 51-55 | H59: ='Age Band Raters'!I11 -> 6099 | I59: ='Age Band Raters'!J11 -> 7133 | J59: ='Age Band Raters'!K11 -> 7818 | K59: ='Age Band Raters'!L11 -> 8773
A60: 56-60 | B60: ='Age Band Raters'!C12 -> 5490 | C60: ='Age Band Raters'!D12 -> 6421 | D60: ='Age Band Raters'!E12 -> 7037 | E60: ='Age Band Raters'!F12 -> 7897 | G60: 56-60 | H60: ='Age Band Raters'!I12 -> 8025 | I60: ='Age Band Raters'!J12 -> 9387 | J60: ='Age Band Raters'!K12 -> 10287 | K60: ='Age Band Raters'!L12 -> 11544
A61: 61-65 | B61: ='Age Band Raters'!C13 -> 7465 | C61: ='Age Band Raters'!D13 -> 8732 | D61: ='Age Band Raters'!E13 -> 9570 | E61: ='Age Band Raters'!F13 -> 10739 | G61: 61-65 | H61: ='Age Band Raters'!I13 -> 10914 | I61: ='Age Band Raters'!J13 -> 12765 | J61: ='Age Band Raters'!K13 -> 13990 | K61: ='Age Band Raters'!L13 -> 15699
A63: ESC (With PED & SD Waiting periods) | G63: ESC (No PED & SD Waiting periods)
B64: 1 Lac | C64: 2 Lacs | D64: 3 Lacs | E64: 5 Lacs | H64: 1 Lac | I64: 2 Lacs | J64: 3 Lacs | K64: 5 Lacs
A65: Upto 20 Yrs | B65: ='Age Band Raters'!C17 -> 923 | C65: ='Age Band Raters'!D17 -> 1080 | D65: ='Age Band Raters'!E17 -> 1183 | E65: ='Age Band Raters'!F17 -> 1328 | G65: Upto 20 Yrs | H65: ='Age Band Raters'!I17 -> 1349 | I65: ='Age Band Raters'!J17 -> 1578 | J65: ='Age Band Raters'!K17 -> 1730 | K65: ='Age Band Raters'!L17 -> 1941
A66: 21-25 | B66: ='Age Band Raters'!C18 -> 1453 | C66: ='Age Band Raters'!D18 -> 1700 | D66: ='Age Band Raters'!E18 -> 1863 | E66: ='Age Band Raters'!F18 -> 2091 | G66: 21-25 | H66: ='Age Band Raters'!I18 -> 2125 | I66: ='Age Band Raters'!J18 -> 2485 | J66: ='Age Band Raters'!K18 -> 2723 | K66: ='Age Band Raters'!L18 -> 3056
A67: 26-30 | B67: ='Age Band Raters'!C19 -> 1531 | C67: ='Age Band Raters'!D19 -> 1791 | D67: ='Age Band Raters'!E19 -> 1963 | E67: ='Age Band Raters'!F19 -> 2203 | G67: 26-30 | H67: ='Age Band Raters'!I19 -> 2239 | I67: ='Age Band Raters'!J19 -> 2618 | J67: ='Age Band Raters'!K19 -> 2870 | K67: ='Age Band Raters'!L19 -> 3220
A68: 31-35 | B68: ='Age Band Raters'!C20 -> 1665 | C68: ='Age Band Raters'!D20 -> 1948 | D68: ='Age Band Raters'!E20 -> 2135 | E68: ='Age Band Raters'!F20 -> 2395 | G68: 31-35 | H68: ='Age Band Raters'!I20 -> 2434 | I68: ='Age Band Raters'!J20 -> 2847 | J68: ='Age Band Raters'!K20 -> 3120 | K68: ='Age Band Raters'!L20 -> 3502
A69: 36-40 | B69: ='Age Band Raters'!C21 -> 1877 | C69: ='Age Band Raters'!D21 -> 2196 | D69: ='Age Band Raters'!E21 -> 2407 | E69: ='Age Band Raters'!F21 -> 2701 | G69: 36-40 | H69: ='Age Band Raters'!I21 -> 2744 | I69: ='Age Band Raters'!J21 -> 3210 | J69: ='Age Band Raters'!K21 -> 3518 | K69: ='Age Band Raters'!L21 -> 3948
A70: 41-45 | B70: ='Age Band Raters'!C22 -> 2272 | C70: ='Age Band Raters'!D22 -> 2657 | D70: ='Age Band Raters'!E22 -> 2912 | E70: ='Age Band Raters'!F22 -> 3268 | G70: 41-45 | H70: ='Age Band Raters'!I22 -> 3321 | I70: ='Age Band Raters'!J22 -> 3885 | J70: ='Age Band Raters'!K22 -> 4257 | K70: ='Age Band Raters'!L22 -> 4778
A71: 46-50 | B71: ='Age Band Raters'!C23 -> 2782 | C71: ='Age Band Raters'!D23 -> 3254 | D71: ='Age Band Raters'!E23 -> 3566 | E71: ='Age Band Raters'!F23 -> 4002 | G71: 46-50 | H71: ='Age Band Raters'!I23 -> 4067 | I71: ='Age Band Raters'!J23 -> 4757 | J71: ='Age Band Raters'!K23 -> 5213 | K71: ='Age Band Raters'!L23 -> 5850
A72: 51-55 | B72: ='Age Band Raters'!C24 -> 3546 | C72: ='Age Band Raters'!D24 -> 4148 | D72: ='Age Band Raters'!E24 -> 4546 | E72: ='Age Band Raters'!F24 -> 5101 | G72: 51-55 | H72: ='Age Band Raters'!I24 -> 5184 | I72: ='Age Band Raters'!J24 -> 6063 | J72: ='Age Band Raters'!K24 -> 6645 | K72: ='Age Band Raters'!L24 -> 7457
A73: 56-60 | B73: ='Age Band Raters'!C25 -> 4666 | C73: ='Age Band Raters'!D25 -> 5458 | D73: ='Age Band Raters'!E25 -> 5981 | E73: ='Age Band Raters'!F25 -> 6712 | G73: 56-60 | H73: ='Age Band Raters'!I25 -> 6821 | I73: ='Age Band Raters'!J25 -> 7979 | J73: ='Age Band Raters'!K25 -> 8744 | K73: ='Age Band Raters'!L25 -> 9812
A74: 61-65 | B74: ='Age Band Raters'!C26 -> 6346 | C74: ='Age Band Raters'!D26 -> 7422 | D74: ='Age Band Raters'!E26 -> 8134 | E74: ='Age Band Raters'!F26 -> 9128 | G74: 61-65 | H74: ='Age Band Raters'!I26 -> 9276 | I74: ='Age Band Raters'!J26 -> 10850 | J74: ='Age Band Raters'!K26 -> 11891 | K74: ='Age Band Raters'!L26 -> 13344
A76: 30K Maternity
A77: E Only (With PED & SD Waiting periods) | G77: E Only (No PED & SD Waiting periods)
B78: 1 Lac | C78: 2 Lacs | D78: 3 Lacs | E78: 5 Lacs | H78: 1 Lac | I78: 2 Lacs | J78: 3 Lacs | K78: 5 Lacs
A79: Upto 20 Yrs | B79: ='Age Band Raters'!C31 -> 1711 | C79: ='Age Band Raters'!D31 -> 1895 | D79: ='Age Band Raters'!E31 -> 2017 | E79: ='Age Band Raters'!F31 -> 2187 | G79: Upto 20 Yrs | H79: ='Age Band Raters'!I31 -> 2212 | I79: ='Age Band Raters'!J31 -> 2482 | J79: ='Age Band Raters'!K31 -> 2660 | K79: ='Age Band Raters'!L31 -> 2908
A80: 21-25 | B80: ='Age Band Raters'!C32 -> 2335 | C80: ='Age Band Raters'!D32 -> 2625 | D80: ='Age Band Raters'!E32 -> 2817 | E80: ='Age Band Raters'!F32 -> 3085 | G80: 21-25 | H80: ='Age Band Raters'!I32 -> 3125 | I80: ='Age Band Raters'!J32 -> 3549 | J80: ='Age Band Raters'!K32 -> 3829 | K80: ='Age Band Raters'!L32 -> 4221
A81: 26-30 | B81: ='Age Band Raters'!C33 -> 2427 | C81: ='Age Band Raters'!D33 -> 2732 | D81: ='Age Band Raters'!E33 -> 2934 | E81: ='Age Band Raters'!F33 -> 3217 | G81: 26-30 | H81: ='Age Band Raters'!I33 -> 3259 | I81: ='Age Band Raters'!J33 -> 3705 | J81: ='Age Band Raters'!K33 -> 4001 | K81: ='Age Band Raters'!L33 -> 4413
A82: 31-35 | B82: ='Age Band Raters'!C34 -> 2584 | C82: ='Age Band Raters'!D34 -> 2916 | D82: ='Age Band Raters'!E34 -> 3136 | E82: ='Age Band Raters'!F34 -> 3443 | G82: 31-35 | H82: ='Age Band Raters'!I34 -> 3489 | I82: ='Age Band Raters'!J34 -> 3975 | J82: ='Age Band Raters'!K34 -> 4296 | K82: ='Age Band Raters'!L34 -> 4745
A83: 36-40 | B83: ='Age Band Raters'!C35 -> 2834 | C83: ='Age Band Raters'!D35 -> 3208 | D83: ='Age Band Raters'!E35 -> 3456 | E83: ='Age Band Raters'!F35 -> 3802 | G83: 36-40 | H83: ='Age Band Raters'!I35 -> 3854 | I83: ='Age Band Raters'!J35 -> 4402 | J83: ='Age Band Raters'!K35 -> 4764 | K83: ='Age Band Raters'!L35 -> 5270
A84: 41-45 | B84: ='Age Band Raters'!C36 -> 3298 | C84: ='Age Band Raters'!D36 -> 3751 | D84: ='Age Band Raters'!E36 -> 4051 | E84: ='Age Band Raters'!F36 -> 4470 | G84: 41-45 | H84: ='Age Band Raters'!I36 -> 4532 | I84: ='Age Band Raters'!J36 -> 5195 | J84: ='Age Band Raters'!K36 -> 5634 | K84: ='Age Band Raters'!L36 -> 6246
A85: 46-50 | B85: ='Age Band Raters'!C37 -> 3898 | C85: ='Age Band Raters'!D37 -> 4453 | D85: ='Age Band Raters'!E37 -> 4821 | E85: ='Age Band Raters'!F37 -> 5333 | G85: 46-50 | H85: ='Age Band Raters'!I37 -> 5410 | I85: ='Age Band Raters'!J37 -> 6222 | J85: ='Age Band Raters'!K37 -> 6758 | K85: ='Age Band Raters'!L37 -> 7508
A86: 51-55 | B86: ='Age Band Raters'!C38 -> 4797 | C86: ='Age Band Raters'!D38 -> 5505 | D86: ='Age Band Raters'!E38 -> 5973 | E86: ='Age Band Raters'!F38 -> 6626 | G86: 51-55 | H86: ='Age Band Raters'!I38 -> 6724 | I86: ='Age Band Raters'!J38 -> 7758 | J86: ='Age Band Raters'!K38 -> 8443 | K86: ='Age Band Raters'!L38 -> 9398
A87: 56-60 | B87: ='Age Band Raters'!C39 -> 6115 | C87: ='Age Band Raters'!D39 -> 7046 | D87: ='Age Band Raters'!E39 -> 7662 | E87: ='Age Band Raters'!F39 -> 8522 | G87: 56-60 | H87: ='Age Band Raters'!I39 -> 8650 | I87: ='Age Band Raters'!J39 -> 10012 | J87: ='Age Band Raters'!K39 -> 10912 | K87: ='Age Band Raters'!L39 -> 12169
A88: 61-65 | B88: ='Age Band Raters'!C40 -> 8090 | C88: ='Age Band Raters'!D40 -> 9357 | D88: ='Age Band Raters'!E40 -> 10195 | E88: ='Age Band Raters'!F40 -> 11364 | G88: 61-65 | H88: ='Age Band Raters'!I40 -> 11539 | I88: ='Age Band Raters'!J40 -> 13390 | J88: ='Age Band Raters'!K40 -> 14615 | K88: ='Age Band Raters'!L40 -> 16324
A90: ESC (With PED & SD Waiting periods) | G90: ESC (No PED & SD Waiting periods)
B91: 1 Lac | C91: 2 Lacs | D91: 3 Lacs | E91: 5 Lacs | H91: 1 Lac | I91: 2 Lacs | J91: 3 Lacs | K91: 5 Lacs
A92: Upto 20 Yrs | B92: ='Age Band Raters'!C44 -> 1548 | C92: ='Age Band Raters'!D44 -> 1705 | D92: ='Age Band Raters'!E44 -> 1808 | E92: ='Age Band Raters'!F44 -> 1953 | G92: Upto 20 Yrs | H92: ='Age Band Raters'!I44 -> 1974 | I92: ='Age Band Raters'!J44 -> 2203 | J92: ='Age Band Raters'!K44 -> 2355 | K92: ='Age Band Raters'!L44 -> 2566
A93: 21-25 | B93: ='Age Band Raters'!C45 -> 2078 | C93: ='Age Band Raters'!D45 -> 2325 | D93: ='Age Band Raters'!E45 -> 2488 | E93: ='Age Band Raters'!F45 -> 2716 | G93: 21-25 | H93: ='Age Band Raters'!I45 -> 2750 | I93: ='Age Band Raters'!J45 -> 3110 | J93: ='Age Band Raters'!K45 -> 3348 | K93: ='Age Band Raters'!L45 -> 3681
A94: 26-30 | B94: ='Age Band Raters'!C46 -> 2156 | C94: ='Age Band Raters'!D46 -> 2416 | D94: ='Age Band Raters'!E46 -> 2588 | E94: ='Age Band Raters'!F46 -> 2828 | G94: 26-30 | H94: ='Age Band Raters'!I46 -> 2864 | I94: ='Age Band Raters'!J46 -> 3243 | J94: ='Age Band Raters'!K46 -> 3495 | K94: ='Age Band Raters'!L46 -> 3845
A95: 31-35 | B95: ='Age Band Raters'!C47 -> 2290 | C95: ='Age Band Raters'!D47 -> 2573 | D95: ='Age Band Raters'!E47 -> 2760 | E95: ='Age Band Raters'!F47 -> 3020 | G95: 31-35 | H95: ='Age Band Raters'!I47 -> 3059 | I95: ='Age Band Raters'!J47 -> 3472 | J95: ='Age Band Raters'!K47 -> 3745 | K95: ='Age Band Raters'!L47 -> 4127
A96: 36-40 | B96: ='Age Band Raters'!C48 -> 2502 | C96: ='Age Band Raters'!D48 -> 2821 | D96: ='Age Band Raters'!E48 -> 3032 | E96: ='Age Band Raters'!F48 -> 3326 | G96: 36-40 | H96: ='Age Band Raters'!I48 -> 3369 | I96: ='Age Band Raters'!J48 -> 3835 | J96: ='Age Band Raters'!K48 -> 4143 | K96: ='Age Band Raters'!L48 -> 4573
A97: 41-45 | B97: ='Age Band Raters'!C49 -> 2897 | C97: ='Age Band Raters'!D49 -> 3282 | D97: ='Age Band Raters'!E49 -> 3537 | E97: ='Age Band Raters'!F49 -> 3893 | G97: 41-45 | H97: ='Age Band Raters'!I49 -> 3946 | I97: ='Age Band Raters'!J49 -> 4510 | J97: ='Age Band Raters'!K49 -> 4882 | K97: ='Age Band Raters'!L49 -> 5403
A98: 46-50 | B98: ='Age Band Raters'!C50 -> 3407 | C98: ='Age Band Raters'!D50 -> 3879 | D98: ='Age Band Raters'!E50 -> 4191 | E98: ='Age Band Raters'!F50 -> 4627 | G98: 46-50 | H98: ='Age Band Raters'!I50 -> 4692 | I98: ='Age Band Raters'!J50 -> 5382 | J98: ='Age Band Raters'!K50 -> 5838 | K98: ='Age Band Raters'!L50 -> 6475
A99: 51-55 | B99: ='Age Band Raters'!C51 -> 4171 | C99: ='Age Band Raters'!D51 -> 4773 | D99: ='Age Band Raters'!E51 -> 5171 | E99: ='Age Band Raters'!F51 -> 5726 | G99: 51-55 | H99: ='Age Band Raters'!I51 -> 5809 | I99: ='Age Band Raters'!J51 -> 6688 | J99: ='Age Band Raters'!K51 -> 7270 | K99: ='Age Band Raters'!L51 -> 8082
A100: 56-60 | B100: ='Age Band Raters'!C52 -> 5291 | C100: ='Age Band Raters'!D52 -> 6083 | D100: ='Age Band Raters'!E52 -> 6606 | E100: ='Age Band Raters'!F52 -> 7337 | G100: 56-60 | H100: ='Age Band Raters'!I52 -> 7446 | I100: ='Age Band Raters'!J52 -> 8604 | J100: ='Age Band Raters'!K52 -> 9369 | K100: ='Age Band Raters'!L52 -> 10437
A101: 61-65 | B101: ='Age Band Raters'!C53 -> 6971 | C101: ='Age Band Raters'!D53 -> 8047 | D101: ='Age Band Raters'!E53 -> 8759 | E101: ='Age Band Raters'!F53 -> 9753 | G101: 61-65 | H101: ='Age Band Raters'!I53 -> 9901 | I101: ='Age Band Raters'!J53 -> 11475 | J101: ='Age Band Raters'!K53 -> 12516 | K101: ='Age Band Raters'!L53 -> 13969
A103: 50K Maternity
A104: E Only (With PED & SD Waiting periods) | G104: E Only (No PED & SD Waiting periods)
B105: 1 Lac | C105: 2 Lacs | D105: 3 Lacs | E105: 5 Lacs | H105: 1 Lac | I105: 2 Lacs | J105: 3 Lacs | K105: 5 Lacs
A106: Upto 20 Yrs | B106: ='Age Band Raters'!C58 -> 2128 | C106: ='Age Band Raters'!D58 -> 2312 | D106: ='Age Band Raters'!E58 -> 2434 | E106: ='Age Band Raters'!F58 -> 2604 | G106: Upto 20 Yrs | H106: ='Age Band Raters'!I58 -> 2629 | I106: ='Age Band Raters'!J58 -> 2899 | J106: ='Age Band Raters'!K58 -> 3077 | K106: ='Age Band Raters'!L58 -> 3325
...

Sheet Age Band Raters
B1: No Maternity
B2: E Only (With PED & SD Waiting periods) | H2: E Only (No PED & SD Waiting periods) | O2: Zone Discount | Q2: SI | R2: 30K | S2: 50K | T2: 75K
C3: 1 Lac | D3: 2 Lacs | E3: 3 Lacs | F3: 5 Lacs | I3: 1 Lac | J3: 2 Lacs | K3: 3 Lacs | L3: 5 Lacs | O3: 0.1652 | Q3: Loading | R3: 625 | S3: 1042 | T3: 1563
B4: Upto 20 Yrs | C4: 1086 | D4: 1270 | E4: 1392 | F4: 1562 | H4: Upto 20 Yrs | I4: 1587 | J4: 1857 | K4: 2035 | L4: 2283
B5: 21-25 | C5: 1710 | D5: 2000 | E5: 2192 | F5: 2460 | H5: 21-25 | I5: 2500 | J5: 2924 | K5: 3204 | L5: 3596
B6: 26-30 | C6: 1802 | D6: 2107 | E6: 2309 | F6: 2592 | H6: 26-30 | I6: 2634 | J6: 3080 | K6: 3376 | L6: 3788
B7: 31-35 | C7: 1959 | D7: 2291 | E7: 2511 | F7: 2818 | H7: 31-35 | I7: 2864 | J7: 3350 | K7: 3671 | L7: 4120 | O7: =TODAY() -> 46169
B8: 36-40 | C8: 2209 | D8: 2583 | E8: 2831 | F8: 3177 | H8: 36-40 | I8: 3229 | J8: 3777 | K8: 4139 | L8: 4645
B9: 41-45 | C9: 2673 | D9: 3126 | E9: 3426 | F9: 3845 | H9: 41-45 | I9: 3907 | J9: 4570 | K9: 5009 | L9: 5621
B10: 46-50 | C10: 3273 | D10: 3828 | E10: 4196 | F10: 4708 | H10: 46-50 | I10: 4785 | J10: 5597 | K10: 6133 | L10: 6883
B11: 51-55 | C11: 4172 | D11: 4880 | E11: 5348 | F11: 6001 | H11: 51-55 | I11: 6099 | J11: 7133 | K11: 7818 | L11: 8773
B12: 56-60 | C12: 5490 | D12: 6421 | E12: 7037 | F12: 7897 | H12: 56-60 | I12: 8025 | J12: 9387 | K12: 10287 | L12: 11544
B13: 61-65 | C13: 7465 | D13: 8732 | E13: 9570 | F13: 10739 | H13: 61-65 | I13: 10914 | J13: 12765 | K13: 13990 | L13: 15699
B15: ESC (With PED & SD Waiting periods) | H15: ESC (No PED & SD Waiting periods)
C16: 1 Lac | D16: 2 Lacs | E16: 3 Lacs | F16: 5 Lacs | I16: 1 Lac | J16: 2 Lacs | K16: 3 Lacs | L16: 5 Lacs
B17: Upto 20 Yrs | C17: 923 | D17: 1080 | E17: 1183 | F17: 1328 | H17: Upto 20 Yrs | I17: 1349 | J17: 1578 | K17: 1730 | L17: 1941
B18: 21-25 | C18: 1453 | D18: 1700 | E18: 1863 | F18: 2091 | H18: 21-25 | I18: 2125 | J18: 2485 | K18: 2723 | L18: 3056
B19: 26-30 | C19: 1531 | D19: 1791 | E19: 1963 | F19: 2203 | H19: 26-30 | I19: 2239 | J19: 2618 | K19: 2870 | L19: 3220
B20: 31-35 | C20: 1665 | D20: 1948 | E20: 2135 | F20: 2395 | H20: 31-35 | I20: 2434 | J20: 2847 | K20: 3120 | L20: 3502
B21: 36-40 | C21: 1877 | D21: 2196 | E21: 2407 | F21: 2701 | H21: 36-40 | I21: 2744 | J21: 3210 | K21: 3518 | L21: 3948
B22: 41-45 | C22: 2272 | D22: 2657 | E22: 2912 | F22: 3268 | H22: 41-45 | I22: 3321 | J22: 3885 | K22: 4257 | L22: 4778
B23: 46-50 | C23: 2782 | D23: 3254 | E23: 3566 | F23: 4002 | H23: 46-50 | I23: 4067 | J23: 4757 | K23: 5213 | L23: 5850
B24: 51-55 | C24: 3546 | D24: 4148 | E24: 4546 | F24: 5101 | H24: 51-55 | I24: 5184 | J24: 6063 | K24: 6645 | L24: 7457
B25: 56-60 | C25: 4666 | D25: 5458 | E25: 5981 | F25: 6712 | H25: 56-60 | I25: 6821 | J25: 7979 | K25: 8744 | L25: 9812
B26: 61-65 | C26: 6346 | D26: 7422 | E26: 8134 | F26: 9128 | H26: 61-65 | I26: 9276 | J26: 10850 | K26: 11891 | L26: 13344
B28: 30K Maternity
B29: E Only (With PED & SD Waiting periods) | H29: E Only (No PED & SD Waiting periods)
C30: 1 Lac | D30: 2 Lacs | E30: 3 Lacs | F30: 5 Lacs | I30: 1 Lac | J30: 2 Lacs | K30: 3 Lacs | L30: 5 Lacs
B31: Upto 20 Yrs | C31: =C4+$R$3 -> 1711 | D31: =D4+$R$3 -> 1895 | E31: =E4+$R$3 -> 2017 | F31: =F4+$R$3 -> 2187 | H31: Upto 20 Yrs | I31: =I4+$R$3 -> 2212 | J31: =J4+$R$3 -> 2482 | K31: =K4+$R$3 -> 2660 | L31: =L4+$R$3 -> 2908
B32: 21-25 | C32: =C5+$R$3 -> 2335 | D32: =D5+$R$3 -> 2625 | E32: =E5+$R$3 -> 2817 | F32: =F5+$R$3 -> 3085 | H32: 21-25 | I32: =I5+$R$3 -> 3125 | J32: =J5+$R$3 -> 3549 | K32: =K5+$R$3 -> 3829 | L32: =L5+$R$3 -> 4221
B33: 26-30 | C33: =C6+$R$3 -> 2427 | D33: =D6+$R$3 -> 2732 | E33: =E6+$R$3 -> 2934 | F33: =F6+$R$3 -> 3217 | H33: 26-30 | I33: =I6+$R$3 -> 3259 | J33: =J6+$R$3 -> 3705 | K33: =K6+$R$3 -> 4001 | L33: =L6+$R$3 -> 4413
B34: 31-35 | C34: =C7+$R$3 -> 2584 | D34: =D7+$R$3 -> 2916 | E34: =E7+$R$3 -> 3136 | F34: =F7+$R$3 -> 3443 | H34: 31-35 | I34: =I7+$R$3 -> 3489 | J34: =J7+$R$3 -> 3975 | K34: =K7+$R$3 -> 4296 | L34: =L7+$R$3 -> 4745
B35: 36-40 | C35: =C8+$R$3 -> 2834 | D35: =D8+$R$3 -> 3208 | E35: =E8+$R$3 -> 3456 | F35: =F8+$R$3 -> 3802 | H35: 36-40 | I35: =I8+$R$3 -> 3854 | J35: =J8+$R$3 -> 4402 | K35: =K8+$R$3 -> 4764 | L35: =L8+$R$3 -> 5270
B36: 41-45 | C36: =C9+$R$3 -> 3298 | D36: =D9+$R$3 -> 3751 | E36: =E9+$R$3 -> 4051 | F36: =F9+$R$3 -> 4470 | H36: 41-45 | I36: =I9+$R$3 -> 4532 | J36: =J9+$R$3 -> 5195 | K36: =K9+$R$3 -> 5634 | L36: =L9+$R$3 -> 6246
B37: 46-50 | C37: =C10+$R$3 -> 3898 | D37: =D10+$R$3 -> 4453 | E37: =E10+$R$3 -> 4821 | F37: =F10+$R$3 -> 5333 | H37: 46-50 | I37: =I10+$R$3 -> 5410 | J37: =J10+$R$3 -> 6222 | K37: =K10+$R$3 -> 6758 | L37: =L10+$R$3 -> 7508
B38: 51-55 | C38: =C11+$R$3 -> 4797 | D38: =D11+$R$3 -> 5505 | E38: =E11+$R$3 -> 5973 | F38: =F11+$R$3 -> 6626 | H38: 51-55 | I38: =I11+$R$3 -> 6724 | J38: =J11+$R$3 -> 7758 | K38: =K11+$R$3 -> 8443 | L38: =L11+$R$3 -> 9398
B39: 56-60 | C39: =C12+$R$3 -> 6115 | D39: =D12+$R$3 -> 7046 | E39: =E12+$R$3 -> 7662 | F39: =F12+$R$3 -> 8522 | H39: 56-60 | I39: =I12+$R$3 -> 8650 | J39: =J12+$R$3 -> 10012 | K39: =K12+$R$3 -> 10912 | L39: =L12+$R$3 -> 12169
B40: 61-65 | C40: =C13+$R$3 -> 8090 | D40: =D13+$R$3 -> 9357 | E40: =E13+$R$3 -> 10195 | F40: =F13+$R$3 -> 11364 | H40: 61-65 | I40: =I13+$R$3 -> 11539 | J40: =J13+$R$3 -> 13390 | K40: =K13+$R$3 -> 14615 | L40: =L13+$R$3 -> 16324
B42: ESC (With PED & SD Waiting periods) | H42: ESC (No PED & SD Waiting periods)
C43: 1 Lac | D43: 2 Lacs | E43: 3 Lacs | F43: 5 Lacs | I43: 1 Lac | J43: 2 Lacs | K43: 3 Lacs | L43: 5 Lacs
B44: Upto 20 Yrs | C44: =C17+$R$3 -> 1548 | D44: =D17+$R$3 -> 1705 | E44: =E17+$R$3 -> 1808 | F44: =F17+$R$3 -> 1953 | H44: Upto 20 Yrs | I44: =I17+$R$3 -> 1974 | J44: =J17+$R$3 -> 2203 | K44: =K17+$R$3 -> 2355 | L44: =L17+$R$3 -> 2566
B45: 21-25 | C45: =C18+$R$3 -> 2078 | D45: =D18+$R$3 -> 2325 | E45: =E18+$R$3 -> 2488 | F45: =F18+$R$3 -> 2716 | H45: 21-25 | I45: =I18+$R$3 -> 2750 | J45: =J18+$R$3 -> 3110 | K45: =K18+$R$3 -> 3348 | L45: =L18+$R$3 -> 3681
B46: 26-30 | C46: =C19+$R$3 -> 2156 | D46: =D19+$R$3 -> 2416 | E46: =E19+$R$3 -> 2588 | F46: =F19+$R$3 -> 2828 | H46: 26-30 | I46: =I19+$R$3 -> 2864 | J46: =J19+$R$3 -> 3243 | K46: =K19+$R$3 -> 3495 | L46: =L19+$R$3 -> 3845
B47: 31-35 | C47: =C20+$R$3 -> 2290 | D47: =D20+$R$3 -> 2573 | E47: =E20+$R$3 -> 2760 | F47: =F20+$R$3 -> 3020 | H47: 31-35 | I47: =I20+$R$3 -> 3059 | J47: =J20+$R$3 -> 3472 | K47: =K20+$R$3 -> 3745 | L47: =L20+$R$3 -> 4127
B48: 36-40 | C48: =C21+$R$3 -> 2502 | D48: =D21+$R$3 -> 2821 | E48: =E21+$R$3 -> 3032 | F48: =F21+$R$3 -> 3326 | H48: 36-40 | I48: =I21+$R$3 -> 3369 | J48: =J21+$R$3 -> 3835 | K48: =K21+$R$3 -> 4143 | L48: =L21+$R$3 -> 4573
B49: 41-45 | C49: =C22+$R$3 -> 2897 | D49: =D22+$R$3 -> 3282 | E49: =E22+$R$3 -> 3537 | F49: =F22+$R$3 -> 3893 | H49: 41-45 | I49: =I22+$R$3 -> 3946 | J49: =J22+$R$3 -> 4510 | K49: =K22+$R$3 -> 4882 | L49: =L22+$R$3 -> 5403
B50: 46-50 | C50: =C23+$R$3 -> 3407 | D50: =D23+$R$3 -> 3879 | E50: =E23+$R$3 -> 4191 | F50: =F23+$R$3 -> 4627 | H50: 46-50 | I50: =I23+$R$3 -> 4692 | J50: =J23+$R$3 -> 5382 | K50: =K23+$R$3 -> 5838 | L50: =L23+$R$3 -> 6475
B51: 51-55 | C51: =C24+$R$3 -> 4171 | D51: =D24+$R$3 -> 4773 | E51: =E24+$R$3 -> 5171 | F51: =F24+$R$3 -> 5726 | H51: 51-55 | I51: =I24+$R$3 -> 5809 | J51: =J24+$R$3 -> 6688 | K51: =K24+$R$3 -> 7270 | L51: =L24+$R$3 -> 8082
B52: 56-60 | C52: =C25+$R$3 -> 5291 | D52: =D25+$R$3 -> 6083 | E52: =E25+$R$3 -> 6606 | F52: =F25+$R$3 -> 7337 | H52: 56-60 | I52: =I25+$R$3 -> 7446 | J52: =J25+$R$3 -> 8604 | K52: =K25+$R$3 -> 9369 | L52: =L25+$R$3 -> 10437
B53: 61-65 | C53: =C26+$R$3 -> 6971 | D53: =D26+$R$3 -> 8047 | E53: =E26+$R$3 -> 8759 | F53: =F26+$R$3 -> 9753 | H53: 61-65 | I53: =I26+$R$3 -> 9901 | J53: =J26+$R$3 -> 11475 | K53: =K26+$R$3 -> 12516 | L53: =L26+$R$3 -> 13969
B55: 50K Maternity
B56: E Only (With PED & SD Waiting periods) | H56: E Only (No PED & SD Waiting periods)
C57: 1 Lac | D57: 2 Lacs | E57: 3 Lacs | F57: 5 Lacs | I57: 1 Lac | J57: 2 Lacs | K57: 3 Lacs | L57: 5 Lacs
B58: Upto 20 Yrs | C58: =C4+$S$3 -> 2128 | D58: =D4+$S$3 -> 2312 | E58: =E4+$S$3 -> 2434 | F58: =F4+$S$3 -> 2604 | H58: Upto 20 Yrs | I58: =I4+$S$3 -> 2629 | J58: =J4+$S$3 -> 2899 | K58: =K4+$S$3 -> 3077 | L58: =L4+$S$3 -> 3325
B59: 21-25 | C59: =C5+$S$3 -> 2752 | D59: =D5+$S$3 -> 3042 | E59: =E5+$S$3 -> 3234 | F59: =F5+$S$3 -> 3502 | H59: 21-25 | I59: =I5+$S$3 -> 3542 | J59: =J5+$S$3 -> 3966 | K59: =K5+$S$3 -> 4246 | L59: =L5+$S$3 -> 4638
B60: 26-30 | C60: =C6+$S$3 -> 2844 | D60: =D6+$S$3 -> 3149 | E60: =E6+$S$3 -> 3351 | F60: =F6+$S$3 -> 3634 | H60: 26-30 | I60: =I6+$S$3 -> 3676 | J60: =J6+$S$3 -> 4122 | K60: =K6+$S$3 -> 4418 | L60: =L6+$S$3 -> 4830
B61: 31-35 | C61: =C7+$S$3 -> 3001 | D61: =D7+$S$3 -> 3333 | E61: =E7+$S$3 -> 3553 | F61: =F7+$S$3 -> 3860 | H61: 31-35 | I61: =I7+$S$3 -> 3906 | J61: =J7+$S$3 -> 4392 | K61: =K7+$S$3 -> 4713 | L61: =L7+$S$3 -> 5162
B62: 36-40 | C62: =C8+$S$3 -> 3251 | D62: =D8+$S$3 -> 3625 | E62: =E8+$S$3 -> 3873 | F62: =F8+$S$3 -> 4219 | H62: 36-40 | I62: =I8+$S$3 -> 4271 | J62: =J8+$S$3 -> 4819 | K62: =K8+$S$3 -> 5181 | L62: =L8+$S$3 -> 5687
B63: 41-45 | C63: =C9+$S$3 -> 3715 | D63: =D9+$S$3 -> 4168 | E63: =E9+$S$3 -> 4468 | F63: =F9+$S$3 -> 4887 | H63: 41-45 | I63: =I9+$S$3 -> 4949 | J63: =J9+$S$3 -> 5612 | K63: =K9+$S$3 -> 6051 | L63: =L9+$S$3 -> 6663
B64: 46-50 | C64: =C10+$S$3 -> 4315 | D64: =D10+$S$3 -> 4870 | E64: =E10+$S$3 -> 5238 | F64: =F10+$S$3 -> 5750 | H64: 46-50 | I64: =I10+$S$3 -> 5827 | J64: =J10+$S$3 -> 6639 | K64: =K10+$S$3 -> 7175 | L64: =L10+$S$3 -> 7925
B65: 51-55 | C65: =C11+$S$3 -> 5214 | D65: =D11+$S$3 -> 5922 | E65: =E11+$S$3 -> 6390 | F65: =F11+$S$3 -> 7043 | H65: 51-55 | I65: =I11+$S$3 -> 7141 | J65: =J11+$S$3 -> 8175 | K65: =K11+$S$3 -> 8860 | L65: =L11+$S$3 -> 9815
B66: 56-60 | C66: =C12+$S$3 -> 6532 | D66: =D12+$S$3 -> 7463 | E66: =E12+$S$3 -> 8079 | F66: =F12+$S$3 -> 8939 | H66: 56-60 | I66: =I12+$S$3 -> 9067 | J66: =J12+$S$3 -> 10429 | K66: =K12+$S$3 -> 11329 | L66: =L12+$S$3 -> 12586
B67: 61-65 | C67: =C13+$S$3 -> 8507 | D67: =D13+$S$3 -> 9774 | E67: =E13+$S$3 -> 10612 | F67: =F13+$S$3 -> 11781 | H67: 61-65 | I67: =I13+$S$3 -> 11956 | J67: =J13+$S$3 -> 13807 | K67: =K13+$S$3 -> 15032 | L67: =L13+$S$3 -> 16741
B69: ESC (With PED & SD Waiting periods) | H69: ESC (No PED & SD Waiting periods)
C70: 1 Lac | D70: 2 Lacs | E70: 3 Lacs | F70: 5 Lacs | I70: 1 Lac | J70: 2 Lacs | K70: 3 Lacs | L70: 5 Lacs
B71: Upto 20 Yrs | C71: =C17+$S$3 -> 1965 | D71: =D17+$S$3 -> 2122 | E71: =E17+$S$3 -> 2225 | F71: =F17+$S$3 -> 2370 | H71: Upto 20 Yrs | I71: =I17+$S$3 -> 2391 | J71: =J17+$S$3 -> 2620 | K71: =K17+$S$3 -> 2772 | L71: =L17+$S$3 -> 2983
B72: 21-25 | C72: =C18+$S$3 -> 2495 | D72: =D18+$S$3 -> 2742 | E72: =E18+$S$3 -> 2905 | F72: =F18+$S$3 -> 3133 | H72: 21-25 | I72: =I18+$S$3 -> 3167 | J72: =J18+$S$3 -> 3527 | K72: =K18+$S$3 -> 3765 | L72: =L18+$S$3 -> 4098
B73: 26-30 | C73: =C19+$S$3 -> 2573 | D73: =D19+$S$3 -> 2833 | E73: =E19+$S$3 -> 3005 | F73: =F19+$S$3 -> 3245 | H73: 26-30 | I73: =I19+$S$3 -> 3281 | J73: =J19+$S$3 -> 3660 | K73: =K19+$S$3 -> 3912 | L73: =L19+$S$3 -> 4262
B74: 31-35 | C74: =C20+$S$3 -> 2707 | D74: =D20+$S$3 -> 2990 | E74: =E20+$S$3 -> 3177 | F74: =F20+$S$3 -> 3437 | H74: 31-35 | I74: =I20+$S$3 -> 3476 | J74: =J20+$S$3 -> 3889 | K74: =K20+$S$3 -> 4162 | L74: =L20+$S$3 -> 4544
B75: 36-40 | C75: =C21+$S$3 -> 2919 | D75: =D21+$S$3 -> 3238 | E75: =E21+$S$3 -> 3449 | F75: =F21+$S$3 -> 3743 | H75: 36-40 | I75: =I21+$S$3 -> 3786 | J75: =J21+$S$3 -> 4252 | K75: =K21+$S$3 -> 4560 | L75: =L21+$S$3 -> 4990
B76: 41-45 | C76: =C22+$S$3 -> 3314 | D76: =D22+$S$3 -> 3699 | E76: =E22+$S$3 -> 3954 | F76: =F22+$S$3 -> 4310 | H76: 41-45 | I76: =I22+$S$3 -> 4363 | J76: =J22+$S$3 -> 4927 | K76: =K22+$S$3 -> 5299 | L76: =L22+$S$3 -> 5820
B77: 46-50 | C77: =C23+$S$3 -> 3824 | D77: =D23+$S$3 -> 4296 | E77: =E23+$S$3 -> 4608 | F77: =F23+$S$3 -> 5044 | H77: 46-50 | I77: =I23+$S$3 -> 5109 | J77: =J23+$S$3 -> 5799 | K77: =K23+$S$3 -> 6255 | L77: =L23+$S$3 -> 6892
B78: 51-55 | C78: =C24+$S$3 -> 4588 | D78: =D24+$S$3 -> 5190 | E78: =E24+$S$3 -> 5588 | F78: =F24+$S$3 -> 6143 | H78: 51-55 | I78: =I24+$S$3 -> 6226 | J78: =J24+$S$3 -> 7105 | K78: =K24+$S$3 -> 7687 | L78: =L24+$S$3 -> 8499
B79: 56-60 | C79: =C25+$S$3 -> 5708 | D79: =D25+$S$3 -> 6500 | E79: =E25+$S$3 -> 7023 | F79: =F25+$S$3 -> 7754 | H79: 56-60 | I79: =I25+$S$3 -> 7863 | J79: =J25+$S$3 -> 9021 | K79: =K25+$S$3 -> 9786 | L79: =L25+$S$3 -> 10854
B80: 61-65 | C80: =C26+$S$3 -> 7388 | D80: =D26+$S$3 -> 8464 | E80: =E26+$S$3 -> 9176 | F80: =F26+$S$3 -> 10170 | H80: 61-65 | I80: =I26+$S$3 -> 10318 | J80: =J26+$S$3 -> 11892 | K80: =K26+$S$3 -> 12933 | L80: =L26+$S$3 -> 14386
B82: 75K Maternity
B83: E Only (With PED & SD Waiting periods) | H83: E Only (No PED & SD Waiting periods)
C84: 1 Lac | D84: 2 Lacs | E84: 3 Lacs | F84: 5 Lacs | I84: 1 Lac | J84: 2 Lacs | K84: 3 Lacs | L84: 5 Lacs
B85: Upto 20 Yrs | C85: =C4+$T$3 -> 2649 | D85: =D4+$T$3 -> 2833 | E85: =E4+$T$3 -> 2955 | F85: =F4+$T$3 -> 3125 | H85: Upto 20 Yrs | I85: =I4+$T$3 -> 3150 | J85: =J4+$T$3 -> 3420 | K85: =K4+$T$3 -> 3598 | L85: =L4+$T$3 -> 3846
B86: 21-25 | C86: =C5+$T$3 -> 3273 | D86: =D5+$T$3 -> 3563 | E86: =E5+$T$3 -> 3755 | F86: =F5+$T$3 -> 4023 | H86: 21-25 | I86: =I5+$T$3 -> 4063 | J86: =J5+$T$3 -> 4487 | K86: =K5+$T$3 -> 4767 | L86: =L5+$T$3 -> 5159
B87: 26-30 | C87: =C6+$T$3 -> 3365 | D87: =D6+$T$3 -> 3670 | E87: =E6+$T$3 -> 3872 | F87: =F6+$T$3 -> 4155 | H87: 26-30 | I87: =I6+$T$3 -> 4197 | J87: =J6+$T$3 -> 4643 | K87: =K6+$T$3 -> 4939 | L87: =L6+$T$3 -> 5351
B88: 31-35 | C88: =C7+$T$3 -> 3522 | D88: =D7+$T$3 -> 3854 | E88: =E7+$T$3 -> 4074 | F88: =F7+$T$3 -> 4381 | H88: 31-35 | I88: =I7+$T$3 -> 4427 | J88: =J7+$T$3 -> 4913 | K88: =K7+$T$3 -> 5234 | L88: =L7+$T$3 -> 5683
B89: 36-40 | C89: =C8+$T$3 -> 3772 | D89: =D8+$T$3 -> 4146 | E89: =E8+$T$3 -> 4394 | F89: =F8+$T$3 -> 4740 | H89: 36-40 | I89: =I8+$T$3 -> 4792 | J89: =J8+$T$3 -> 5340 | K89: =K8+$T$3 -> 5702 | L89: =L8+$T$3 -> 6208
B90: 41-45 | C90: =C9+$T$3 -> 4236 | D90: =D9+$T$3 -> 4689 | E90: =E9+$T$3 -> 4989 | F90: =F9+$T$3 -> 5408 | H90: 41-45 | I90: =I9+$T$3 -> 5470 | J90: =J9+$T$3 -> 6133 | K90: =K9+$T$3 -> 6572 | L90: =L9+$T$3 -> 7184
B91: 46-50 | C91: =C10+$T$3 -> 4836 | D91: =D10+$T$3 -> 5391 | E91: =E10+$T$3 -> 5759 | F91: =F10+$T$3 -> 6271 | H91: 46-50 | I91: =I10+$T$3 -> 6348 | J91: =J10+$T$3 -> 7160 | K91: =K10+$T$3 -> 7696 | L91: =L10+$T$3 -> 8446
B92: 51-55 | C92: =C11+$T$3 -> 5735 | D92: =D11+$T$3 -> 6443 | E92: =E11+$T$3 -> 6911 | F92: =F11+$T$3 -> 7564 | H92: 51-55 | I92: =I11+$T$3 -> 7662 | J92: =J11+$T$3 -> 8696 | K92: =K11+$T$3 -> 9381 | L92: =L11+$T$3 -> 10336
B93: 56-60 | C93: =C12+$T$3 -> 7053 | D93: =D12+$T$3 -> 7984 | E93: =E12+$T$3 -> 8600 | F93: =F12+$T$3 -> 9460 | H93: 56-60 | I93: =I12+$T$3 -> 9588 | J93: =J12+$T$3 -> 10950 | K93: =K12+$T$3 -> 11850 | L93: =L12+$T$3 -> 13107
B94: 61-65 | C94: =C13+$T$3 -> 9028 | D94: =D13+$T$3 -> 10295 | E94: =E13+$T$3 -> 11133 | F94: =F13+$T$3 -> 12302 | H94: 61-65 | I94: =I13+$T$3 -> 12477 | J94: =J13+$T$3 -> 14328 | K94: =K13+$T$3 -> 15553 | L94: =L13+$T$3 -> 17262
B96: ESC (With PED & SD Waiting periods) | H96: ESC (No PED & SD Waiting periods)
C97: 1 Lac | D97: 2 Lacs | E97: 3 Lacs | F97: 5 Lacs | I97: 1 Lac | J97: 2 Lacs | K97: 3 Lacs | L97: 5 Lacs
B98: Upto 20 Yrs | C98: =C17+$T$3 -> 2486 | D98: =D17+$T$3 -> 2643 | E98: =E17+$T$3 -> 2746 | F98: =F17+$T$3 -> 2891 | H98: Upto 20 Yrs | I98: =I17+$T$3 -> 2912 | J98: =J17+$T$3 -> 3141 | K98: =K17+$T$3 -> 3293 | L98: =L17+$T$3 -> 3504
B99: 21-25 | C99: =C18+$T$3 -> 3016 | D99: =D18+$T$3 -> 3263 | E99: =E18+$T$3 -> 3426 | F99: =F18+$T$3 -> 3654 | H99: 21-25 | I99: =I18+$T$3 -> 3688 | J99: =J18+$T$3 -> 4048 | K99: =K18+$T$3 -> 4286 | L99: =L18+$T$3 -> 4619
B100: 26-30 | C100: =C19+$T$3 -> 3094 | D100: =D19+$T$3 -> 3354 | E100: =E19+$T$3 -> 3526 | F100: =F19+$T$3 -> 3766 | H100: 26-30 | I100: =I19+$T$3 -> 3802 | J100: =J19+$T$3 -> 4181 | K100: =K19+$T$3 -> 4433 | L100: =L19+$T$3 -> 4783
B101: 31-35 | C101: =C20+$T$3 -> 3228 | D101: =D20+$T$3 -> 3511 | E101: =E20+$T$3 -> 3698 | F101: =F20+$T$3 -> 3958 | H101: 31-35 | I101: =I20+$T$3 -> 3997 | J101: =J20+$T$3 -> 4410 | K101: =K20+$T$3 -> 4683 | L101: =L20+$T$3 -> 5065
B102: 36-40 | C102: =C21+$T$3 -> 3440 | D102: =D21+$T$3 -> 3759 | E102: =E21+$T$3 -> 3970 | F102: =F21+$T$3 -> 4264 | H102: 36-40 | I102: =I21+$T$3 -> 4307 | J102: =J21+$T$3 -> 4773 | K102: =K21+$T$3 -> 5081 | L102: =L21+$T$3 -> 5511
B103: 41-45 | C103: =C22+$T$3 -> 3835 | D103: =D22+$T$3 -> 4220 | E103: =E22+$T$3 -> 4475 | F103: =F22+$T$3 -> 4831 | H103: 41-45 | I103: =I22+$T$3 -> 4884 | J103: =J22+$T$3 -> 5448 | K103: =K22+$T$3 -> 5820 | L103: =L22+$T$3 -> 6341
B104: 46-50 | C104: =C23+$T$3 -> 4345 | D104: =D23+$T$3 -> 4817 | E104: =E23+$T$3 -> 5129 | F104: =F23+$T$3 -> 5565 | H104: 46-50 | I104: =I23+$T$3 -> 5630 | J104: =J23+$T$3 -> 6320 | K104: =K23+$T$3 -> 6776 | L104: =L23+$T$3 -> 7413
B105: 51-55 | C105: =C24+$T$3 -> 5109 | D105: =D24+$T$3 -> 5711 | E105: =E24+$T$3 -> 6109 | F105: =F24+$T$3 -> 6664 | H105: 51-55 | I105: =I24+$T$3 -> 6747 | J105: =J24+$T$3 -> 7626 | K105: =K24+$T$3 -> 8208 | L105: =L24+$T$3 -> 9020
B106: 56-60 | C106: =C25+$T$3 -> 6229 | D106: =D25+$T$3 -> 7021 | E106: =E25+$T$3 -> 7544 | F106: =F25+$T$3 -> 8275 | H106: 56-60 | I106: =I25+$T$3 -> 8384 | J106: =J25+$T$3 -> 9542 | K106: =K25+$T$3 -> 10307 | L106: =L25+$T$3 -> 11375
B107: 61-65 | C107: =C26+$T$3 -> 7909 | D107: =D26+$T$3 -> 8985 | E107: =E26+$T$3 -> 9697 | F107: =F26+$T$3 -> 10691 | H107: 61-65 | I107: =I26+$T$3 -> 10839 | J107: =J26+$T$3 -> 12413 | K107: =K26+$T$3 -> 13454 | L107: =L26+$T$3 -> 14907

Sheet Drop Down Options
A1: Cities | B1: Zone | D1: Industries | G1: Insurer Names | I1: Policy Type | K1: Sum Insured | M1: Family Definition | O1: Room Rent | Q1: Maternity | S1: PY Broker | U1: Maternity
A2: Agra | B2: Zone B | D2: Agricultural commodity trading | E2: Good to proceed | G2: Acko General Insurance | I2: Fresh | K2: 1 Lac | M2: E Only | O2: Normal - 2% of SI (Max 7.5K), ICU - No Limit | Q2: No | S2: Healthysure | U2: 0.075
A3: Ahmedabad | B3: Zone A | D3: Auto components manufacturing | E3: Good to proceed | G3: Aditya Birla Health Insurance | I3: Rollover | K3: 2 Lac | M3: ESC | O3: Normal - No Limit, ICU - No Limit | Q3: Normal - 30K, C Section - 30K | S3: Others | U3: 0.1
A4: Allahabad (Prayagraj) | B4: Zone B | D4: Bakery and confectionery | E4: Good to proceed | G4: Bajaj General Insurance | I4: Own Renewal | K4: 3 Lac | Q4: Normal - 50K, C Section - 50K | U4: 0.15
A5: Amritsar | B5: Zone B | D5: Building materials manufacturing | E5: Good to proceed | G5: Care Health Insurance | K5: 5 Lac | Q5: Normal - 75K, C Section - 75K | U5: 0.2
A6: Aurangabad | B6: Zone B | D6: Chemical manufacturing (small scale) | E6: Good to proceed | G6: Cholamandalam MS General Insurance | U6: 0.25
A7: Bengaluru | B7: Zone B | D7: Construction contractors | E7: Good to proceed | G7: Future Generali India Insurance
A8: Bhopal | B8: Zone B | D8: Dairy processing | E8: Good to proceed | G8: Go Digit General Insurance
A9: Chandigarh | B9: Zone B | D9: Digital marketing agencies | E9: Good to proceed | G9: HDFC ERGO General Insurance
A10: Chennai | B10: Zone B | D10: Edible oil processing | E10: Good to proceed | G10: ICICI Lombard General Insurance
A11: Coimbatore | B11: Zone B | D11: Education and training institutes | E11: Good to proceed | G11: Kotak Mahindra General Insurance
A12: Delhi | B12: Zone A | D12: Electrical equipment manufacturing | E12: Good to proceed | G12: Liberty General Insurance
A13: Faridabad | B13: Zone A | D13: Electronics assembly | E13: Good to proceed | G13: Magma General Insurance
A14: Ghaziabad | B14: Zone A | D14: Event management companies | E14: Good to proceed | G14: ManipalCigna Health Insurance
A15: Gurugram | B15: Zone A | D15: Fabrication and metal works | E15: Good to proceed | G15: National Insurance Company
A16: Guwahati | B16: Zone B | D16: FMCG distributors | E16: Good to proceed | G16: Niva Bupa Health Insurance
A17: Gwalior | B17: Zone B | D17: Food processing | E17: Good to proceed | G17: Reliance General Insurance
A18: Howrah | B18: Zone A | D18: Footwear manufacturing | E18: Good to proceed | G18: Royal Sundaram General Insurance
... A26: Kalyan–Dombivli | B26: Zone A | D26: Industrial repair and maintenance | E26: Good to proceed | G26: Others
A27: Kanpur | B27: Zone B | D27: Industrial tooling | E27: Good to proceed
A28: Kolkata | B28: Zone A | D28: Interior design and fit-out services | E28: Good to proceed
A29: Lucknow | B29: Zone B | D29: IT services and consulting | E29: Good to proceed
A30: Ludhiana | B30: Zone B | D30: Leather goods manufacturing | E30: Good to proceed
A31: Madurai | B31: Zone B | D31: Logistics and transportation companies | E31: Good to proceed
A32: Meerut | B32: Zone B | D32: Machine parts manufacturing | E32: Good to proceed
A33: Mumbai | B33: Zone A | D33: Marketing and advertising agencies | E33: Good to proceed
A34: Mysuru | B34: Zone B | D34: Media | E34: Decline List
A35: Nagpur | B35: Zone B | D35: Military/Paramilitary/Law Enforcement | E35: Decline List
A36: Nashik | B36: Zone B | D36: NGO | E36: Decline List
A37: North 24 Parganas | B37: Zone A | D37: Paint and coating businesses | E37: Good to proceed
A38: Patna | B38: Zone B | D38: Paper and packaging manufacturing | E38: Good to proceed
... A56: Others | B56: Zone B | D56: Others | E56: Good to proceed
