Workbook
Name AdditionsandDeletions: 'GHI DB'!$BG$3:$BH$3
Name AYUSHTreatments: 'GHI DB'!$BA$3:$BB$3
Name CashlessAuthorizationTAT: 'GHI DB'!$BO$3
Name CashlessNetwork: 'GHI DB'!$W$3
Name ClaimsIntermediary: 'GHI DB'!$Y$3
Name CoPay: 'GHI DB'!$M$3:$R$3
Name CorporateBuffer: 'GHI DB'!$S$3:$T$3
Name COVID19Coverage: 'GHI DB'!$AC$3
Name DayCareTreatments: 'GHI DB'!$AA$3
Name DentalCoverage: 'GHI DB'!$AM$3
Name DiseaseCapping: 'GHI DB'!$AB$3
Name DoctorTeleconsultations: 'GHI DB'!$AG$3
Name DomicillaryHospitalization: 'GHI DB'!$AD$3
Name EmergencyAirAmbulance: 'GHI DB'!$AW$3:$AW$3
Name EmergencyAmbulance: 'GHI DB'!$AV$3
Name FamilyDefinition: 'GHI DB'!$C$3:$F$3
Name features: 'GHI DB'!$B$1:$BS$1
Name GHI_Quotes: 'High Level Quotes - Working'!$B$3:$N$15
Name GPA_features: 'GPA DB'!$D$3:$O$3
Name GPA_Insurers: 'GPA DB'!$A$4:$A$9
Name GPA_number_of_lives_expiring: 'High Level Quotes - Working'!$T$22
Name GPA_opt1_number_of_employees_expiring: 'High Level Quotes - Working'!$T$22
Name GPA_opt1_number_of_employees_renewal: 'High Level Quotes - Working'!$R$22
Name GPA_opt1_number_of_lives_renewal: 'High Level Quotes - Working'!$S$22
Name GPA_opt2_number_of_employees_expiring: 'High Level Quotes - Working'!$T$24
Name GPA_opt2_number_of_employees_renewal: 'High Level Quotes - Working'!$R$24
Name GPA_opt2_number_of_lives_renewal: 'High Level Quotes - Working'!$S$24
Name GPA_Quotes: 'High Level Quotes - Working'!$B$18:$N$25
Name GPA_Quotes: 'High Level Quotes - Slide 1'!$B$13:$N$18
Name GTLI_Features: 'GTLI DB'!$D$7:$J$7
Name GTLI_number_of_employees_expiring: 'High Level Quotes - Working'!$T$32
Name GTLI_number_of_lives_expiring: 'High Level Quotes - Working'!$T$32
Name GTLI_opt1_number_of_employees_renewal: 'High Level Quotes - Working'!$R$32
Name GTLI_opt2_number_of_employees_renewal: 'High Level Quotes - Working'!$R$34
Name GTLI_Quotes: 'High Level Quotes - Working'!$B$28:$N$35
Name GTLI_Quotes: 'High Level Quotes - Slide 1'!$B$22:$N$27
Name HealthCheckups: 'GHI DB'!$AJ$3
Name InitialWaitingPeriod: 'GHI DB'!$AS$3
Name InpatientHospitalization: 'GHI DB'!$Z$3
Name Know_Your_Insurers: 'Policy & Technical Features'!$Q$27:$Z$42
Name Know_Your_Insurers: 'Policy & Technical Features - o'!$Q$26:$Z$41
Name LasikEyeSurgery: 'GHI DB'!$BE$3
Name Logo: 'GHI DB'!$B$3
Name MaternityCover: 'GHI DB'!$AN$3:$AO$3
Name MaternityWaitingPeriod: 'GHI DB'!$AP$3:$AQ$3
Name MedicinesDelivery: 'GHI DB'!$AL$3
Name MidtermAdditionofDependents: 'GHI DB'!$BK$3:$BL$3
Name Midtermadditionofparents: 'GHI DB'!$BM$3:$BN$3
Name MidtermIncreaseinSumInsured: 'GHI DB'!$BI$3:$BJ$3
Name ModernTreatmentsandRoboticSurgeries: 'GHI DB'!$AX$3
Name number_of_employees_expiring: 'High Level Quotes - Working'!$T$6
Name number_of_employees_expiring: 'High Level Quotes - Slide 1'!$U$6
Name number_of_lives_expiring: 'High Level Quotes - Working'!$U$6
Name number_of_lives_expiring: 'High Level Quotes - Slide 1'!$V$6
Name opt1_number_of_employees_renewal: 'High Level Quotes - Working'!$R$6
Name opt1_number_of_employees_renewal: 'High Level Quotes - Slide 1'!$R$6
Name opt1_number_of_lives_renewal: 'High Level Quotes - Working'!$S$6
Name opt1_number_of_lives_renewal: 'High Level Quotes - Slide 1'!$S$6
Name opt2_number_of_employees_renewal: 'High Level Quotes - Working'!$R$8
Name opt2_number_of_employees_renewal: 'High Level Quotes - Slide 1'!$R$7

Sheet High Level Quotes - Slide 1
D2: Group Health Insurance | P2: File Path of Proposal Deck | AH2: =D2 -> Group Health Insurance
D3: Options for Renewal | M3: Previous Policy | P3: C:\Users\shali\Downloads\Key Policy Features\Product Deck Editable Slides (In Use).pptx | AH3: Options for Renewal | AQ3: Incumbent Policy
D4: ='Policy & Technical Features - o'!F6 -> Manipal Cigna Standard Rater | G4: ='Policy & Technical Features - o'!H6 -> SBI General | J4: ='Policy & Technical Features - o'!J6 -> Manipal Cigna | M4: ='Policy & Technical Features - o'!L6 -> IFFCO Tokio | P4: Our Options | R4: No. of Employees (renewal) | S4: No. of Lives (renewal) | T4: Premium (excl GST) | U4: No. of Employees (expiring policy) | V4: No. of Lives (expiring policy) | AF4: Our Options | AH4: =D4 -> Manipal Cigna Standard Rater | AK4: =G4 -> SBI General | AN4: =J4 -> Manipal Cigna | AQ4: =M4 -> IFFCO Tokio
D5: Total Premium (excl. GST) | E5: Premium per Life | G5: Total Premium (excl. GST) | H5: Premium per Life | J5: Total Premium (excl. GST) | K5: Premium per Life | M5: Total Premium (excl. GST) | N5: Premium per Life | AH5: Total Premium (excl. GST) | AI5: Premium per Life | AK5: Total Premium (excl. GST) | AL5: Premium per Life | AN5: Total Premium (excl. GST) | AO5: Premium per Life | AQ5: Total Premium (excl. GST) | AR5: Premium per Life
B6: I. Expiring Terms (SI: 2 L) | D6: =CONCATENATE(TRUNC(T6,0), CHAR(10), "(", S6, " lives)") -> 2000000 (450 lives) | E6: =T6/opt1_number_of_lives_renewal -> 4444.4444 | G6: 20,00,000 | J6: 20,00,000 | M6: 20,00,000 | P6: =B6 -> I. Expiring Terms (SI: 2 L) | R6: 300 | S6: 450 | T6: 2000000 | U6: 200 | V6: 300 | AF6: I. Expiring Terms (SI: 2 L) | AH6: =D6 -> 2000000 (450 lives) | AI6: =AH6/opt1_number_of_lives_renewal -> #VALUE! | AK6: =G6 -> 20,00,000 | AL6: =AK6/opt1_number_of_lives_renewal -> #VALUE! | AN6: =J6 -> 20,00,000 | AO6: =AN6/opt1_number_of_lives_renewal -> #VALUE! | AQ6: =M6 -> 20,00,000 | AR6: =AQ6/number_of_lives_expiring -> #VALUE!
B7: II. ESC with 0% Co-Pay (SI : 5 L) | D7: =CONCATENATE(TRUNC(T7,0), CHAR(10), "(", S7, " lives)") -> 2500000 (450 lives) | E7: =T7/opt1_number_of_lives_renewal -> 5555.5556 | G7: 30,00,000 | J7: 30,00,000 | P7: =B7 -> II. ESC with 0% Co-Pay (SI : 5 L) | R7: =opt1_number_of_employees_renewal -> 300 | S7: 450 | T7: 2500000 | AF7: II. ESC with 0% Co-Pay (SI : 5 L) | AH7: =D7 -> 2500000 (450 lives) | AI7: =AH7/opt2_number_of_lives_renewal -> #VALUE! | AK7: =G7 -> 30,00,000 | AL7: =AK7/opt2_number_of_lives_renewal -> #VALUE! | AN7: =J7 -> 30,00,000 | AO7: =AN7/opt2_number_of_lives_renewal -> #VALUE!
B8: III. ESCP with 0% Co-Pay (SI : 3 L) | D8: =CONCATENATE(TRUNC(T8,0), CHAR(10), "(", S8, " lives)") -> 3000000 (600 lives) | E8: =T8/opt1_number_of_lives_renewal -> 6666.6667 | G8: 40,00,000 | J8: 40,00,000 | P8: =B8 -> III. ESCP with 0% Co-Pay (SI : 3 L) | R8: =opt1_number_of_employees_renewal -> 300 | S8: 600 | T8: 3000000 | AF8: III. ESCP with 0% Co-Pay (SI : 3 L) | AH8: =D8 -> 3000000 (600 lives) | AI8: =AH8/opt3_number_of_lives_renewal -> #VALUE! | AK8: =G8 -> 40,00,000 | AL8: =AK8/opt3_number_of_lives_renewal -> #VALUE! | AN8: =J8 -> 40,00,000 | AO8: =AN8/opt3_number_of_lives_renewal -> #VALUE!
B9: IV. ESCP with 0% Co-Pay (SI : 5 L) | D9: =CONCATENATE(TRUNC(T9,0), CHAR(10), "(", S9, " lives)") -> 4000000 (600 lives) | E9: =T9/opt1_number_of_lives_renewal -> 8888.8889 | G9: 50,00,000 | J9: 50,00,000 | P9: =B9 -> IV. ESCP with 0% Co-Pay (SI : 5 L) | R9: =opt1_number_of_employees_renewal -> 300 | S9: 600 | T9: 4000000 | AF9: IV. ESCP with 0% Co-Pay (SI : 5 L) | AH9: =D9 -> 4000000 (600 lives) | AI9: =AH9/opt4_number_of_lives_renewal -> #VALUE! | AK9: =G9 -> 50,00,000 | AL9: =AK9/opt4_number_of_lives_renewal -> #VALUE! | AN9: =J9 -> 50,00,000 | AO9: =AN9/opt4_number_of_lives_renewal -> #VALUE!
B10: V. ESCP with 0% Co-Pay (SI : 5 L) | D10: =CONCATENATE(TRUNC(T10,0), CHAR(10), "(", S10, " lives)") -> 5000000 (600 lives) | E10: =T10/opt1_number_of_lives_renewal -> 11111.111 | G10: 60,00,000 | J10: 60,00,000 | P10: =B10 -> V. ESCP with 0% Co-Pay (SI : 5 L) | R10: =opt1_number_of_employees_renewal -> 300 | S10: 600 | T10: 5000000 | AF10: V. ESCP with 0% Co-Pay (SI : 5 L) | AH10: =D10 -> 5000000 (600 lives) | AI10: =AH10/opt5_number_of_lives_renewal -> #VALUE! | AK10: =G10 -> 60,00,000 | AL10: =AK10/opt5_number_of_lives_renewal -> #VALUE! | AN10: =J10 -> 60,00,000 | AO10: =AN10/opt5_number_of_lives_renewal -> #VALUE!
D13: Group Personal Accident Insurance | AH13: Group Personal Accident Insurance
D14: Options for Renewal | M14: Incumbent Insurer | AH14: Options for Renewal | AQ14: Incumbent Policy
B15: Our Options | D15: Insurer 1 | G15: Insurer 2 | J15: Insurer 3 | M15: Insurer 4 | AF15: Our Options | AH15: Insurer 1 | AK15: Insurer 2 | AN15: Insurer 3 | AQ15: Insurer 4
D16: Total Premium (excl. GST) | E16: Premium per Employee | G16: Total Premium (excl. GST) | H16: Premium per Employee | J16: Total Premium (excl. GST) | K16: Premium per Employee | M16: Total Premium (excl. GST) | N16: Premium per Employee | AH16: Total Premium (excl. GST) | AI16: Premium per Employee | AK16: Total Premium (excl. GST) | AL16: Premium per Employee | AN16: Total Premium (excl. GST) | AO16: Premium per Employee | AQ16: Total Premium (excl. GST) | AR16: Premium per Employee
B17: I. Expiring Terms (SI: 10 L) | D17: 2,00,000 | G17: 2,00,000 | J17: 2,00,000 | M17: 2,00,000 | N17: =M17/number_of_employees_expiring -> #VALUE! | AF17: I. Expiring Terms (SI: 10 L) | AH17: 2,00,000 | AI17: =AH17/opt1_number_of_employees_renewal -> #VALUE! | AK17: 2,00,000 | AL17: =AK17/opt1_number_of_employees_renewal -> #VALUE! | AN17: 2,00,000 | AO17: =AN17/opt1_number_of_employees_renewal -> #VALUE! | AQ17: 2,00,000 | AR17: =AQ17/number_of_employees_expiring -> #VALUE!
B18: II. SI: 25 L | D18: 4,00,000 | G18: 4,00,000 | J18: 4,00,000 | AF18: II. SI: 25 L | AH18: 4,00,000 | AI18: =AH18/opt1_number_of_employees_renewal -> #VALUE! | AK18: 4,00,000 | AL18: =AK18/opt1_number_of_employees_renewal -> #VALUE! | AN18: 4,00,000 | AO18: =AN18/opt1_number_of_employees_renewal -> #VALUE!
D22: Group Term Life Insurance | AH22: Group Term Life Insurance
D23: Options for Renewal | M23: Incumbent Policy | AH23: Options for Renewal | AQ23: Incumbent Policy
B24: Our Options | D24: Insurer 1 | G24: Insurer 2 | J24: Insurer 3 | M24: Insurer 4 | AF24: Our Options | AH24: Insurer 1 | AK24: Insurer 2 | AN24: Insurer 3 | AQ24: Insurer 4
D25: Total Premium (excl. GST) | E25: Premium per Employee | G25: Total Premium (excl. GST) | H25: Premium per Employee | J25: Total Premium (excl. GST) | K25: Premium per Employee | M25: Total Premium (excl. GST) | N25: Premium per Employee | AH25: Total Premium (excl. GST) | AI25: Premium per Employee | AK25: Total Premium (excl. GST) | AL25: Premium per Employee | AN25: Total Premium (excl. GST) | AO25: Premium per Employee | AQ25: Total Premium (excl. GST) | AR25: Premium per Employee
B26: I. Expiring Terms (SI: 10 L) | D26: 4,00,000 | G26: 4,00,000 | J26: 4,00,000 | M26: 4,00,000 | N26: =M26/number_of_employees_expiring -> #VALUE! | AF26: I. Expiring Terms (SI: 10 L) | AH26: 4,00,000 | AI26: =AH26/opt1_number_of_employees_renewal -> #VALUE! | AK26: 4,00,000 | AL26: =AK26/opt1_number_of_employees_renewal -> #VALUE! | AN26: 4,00,000 | AO26: =AN26/opt1_number_of_employees_renewal -> #VALUE! | AQ26: 4,00,000 | AR26: =AQ26/number_of_employees_expiring -> #VALUE!
B27: II. SI: 25 L | D27: 8,00,000 | G27: 8,00,000 | J27: 8,00,000 | AF27: II. SI: 25 L | AH27: 8,00,000 | AI27: =AH27/opt1_number_of_employees_renewal -> #VALUE! | AK27: 8,00,000 | AL27: =AK27/opt1_number_of_employees_renewal -> #VALUE! | AN27: 8,00,000 | AO27: =AN27/opt1_number_of_employees_renewal -> #VALUE!

Sheet SOP
B2: DISCLAIMER
B3: =B1+1 -> 1 | C3: Do not change any formula in the Excel file or add/delete/hide/unhide/shift any sheets till you complete running the automation and are satisfied with the output.
B4: =B3+1 -> 2 | C4: Do not meddle with any of the data validation/macros/formatting in this Excel file.
B5: =B4+1 -> 3 | C5: Do not change the order of the slides in the Proposal Deck before running the automation. You can change the order of slides only on completion of the steps in the SOP mentioned below.
B6: =B5+1 -> 4 | C6: Similarly, do not add/delete any slides in the proposal deck before you complete the SOP mentioned below.
B9: SOP for running automation for Quotes, Policy Features, and Technical Parameters.
B10: 1 | C10: Before beginning, move the Template folder containing this file and the Proposal Deck to the Downloads folder of your PC. If this is not done at this step, close this file, move the folder to Downloads and resume with your work.
B11: =B10+1 -> 2 | C11: In the 'Inputs' tab, enter the following things (All the cells highlighted in blue need to be filled): 1. Name of the client (brand name) - Cell B5 2. File Path of the Proposal Deck - Cell B9 - Go to the Folder containing the Proposal Deck (in Downloads) --> Click on Proposal Deck --> Ctrl+Shift+C (this will copy the file path) --> Paste this in cell B9 3. The top 3 renewal insurers for GHI + expiring insurer in cells B14 to E14. 4. The number of employees and lives in the expiring policy - Cells F25 and G25 5. The various policy options for GHI in cells B25 to B34 along with the number of lives in each plan - Use short forms like ESC, ESCP, SI, etc. as per your convenience 6. The premiums (excluding GST) for each of the options in the area alongside the table 7. Repeat steps 4 to 6 for GPA and GTLI (if applicable)
B12: =B11+1 -> 3 | C12: Make copies of GHI Policy Features (Option 1) for as many options as you're giving the client. You can also rename with sheet with the option. For example: GHI Policy Features (ESC - 5 Lakh SI)
B13: =B12+1 -> 4 | C13: Enter the following things in each of these sheets: Policy Period, Net Premium for each insurer, Sum Insured for each option, Number of Lives (for the copied sheets)
B14: =B13+1 -> 5 | C14: Now, in each of the sheets of 'GHI Policy Features), as per the family definition, delete rows all/any of 17, 18, or 19 from the table if required. For example, if it is an Employee only policy, delete all 3 rows. If it is an ESC policy, delete only row 19. Recolour the red cells to the color of the cells above it (light grey)
B15: =B14+1 -> 6 | C15: Verify whether the rest if the features populated in the sheet are as desired by the client.
B16: =B15+1 -> 7 | C16: Now, go to the 'Policy & Technical Features' tab and start selecting the features which you want to show in the Policy Features comparison.
B17: =B16+1 -> 8 | C17: For Family Definition, select the appropriate option as desired by the GM/Client
B18: =B17+1 -> 9 | C18: For other features, following is the methodology: a. First, select the feature in column B from the dropdown list (Use Alt+Down Arrow key to open the dropdown) b. Based on what you select in Column B, you will get option/benefit in the dropdown list in Column D. Select the desired option/benefit. The cells from Column F to L will get populated automatically based on the insurers chosen as and when you select the desired feature to be shown. Please note that you need to select only 9 features apart from Family Definition which you would like to display in the Proposal Deck.
B19: =B18+1 -> 10 | C19: The Technical Parameters (Insurer Credentials) will automatically get populated.
B20: =B19+1 -> 11 | C20: Once the 'GHI Policy Features' and 'Know your Insurer - Credentials' tabs are final, select all the sheets which you want to send to the client (Policy Features of all options + Know your Insurers), click on the '…' button on the 'GHI Policy Features' tab. By doing this, a new Excel file with the selected tabs will be created to be sent to the client. The file will be saved in the same folder as this Excel file.
B21: =B20+1 -> 12 | C21: Open the new Excel file from the folder bearing the name 'Client GHI Quotes.' On every tab in that workbook, do the following: Ctrl+A Ctrl+C Ctrl+Alt+V Press Enter Next, delete the content from cell A1 of the 'Know your Insurer - Credentials' tab in the new workbook. Delete the button on the 'GHI Policy Features (Option 1)' sheet
B22: =B21+1 -> 13 | C22: Go to the tab 'High Level Quotes - Working' and verify whether all the details are numbers have been populated as required. Once you have verified everything: Click on the button: Send GHI Quotes to Proposal Deck Click on the button: Send GPA Quotes to Proposal Deck Click on the button: Send GTLI Quotes to Proposal Deck
... B27: =B26+1 -> 18 | C27: Once everything is final, save all the files, and transfer the files to the relevant client's folder on Sharepoint

Sheet Inputs
B1: Date
B2: 45177
B4: Name of the Client
B5: Bandana Gupta Class
B8: Proposal Deck File Path
B9: C:\Users\shali\Downloads\ABCD\Healthysure Proposal Deck.pptx
B12: GHI Insurer Options
B13: PROPOSED INSURERS | E13: PREVIOUS INSURER
B14: Manipal Cigna Standard Rater | C14: SBI General | D14: Manipal Cigna | E14: IFFCO Tokio
B19: GHI Quotes
B21: File Path of Proposal Deck | I21: Options for Renewal | L21: Previous Policy
I22: =B14 -> Manipal Cigna Standard Rater | J22: =C14 -> SBI General | K22: =D14 -> Manipal Cigna | L22: =E14 -> IFFCO Tokio
B23: Proposed Options | D23: No. of Employees (renewal) | E23: No. of Lives (renewal) | F23: No. of Employees (expiring policy) | G23: No. of Lives (expiring policy) | I23: Total Premium (₹) | J23: Total Premium (₹) | K23: Total Premium (₹) | L23: Total Premium (₹)
B25: I. ESCP with 10% Co-pay (SI: 10 L) | D25: 6 | E25: 6 | F25: 20 | G25: 30 | I25: 4,55,316 | J25: 5,19,638 | K25: 5,26,249 | L25: 3,13,559
B27: II. ESC with 0% Co-Pay (SI : 5 L) | D27: =D25 -> 6 | E27: z | F27: - | I27: 25,00,000 | J27: 30,00,000 | K27: 30,00,000 | L27: -
B29: III. ESCP with 0% Co-Pay (SI : 3 L) | D29: =D25 -> 6 | E29: 800 | I29: 30,00,000 | J29: 40,00,000 | K29: 40,00,000 | L29: -
B31: IV. ESCP with 0% Co-Pay (SI : 5 L) | D31: =D25 -> 6 | E31: 800 | I31: 50,00,000 | J31: 50,00,000 | K31: 50,00,000 | L31: -
B33: V. ESCP with 0% Co-Pay (SI : 5 L) | D33: =D25 -> 6 | E33: 800 | I33: 60,00,000 | J33: 60,00,000 | K33: 60,00,000 | L33: -
B37: GPA Insurer Options
B38: PROPOSED INSURERS | E38: PREVIOUS INSURER
B39: Magma HDI (Basic Plan) - NEE Group | C39: Magma HDI (Pro Plan) - NEE Group | D39: Go Digit (Pro Plan) | E39: IFFCO Tokio ( Pro Plan)
B41: GPA Quotes
B43: Proposed Options | D43: No. of Employees (renewal) | F43: No. of Employees (expiring policy) | I43: =B39 -> Magma HDI (Basic Plan) - NEE Group | J43: =C39 -> Magma HDI (Pro Plan) - NEE Group | K43: =D39 -> Go Digit (Pro Plan) | L43: =E39 -> IFFCO Tokio ( Pro Plan)
I44: Total Premium (₹) | J44: Total Premium (₹) | K44: Total Premium (₹) | L44: Total Premium (₹)
B45: I. Expiring Terms (SI: 10 L) | D45: 30 | F45: 20 | I45: 20,00,000 | J45: 20,00,000 | K45: 20,00,000 | L45: 20,00,000
B47: II. SI: 25 L | D47: =D45 -> 30 | F47: - | I47: 39,00,000 | J47: 30,00,000 | K47: 30,00,000 | L47: -
B51: GTLI Insurer Options
B52: PROPOSED INSURERS | E52: PREVIOUS INSURER
B53: CALI (Exclusive) | C53: CALI (Exclusive) | D53: HDFC Life | E53: Pramerica Life
B55: GTLI Quotes
B57: Proposed Options | D57: No. of Employees (renewal) | F57: No. of Employees (expiring policy) | I57: =B53 -> CALI (Exclusive) | J57: =C53 -> CALI (Exclusive) | K57: =D53 -> HDFC Life | L57: =E53 -> Pramerica Life
I58: Total Premium (₹) | J58: Total Premium (₹) | K58: Total Premium (₹) | L58: Total Premium (₹)
B59: I. Expiring Terms (SI: 10 L) | D59: 300 | F59: 150 | I59: 25,00,000 | J59: 20,00,000 | K59: 20,00,000 | L59: 20,00,000
B61: II. SI: 25 L | D61: =D59 -> 300 | F61: - | I61: 35,00,000 | J61: 30,00,000 | K61: 30,00,000 | L61: -
B68: OPD Options
B69: PROPOSED INSURERS
B70: Visit SI - 5000 | C70: Even SI - 5000 | D70: Even SI - 5000

Sheet Premium Breakdown
B2: Premium of Recommended Option: | M2: Breakdown of Premium per Life
B3: 300 | D3: x | F3: 6000 | H3: = | J3: 11800000 | M3: 200 | N3: + | O3: 50 | P3: + | Q3: 50
B4: Premium per Life | F4: Number of Lives | J4: Total Premium | M4: Claims per life | O4: Proposed Terms Impact | Q4: Inflation and Buffer

Sheet High Level Quotes - Working
G1: ₹
P2: File Path of Proposal Deck
D3: Options for Renewal | M3: Previous Policy | P3: =Inputs!B9 -> C:\Users\shali\Downloads\ABCD\Healthysure Proposal Deck.pptx
D4: ='GHI Features (Option 1)'!G8 -> HDFC Ergo | G4: ='GHI Features (Option 1)'!H8 -> Manipal Cigna (Gig Exclusive) | J4: ='GHI Features (Option 1)'!I8 -> Manipal Cigna (SME Exclusive) | M4: ='GHI Features (Option 1)'!J8 -> Care Health | P4: Proposed Options | R4: No. of Employees (renewal) | S4: No. of Lives (renewal) | T4: No. of Employees (expiring policy) | U4: No. of Lives (expiring policy)
D5: Total Premium (₹) | E5: Avg. Premium/Life | G5: Total Premium (₹) | H5: Avg. Premium/Life | J5: Total Premium (₹) | K5: Avg. Premium/Life | M5: Total Premium (₹) | N5: Avg. Premium/Life
B6: =Inputs!B25 -> I. ESCP with 10% Co-pay (SI: 10 L) | D6: =Inputs!I25 | E6: =D6/opt1_number_of_lives_renewal -> #VALUE! | G6: =Inputs!J25 -> 5,19,638 | H6: =G6/opt1_number_of_lives_renewal -> #VALUE! | J6: =Inputs!K25 -> 5,26,249 | K6: =J6/opt1_number_of_lives_renewal -> #VALUE! | M6: =Inputs!L25 -> 3,13,559 | N6: =M6/number_of_lives_expiring -> #VALUE! | P6: =Inputs!B25 -> I. ESCP with 10% Co-pay (SI: 10 L) | R6: =Inputs!D25 -> 6 | S6: =Inputs!E25 -> 6 | T6: =Inputs!F25 -> 20 | U6: =Inputs!G25 -> 30
D7: =CONCATENATE("(", opt1_number_of_lives_renewal, " lives)") -> (6 lives) | G7: =CONCATENATE("(", opt1_number_of_lives_renewal, " lives)") -> (6 lives) | J7: =CONCATENATE("(", opt1_number_of_lives_renewal, " lives)") -> (6 lives) | M7: =CONCATENATE("(", number_of_lives_expiring, " lives)") -> (30 lives)
B8: =Inputs!B27 -> II. ESC with 0% Co-Pay (SI : 5 L) | D8: =Inputs!I27 -> 25,00,000 | E8: =D8/opt2_number_of_lives_renewal -> #VALUE! | G8: =Inputs!J27 -> 30,00,000 | H8: =G8/opt2_number_of_lives_renewal -> #VALUE! | J8: =Inputs!K27 -> 30,00,000 | K8: =J8/opt2_number_of_lives_renewal -> #VALUE! | M8: - | N8: - | P8: =Inputs!B27 -> II. ESC with 0% Co-Pay (SI : 5 L) | R8: =Inputs!D27 -> 6 | S8: =Inputs!E27 -> z | T8: -
D9: =CONCATENATE("(", opt2_number_of_lives_renewal, " lives)") -> (z lives) | G9: =CONCATENATE("(", opt2_number_of_lives_renewal, " lives)") -> (z lives) | J9: =CONCATENATE("(", opt2_number_of_lives_renewal, " lives)") -> (z lives)
B10: =Inputs!B29 -> III. ESCP with 0% Co-Pay (SI : 3 L) | D10: =Inputs!I29 -> 30,00,000 | E10: =D10/opt3_number_of_lives_renewal -> #VALUE! | G10: =Inputs!J29 -> 40,00,000 | H10: =G10/opt3_number_of_lives_renewal -> #VALUE! | J10: =Inputs!K29 -> 40,00,000 | K10: =J10/opt3_number_of_lives_renewal -> #VALUE! | M10: - | N10: - | P10: =Inputs!B29 -> III. ESCP with 0% Co-Pay (SI : 3 L) | R10: =Inputs!D29 -> 6 | S10: =Inputs!E29 -> 800
D11: =CONCATENATE("(", opt3_number_of_lives_renewal, " lives)") -> (800 lives) | G11: =CONCATENATE("(", opt3_number_of_lives_renewal, " lives)") -> (800 lives) | J11: =CONCATENATE("(", opt3_number_of_lives_renewal, " lives)") -> (800 lives)
B12: =Inputs!B31 -> IV. ESCP with 0% Co-Pay (SI : 5 L) | D12: =Inputs!I31 -> 50,00,000 | E12: =D12/opt4_number_of_lives_renewal -> #VALUE! | G12: =Inputs!J31 -> 50,00,000 | H12: =G12/opt4_number_of_lives_renewal -> #VALUE! | J12: =Inputs!K31 -> 50,00,000 | K12: =J12/opt4_number_of_lives_renewal -> #VALUE! | M12: - | N12: - | P12: =Inputs!B31 -> IV. ESCP with 0% Co-Pay (SI : 5 L) | R12: =Inputs!D31 -> 6 | S12: =Inputs!E31 -> 800
D13: =CONCATENATE("(", opt4_number_of_lives_renewal, " lives)") -> (800 lives) | G13: =CONCATENATE("(", opt4_number_of_lives_renewal, " lives)") -> (800 lives) | J13: =CONCATENATE("(", opt4_number_of_lives_renewal, " lives)") -> (800 lives)
B14: =Inputs!B33 -> V. ESCP with 0% Co-Pay (SI : 5 L) | D14: =Inputs!I33 -> 60,00,000 | E14: =D14/opt5_number_of_lives_renewal -> #VALUE! | G14: =Inputs!J33 -> 60,00,000 | H14: =G14/opt5_number_of_lives_renewal -> #VALUE! | J14: =Inputs!K33 -> 60,00,000 | K14: =J14/opt5_number_of_lives_renewal -> #VALUE! | M14: - | N14: - | P14: =Inputs!B33 -> V. ESCP with 0% Co-Pay (SI : 5 L) | R14: =Inputs!D33 -> 6 | S14: =Inputs!E33 -> 800
D15: =CONCATENATE("(", opt5_number_of_lives_renewal, " lives)") -> (800 lives) | G15: =CONCATENATE("(", opt5_number_of_lives_renewal, " lives)") -> (800 lives) | J15: =CONCATENATE("(", opt5_number_of_lives_renewal, " lives)") -> (800 lives)
D18: Group Personal Accident Insurance
D19: Options for Renewal | M19: Previous Policy
D20: =Inputs!I43 -> Magma HDI (Basic Plan) - NEE Group | G20: =Inputs!J43 -> Magma HDI (Pro Plan) - NEE Group | J20: =Inputs!K43 -> Go Digit (Pro Plan) | M20: =Inputs!L43 -> IFFCO Tokio ( Pro Plan) | P20: Proposed Options | R20: No. of Employees (renewal) | T20: No. of Employees (expiring policy)
D21: Total Premium (₹) | E21: Premium per Mille | G21: Total Premium (₹) | H21: Premium per Mille | J21: Total Premium (₹) | K21: Premium per Mille | M21: Total Premium (₹) | N21: Premium per Mille
B22: =Inputs!B45 -> I. Expiring Terms (SI: 10 L) | D22: =Inputs!I45 -> 20,00,000 | E22: =D22/GPA_opt1_number_of_employees_renewal -> #VALUE! | G22: =Inputs!J45 -> 20,00,000 | H22: =G22/GPA_opt1_number_of_employees_renewal -> #VALUE! | J22: =Inputs!K45 -> 20,00,000 | K22: =J22/GPA_opt1_number_of_employees_renewal -> #VALUE! | M22: =Inputs!L45 -> 20,00,000 | N22: =M22/GPA_number_of_lives_expiring -> #VALUE! | P22: =Inputs!B45 -> I. Expiring Terms (SI: 10 L) | R22: =Inputs!D45 -> 30 | T22: =Inputs!F45 -> 20
D23: =CONCATENATE("(", GPA_opt1_number_of_employees_renewal, " employees)") -> (30 employees) | G23: =CONCATENATE("(", GPA_opt1_number_of_employees_renewal, " employees)") -> (30 employees) | J23: =CONCATENATE("(", GPA_opt1_number_of_employees_renewal, " employees)") -> (30 employees) | M23: =CONCATENATE("(", GPA_opt1_number_of_employees_expiring, " employees)") -> (20 employees)
B24: =Inputs!B47 -> II. SI: 25 L | D24: =Inputs!I47 -> 39,00,000 | E24: =D24/GPA_opt2_number_of_employees_renewal -> #VALUE! | G24: =Inputs!J47 -> 30,00,000 | H24: =G24/GPA_opt2_number_of_employees_renewal -> #VALUE! | J24: =Inputs!K47 -> 30,00,000 | K24: =J24/GPA_opt2_number_of_employees_renewal -> #VALUE! | M24: - | N24: - | P24: =Inputs!B47 -> II. SI: 25 L | R24: =Inputs!D47 -> 30 | T24: -
D25: =CONCATENATE("(", GPA_opt2_number_of_employees_renewal, " employees)") -> (30 employees) | G25: =CONCATENATE("(", GPA_opt2_number_of_employees_renewal, " employees)") -> (30 employees) | J25: =CONCATENATE("(", GPA_opt2_number_of_employees_renewal, " employees)") -> (30 employees)
D28: Group Term Life Insurance
D29: Options for Renewal | M29: Previous Policy
D30: =Inputs!I57 -> CALI (Exclusive) | G30: =Inputs!J57 -> CALI (Exclusive) | J30: =Inputs!K57 -> HDFC Life | M30: =Inputs!L57 -> Pramerica Life | P30: Proposed Options | R30: No. of Employees (renewal) | T30: No. of Employees (expiring policy)
D31: Total Premium (₹) | E31: Premium per Mille | G31: Total Premium (₹) | H31: Premium per Mille | J31: Total Premium (₹) | K31: Premium per Mille | M31: Total Premium (₹) | N31: Premium per Mille
B32: =Inputs!B59 -> I. Expiring Terms (SI: 10 L) | D32: =Inputs!I59 -> 25,00,000 | E32: =D32/GTLI_opt1_number_of_employees_renewal -> #VALUE! | G32: =Inputs!J59 -> 20,00,000 | H32: =G32/GTLI_opt1_number_of_employees_renewal -> #VALUE! | J32: =Inputs!K59 -> 20,00,000 | K32: =J32/GTLI_opt1_number_of_employees_renewal -> #VALUE! | M32: =Inputs!L59 -> 20,00,000 | N32: =M32/GTLI_number_of_employees_expiring -> #VALUE! | P32: =B32 -> I. Expiring Terms (SI: 10 L) | R32: =Inputs!D59 -> 300 | T32: =Inputs!F59 -> 150
D33: =CONCATENATE("(", GTLI_opt1_number_of_employees_renewal, " employees)") -> (300 employees) | G33: =CONCATENATE("(", GTLI_opt1_number_of_employees_renewal, " employees)") -> (300 employees) | J33: =CONCATENATE("(", GTLI_opt1_number_of_employees_renewal, " employees)") -> (300 employees) | M33: {=CONCATENATE("(", GTLI_number_of_employees_expiring, " employees)")} -> (150 employees)
B34: =Inputs!B61 -> II. SI: 25 L | D34: =Inputs!I61 -> 35,00,000 | E34: =D34/GTLI_opt2_number_of_employees_renewal -> #VALUE! | G34: =Inputs!J61 -> 30,00,000 | H34: =G34/GTLI_opt2_number_of_employees_renewal -> #VALUE! | J34: =Inputs!K61 -> 30,00,000 | K34: =J34/GTLI_opt2_number_of_employees_renewal -> #VALUE! | M34: - | N34: - | P34: =B34 -> II. SI: 25 L | R34: =Inputs!D61 -> 300 | T34: -
D35: =CONCATENATE("(", GTLI_opt1_number_of_employees_renewal, " employees)") -> (300 employees) | G35: =CONCATENATE("(", GTLI_opt2_number_of_employees_renewal, " employees)") -> (300 employees) | J35: =CONCATENATE("(", GTLI_opt2_number_of_employees_renewal, " employees)") -> (300 employees)

Sheet Policy & Technical Features - o
B3: Policy Features – Group Health Insurance
L5: Incumbent Insurer | Z5: =L5 -> Incumbent Insurer
A6: Logo | B6: Features | C6: =SUBSTITUTE(B6," ","") -> Features | D6: Benefits | F6: =Inputs!B14 -> Manipal Cigna Standard Rater | H6: =Inputs!C14 -> SBI General | J6: =Inputs!D14 -> Manipal Cigna | L6: =Inputs!E14 -> IFFCO Tokio | O6: Plan Type:- | Q6: =B6 -> Features | R6: =D6 -> Benefits | T6: =F6 -> Manipal Cigna Standard Rater | V6: =H6 -> SBI General | X6: =J6 -> Manipal Cigna | Z6: =L6 -> IFFCO Tokio
B7: Family Definition | D7: Plan Type | F7: Employee, Spouse, and Children | H7: Employee, Spouse, and Children | J7: Employee, Spouse, and Children | L7: Employee, Spouse, and Children | O7: Employee only | Q7: =B7 -> Family Definition | R7: =D7 -> Plan Type | T7: =F7 -> Employee, Spouse, and Children | V7: =H7 -> Employee, Spouse, and Children | X7: =J7 -> Employee, Spouse, and Children | Z7: =L7 -> Employee, Spouse, and Children
C8: =SUBSTITUTE(B7," ","") -> FamilyDefinition | D8: Children - upto 25 yrs of age | F8: =INDEX('GHI DB'!$C$4:$BS$21,MATCH('Policy & Technical Features - o'!F$6,'GHI DB'!$A$4:$A$21,0),MATCH('Policy & Technical Features - o'!$D8,'GHI DB'!$C$3:$BS$3,0)) -> #N/A | H8: =INDEX('GHI DB'!$C$4:$BS$21,MATCH('Policy & Technical Features - o'!H$6,'GHI DB'!$A$4:$A$21,0),MATCH('Policy & Technical Features - o'!$D8,'GHI DB'!$C$3:$BS$3,0)) -> #N/A | J8: =INDEX('GHI DB'!$C$4:$BS$21,MATCH('Policy & Technical Features - o'!J$6,'GHI DB'!$A$4:$A$21,0),MATCH('Policy & Technical Features - o'!$D8,'GHI DB'!$C$3:$BS$3,0)) -> 2 | L8: =INDEX('GHI DB'!$C$4:$BS$21,MATCH('Policy & Technical Features - o'!L$6,'GHI DB'!$A$4:$A$21,0),MATCH('Policy & Technical Features - o'!$D8,'GHI DB'!$C$3:$BS$3,0)) -> 2 | O8: Employee, Spouse, and Children | R8: =D8 -> Children - upto 25 yrs of age | T8: =F8 -> #N/A | V8: =H8 -> #N/A | X8: =J8 -> 2 | Z8: =L8 -> 2
C9: =SUBSTITUTE(B7," ","") -> FamilyDefinition | D9: 2 Parents/PIL - upto 80 yrs of age | F9: =INDEX('GHI DB'!$C$4:$BS$21,MATCH('Policy & Technical Features - o'!F$6,'GHI DB'!$A$4:$A$21,0),MATCH('Policy & Technical Features - o'!$D9,'GHI DB'!$C$3:$BS$3,0)) -> #N/A | H9: =INDEX('GHI DB'!$C$4:$BS$21,MATCH('Policy & Technical Features - o'!H$6,'GHI DB'!$A$4:$A$21,0),MATCH('Policy & Technical Features - o'!$D9,'GHI DB'!$C$3:$BS$3,0)) -> #N/A | J9: =INDEX('GHI DB'!$C$4:$BS$21,MATCH('Policy & Technical Features - o'!J$6,'GHI DB'!$A$4:$A$21,0),MATCH('Policy & Technical Features - o'!$D9,'GHI DB'!$C$3:$BS$3,0)) -> ✔ | L9: =INDEX('GHI DB'!$C$4:$BS$21,MATCH('Policy & Technical Features - o'!L$6,'GHI DB'!$A$4:$A$21,0),MATCH('Policy & Technical Features - o'!$D9,'GHI DB'!$C$3:$BS$3,0)) -> ✔ | O9: Employee, Spouse, Children, and Parents/Parents-in-law | R9: =D9 -> 2 Parents/PIL - upto 80 yrs of age | T9: =F9 -> #N/A | V9: =H9 -> #N/A | X9: =J9 -> ✔ | Z9: =L9 -> ✔
B10: Room Rent Restriction | C10: =SUBSTITUTE(B10," ","") -> RoomRentRestriction | D10: Normal -Single Pvt. AC ICU - No Capping (per day) | F10: =INDEX('GHI DB'!$C$4:$BS$21,MATCH('Policy & Technical Features - o'!F$6,'GHI DB'!$A$4:$A$21,0),MATCH('Policy & Technical Features - o'!$D10,'GHI DB'!$C$3:$BS$3,0)) -> #N/A | H10: =INDEX('GHI DB'!$C$4:$BS$21,MATCH('Policy & Technical Features - o'!H$6,'GHI DB'!$A$4:$A$21,0),MATCH('Policy & Technical Features - o'!$D10,'GHI DB'!$C$3:$BS$3,0)) -> #N/A | J10: =INDEX('GHI DB'!$C$4:$BS$21,MATCH('Policy & Technical Features - o'!J$6,'GHI DB'!$A$4:$A$21,0),MATCH('Policy & Technical Features - o'!$D10,'GHI DB'!$C$3:$BS$3,0)) -> #N/A | L10: =INDEX('GHI DB'!$C$4:$BS$21,MATCH('Policy & Technical Features - o'!L$6,'GHI DB'!$A$4:$A$21,0),MATCH('Policy & Technical Features - o'!$D10,'GHI DB'!$C$3:$BS$3,0)) -> #N/A | Q10: =B10 -> Room Rent Restriction | R10: =D10 -> Normal -Single Pvt. AC ICU - No Capping (per day) | T10: =F10 -> #N/A | V10: =H10 -> #N/A | X10: =J10 -> #N/A | Z10: =L10 -> #N/A
B11: Maternity Cover | C11: =SUBSTITUTE(B11," ","") -> MaternityCover | D11: Normal - Rs. 50k C Section - Rs. 50K | F11: =INDEX('GHI DB'!$C$4:$BS$21,MATCH('Policy & Technical Features - o'!F$6,'GHI DB'!$A$4:$A$21,0),MATCH('Policy & Technical Features - o'!$D11,'GHI DB'!$C$3:$BS$3,0)) -> #N/A | H11: =INDEX('GHI DB'!$C$4:$BS$21,MATCH('Policy & Technical Features - o'!H$6,'GHI DB'!$A$4:$A$21,0),MATCH('Policy & Technical Features - o'!$D11,'GHI DB'!$C$3:$BS$3,0)) -> #N/A | J11: =INDEX('GHI DB'!$C$4:$BS$21,MATCH('Policy & Technical Features - o'!J$6,'GHI DB'!$A$4:$A$21,0),MATCH('Policy & Technical Features - o'!$D11,'GHI DB'!$C$3:$BS$3,0)) -> ✔ | L11: =INDEX('GHI DB'!$C$4:$BS$21,MATCH('Policy & Technical Features - o'!L$6,'GHI DB'!$A$4:$A$21,0),MATCH('Policy & Technical Features - o'!$D11,'GHI DB'!$C$3:$BS$3,0)) -> ✔ | Q11: =B11 -> Maternity Cover | R11: =D11 -> Normal - Rs. 50k C Section - Rs. 50K | T11: =F11 -> #N/A | V11: =H11 -> #N/A | X11: =J11 -> ✔ | Z11: =L11 -> ✔
B12: Co Pay | C12: =SUBSTITUTE(B12," ","") -> CoPay | D12: 0% Co-Pay | F12: =INDEX('GHI DB'!$C$4:$BS$21,MATCH('Policy & Technical Features - o'!F$6,'GHI DB'!$A$4:$A$21,0),MATCH('Policy & Technical Features - o'!$D12,'GHI DB'!$C$3:$BS$3,0)) -> #N/A | H12: =INDEX('GHI DB'!$C$4:$BS$21,MATCH('Policy & Technical Features - o'!H$6,'GHI DB'!$A$4:$A$21,0),MATCH('Policy & Technical Features - o'!$D12,'GHI DB'!$C$3:$BS$3,0)) -> #N/A | J12: =INDEX('GHI DB'!$C$4:$BS$21,MATCH('Policy & Technical Features - o'!J$6,'GHI DB'!$A$4:$A$21,0),MATCH('Policy & Technical Features - o'!$D12,'GHI DB'!$C$3:$BS$3,0)) -> ✔ | L12: =INDEX('GHI DB'!$C$4:$BS$21,MATCH('Policy & Technical Features - o'!L$6,'GHI DB'!$A$4:$A$21,0),MATCH('Policy & Technical Features - o'!$D12,'GHI DB'!$C$3:$BS$3,0)) -> ✔ | Q12: =B12 -> Co Pay | R12: =D12 -> 0% Co-Pay | T12: =F12 -> #N/A | V12: =H12 -> #N/A | X12: =J12 -> ✔ | Z12: =L12 -> ✔
B13: Psychiatric Illness | C13: =SUBSTITUTE(B13," ","") -> PsychiatricIllness | D13: Hospitalization > 24 hours | F13: =INDEX('GHI DB'!$C$4:$BS$21,MATCH('Policy & Technical Features - o'!F$6,'GHI DB'!$A$4:$A$21,0),MATCH('Policy & Technical Features - o'!$D13,'GHI DB'!$C$3:$BS$3,0)) -> #N/A | H13: =INDEX('GHI DB'!$C$4:$BS$21,MATCH('Policy & Technical Features - o'!H$6,'GHI DB'!$A$4:$A$21,0),MATCH('Policy & Technical Features - o'!$D13,'GHI DB'!$C$3:$BS$3,0)) -> #N/A | J13: =INDEX('GHI DB'!$C$4:$BS$21,MATCH('Policy & Technical Features - o'!J$6,'GHI DB'!$A$4:$A$21,0),MATCH('Policy & Technical Features - o'!$D13,'GHI DB'!$C$3:$BS$3,0)) -> ✔ | L13: =INDEX('GHI DB'!$C$4:$BS$21,MATCH('Policy & Technical Features - o'!L$6,'GHI DB'!$A$4:$A$21,0),MATCH('Policy & Technical Features - o'!$D13,'GHI DB'!$C$3:$BS$3,0)) -> ✔ | Q13: =B13 -> Psychiatric Illness | R13: =D13 -> Hospitalization > 24 hours | T13: =F13 -> #N/A | V13: =H13 -> #N/A | X13: =J13 -> ✔ | Z13: =L13 -> ✔
B14: Pre and Post Hospitalization Coverage | C14: =SUBSTITUTE(B14," ","") -> PreandPostHospitalizationCoverage | D14: 30/60 days (For in-patient Hospitalization) | F14: =INDEX('GHI DB'!$C$4:$BS$21,MATCH('Policy & Technical Features - o'!F$6,'GHI DB'!$A$4:$A$21,0),MATCH('Policy & Technical Features - o'!$D14,'GHI DB'!$C$3:$BS$3,0)) -> #N/A | H14: =INDEX('GHI DB'!$C$4:$BS$21,MATCH('Policy & Technical Features - o'!H$6,'GHI DB'!$A$4:$A$21,0),MATCH('Policy & Technical Features - o'!$D14,'GHI DB'!$C$3:$BS$3,0)) -> #N/A | J14: =INDEX('GHI DB'!$C$4:$BS$21,MATCH('Policy & Technical Features - o'!J$6,'GHI DB'!$A$4:$A$21,0),MATCH('Policy & Technical Features - o'!$D14,'GHI DB'!$C$3:$BS$3,0)) -> #N/A | L14: =INDEX('GHI DB'!$C$4:$BS$21,MATCH('Policy & Technical Features - o'!L$6,'GHI DB'!$A$4:$A$21,0),MATCH('Policy & Technical Features - o'!$D14,'GHI DB'!$C$3:$BS$3,0)) -> #N/A | Q14: =B14 -> Pre and Post Hospitalization Coverage | R14: =D14 -> 30/60 days (For in-patient Hospitalization) | T14: =F14 -> #N/A | V14: =H14 -> #N/A | X14: =J14 -> #N/A | Z14: =L14 -> #N/A
B15: Mid term Addition of Dependents | C15: =SUBSTITUTE(B15," ","") -> MidtermAdditionofDependents | D15: Hospitallization > 24 hours in Govt Approved Hospitals | F15: =INDEX('GHI DB'!$C$4:$BS$21,MATCH('Policy & Technical Features - o'!F$6,'GHI DB'!$A$4:$A$21,0),MATCH('Policy & Technical Features - o'!$D15,'GHI DB'!$C$3:$BS$3,0)) -> #N/A | H15: =INDEX('GHI DB'!$C$4:$BS$21,MATCH('Policy & Technical Features - o'!H$6,'GHI DB'!$A$4:$A$21,0),MATCH('Policy & Technical Features - o'!$D15,'GHI DB'!$C$3:$BS$3,0)) -> #N/A | J15: =INDEX('GHI DB'!$C$4:$BS$21,MATCH('Policy & Technical Features - o'!J$6,'GHI DB'!$A$4:$A$21,0),MATCH('Policy & Technical Features - o'!$D15,'GHI DB'!$C$3:$BS$3,0)) -> Not Covered | L15: =INDEX('GHI DB'!$C$4:$BS$21,MATCH('Policy & Technical Features - o'!L$6,'GHI DB'!$A$4:$A$21,0),MATCH('Policy & Technical Features - o'!$D15,'GHI DB'!$C$3:$BS$3,0)) -> ✔ | Q15: =B15 -> Mid term Addition of Dependents | R15: =D15 -> Hospitallization > 24 hours in Govt Approved Hospitals | T15: =F15 -> #N/A | V15: =H15 -> #N/A | X15: =J15 -> Not Covered | Z15: =L15 -> ✔
B16: Emergency Ambulance | C16: =SUBSTITUTE(B16," ","") -> EmergencyAmbulance | D16: Coverage per event | F16: =INDEX('GHI DB'!$C$4:$BS$21,MATCH('Policy & Technical Features - o'!F$6,'GHI DB'!$A$4:$A$21,0),MATCH('Policy & Technical Features - o'!$D16,'GHI DB'!$C$3:$BS$3,0)) -> #N/A | H16: =INDEX('GHI DB'!$C$4:$BS$21,MATCH('Policy & Technical Features - o'!H$6,'GHI DB'!$A$4:$A$21,0),MATCH('Policy & Technical Features - o'!$D16,'GHI DB'!$C$3:$BS$3,0)) -> #N/A | J16: =INDEX('GHI DB'!$C$4:$BS$21,MATCH('Policy & Technical Features - o'!J$6,'GHI DB'!$A$4:$A$21,0),MATCH('Policy & Technical Features - o'!$D16,'GHI DB'!$C$3:$BS$3,0)) -> Upto Rs. 2.5k | L16: =INDEX('GHI DB'!$C$4:$BS$21,MATCH('Policy & Technical Features - o'!L$6,'GHI DB'!$A$4:$A$21,0),MATCH('Policy & Technical Features - o'!$D16,'GHI DB'!$C$3:$BS$3,0)) -> Upto Rs. 1k | Q16: =B16 -> Emergency Ambulance | R16: =D16 -> Coverage per event | T16: =F16 -> #N/A | V16: =H16 -> #N/A | X16: =J16 -> Upto Rs. 2.5k | Z16: =L16 -> Upto Rs. 1k
B17: Emergency Ambulance | C17: =SUBSTITUTE(B17," ","") -> EmergencyAmbulance | D17: Coverage per event | F17: =INDEX('GHI DB'!$C$4:$BS$21,MATCH('Policy & Technical Features - o'!F$6,'GHI DB'!$A$4:$A$21,0),MATCH('Policy & Technical Features - o'!$D17,'GHI DB'!$C$3:$BS$3,0)) -> #N/A | H17: =INDEX('GHI DB'!$C$4:$BS$21,MATCH('Policy & Technical Features - o'!H$6,'GHI DB'!$A$4:$A$21,0),MATCH('Policy & Technical Features - o'!$D17,'GHI DB'!$C$3:$BS$3,0)) -> #N/A | J17: =INDEX('GHI DB'!$C$4:$BS$21,MATCH('Policy & Technical Features - o'!J$6,'GHI DB'!$A$4:$A$21,0),MATCH('Policy & Technical Features - o'!$D17,'GHI DB'!$C$3:$BS$3,0)) -> Upto Rs. 2.5k | L17: =INDEX('GHI DB'!$C$4:$BS$21,MATCH('Policy & Technical Features - o'!L$6,'GHI DB'!$A$4:$A$21,0),MATCH('Policy & Technical Features - o'!$D17,'GHI DB'!$C$3:$BS$3,0)) -> Upto Rs. 1k | Q17: =B17 -> Emergency Ambulance | R17: =D17 -> Coverage per event | T17: =F17 -> #N/A | V17: =H17 -> #N/A | X17: =J17 -> Upto Rs. 2.5k | Z17: =L17 -> Upto Rs. 1k
B18: Inpatient Hospitalization | C18: =SUBSTITUTE(B18," ","") -> InpatientHospitalization | D18: Hospitallization > 24 hours in Govt Approved Hospitals | F18: =INDEX('GHI DB'!$C$4:$BS$21,MATCH('Policy & Technical Features - o'!F$6,'GHI DB'!$A$4:$A$21,0),MATCH('Policy & Technical Features - o'!$D18,'GHI DB'!$C$3:$BS$3,0)) -> #N/A | H18: =INDEX('GHI DB'!$C$4:$BS$21,MATCH('Policy & Technical Features - o'!H$6,'GHI DB'!$A$4:$A$21,0),MATCH('Policy & Technical Features - o'!$D18,'GHI DB'!$C$3:$BS$3,0)) -> #N/A | J18: =INDEX('GHI DB'!$C$4:$BS$21,MATCH('Policy & Technical Features - o'!J$6,'GHI DB'!$A$4:$A$21,0),MATCH('Policy & Technical Features - o'!$D18,'GHI DB'!$C$3:$BS$3,0)) -> Not Covered | L18: =INDEX('GHI DB'!$C$4:$BS$21,MATCH('Policy & Technical Features - o'!L$6,'GHI DB'!$A$4:$A$21,0),MATCH('Policy & Technical Features - o'!$D18,'GHI DB'!$C$3:$BS$3,0)) -> ✔ | Q18: =B18 -> Inpatient Hospitalization | R18: =D18 -> Hospitallization > 24 hours in Govt Approved Hospitals | T18: =F18 -> #N/A | V18: =H18 -> #N/A | X18: =J18 -> Not Covered | Z18: =L18 -> ✔
B24: Know Your Insurer - Credentials
L26: Incumbent Insurer | Z26: =L26 -> Incumbent Insurer
A27: Logo | B27: Features | D27: Parameter | F27: =Inputs!B14 -> Manipal Cigna Standard Rater | H27: =Inputs!C14 -> SBI General | J27: =Inputs!D14 -> Manipal Cigna | L27: =Inputs!E14 -> IFFCO Tokio | Q27: =B27 -> Features | R27: =D27 -> Parameter | T27: =F27 -> Manipal Cigna Standard Rater | V27: =H27 -> SBI General | X27: =J27 -> Manipal Cigna | Z27: =L27 -> IFFCO Tokio
B28: Background and Credibility | C28: Background and Credibility | D28: Founding Year | F28: =INDEX('Technical DB (Health)'!$C$3:$Q$20,MATCH(F$27,'Technical DB (Health)'!$A$3:$A$20,0),MATCH($D28,'Technical DB (Health)'!$C$2:$Q$2,0)) -> #N/A | H28: =INDEX('Technical DB (Health)'!$C$3:$Q$20,MATCH(H$27,'Technical DB (Health)'!$A$3:$A$20,0),MATCH($D28,'Technical DB (Health)'!$C$2:$Q$2,0)) -> #N/A | J28: =INDEX('Technical DB (Health)'!$C$3:$Q$20,MATCH(J$27,'Technical DB (Health)'!$A$3:$A$20,0),MATCH($D28,'Technical DB (Health)'!$C$2:$Q$2,0)) -> 2014 | L28: =INDEX('Technical DB (Health)'!$C$3:$Q$20,MATCH(L$27,'Technical DB (Health)'!$A$3:$A$20,0),MATCH($D28,'Technical DB (Health)'!$C$2:$Q$2,0)) -> 2000 | Q28: =B28 -> Background and Credibility | R28: =D28 -> Founding Year | T28: =F28 -> #N/A | V28: =H28 -> #N/A | X28: =J28 -> 2014 | Z28: =L28 -> 2000
D29: Backed by | F29: =INDEX('Technical DB (Health)'!$C$3:$Q$20,MATCH(F$27,'Technical DB (Health)'!$A$3:$A$20,0),MATCH($D29,'Technical DB (Health)'!$C$2:$Q$2,0)) -> #N/A | H29: =INDEX('Technical DB (Health)'!$C$3:$Q$20,MATCH(H$27,'Technical DB (Health)'!$A$3:$A$20,0),MATCH($D29,'Technical DB (Health)'!$C$2:$Q$2,0)) -> #N/A | J29: =INDEX('Technical DB (Health)'!$C$3:$Q$20,MATCH(J$27,'Technical DB (Health)'!$A$3:$A$20,0),MATCH($D29,'Technical DB (Health)'!$C$2:$Q$2,0)) -> Manipal Group, Cigna Holdings | L29: =INDEX('Technical DB (Health)'!$C$3:$Q$20,MATCH(L$27,'Technical DB (Health)'!$A$3:$A$20,0),MATCH($D29,'Technical DB (Health)'!$C$2:$Q$2,0)) -> IFFCO India, Tokio Marine Insurance (Japan) | R29: =D29 -> Backed by | T29: =F29 -> #N/A | V29: =H29 -> #N/A | X29: =J29 -> Manipal Group, Cigna Holdings | Z29: =L29 -> IFFCO India, Tokio Marine Insurance (Japan)
B30: Market Presence | C30: Market Presence | D30: GHI Book Size (INR Crores) | F30: =INDEX('Technical DB (Health)'!$C$3:$Q$20,MATCH(F$27,'Technical DB (Health)'!$A$3:$A$20,0),MATCH($D30,'Technical DB (Health)'!$C$2:$Q$2,0)) -> #N/A | H30: =INDEX('Technical DB (Health)'!$C$3:$Q$20,MATCH(H$27,'Technical DB (Health)'!$A$3:$A$20,0),MATCH($D30,'Technical DB (Health)'!$C$2:$Q$2,0)) -> #N/A | J30: =INDEX('Technical DB (Health)'!$C$3:$Q$20,MATCH(J$27,'Technical DB (Health)'!$A$3:$A$20,0),MATCH($D30,'Technical DB (Health)'!$C$2:$Q$2,0)) -> #N/A | L30: =INDEX('Technical DB (Health)'!$C$3:$Q$20,MATCH(L$27,'Technical DB (Health)'!$A$3:$A$20,0),MATCH($D30,'Technical DB (Health)'!$C$2:$Q$2,0)) -> #N/A | Q30: =B30 -> Market Presence | R30: =D30 -> GHI Book Size (INR Crores) | T30: =F30 -> #N/A | V30: =H30 -> #N/A | X30: =J30 -> #N/A | Z30: =L30 -> #N/A
D31: GHI Growth Rate | F31: =INDEX('Technical DB (Health)'!$C$3:$Q$20,MATCH(F$27,'Technical DB (Health)'!$A$3:$A$20,0),MATCH($D31,'Technical DB (Health)'!$C$2:$Q$2,0)) -> #N/A | H31: =INDEX('Technical DB (Health)'!$C$3:$Q$20,MATCH(H$27,'Technical DB (Health)'!$A$3:$A$20,0),MATCH($D31,'Technical DB (Health)'!$C$2:$Q$2,0)) -> #N/A | J31: =INDEX('Technical DB (Health)'!$C$3:$Q$20,MATCH(J$27,'Technical DB (Health)'!$A$3:$A$20,0),MATCH($D31,'Technical DB (Health)'!$C$2:$Q$2,0)) -> #N/A | L31: =INDEX('Technical DB (Health)'!$C$3:$Q$20,MATCH(L$27,'Technical DB (Health)'!$A$3:$A$20,0),MATCH($D31,'Technical DB (Health)'!$C$2:$Q$2,0)) -> #N/A | R31: =D31 -> GHI Growth Rate | T31: =F31 -> #N/A | V31: =H31 -> #N/A | X31: =J31 -> #N/A | Z31: =L31 -> #N/A
B32: Financial Health | C32: Financial Health | D32: Solvency Ratio (IRDAI recommended: >1.5) | F32: =INDEX('Technical DB (Health)'!$C$3:$Q$20,MATCH(F$27,'Technical DB (Health)'!$A$3:$A$20,0),MATCH($D32,'Technical DB (Health)'!$C$2:$Q$2,0)) -> #N/A | H32: =INDEX('Technical DB (Health)'!$C$3:$Q$20,MATCH(H$27,'Technical DB (Health)'!$A$3:$A$20,0),MATCH($D32,'Technical DB (Health)'!$C$2:$Q$2,0)) -> #N/A | J32: =INDEX('Technical DB (Health)'!$C$3:$Q$20,MATCH(J$27,'Technical DB (Health)'!$A$3:$A$20,0),MATCH($D32,'Technical DB (Health)'!$C$2:$Q$2,0)) -> #N/A | L32: =INDEX('Technical DB (Health)'!$C$3:$Q$20,MATCH(L$27,'Technical DB (Health)'!$A$3:$A$20,0),MATCH($D32,'Technical DB (Health)'!$C$2:$Q$2,0)) -> #N/A | Q32: =B32 -> Financial Health | R32: =D32 -> Solvency Ratio (IRDAI recommended: >1.5) | T32: =F32 -> #N/A | V32: =H32 -> #N/A | X32: =J32 -> #N/A | Z32: =L32 -> #N/A
B33: Policy Administration | C33: Policy Administration | D33: Policy Issuance TAT | F33: =INDEX('Technical DB (Health)'!$C$3:$Q$20,MATCH(F$27,'Technical DB (Health)'!$A$3:$A$20,0),MATCH($D33,'Technical DB (Health)'!$C$2:$Q$2,0)) -> #N/A | H33: =INDEX('Technical DB (Health)'!$C$3:$Q$20,MATCH(H$27,'Technical DB (Health)'!$A$3:$A$20,0),MATCH($D33,'Technical DB (Health)'!$C$2:$Q$2,0)) -> #N/A | J33: =INDEX('Technical DB (Health)'!$C$3:$Q$20,MATCH(J$27,'Technical DB (Health)'!$A$3:$A$20,0),MATCH($D33,'Technical DB (Health)'!$C$2:$Q$2,0)) -> 10 to 20 days | L33: =INDEX('Technical DB (Health)'!$C$3:$Q$20,MATCH(L$27,'Technical DB (Health)'!$A$3:$A$20,0),MATCH($D33,'Technical DB (Health)'!$C$2:$Q$2,0)) -> 10 to 20 days | Q33: =B33 -> Policy Administration | R33: =D33 -> Policy Issuance TAT | T33: =F33 -> #N/A | V33: =H33 -> #N/A | X33: =J33 -> 10 to 20 days | Z33: =L33 -> 10 to 20 days
D34: Endorsement TAT | F34: =INDEX('Technical DB (Health)'!$C$3:$Q$20,MATCH(F$27,'Technical DB (Health)'!$A$3:$A$20,0),MATCH($D34,'Technical DB (Health)'!$C$2:$Q$2,0)) -> #N/A | H34: =INDEX('Technical DB (Health)'!$C$3:$Q$20,MATCH(H$27,'Technical DB (Health)'!$A$3:$A$20,0),MATCH($D34,'Technical DB (Health)'!$C$2:$Q$2,0)) -> #N/A | J34: =INDEX('Technical DB (Health)'!$C$3:$Q$20,MATCH(J$27,'Technical DB (Health)'!$A$3:$A$20,0),MATCH($D34,'Technical DB (Health)'!$C$2:$Q$2,0)) -> 3 to 5 days | L34: =INDEX('Technical DB (Health)'!$C$3:$Q$20,MATCH(L$27,'Technical DB (Health)'!$A$3:$A$20,0),MATCH($D34,'Technical DB (Health)'!$C$2:$Q$2,0)) -> 5 to 10 days | R34: =D34 -> Endorsement TAT | T34: =F34 -> #N/A | V34: =H34 -> #N/A | X34: =J34 -> 3 to 5 days | Z34: =L34 -> 5 to 10 days
B35: Claims Summary | C35: Claims Summary | D35: Cashless Network | F35: =INDEX('Technical DB (Health)'!$C$3:$Q$20,MATCH(F$27,'Technical DB (Health)'!$A$3:$A$20,0),MATCH($D35,'Technical DB (Health)'!$C$2:$Q$2,0)) -> #N/A | H35: =INDEX('Technical DB (Health)'!$C$3:$Q$20,MATCH(H$27,'Technical DB (Health)'!$A$3:$A$20,0),MATCH($D35,'Technical DB (Health)'!$C$2:$Q$2,0)) -> #N/A | J35: =INDEX('Technical DB (Health)'!$C$3:$Q$20,MATCH(J$27,'Technical DB (Health)'!$A$3:$A$20,0),MATCH($D35,'Technical DB (Health)'!$C$2:$Q$2,0)) -> 8,500+ | L35: =INDEX('Technical DB (Health)'!$C$3:$Q$20,MATCH(L$27,'Technical DB (Health)'!$A$3:$A$20,0),MATCH($D35,'Technical DB (Health)'!$C$2:$Q$2,0)) -> 7,000+ | Q35: =B35 -> Claims Summary | R35: =D35 -> Cashless Network | T35: =F35 -> #N/A | V35: =H35 -> #N/A | X35: =J35 -> 8,500+ | Z35: =L35 -> 7,000+
D36: Claim Settlement Ratio | F36: =INDEX('Technical DB (Health)'!$C$3:$Q$20,MATCH(F$27,'Technical DB (Health)'!$A$3:$A$20,0),MATCH($D36,'Technical DB (Health)'!$C$2:$Q$2,0)) -> #N/A | H36: =INDEX('Technical DB (Health)'!$C$3:$Q$20,MATCH(H$27,'Technical DB (Health)'!$A$3:$A$20,0),MATCH($D36,'Technical DB (Health)'!$C$2:$Q$2,0)) -> #N/A | J36: =INDEX('Technical DB (Health)'!$C$3:$Q$20,MATCH(J$27,'Technical DB (Health)'!$A$3:$A$20,0),MATCH($D36,'Technical DB (Health)'!$C$2:$Q$2,0)) -> 0.98 | L36: =INDEX('Technical DB (Health)'!$C$3:$Q$20,MATCH(L$27,'Technical DB (Health)'!$A$3:$A$20,0),MATCH($D36,'Technical DB (Health)'!$C$2:$Q$2,0)) -> 0.98 | R36: =D36 -> Claim Settlement Ratio | T36: =F36 -> #N/A | V36: =H36 -> #N/A | X36: =J36 -> 0.98 | Z36: =L36 -> 0.98
D37: Cashless TAT | F37: =INDEX('Technical DB (Health)'!$C$3:$Q$20,MATCH(F$27,'Technical DB (Health)'!$A$3:$A$20,0),MATCH($D37,'Technical DB (Health)'!$C$2:$Q$2,0)) -> #N/A | H37: =INDEX('Technical DB (Health)'!$C$3:$Q$20,MATCH(H$27,'Technical DB (Health)'!$A$3:$A$20,0),MATCH($D37,'Technical DB (Health)'!$C$2:$Q$2,0)) -> #N/A | J37: =INDEX('Technical DB (Health)'!$C$3:$Q$20,MATCH(J$27,'Technical DB (Health)'!$A$3:$A$20,0),MATCH($D37,'Technical DB (Health)'!$C$2:$Q$2,0)) -> 2 to 4 hours | L37: =INDEX('Technical DB (Health)'!$C$3:$Q$20,MATCH(L$27,'Technical DB (Health)'!$A$3:$A$20,0),MATCH($D37,'Technical DB (Health)'!$C$2:$Q$2,0)) -> 2 to 4 hours | R37: =D37 -> Cashless TAT | T37: =F37 -> #N/A | V37: =H37 -> #N/A | X37: =J37 -> 2 to 4 hours | Z37: =L37 -> 2 to 4 hours
D38: Reimbursement TAT | F38: =INDEX('Technical DB (Health)'!$C$3:$Q$20,MATCH(F$27,'Technical DB (Health)'!$A$3:$A$20,0),MATCH($D38,'Technical DB (Health)'!$C$2:$Q$2,0)) -> #N/A | H38: =INDEX('Technical DB (Health)'!$C$3:$Q$20,MATCH(H$27,'Technical DB (Health)'!$A$3:$A$20,0),MATCH($D38,'Technical DB (Health)'!$C$2:$Q$2,0)) -> #N/A | J38: =INDEX('Technical DB (Health)'!$C$3:$Q$20,MATCH(J$27,'Technical DB (Health)'!$A$3:$A$20,0),MATCH($D38,'Technical DB (Health)'!$C$2:$Q$2,0)) -> 15 to 30 days | L38: =INDEX('Technical DB (Health)'!$C$3:$Q$20,MATCH(L$27,'Technical DB (Health)'!$A$3:$A$20,0),MATCH($D38,'Technical DB (Health)'!$C$2:$Q$2,0)) -> 15 to 30 days | R38: =D38 -> Reimbursement TAT | T38: =F38 -> #N/A | V38: =H38 -> #N/A | X38: =J38 -> 15 to 30 days | Z38: =L38 -> 15 to 30 days
D39: % of claims settled in 3 months | F39: =INDEX('Technical DB (Health)'!$C$3:$Q$20,MATCH(F$27,'Technical DB (Health)'!$A$3:$A$20,0),MATCH($D39,'Technical DB (Health)'!$C$2:$Q$2,0)) -> #N/A | H39: =INDEX('Technical DB (Health)'!$C$3:$Q$20,MATCH(H$27,'Technical DB (Health)'!$A$3:$A$20,0),MATCH($D39,'Technical DB (Health)'!$C$2:$Q$2,0)) -> #N/A | J39: =INDEX('Technical DB (Health)'!$C$3:$Q$20,MATCH(J$27,'Technical DB (Health)'!$A$3:$A$20,0),MATCH($D39,'Technical DB (Health)'!$C$2:$Q$2,0)) -> 0.999 | L39: =INDEX('Technical DB (Health)'!$C$3:$Q$20,MATCH(L$27,'Technical DB (Health)'!$A$3:$A$20,0),MATCH($D39,'Technical DB (Health)'!$C$2:$Q$2,0)) -> 0.8989 | R39: =D39 -> % of claims settled in 3 months | T39: =F39 -> #N/A | V39: =H39 -> #N/A | X39: =J39 -> 0.999 | Z39: =L39 -> 0.8989
D40: Reimbursement Mode (Paperless/Paper) | F40: =INDEX('Technical DB (Health)'!$C$3:$Q$20,MATCH(F$27,'Technical DB (Health)'!$A$3:$A$20,0),MATCH($D40,'Technical DB (Health)'!$C$2:$Q$2,0)) -> #N/A | H40: =INDEX('Technical DB (Health)'!$C$3:$Q$20,MATCH(H$27,'Technical DB (Health)'!$A$3:$A$20,0),MATCH($D40,'Technical DB (Health)'!$C$2:$Q$2,0)) -> #N/A | J40: =INDEX('Technical DB (Health)'!$C$3:$Q$20,MATCH(J$27,'Technical DB (Health)'!$A$3:$A$20,0),MATCH($D40,'Technical DB (Health)'!$C$2:$Q$2,0)) -> Paperless | L40: =INDEX('Technical DB (Health)'!$C$3:$Q$20,MATCH(L$27,'Technical DB (Health)'!$A$3:$A$20,0),MATCH($D40,'Technical DB (Health)'!$C$2:$Q$2,0)) -> Paper-based | R40: =D40 -> Reimbursement Mode (Paperless/Paper) | T40: =F40 -> #N/A | V40: =H40 -> #N/A | X40: =J40 -> Paperless | Z40: =L40 -> Paper-based
D41: TPA (in-house or External) | F41: =INDEX('Technical DB (Health)'!$C$3:$Q$20,MATCH(F$27,'Technical DB (Health)'!$A$3:$A$20,0),MATCH($D41,'Technical DB (Health)'!$C$2:$Q$2,0)) -> #N/A | H41: =INDEX('Technical DB (Health)'!$C$3:$Q$20,MATCH(H$27,'Technical DB (Health)'!$A$3:$A$20,0),MATCH($D41,'Technical DB (Health)'!$C$2:$Q$2,0)) -> #N/A | J41: =INDEX('Technical DB (Health)'!$C$3:$Q$20,MATCH(J$27,'Technical DB (Health)'!$A$3:$A$20,0),MATCH($D41,'Technical DB (Health)'!$C$2:$Q$2,0)) -> In-house External Option available | L41: =INDEX('Technical DB (Health)'!$C$3:$Q$20,MATCH(L$27,'Technical DB (Health)'!$A$3:$A$20,0),MATCH($D41,'Technical DB (Health)'!$C$2:$Q$2,0)) -> In-house External Option available | R41: =D41 -> TPA (in-house or External) | T41: =F41 -> #N/A | V41: =H41 -> #N/A | X41: =J41 -> In-house External Option available | Z41: =L41 -> In-house External Option available
D44: ='High Level Quotes - Slide 1'!P2 -> File Path of Proposal Deck
B45: =Inputs!B9 -> C:\Users\shali\Downloads\ABCD\Healthysure Proposal Deck.pptx

Sheet Policy & Technical Features
B2: =Inputs!B9 -> C:\Users\shali\Downloads\ABCD\Healthysure Proposal Deck.pptx
B4: Policy Features – Group Health Insurance
L6: Incumbent Insurer | Z6: =L6 -> Incumbent Insurer
A7: Logo | B7: Features | C7: =SUBSTITUTE(B7," ","") -> Features | D7: Benefits | F7: =Inputs!B14 -> Manipal Cigna Standard Rater | H7: =Inputs!C14 -> SBI General | J7: =Inputs!D14 -> Manipal Cigna | L7: =Inputs!E14 -> IFFCO Tokio | O7: Plan Type:- | Q7: =B7 -> Features | R7: =D7 -> Benefits | T7: =F7 -> Manipal Cigna Standard Rater | V7: =H7 -> SBI General | X7: =J7 -> Manipal Cigna | Z7: =L7 -> IFFCO Tokio
B8: Family Definition | D8: Plan Type | F8: Employee, Spouse, and Children | H8: Employee, Spouse, and Children | J8: Employee, Spouse, and Children | L8: Employee, Spouse, and Children | O8: Employee only | Q8: =B8 -> Family Definition | R8: =D8 -> Plan Type | T8: =F8 -> Employee, Spouse, and Children | V8: =H8 -> Employee, Spouse, and Children | X8: =J8 -> Employee, Spouse, and Children | Z8: =L8 -> Employee, Spouse, and Children
C9: =SUBSTITUTE(B8," ","") -> FamilyDefinition | D9: Children - upto 25 yrs of age | F9: =VLOOKUP(D9,'GHI Features (Option 1)'!$E$15:$J$60,3,0) -> 2 | H9: =VLOOKUP(D9,'GHI Features (Option 1)'!$E$15:$J$60,4,0) -> 4 | J9: =VLOOKUP(D9,'GHI Features (Option 1)'!$E$15:$J$60,5,0) -> 4 | L9: =VLOOKUP(D9,'GHI Features (Option 1)'!$E$15:$J$60,6,0) -> 4 | O9: Employee, Spouse, and Children | R9: =D9 -> Children - upto 25 yrs of age | T9: =F9 -> 2 | V9: =H9 -> 4 | X9: =J9 -> 4 | Z9: =L9 -> 4
C10: =SUBSTITUTE(B8," ","") -> FamilyDefinition | D10: 2 Parents/PIL - upto 80 yrs of age | F10: =VLOOKUP(D10,'GHI Features (Option 1)'!$E$15:$J$60,3,0) -> ✔ | H10: =VLOOKUP(D10,'GHI Features (Option 1)'!$E$15:$J$60,4,0) -> ✖ | J10: =VLOOKUP(D10,'GHI Features (Option 1)'!$E$15:$J$60,5,0) -> ✖ | L10: =VLOOKUP(D10,'GHI Features (Option 1)'!$E$15:$J$60,6,0) -> ✔ | O10: Employee, Spouse, Children, and Parents/Parents-in-law | R10: =D10 -> 2 Parents/PIL - upto 80 yrs of age | T10: =F10 -> ✔ | V10: =H10 -> ✖ | X10: =J10 -> ✖ | Z10: =L10 -> ✔
B11: Inpatient Hospitalization | C11: =SUBSTITUTE(B11," ","") -> InpatientHospitalization | D11: =VLOOKUP(B11,'GHI Features (Option 1)'!$C$15:$J$60,3,0) -> Hospitalization > 24 hours | F11: =VLOOKUP(D11,'GHI Features (Option 1)'!$E$15:$J$60,3,0) -> ✔ | H11: =VLOOKUP(D11,'GHI Features (Option 1)'!$E$15:$J$60,4,0) -> ✔ | J11: =VLOOKUP(D11,'GHI Features (Option 1)'!$E$15:$J$60,5,0) -> ✔ | L11: =VLOOKUP(D11,'GHI Features (Option 1)'!$E$15:$J$60,6,0) -> ✔ | Q11: =B11 -> Inpatient Hospitalization | R11: =D11 -> Hospitalization > 24 hours | T11: =F11 -> ✔ | V11: =H11 -> ✔ | X11: =J11 -> ✔ | Z11: =L11 -> ✔
B12: Pre and Post Natal Expenses | C12: =SUBSTITUTE(B12," ","") -> PreandPostNatalExpenses | D12: =VLOOKUP(B12,'GHI Features (Option 1)'!$C$15:$J$60,3,0) -> Covered within maternity limit | F12: =VLOOKUP(D12,'GHI Features (Option 1)'!$E$15:$J$60,3,0) -> ✖ | H12: =VLOOKUP(D12,'GHI Features (Option 1)'!$E$15:$J$60,4,0) -> ✖ | J12: =VLOOKUP(D12,'GHI Features (Option 1)'!$E$15:$J$60,5,0) -> ✔ | L12: =VLOOKUP(D12,'GHI Features (Option 1)'!$E$15:$J$60,6,0) -> ✖ | Q12: =B12 -> Pre and Post Natal Expenses | R12: =D12 -> Covered within maternity limit | T12: =F12 -> ✖ | V12: =H12 -> ✖ | X12: =J12 -> ✔ | Z12: =L12 -> ✖
B13: Corporate Buffer | C13: =SUBSTITUTE(B13," ","") -> CorporateBuffer | D13: =VLOOKUP(B13,'GHI Features (Option 1)'!$C$15:$J$60,3,0) -> Not Covered | F13: =VLOOKUP(D13,'GHI Features (Option 1)'!$E$15:$J$60,3,0) -> Not Covered | H13: =VLOOKUP(D13,'GHI Features (Option 1)'!$E$15:$J$60,4,0) -> Not Covered | J13: =VLOOKUP(D13,'GHI Features (Option 1)'!$E$15:$J$60,5,0) -> Not Covered | L13: =VLOOKUP(D13,'GHI Features (Option 1)'!$E$15:$J$60,6,0) -> Not Covered | Q13: =B13 -> Corporate Buffer | R13: =D13 -> Not Covered | T13: =F13 -> Not Covered | V13: =H13 -> Not Covered | X13: =J13 -> Not Covered | Z13: =L13 -> Not Covered
B14: Psychiatric Illness | C14: =SUBSTITUTE(B14," ","") -> PsychiatricIllness | D14: =VLOOKUP(B14,'GHI Features (Option 1)'!$C$15:$J$60,3,0) -> Hospitalization > 24 hours | F14: =VLOOKUP(D14,'GHI Features (Option 1)'!$E$15:$J$60,3,0) -> ✔ | H14: =VLOOKUP(D14,'GHI Features (Option 1)'!$E$15:$J$60,4,0) -> ✔ | J14: =VLOOKUP(D14,'GHI Features (Option 1)'!$E$15:$J$60,5,0) -> ✔ | L14: =VLOOKUP(D14,'GHI Features (Option 1)'!$E$15:$J$60,6,0) -> ✔ | Q14: =B14 -> Psychiatric Illness | R14: =D14 -> Hospitalization > 24 hours | T14: =F14 -> ✔ | V14: =H14 -> ✔ | X14: =J14 -> ✔ | Z14: =L14 -> ✔
B15: Pre and Post Hospitalization Coverage | C15: =SUBSTITUTE(B15," ","") -> PreandPostHospitalizationCoverage | D15: =VLOOKUP(B15,'GHI Features (Option 1)'!$C$15:$J$60,3,0) -> Covered | F15: =VLOOKUP(D15,'GHI Features (Option 1)'!$E$15:$J$60,3,0) -> 30/60 days | H15: =VLOOKUP(D15,'GHI Features (Option 1)'!$E$15:$J$60,4,0) -> 60/90 Days | J15: =VLOOKUP(D15,'GHI Features (Option 1)'!$E$15:$J$60,5,0) -> 60/90 Days | L15: =VLOOKUP(D15,'GHI Features (Option 1)'!$E$15:$J$60,6,0) -> 30/60 days | Q15: =B15 -> Pre and Post Hospitalization Coverage | R15: =D15 -> Covered | T15: =F15 -> 30/60 days | V15: =H15 -> 60/90 Days | X15: =J15 -> 60/90 Days | Z15: =L15 -> 30/60 days
B16: Maternity Cover | C16: =SUBSTITUTE(B16," ","") -> MaternityCover | D16: =VLOOKUP(B16,'GHI Features (Option 1)'!$C$15:$J$60,3,0) -> Normal - Rs. 50k C Section - Rs. 50K | F16: =VLOOKUP(D16,'GHI Features (Option 1)'!$E$15:$J$60,3,0) -> ✔ | H16: =VLOOKUP(D16,'GHI Features (Option 1)'!$E$15:$J$60,4,0) -> Optional -50k (with extra loading) | J16: =VLOOKUP(D16,'GHI Features (Option 1)'!$E$15:$J$60,5,0) -> Optional - 35K, 50K, 75K (with extra loading) | L16: =VLOOKUP(D16,'GHI Features (Option 1)'!$E$15:$J$60,6,0) -> ✔ | Q16: =B16 -> Maternity Cover | R16: =D16 -> Normal - Rs. 50k C Section - Rs. 50K | T16: =F16 -> ✔ | V16: =H16 -> Optional -50k (with extra loading) | X16: =J16 -> Optional - 35K, 50K, 75K (with extra loading) | Z16: =L16 -> ✔
B17: Emergency Ambulance | C17: =SUBSTITUTE(B17," ","") -> EmergencyAmbulance | D17: =VLOOKUP(B17,'GHI Features (Option 1)'!$C$15:$J$60,3,0) -> Within 25 min Pan-India | F17: =VLOOKUP(D17,'GHI Features (Option 1)'!$E$15:$J$60,3,0) -> ✔ | H17: =VLOOKUP(D17,'GHI Features (Option 1)'!$E$15:$J$60,4,0) -> ✔ | J17: =VLOOKUP(D17,'GHI Features (Option 1)'!$E$15:$J$60,5,0) -> ✔ | L17: =VLOOKUP(D17,'GHI Features (Option 1)'!$E$15:$J$60,6,0) -> ✔ | Q17: =B17 -> Emergency Ambulance | R17: =D17 -> Within 25 min Pan-India | T17: =F17 -> ✔ | V17: =H17 -> ✔ | X17: =J17 -> ✔ | Z17: =L17 -> ✔
B18: Co Pay | C18: =SUBSTITUTE(B18," ","") -> CoPay | D18: =VLOOKUP(B18,'GHI Features (Option 1)'!$C$15:$J$60,3,0) -> 25% Co-Pay | F18: =VLOOKUP(D18,'GHI Features (Option 1)'!$E$15:$J$60,3,0) -> ✖ | H18: =VLOOKUP(D18,'GHI Features (Option 1)'!$E$15:$J$60,4,0) -> ✖ | J18: =VLOOKUP(D18,'GHI Features (Option 1)'!$E$15:$J$60,5,0) -> ✔ | L18: =VLOOKUP(D18,'GHI Features (Option 1)'!$E$15:$J$60,6,0) -> ✔ | Q18: =B18 -> Co Pay | R18: =D18 -> 25% Co-Pay | T18: =F18 -> ✖ | V18: =H18 -> ✖ | X18: =J18 -> ✔ | Z18: =L18 -> ✔
B19: Pre and Post Hospitalization Coverage | C19: =SUBSTITUTE(B19," ","") -> PreandPostHospitalizationCoverage | D19: =VLOOKUP(B19,'GHI Features (Option 1)'!$C$15:$J$60,3,0) -> Covered | F19: =VLOOKUP(D19,'GHI Features (Option 1)'!$E$15:$J$60,3,0) -> 30/60 days | H19: =VLOOKUP(D19,'GHI Features (Option 1)'!$E$15:$J$60,4,0) -> 60/90 Days | J19: =VLOOKUP(D19,'GHI Features (Option 1)'!$E$15:$J$60,5,0) -> 60/90 Days | L19: =VLOOKUP(D19,'GHI Features (Option 1)'!$E$15:$J$60,6,0) -> 30/60 days | Q19: =B19 -> Pre and Post Hospitalization Coverage | R19: =D19 -> Covered | T19: =F19 -> 30/60 days | V19: =H19 -> 60/90 Days | X19: =J19 -> 60/90 Days | Z19: =L19 -> 30/60 days
B25: Know Your Insurer - Credentials
L27: Incumbent Insurer | Z27: =L27 -> Incumbent Insurer
A28: Logo | B28: Features | D28: Parameter | F28: =Inputs!B14 -> Manipal Cigna Standard Rater | H28: =Inputs!C14 -> SBI General | J28: =Inputs!D14 -> Manipal Cigna | L28: =Inputs!E14 -> IFFCO Tokio | Q28: =B28 -> Features | R28: =D28 -> Parameter | T28: =F28 -> Manipal Cigna Standard Rater | V28: =H28 -> SBI General | X28: =J28 -> Manipal Cigna | Z28: =L28 -> IFFCO Tokio
B29: Background and Credibility | C29: Background and Credibility | D29: Founding Year | F29: ='GHI Insurers'!F10 -> 2001 | H29: ='GHI Insurers'!G10 -> 2001 | J29: ='GHI Insurers'!H10 -> 2014 | L29: ='GHI Insurers'!I10 -> 2000 | Q29: =B29 -> Background and Credibility | R29: =D29 -> Founding Year | T29: =F29 -> 2001 | V29: =H29 -> 2001 | X29: =J29 -> 2014 | Z29: =L29 -> 2000
D30: Backed by | F30: ='GHI Insurers'!F11 -> Bajaj Finserv and Allianz SE | H30: ='GHI Insurers'!G11 -> ICICI Bank | J30: ='GHI Insurers'!H11 -> Manipal Group, Cigna Holdings | L30: ='GHI Insurers'!I11 -> IFFCO India, Tokio Marine Insurance (Japan) | R30: =D30 -> Backed by | T30: =F30 -> Bajaj Finserv and Allianz SE | V30: =H30 -> ICICI Bank | X30: =J30 -> Manipal Group, Cigna Holdings | Z30: =L30 -> IFFCO India, Tokio Marine Insurance (Japan)
B31: Market Presence | C31: Market Presence | D31: GHI Book Size (INR Crores) | F31: ='GHI Insurers'!F13 -> ₹ 3,260 Cr | H31: ='GHI Insurers'!G13 -> ₹ 5,394 Cr | J31: ='GHI Insurers'!H13 -> ₹ 924 Cr | L31: ='GHI Insurers'!I13 -> ₹ 531 Cr | Q31: =B31 -> Market Presence | R31: =D31 -> GHI Book Size (INR Crores) | T31: =F31 -> ₹ 3,260 Cr | V31: =H31 -> ₹ 5,394 Cr | X31: =J31 -> ₹ 924 Cr | Z31: =L31 -> ₹ 531 Cr
D32: GHI Growth Rate | F32: ='GHI Insurers'!F14 -> 0.1795 | H32: ='GHI Insurers'!G14 -> 0.0948 | J32: ='GHI Insurers'!H14 -> 0.0151 | L32: ='GHI Insurers'!I14 -> -0.3608 | R32: =D32 -> GHI Growth Rate | T32: =F32 -> 0.1795 | V32: =H32 -> 0.0948 | X32: =J32 -> 0.0151 | Z32: =L32 -> -0.3608
B33: Financial Health | C33: Financial Health | D33: Solvency Ratio (IRDAI recommended: >1.5) | F33: ='GHI Insurers'!F15 -> 3.52 | H33: ='GHI Insurers'!G15 -> 2.70 | J33: ='GHI Insurers'!H15 -> 1.91 | L33: ='GHI Insurers'!I15 -> 1.86 | Q33: =B33 -> Financial Health | R33: =D33 -> Solvency Ratio (IRDAI recommended: >1.5) | T33: =F33 -> 3.52 | V33: =H33 -> 2.70 | X33: =J33 -> 1.91 | Z33: =L33 -> 1.86
B34: Policy Administration | C34: Policy Administration | D34: Policy Issuance TAT | F34: ='GHI Insurers'!F17 -> 10 to 20 days | H34: ='GHI Insurers'!G17 -> 10 to 20 days | J34: ='GHI Insurers'!H17 -> 10 to 20 days | L34: ='GHI Insurers'!I17 -> 10 to 20 days | Q34: =B34 -> Policy Administration | R34: =D34 -> Policy Issuance TAT | T34: =F34 -> 10 to 20 days | V34: =H34 -> 10 to 20 days | X34: =J34 -> 10 to 20 days | Z34: =L34 -> 10 to 20 days
D35: Endorsement TAT | F35: ='GHI Insurers'!F18 -> 1 to 3 days | H35: ='GHI Insurers'!G18 -> 1 to 3 days | J35: ='GHI Insurers'!H18 -> 3 to 5 days | L35: ='GHI Insurers'!I18 -> 5 to 10 days | R35: =D35 -> Endorsement TAT | T35: =F35 -> 1 to 3 days | V35: =H35 -> 1 to 3 days | X35: =J35 -> 3 to 5 days | Z35: =L35 -> 5 to 10 days
B36: Claims Summary | C36: Claims Summary | D36: Cashless Network | F36: ='GHI Insurers'!F20 -> 12000+ | H36: ='GHI Insurers'!G20 -> 10,200+ | J36: ='GHI Insurers'!H20 -> 8,500+ | L36: ='GHI Insurers'!I20 -> 7,000+ | Q36: =B36 -> Claims Summary | R36: =D36 -> Cashless Network | T36: =F36 -> 12000+ | V36: =H36 -> 10,200+ | X36: =J36 -> 8,500+ | Z36: =L36 -> 7,000+
D37: Claim Settlement Ratio | F37: ='GHI Insurers'!F21 -> 0.98 | H37: ='GHI Insurers'!G21 -> 0.98 | J37: ='GHI Insurers'!H21 -> 0.98 | L37: ='GHI Insurers'!I21 -> 0.98 | R37: =D37 -> Claim Settlement Ratio | T37: =F37 -> 0.98 | V37: =H37 -> 0.98 | X37: =J37 -> 0.98 | Z37: =L37 -> 0.98
D38: Cashless TAT | F38: ='GHI Insurers'!F22 -> 1 to 3 hours | H38: ='GHI Insurers'!G22 -> 1 to 3 hours | J38: ='GHI Insurers'!H22 -> 2 to 4 hours | L38: ='GHI Insurers'!I22 -> 2 to 4 hours | R38: =D38 -> Cashless TAT | T38: =F38 -> 1 to 3 hours | V38: =H38 -> 1 to 3 hours | X38: =J38 -> 2 to 4 hours | Z38: =L38 -> 2 to 4 hours
D39: Reimbursement TAT | F39: ='GHI Insurers'!F23 -> 15 to 30 days | H39: ='GHI Insurers'!G23 -> 7 to 15 days | J39: ='GHI Insurers'!H23 -> 15 to 30 days | L39: ='GHI Insurers'!I23 -> 15 to 30 days | R39: =D39 -> Reimbursement TAT | T39: =F39 -> 15 to 30 days | V39: =H39 -> 7 to 15 days | X39: =J39 -> 15 to 30 days | Z39: =L39 -> 15 to 30 days
D40: % of claims settled in 3 months | F40: ='GHI Insurers'!F24 -> 0.996 | H40: ='GHI Insurers'!G24 -> 1 | J40: ='GHI Insurers'!H24 -> 0.999 | L40: ='GHI Insurers'!I24 -> 0.8989 | R40: =D40 -> % of claims settled in 3 months | T40: =F40 -> 0.996 | V40: =H40 -> 1 | X40: =J40 -> 0.999 | Z40: =L40 -> 0.8989
D41: Reimbursement Mode (Paperless/Paper) | F41: ='GHI Insurers'!F25 -> Paperless | H41: ='GHI Insurers'!G25 -> Paperless | J41: ='GHI Insurers'!H25 -> Paperless | L41: ='GHI Insurers'!I25 -> Paper-based | R41: =D41 -> Reimbursement Mode (Paperless/Paper) | T41: =F41 -> Paperless | V41: =H41 -> Paperless | X41: =J41 -> Paperless | Z41: =L41 -> Paper-based
D42: TPA (in-house or External) | F42: ='GHI Insurers'!F26 -> In-house | H42: ='GHI Insurers'!G26 -> In-house | J42: ='GHI Insurers'!H26 -> In-house External Option available | L42: ='GHI Insurers'!I26 -> In-house External Option available | R42: =D42 -> TPA (in-house or External) | T42: =F42 -> In-house | V42: =H42 -> In-house | X42: =J42 -> In-house External Option available | Z42: =L42 -> In-house External Option available
D45: ='High Level Quotes - Slide 1'!P2 -> File Path of Proposal Deck

Sheet Company Info
A1: Healthysure Template
A2: Basic Company Details
A4: Brand Name of the Company | B4: ABC
A5: Legal Name of the Company | B5: M/S ABC Private Limited
A6: Address of the Company | B6: XXXX
A7: Pincode of the Company | B7: 400009
A8: Contact Person - Name | B8: Pending
A9: Contact Person - Mobile No | B9: Pending
A10: Contact Person - Email ID | B10: Pending
A11: GST or PAN of Company | B11: Pending
A12: Nature of Industry | B12: Education

Sheet Base GHI
A1: Features | B1: Remarks | C1: Go Digit | D1: Care Health (Religare) | E1: TATA AIG | F1: Niva Bupa | G1: Magma HDI | H1: New India Assurance | I1: IFFCO Tokio | J1: ICICI Lombard | K1: ICICI Lombard - Startup Pack | L1: Star Health | M1: Bajaj Allianz | N1: Oriental Insurance | O1: Future Generali | P1: Kenko | Q1: Acko | R1: Aditya Birla Health | S1: Raheja QBE
A2: Family Definition | B2: Self | C2: ✔ | D2: ✔ | E2: ✔ | F2: ✔ | G2: ✔ | H2: ✔ | I2: ✔ | J2: ✔ | K2: ✔ | L2: ✔ | M2: ✔ | N2: ✔ | O2: ✔ | P2: ✔ | Q2: ✔ | R2: ✔ | S2: ✔
B3: Spouse | C3: ✔ | D3: ✔ | E3: ✔ | F3: ✔ | G3: ✔ | H3: ✔ | I3: ✔ | J3: ✔ | K3: ✔ | L3: ✔ | M3: ✔ | N3: ✔ | O3: ✔ | P3: ✔ | Q3: ✔ | R3: ✔ | S3: ✔
B4: Children - upto 25 yrs of age | C4: 6 | D4: 4 | E4: 3 | F4: 3 | G4: 2 | H4: 2 | I4: 2 | J4: 4 | K4: 2 | L4: 2 | N4: 2 | P4: 2 | Q4: 2 | R4: 2 | S4: 2
B5: 2 Parents/PIL - upto 80 yrs of age | C5: ✔ | D5: ✔ | E5: ✔ | F5: ✔ | G5: ✔ | H5: ✔ | I5: Parents Only | J5: ✔ | K5: r | L5: Parents Only | N5: ✔ | P5: ✔ | Q5: ✔ | R5: Upto 90 Years | S5: Upto 90 Years
A6: Type of Over | B6: Family Floater/ Individual | C6: ✔ | D6: ✔ | E6: ✔ | F6: ✔ | G6: ✔ | H6: ✔ | I6: ✔ | J6: ✔ | K6: ✔ | L6: ✔ | M6: ✔ | N6: ✔ | O6: ✔ | P6: ✔ | Q6: ✔ | R6: ✔ | S6: ✔
A7: Room Rent Restriction | B7: Normal- Single Pvt AC | C7: ✔ | D7: ✔ | E7: 2% of SI upto Rs. 4k per day | F7: 2% of SI | G7: 2% of SI upto Rs. 5k per day | H7: 2% of SI upto Rs. 5k per day | I7: 2% of SI | J7: 2% of SI | K7: Rs. 5k per day | L7: Rs. 5k per day | N7: 2% of SI | O7: ✔ | P7: ✔ | Q7: 2% of SI | R7: 2% of SI | S7: 2% of SI
B8: ICU - No Capping | C8: ✔ | D8: ✔ | E8: ✔ | F8: 4% of SI | G8: 4% of SI upto Rs. 10k per day | H8: 4% of SI upto Rs. 10k per day | I8: 4% of SI | J8: 4% of SI | K8: Rs. 8k per day | L8: ✔ | N8: 4% of SI | O8: ✔ | P8: ✔ | Q8: 4% of SI | R8: 4% of SI | S8: 4% of SI
A9: Co Pay | B9: 0% Co-Pay | C9: ✔ | D9: ✔ | E9: ✔ | F9: ✔ | G9: ✔ | H9: ✔ | I9: ✔ | J9: ✔ | K9: ✔ | L9: ✔ | N9: ✔ | O9: ✔ | P9: ✔ | Q9: ✔ | R9: ✔ | S9: ✔
A10: Corporate Buffer | B10: Rs. XXX restricted to Family Floater SI | C10: ✔ | D10: ✔ | E10: ✔ | F10: ✔ | G10: ✔ | H10: ✔ | I10: ✔ | J10: ✔ | K10: ✔ | L10: ✔ | N10: ✔ | O10: ✔ | P10: ✔ | Q10: ✔ | R10: ✔ | S10: ✔
B11: Applicable for | C11: For all ailments | D11: For critical illness only | E11: For critical illness only | F11: For all ailments | G11: For all ailments | H11: For all ailments | I11: For all ailments | J11: For all ailments | K11: For all ailments | L11: For all ailments | M11: For all ailments | N11: For all ailments | O11: For all ailments | P11: For all ailments | Q11: For all ailments | R11: For all ailments | S11: For all ailments
A12: Upgrade Option | B12: Flexi Top-up Insurance of Rs 30 Lacs with continuity option | C12: ✔ | D12: ✔ | E12: ✔ | F12: ✔ | G12: ✔ | H12: ✔ | I12: ✔ | J12: ✔ | K12: ✔ | L12: ✔ | M12: ✔ | N12: ✔ | O12: ✔ | P12: ✔ | Q12: ✔ | R12: ✔ | S12: ✔
A13: Pan-India Coverage | B13: Pan-India Coverage | C13: ✔ | D13: ✔ | E13: ✔ | F13: ✔ | G13: ✔ | H13: ✔ | I13: ✔ | J13: ✔ | K13: ✔ | L13: ✔ | M13: ✔ | N13: ✔ | O13: ✔ | P13: ✔ | Q13: ✔ | R13: ✔ | S13: ✔
A14: Cashless Network | B14: No. of Network Hospitals | C14: 8,500+ Hospitals | D14: 8,350+ Hospitals | E14: 7,200+ Hospitals | F14: 8,600+ Hospitals | G14: 6,000+ Hospitals | H14: 6,500+ Hospitals | I14: 7,500+ Hospitals | J14: 6,500+ Hospitals | K14: 6,500+ Hospitals | L14: 8,500+ Hospitals | M14: 6500+ Hospitals | N14: 6,500+ Hospitals | O14: 6,000+ Hospitals | P14: All hospitals (Cashless option substituted by Advance Reimbursement) | Q14: 6,500+ Hospitals | R14: 10,000+ Hospitals | S14: 8,500+ Hospitals
A15: Reimbursement Network | B15: All Hospitals | C15: ✔ | D15: ✔ | E15: ✔ | F15: ✔ | G15: ✔ | H15: ✔ | I15: ✔ | J15: ✔ | K15: ✔ | L15: ✔ | M15: ✔ | N15: ✔ | O15: ✔ | P15: ✔ | Q15: ✔ | R15: ✔ | S15: ✔
A16: TPA | B16: TPA | C16: Medi Assist Insurance | D16: Inhouse TPA | E16: Family Health Insurance TPA | F16: Inhouse TPA | G16: Paramount TPA | H16: Paramount TPA | I16: Paramount TPA/ Internal TPA | J16: Inhouse TPA | K16: Inhouse TPA | L16: Inhouse TPA | M16: Inhouse TPA | N16: Paramount TPA | O16: Inhouse TPA | P16: Inhouse TPA | Q16: Cashless through Family Health & Reimbursement through Inhouse TPA | R16: Inhouse TPA / Medi Assist TPA/ Paramount TPA | S16: Paramount TPA
A17: Inpatient Hospitalization | B17: Hospitallization > 24 hours | C17: ✔ | D17: ✔ | E17: ✔ | F17: ✔ | G17: ✔ | H17: ✔ | I17: ✔ | J17: ✔ | K17: ✔ | L17: ✔ | M17: ✔ | N17: ✔ | O17: ✔ | P17: ✔ | Q17: ✔ | R17: ✔ | S17: ✔
A18: Day Care Treatments | B18: Hospitallization < 24 hours | C18: All procedures | D18: All procedures | E18: 540+ Listed Procedures | F18: 540+ Listed Procedures | G18: 540+ Listed Procedures | H18: 130+ Listed Procedures | I18: 380+ Listed Procedures | J18: 150+ Listed Procedures | K18: 150+ Listed Procedures | L18: All procedures | M18: 130+ Listed Procedures | N18: 110+ Listed Procedures | O18: 400+ Listed Procedures | P18: All procedures | Q18: 130+ Listed Procedures | R18: 527+ Listed Procedures | S18: All procedures
A19: Disease Capping | B19: No disease capping | C19: ✔ | D19: ✔ | E19: ✔ | F19: ✔ | G19: Only on CKD and Cancer Upto 3 Lacs | H19: ✔ | I19: ✔ | J19: ✔ | K19: ✔ | L19: ✔ | M19: ✔ | N19: ✔ | O19: ✔ | P19: Only on Cataract upto 50K | Q19: ✔ | R19: ✔ | S19: ✔
A20: COVID-19 Coverage | B20: Hospitallization > 24 hours | C20: ✔ | D20: ✔ | E20: ✔ | F20: ✔ | G20: ✔ | H20: ✔ | I20: ✔ | J20: ✔ | K20: ✔ | L20: ✔ | M20: ✔ | N20: ✔ | O20: ✔ | P20: ✔ | Q20: ✔ | R20: ✔ | S20: ✔
A21: Domicillary Hospitalization | B21: Home hospitalization > 3 days + Patient unable to move OR hospital bed not available | C21: ✔ | D21: r | E21: ✔ | F21: ✔ | G21: r | H21: r | I21: ✔ | J21: r | K21: ✔ | L21: r | M21: r | N21: r | O21: r | P21: r | Q21: r | R21: ✔ | S21: ✔
A22: Pre/Post Hospitalization Coverage (medicines, lab tests and consultations for IPD treatments) | B22: 30/60 days (For in-patient Hospitalization) | C22: ✔ | D22: ✔ | E22: ✔ | F22: ✔ | G22: ✔ | H22: ✔ | I22: ✔ | J22: 60/90 Days | K22: ✔ | L22: ✔ | M22: ✔ | N22: ✔ | O22: ✔ | P22: 90/90 Days | Q22: ✔ | R22: ✔ | S22: ✔
A23: Doctor Teleconsultations | B23: Unlimited with General Physicians | C23: ✔ | D23: ✔ | E23: ✔ | F23: ✔ | G23: ✔ | H23: ✔ | I23: ✔ | J23: ✔ | K23: ✔ | L23: ✔ | M23: ✔ | N23: ✔ | O23: ✔ | P23: ✔ | Q23: ✔ | R23: ✔ | S23: ✔
... A49: Reimbursement Claim Submission | B49: Criteria for document submission within 30 days from date of discharge waived off | C49: ✔ | D49: ✔ | E49: ✔ | F49: ✔ | G49: ✔ | H49: ✔ | I49: ✔ | J49: ✔ | K49: ✔ | L49: ✔ | M49: ✔ | N49: ✔ | O49: ✔ | P49: ✔ | Q49: ✔ | R49: ✔ | S49: ✔
A50: *Terms and conditions as per policy wordings apply

Sheet GHI Features (Option 1)
A1: x
A2: =Inputs!B2 -> 45177 | C2: Group Health Insurance
C3: Client Name | G3: ='Company Info'!B4 -> ABC
C4: Type of Policy | G4: Rollover | K4: Manual
C5: Policy Period | G5: 1-Apr-25 To 31-Mar-26 | K5: Manual
G7: PROPOSED INSURERS | J7: PREVIOUS INSURER
G8: HDFC Ergo | H8: Manipal Cigna (Gig Exclusive) | I8: Manipal Cigna (SME Exclusive) | J8: Care Health
C9: Premium Details
C10: Sum Insured (Rs.) | E10: In INR | G10: 5 lacs | H10: 5 lacs | I10: 5 lacs | J10: 5 lacs | K10: Manual
C11: Annual Premium (Excl. GST) | E11: In INR | G11: 629670 | H11: 700000 | I11: 750000 | J11: =Inputs!L25 -> 3,13,559 | K11: Manual
C12: Total Number of Lives | E12: Count | G12: 60 | H12: 60 | I12: 60 | J12: =Inputs!G25 -> 30 | K12: Manual
C13: Avg. Premium Per Life | E13: In INR | G13: =G11/G12 -> 10494.5 | H13: =H11/H12 -> 11666.667 | I13: =I11/I12 -> 12500 | J13: =J11/J12 -> 10451.967
C14: Policy Features - Group Health Insurance
B15: Members Covered | C15: Family Definition | D15: =SUBSTITUTE($C$15," ","") -> FamilyDefinition | E15: Self | G15: =INDEX('GHI DB'!$A$3:$BS$27,MATCH('GHI Features (Option 1)'!G$8,'GHI DB'!$A$3:$A$27,0),MATCH('GHI Features (Option 1)'!$E15,'GHI DB'!$A$3:$BS$3,0)) -> ✔ | H15: =INDEX('GHI DB'!$A$3:$BS$27,MATCH('GHI Features (Option 1)'!H$8,'GHI DB'!$A$3:$A$27,0),MATCH('GHI Features (Option 1)'!$E15,'GHI DB'!$A$3:$BS$3,0)) -> ✔ | I15: =INDEX('GHI DB'!$A$3:$BS$27,MATCH('GHI Features (Option 1)'!I$8,'GHI DB'!$A$3:$A$27,0),MATCH('GHI Features (Option 1)'!$E15,'GHI DB'!$A$3:$BS$3,0)) -> ✔ | J15: =INDEX('GHI DB'!$A$3:$BS$27,MATCH('GHI Features (Option 1)'!J$8,'GHI DB'!$A$3:$A$27,0),MATCH('GHI Features (Option 1)'!$E15,'GHI DB'!$A$3:$BS$3,0)) -> ✔
D16: =SUBSTITUTE($C$15," ","") -> FamilyDefinition | E16: Spouse | G16: =INDEX('GHI DB'!$A$3:$BS$27,MATCH('GHI Features (Option 1)'!G$8,'GHI DB'!$A$3:$A$27,0),MATCH('GHI Features (Option 1)'!$E16,'GHI DB'!$A$3:$BS$3,0)) -> ✔ | H16: =INDEX('GHI DB'!$A$3:$BS$27,MATCH('GHI Features (Option 1)'!H$8,'GHI DB'!$A$3:$A$27,0),MATCH('GHI Features (Option 1)'!$E16,'GHI DB'!$A$3:$BS$3,0)) -> ✔ | I16: =INDEX('GHI DB'!$A$3:$BS$27,MATCH('GHI Features (Option 1)'!I$8,'GHI DB'!$A$3:$A$27,0),MATCH('GHI Features (Option 1)'!$E16,'GHI DB'!$A$3:$BS$3,0)) -> ✔ | J16: =INDEX('GHI DB'!$A$3:$BS$27,MATCH('GHI Features (Option 1)'!J$8,'GHI DB'!$A$3:$A$27,0),MATCH('GHI Features (Option 1)'!$E16,'GHI DB'!$A$3:$BS$3,0)) -> ✔
D17: =SUBSTITUTE($C$15," ","") -> FamilyDefinition | E17: Children - upto 25 yrs of age | G17: =INDEX('GHI DB'!$A$3:$BS$27,MATCH('GHI Features (Option 1)'!G$8,'GHI DB'!$A$3:$A$27,0),MATCH('GHI Features (Option 1)'!$E17,'GHI DB'!$A$3:$BS$3,0)) -> 2 | H17: =INDEX('GHI DB'!$A$3:$BS$27,MATCH('GHI Features (Option 1)'!H$8,'GHI DB'!$A$3:$A$27,0),MATCH('GHI Features (Option 1)'!$E17,'GHI DB'!$A$3:$BS$3,0)) -> 4 | I17: =INDEX('GHI DB'!$A$3:$BS$27,MATCH('GHI Features (Option 1)'!I$8,'GHI DB'!$A$3:$A$27,0),MATCH('GHI Features (Option 1)'!$E17,'GHI DB'!$A$3:$BS$3,0)) -> 4 | J17: =INDEX('GHI DB'!$A$3:$BS$27,MATCH('GHI Features (Option 1)'!J$8,'GHI DB'!$A$3:$A$27,0),MATCH('GHI Features (Option 1)'!$E17,'GHI DB'!$A$3:$BS$3,0)) -> 4
D18: =SUBSTITUTE($C$15," ","") -> FamilyDefinition | E18: 2 Parents/PIL - upto 80 yrs of age | G18: =INDEX('GHI DB'!$A$3:$BS$27,MATCH('GHI Features (Option 1)'!G$8,'GHI DB'!$A$3:$A$27,0),MATCH('GHI Features (Option 1)'!$E18,'GHI DB'!$A$3:$BS$3,0)) -> ✔ | H18: =INDEX('GHI DB'!$A$3:$BS$27,MATCH('GHI Features (Option 1)'!H$8,'GHI DB'!$A$3:$A$27,0),MATCH('GHI Features (Option 1)'!$E18,'GHI DB'!$A$3:$BS$3,0)) -> ✖ | I18: =INDEX('GHI DB'!$A$3:$BS$27,MATCH('GHI Features (Option 1)'!I$8,'GHI DB'!$A$3:$A$27,0),MATCH('GHI Features (Option 1)'!$E18,'GHI DB'!$A$3:$BS$3,0)) -> ✖ | J18: =INDEX('GHI DB'!$A$3:$BS$27,MATCH('GHI Features (Option 1)'!J$8,'GHI DB'!$A$3:$A$27,0),MATCH('GHI Features (Option 1)'!$E18,'GHI DB'!$A$3:$BS$3,0)) -> ✔ | O18: `
B20: Policy Type | C20: Type of Cover | D20: =SUBSTITUTE(C20," ","") -> TypeofCover | E20: Family Floater | G20: =INDEX('GHI DB'!$A$3:$BS$27,MATCH('GHI Features (Option 1)'!G$8,'GHI DB'!$A$3:$A$27,0),MATCH('GHI Features (Option 1)'!$E20,'GHI DB'!$A$3:$BS$3,0)) -> ✔ | H20: =INDEX('GHI DB'!$A$3:$BS$27,MATCH('GHI Features (Option 1)'!H$8,'GHI DB'!$A$3:$A$27,0),MATCH('GHI Features (Option 1)'!$E20,'GHI DB'!$A$3:$BS$3,0)) -> ✖ | I20: =INDEX('GHI DB'!$A$3:$BS$27,MATCH('GHI Features (Option 1)'!I$8,'GHI DB'!$A$3:$A$27,0),MATCH('GHI Features (Option 1)'!$E20,'GHI DB'!$A$3:$BS$3,0)) -> ✔ | J20: =INDEX('GHI DB'!$A$3:$BS$27,MATCH('GHI Features (Option 1)'!J$8,'GHI DB'!$A$3:$A$27,0),MATCH('GHI Features (Option 1)'!$E20,'GHI DB'!$A$3:$BS$3,0)) -> ✔
C21: Room Rent Restriction | D21: =SUBSTITUTE(C21," ","") -> RoomRentRestriction | E21: Normal - No Capping ICU - No Capping | G21: =INDEX('GHI DB'!$A$3:$BS$27,MATCH('GHI Features (Option 1)'!G$8,'GHI DB'!$A$3:$A$27,0),MATCH('GHI Features (Option 1)'!$E21,'GHI DB'!$A$3:$BS$3,0)) -> ✔ | H21: =INDEX('GHI DB'!$A$3:$BS$27,MATCH('GHI Features (Option 1)'!H$8,'GHI DB'!$A$3:$A$27,0),MATCH('GHI Features (Option 1)'!$E21,'GHI DB'!$A$3:$BS$3,0)) -> For SI 1 lac - Rs. 2,000 for Normal, Rs. 4,000 for ICU For SI 2/3 lac - Rs. 5,000 for Normal, Rs. 10,000 for ICU | I21: =INDEX('GHI DB'!$A$3:$BS$27,MATCH('GHI Features (Option 1)'!I$8,'GHI DB'!$A$3:$A$27,0),MATCH('GHI Features (Option 1)'!$E21,'GHI DB'!$A$3:$BS$3,0)) -> For SI 1 lac - Rs. 2,000 for Normal, Rs. 4,000 for ICU For SI 2 lac/ 3 lac - Rs. 5,000 for Normal, Rs. 10,000 for ICU For SI 5 lac - Single Private AC, No Limit for ICU | J21: =INDEX('GHI DB'!$A$3:$BS$27,MATCH('GHI Features (Option 1)'!J$8,'GHI DB'!$A$3:$A$27,0),MATCH('GHI Features (Option 1)'!$E21,'GHI DB'!$A$3:$BS$3,0)) -> ✔ | K21: Recheck with Quote Slip for non-standard programs
C22: Co Pay | D22: =SUBSTITUTE(C22," ","") -> CoPay | E22: 25% Co-Pay | G22: =INDEX('GHI DB'!$A$3:$BS$27,MATCH('GHI Features (Option 1)'!G$8,'GHI DB'!$A$3:$A$27,0),MATCH('GHI Features (Option 1)'!$E22,'GHI DB'!$A$3:$BS$3,0)) -> ✖ | H22: =INDEX('GHI DB'!$A$3:$BS$27,MATCH('GHI Features (Option 1)'!H$8,'GHI DB'!$A$3:$A$27,0),MATCH('GHI Features (Option 1)'!$E22,'GHI DB'!$A$3:$BS$3,0)) -> ✖ | I22: =INDEX('GHI DB'!$A$3:$BS$27,MATCH('GHI Features (Option 1)'!I$8,'GHI DB'!$A$3:$A$27,0),MATCH('GHI Features (Option 1)'!$E22,'GHI DB'!$A$3:$BS$3,0)) -> ✔ | J22: =INDEX('GHI DB'!$A$3:$BS$27,MATCH('GHI Features (Option 1)'!J$8,'GHI DB'!$A$3:$A$27,0),MATCH('GHI Features (Option 1)'!$E22,'GHI DB'!$A$3:$BS$3,0)) -> ✔
C23: Corporate Buffer | D23: =SUBSTITUTE(C23," ","") -> CorporateBuffer | E23: Not Covered | G23: =INDEX('GHI DB'!$A$3:$BS$27,MATCH('GHI Features (Option 1)'!G$8,'GHI DB'!$A$3:$A$27,0),MATCH('GHI Features (Option 1)'!$E23,'GHI DB'!$A$3:$BS$3,0)) -> Not Covered | H23: =INDEX('GHI DB'!$A$3:$BS$27,MATCH('GHI Features (Option 1)'!H$8,'GHI DB'!$A$3:$A$27,0),MATCH('GHI Features (Option 1)'!$E23,'GHI DB'!$A$3:$BS$3,0)) -> Not Covered | I23: =INDEX('GHI DB'!$A$3:$BS$27,MATCH('GHI Features (Option 1)'!I$8,'GHI DB'!$A$3:$A$27,0),MATCH('GHI Features (Option 1)'!$E23,'GHI DB'!$A$3:$BS$3,0)) -> Not Covered | J23: =INDEX('GHI DB'!$A$3:$BS$27,MATCH('GHI Features (Option 1)'!J$8,'GHI DB'!$A$3:$A$27,0),MATCH('GHI Features (Option 1)'!$E23,'GHI DB'!$A$3:$BS$3,0)) -> Not Covered
B25: Hospitalization Coverage | C25: Inpatient Hospitalization | D25: =SUBSTITUTE(C25," ","") -> InpatientHospitalization | E25: Hospitalization > 24 hours | G25: =INDEX('GHI DB'!$A$3:$BS$27,MATCH('GHI Features (Option 1)'!G$8,'GHI DB'!$A$3:$A$27,0),MATCH('GHI Features (Option 1)'!$E25,'GHI DB'!$A$3:$BS$3,0)) -> ✔ | H25: =INDEX('GHI DB'!$A$3:$BS$27,MATCH('GHI Features (Option 1)'!H$8,'GHI DB'!$A$3:$A$27,0),MATCH('GHI Features (Option 1)'!$E25,'GHI DB'!$A$3:$BS$3,0)) -> ✔ | I25: =INDEX('GHI DB'!$A$3:$BS$27,MATCH('GHI Features (Option 1)'!I$8,'GHI DB'!$A$3:$A$27,0),MATCH('GHI Features (Option 1)'!$E25,'GHI DB'!$A$3:$BS$3,0)) -> ✔ | J25: =INDEX('GHI DB'!$A$3:$BS$27,MATCH('GHI Features (Option 1)'!J$8,'GHI DB'!$A$3:$A$27,0),MATCH('GHI Features (Option 1)'!$E25,'GHI DB'!$A$3:$BS$3,0)) -> ✔
C26: Day Care Treatments | D26: =SUBSTITUTE(C26," ","") -> DayCareTreatments | E26: Hospitalization < 24 hours | G26: =INDEX('GHI DB'!$A$3:$BS$27,MATCH('GHI Features (Option 1)'!G$8,'GHI DB'!$A$3:$A$27,0),MATCH('GHI Features (Option 1)'!$E26,'GHI DB'!$A$3:$BS$3,0)) -> ✔ (Listed Procedures Only) | H26: =INDEX('GHI DB'!$A$3:$BS$27,MATCH('GHI Features (Option 1)'!H$8,'GHI DB'!$A$3:$A$27,0),MATCH('GHI Features (Option 1)'!$E26,'GHI DB'!$A$3:$BS$3,0)) -> ✔ (Listed Procedures Only) | I26: =INDEX('GHI DB'!$A$3:$BS$27,MATCH('GHI Features (Option 1)'!I$8,'GHI DB'!$A$3:$A$27,0),MATCH('GHI Features (Option 1)'!$E26,'GHI DB'!$A$3:$BS$3,0)) -> ✔ (Listed Procedures Only) | J26: =INDEX('GHI DB'!$A$3:$BS$27,MATCH('GHI Features (Option 1)'!J$8,'GHI DB'!$A$3:$A$27,0),MATCH('GHI Features (Option 1)'!$E26,'GHI DB'!$A$3:$BS$3,0)) -> ✔ (Listed Procedures Only)
C27: Disease Capping | D27: =SUBSTITUTE(C27," ","") -> DiseaseCapping | E27: No disease capping | G27: =INDEX('GHI DB'!$A$3:$BS$27,MATCH('GHI Features (Option 1)'!G$8,'GHI DB'!$A$3:$A$27,0),MATCH('GHI Features (Option 1)'!$E27,'GHI DB'!$A$3:$BS$3,0)) -> ✔ | H27: =INDEX('GHI DB'!$A$3:$BS$27,MATCH('GHI Features (Option 1)'!H$8,'GHI DB'!$A$3:$A$27,0),MATCH('GHI Features (Option 1)'!$E27,'GHI DB'!$A$3:$BS$3,0)) -> ✔ | I27: =INDEX('GHI DB'!$A$3:$BS$27,MATCH('GHI Features (Option 1)'!I$8,'GHI DB'!$A$3:$A$27,0),MATCH('GHI Features (Option 1)'!$E27,'GHI DB'!$A$3:$BS$3,0)) -> ✔ | J27: =INDEX('GHI DB'!$A$3:$BS$27,MATCH('GHI Features (Option 1)'!J$8,'GHI DB'!$A$3:$A$27,0),MATCH('GHI Features (Option 1)'!$E27,'GHI DB'!$A$3:$BS$3,0)) -> ✔
C28: COVID 19 Coverage | D28: =SUBSTITUTE(C28," ","") -> COVID19Coverage | E28: Hospitalization > 24 hours | G28: =INDEX('GHI DB'!$A$3:$BS$27,MATCH('GHI Features (Option 1)'!G$8,'GHI DB'!$A$3:$A$27,0),MATCH('GHI Features (Option 1)'!$E28,'GHI DB'!$A$3:$BS$3,0)) -> ✔ | H28: =INDEX('GHI DB'!$A$3:$BS$27,MATCH('GHI Features (Option 1)'!H$8,'GHI DB'!$A$3:$A$27,0),MATCH('GHI Features (Option 1)'!$E28,'GHI DB'!$A$3:$BS$3,0)) -> ✔ | I28: =INDEX('GHI DB'!$A$3:$BS$27,MATCH('GHI Features (Option 1)'!I$8,'GHI DB'!$A$3:$A$27,0),MATCH('GHI Features (Option 1)'!$E28,'GHI DB'!$A$3:$BS$3,0)) -> ✔ | J28: =INDEX('GHI DB'!$A$3:$BS$27,MATCH('GHI Features (Option 1)'!J$8,'GHI DB'!$A$3:$A$27,0),MATCH('GHI Features (Option 1)'!$E28,'GHI DB'!$A$3:$BS$3,0)) -> ✔
C29: Domicillary Hospitalization | D29: =SUBSTITUTE(C29," ","") -> DomicillaryHospitalization | E29: Home hospitalization > 3 days + Patient unable to move OR hospital bed not available | G29: =INDEX('GHI DB'!$A$3:$BS$27,MATCH('GHI Features (Option 1)'!G$8,'GHI DB'!$A$3:$A$27,0),MATCH('GHI Features (Option 1)'!$E29,'GHI DB'!$A$3:$BS$3,0)) -> ✖ | H29: =INDEX('GHI DB'!$A$3:$BS$27,MATCH('GHI Features (Option 1)'!H$8,'GHI DB'!$A$3:$A$27,0),MATCH('GHI Features (Option 1)'!$E29,'GHI DB'!$A$3:$BS$3,0)) -> ✖ | I29: =INDEX('GHI DB'!$A$3:$BS$27,MATCH('GHI Features (Option 1)'!I$8,'GHI DB'!$A$3:$A$27,0),MATCH('GHI Features (Option 1)'!$E29,'GHI DB'!$A$3:$BS$3,0)) -> ✖ | J29: =INDEX('GHI DB'!$A$3:$BS$27,MATCH('GHI Features (Option 1)'!J$8,'GHI DB'!$A$3:$A$27,0),MATCH('GHI Features (Option 1)'!$E29,'GHI DB'!$A$3:$BS$3,0)) -> ✔
B31: Pre and Post Hospitalization Coverage (medicines, lab tests and consultations for IPD treatments) | C31: Pre and Post Hospitalization Coverage | D31: =SUBSTITUTE(C31," ","") -> PreandPostHospitalizationCoverage | E31: Covered | G31: =INDEX('GHI DB'!$A$3:$BS$27,MATCH('GHI Features (Option 1)'!G$8,'GHI DB'!$A$3:$A$27,0),MATCH('GHI Features (Option 1)'!$E31,'GHI DB'!$A$3:$BS$3,0)) -> 30/60 days | H31: =INDEX('GHI DB'!$A$3:$BS$27,MATCH('GHI Features (Option 1)'!H$8,'GHI DB'!$A$3:$A$27,0),MATCH('GHI Features (Option 1)'!$E31,'GHI DB'!$A$3:$BS$3,0)) -> 60/90 Days | I31: =INDEX('GHI DB'!$A$3:$BS$27,MATCH('GHI Features (Option 1)'!I$8,'GHI DB'!$A$3:$A$27,0),MATCH('GHI Features (Option 1)'!$E31,'GHI DB'!$A$3:$BS$3,0)) -> 60/90 Days | J31: =INDEX('GHI DB'!$A$3:$BS$27,MATCH('GHI Features (Option 1)'!J$8,'GHI DB'!$A$3:$A$27,0),MATCH('GHI Features (Option 1)'!$E31,'GHI DB'!$A$3:$BS$3,0)) -> 30/60 days
B33: Maternity Coverage | C33: Maternity Cover | D33: =SUBSTITUTE(C33," ","") -> MaternityCover | E33: Normal - Rs. 50k C Section - Rs. 50K | G33: =INDEX('GHI DB'!$A$3:$BS$27,MATCH('GHI Features (Option 1)'!G$8,'GHI DB'!$A$3:$A$27,0),MATCH('GHI Features (Option 1)'!$E33,'GHI DB'!$A$3:$BS$3,0)) -> ✔ | H33: =INDEX('GHI DB'!$A$3:$BS$27,MATCH('GHI Features (Option 1)'!H$8,'GHI DB'!$A$3:$A$27,0),MATCH('GHI Features (Option 1)'!$E33,'GHI DB'!$A$3:$BS$3,0)) -> Optional -50k (with extra loading) | I33: =INDEX('GHI DB'!$A$3:$BS$27,MATCH('GHI Features (Option 1)'!I$8,'GHI DB'!$A$3:$A$27,0),MATCH('GHI Features (Option 1)'!$E33,'GHI DB'!$A$3:$BS$3,0)) -> Optional - 35K, 50K, 75K (with extra loading) | J33: =INDEX('GHI DB'!$A$3:$BS$27,MATCH('GHI Features (Option 1)'!J$8,'GHI DB'!$A$3:$A$27,0),MATCH('GHI Features (Option 1)'!$E33,'GHI DB'!$A$3:$BS$3,0)) -> ✔
C34: Maternity Waiting Period | D34: =SUBSTITUTE(C34," ","") -> MaternityWaitingPeriod | E34: Not Applicable | G34: =INDEX('GHI DB'!$A$3:$BS$27,MATCH('GHI Features (Option 1)'!G$8,'GHI DB'!$A$3:$A$27,0),MATCH('GHI Features (Option 1)'!$E34,'GHI DB'!$A$3:$BS$3,0)) -> Not Applicable | H34: =INDEX('GHI DB'!$A$3:$BS$27,MATCH('GHI Features (Option 1)'!H$8,'GHI DB'!$A$3:$A$27,0),MATCH('GHI Features (Option 1)'!$E34,'GHI DB'!$A$3:$BS$3,0)) -> Not Applicable | I34: =INDEX('GHI DB'!$A$3:$BS$27,MATCH('GHI Features (Option 1)'!I$8,'GHI DB'!$A$3:$A$27,0),MATCH('GHI Features (Option 1)'!$E34,'GHI DB'!$A$3:$BS$3,0)) -> Not Applicable | J34: =INDEX('GHI DB'!$A$3:$BS$27,MATCH('GHI Features (Option 1)'!J$8,'GHI DB'!$A$3:$A$27,0),MATCH('GHI Features (Option 1)'!$E34,'GHI DB'!$A$3:$BS$3,0)) -> Not Applicable
C35: Pre and Post Natal Expenses | D35: =SUBSTITUTE(C35," ","") -> PreandPostNatalExpenses | E35: Covered within maternity limit | G35: =INDEX('GHI DB'!$A$3:$BS$27,MATCH('GHI Features (Option 1)'!G$8,'GHI DB'!$A$3:$A$27,0),MATCH('GHI Features (Option 1)'!$E35,'GHI DB'!$A$3:$BS$3,0)) -> ✖ | H35: =INDEX('GHI DB'!$A$3:$BS$27,MATCH('GHI Features (Option 1)'!H$8,'GHI DB'!$A$3:$A$27,0),MATCH('GHI Features (Option 1)'!$E35,'GHI DB'!$A$3:$BS$3,0)) -> ✖ | I35: =INDEX('GHI DB'!$A$3:$BS$27,MATCH('GHI Features (Option 1)'!I$8,'GHI DB'!$A$3:$A$27,0),MATCH('GHI Features (Option 1)'!$E35,'GHI DB'!$A$3:$BS$3,0)) -> ✔ | J35: =INDEX('GHI DB'!$A$3:$BS$27,MATCH('GHI Features (Option 1)'!J$8,'GHI DB'!$A$3:$A$27,0),MATCH('GHI Features (Option 1)'!$E35,'GHI DB'!$A$3:$BS$3,0)) -> ✖
B37: Waiting Period Benefits | C37: Initial Waiting Period | D37: =SUBSTITUTE(C37," ","") -> InitialWaitingPeriod | E37: Waived Off | G37: =INDEX('GHI DB'!$A$3:$BS$27,MATCH('GHI Features (Option 1)'!G$8,'GHI DB'!$A$3:$A$27,0),MATCH('GHI Features (Option 1)'!$E37,'GHI DB'!$A$3:$BS$3,0)) -> ✔ | H37: =INDEX('GHI DB'!$A$3:$BS$27,MATCH('GHI Features (Option 1)'!H$8,'GHI DB'!$A$3:$A$27,0),MATCH('GHI Features (Option 1)'!$E37,'GHI DB'!$A$3:$BS$3,0)) -> ✖ | I37: =INDEX('GHI DB'!$A$3:$BS$27,MATCH('GHI Features (Option 1)'!I$8,'GHI DB'!$A$3:$A$27,0),MATCH('GHI Features (Option 1)'!$E37,'GHI DB'!$A$3:$BS$3,0)) -> ✔ | J37: =INDEX('GHI DB'!$A$3:$BS$27,MATCH('GHI Features (Option 1)'!J$8,'GHI DB'!$A$3:$A$27,0),MATCH('GHI Features (Option 1)'!$E37,'GHI DB'!$A$3:$BS$3,0)) -> ✔
C38: Specific Diseases Waiting Period | D38: =SUBSTITUTE(C38," ","") -> SpecificDiseasesWaitingPeriod | E38: Waived Off | G38: =INDEX('GHI DB'!$A$3:$BS$27,MATCH('GHI Features (Option 1)'!G$8,'GHI DB'!$A$3:$A$27,0),MATCH('GHI Features (Option 1)'!$E38,'GHI DB'!$A$3:$BS$3,0)) -> ✔ | H38: =INDEX('GHI DB'!$A$3:$BS$27,MATCH('GHI Features (Option 1)'!H$8,'GHI DB'!$A$3:$A$27,0),MATCH('GHI Features (Option 1)'!$E38,'GHI DB'!$A$3:$BS$3,0)) -> Nil | I38: =INDEX('GHI DB'!$A$3:$BS$27,MATCH('GHI Features (Option 1)'!I$8,'GHI DB'!$A$3:$A$27,0),MATCH('GHI Features (Option 1)'!$E38,'GHI DB'!$A$3:$BS$3,0)) -> ✔ | J38: =INDEX('GHI DB'!$A$3:$BS$27,MATCH('GHI Features (Option 1)'!J$8,'GHI DB'!$A$3:$A$27,0),MATCH('GHI Features (Option 1)'!$E38,'GHI DB'!$A$3:$BS$3,0)) -> ✔
C39: PreExisting Diseases Waiting Period | D39: =SUBSTITUTE(C39," ","") -> PreExistingDiseasesWaitingPeriod | E39: Waived Off | G39: =INDEX('GHI DB'!$A$3:$BS$27,MATCH('GHI Features (Option 1)'!G$8,'GHI DB'!$A$3:$A$27,0),MATCH('GHI Features (Option 1)'!$E39,'GHI DB'!$A$3:$BS$3,0)) -> ✔ | H39: =INDEX('GHI DB'!$A$3:$BS$27,MATCH('GHI Features (Option 1)'!H$8,'GHI DB'!$A$3:$A$27,0),MATCH('GHI Features (Option 1)'!$E39,'GHI DB'!$A$3:$BS$3,0)) -> Nil | I39: =INDEX('GHI DB'!$A$3:$BS$27,MATCH('GHI Features (Option 1)'!I$8,'GHI DB'!$A$3:$A$27,0),MATCH('GHI Features (Option 1)'!$E39,'GHI DB'!$A$3:$BS$3,0)) -> ✔ | J39: =INDEX('GHI DB'!$A$3:$BS$27,MATCH('GHI Features (Option 1)'!J$8,'GHI DB'!$A$3:$A$27,0),MATCH('GHI Features (Option 1)'!$E39,'GHI DB'!$A$3:$BS$3,0)) -> ✔
B41: Hospital Transportation Benefits | C41: Road Ambulance | D41: =SUBSTITUTE(C41," ","") -> RoadAmbulance | E41: Coverage per event | G41: =INDEX('GHI DB'!$A$3:$BS$27,MATCH('GHI Features (Option 1)'!G$8,'GHI DB'!$A$3:$A$27,0),MATCH('GHI Features (Option 1)'!$E41,'GHI DB'!$A$3:$BS$3,0)) -> Upto Actuals | H41: =INDEX('GHI DB'!$A$3:$BS$27,MATCH('GHI Features (Option 1)'!H$8,'GHI DB'!$A$3:$A$27,0),MATCH('GHI Features (Option 1)'!$E41,'GHI DB'!$A$3:$BS$3,0)) -> Upto Rs. 2.5k | I41: =INDEX('GHI DB'!$A$3:$BS$27,MATCH('GHI Features (Option 1)'!I$8,'GHI DB'!$A$3:$A$27,0),MATCH('GHI Features (Option 1)'!$E41,'GHI DB'!$A$3:$BS$3,0)) -> Upto Rs. 2.5k | J41: =INDEX('GHI DB'!$A$3:$BS$27,MATCH('GHI Features (Option 1)'!J$8,'GHI DB'!$A$3:$A$27,0),MATCH('GHI Features (Option 1)'!$E41,'GHI DB'!$A$3:$BS$3,0)) -> Upto Rs. 2k | K41: Change as per expiring policy for renewal cases
C42: Air Ambulance | D42: =SUBSTITUTE(C42," ","") -> AirAmbulance | E42: Coverage per event | G42: =INDEX('GHI DB'!$A$3:$BS$27,MATCH('GHI Features (Option 1)'!G$8,'GHI DB'!$A$3:$A$27,0),MATCH('GHI Features (Option 1)'!$E42,'GHI DB'!$A$3:$BS$3,0)) -> Upto Rs. 100k | H42: =INDEX('GHI DB'!$A$3:$BS$27,MATCH('GHI Features (Option 1)'!H$8,'GHI DB'!$A$3:$A$27,0),MATCH('GHI Features (Option 1)'!$E42,'GHI DB'!$A$3:$BS$3,0)) -> ✖ | I42: =INDEX('GHI DB'!$A$3:$BS$27,MATCH('GHI Features (Option 1)'!I$8,'GHI DB'!$A$3:$A$27,0),MATCH('GHI Features (Option 1)'!$E42,'GHI DB'!$A$3:$BS$3,0)) -> ✖ | J42: =INDEX('GHI DB'!$A$3:$BS$27,MATCH('GHI Features (Option 1)'!J$8,'GHI DB'!$A$3:$A$27,0),MATCH('GHI Features (Option 1)'!$E42,'GHI DB'!$A$3:$BS$3,0)) -> ✖ | K42: Change as per expiring policy for renewal cases
B44: Other Benefits | C44: Modern Treatments and Robotic Surgeries | D44: =SUBSTITUTE(C44," ","") -> ModernTreatmentsandRoboticSurgeries | E44: As per Regulatory Guidelines | G44: =INDEX('GHI DB'!$A$3:$BS$27,MATCH('GHI Features (Option 1)'!G$8,'GHI DB'!$A$3:$A$27,0),MATCH('GHI Features (Option 1)'!$E44,'GHI DB'!$A$3:$BS$3,0)) -> 50% Co-Pay | H44: =INDEX('GHI DB'!$A$3:$BS$27,MATCH('GHI Features (Option 1)'!H$8,'GHI DB'!$A$3:$A$27,0),MATCH('GHI Features (Option 1)'!$E44,'GHI DB'!$A$3:$BS$3,0)) -> 50% Co-Pay | I44: =INDEX('GHI DB'!$A$3:$BS$27,MATCH('GHI Features (Option 1)'!I$8,'GHI DB'!$A$3:$A$27,0),MATCH('GHI Features (Option 1)'!$E44,'GHI DB'!$A$3:$BS$3,0)) -> 50% Co-Pay | J44: =INDEX('GHI DB'!$A$3:$BS$27,MATCH('GHI Features (Option 1)'!J$8,'GHI DB'!$A$3:$A$27,0),MATCH('GHI Features (Option 1)'!$E44,'GHI DB'!$A$3:$BS$3,0)) -> 50% Co-Pay
C45: Psychiatric Illness | D45: =SUBSTITUTE(C45," ","") -> PsychiatricIllness | E45: Hospitalization > 24 hours | G45: =INDEX('GHI DB'!$A$3:$BS$27,MATCH('GHI Features (Option 1)'!G$8,'GHI DB'!$A$3:$A$27,0),MATCH('GHI Features (Option 1)'!$E45,'GHI DB'!$A$3:$BS$3,0)) -> ✔ | H45: =INDEX('GHI DB'!$A$3:$BS$27,MATCH('GHI Features (Option 1)'!H$8,'GHI DB'!$A$3:$A$27,0),MATCH('GHI Features (Option 1)'!$E45,'GHI DB'!$A$3:$BS$3,0)) -> ✔ | I45: =INDEX('GHI DB'!$A$3:$BS$27,MATCH('GHI Features (Option 1)'!I$8,'GHI DB'!$A$3:$A$27,0),MATCH('GHI Features (Option 1)'!$E45,'GHI DB'!$A$3:$BS$3,0)) -> ✔ | J45: =INDEX('GHI DB'!$A$3:$BS$27,MATCH('GHI Features (Option 1)'!J$8,'GHI DB'!$A$3:$A$27,0),MATCH('GHI Features (Option 1)'!$E45,'GHI DB'!$A$3:$BS$3,0)) -> ✔ | K45: Change as per expiring policy for renewal cases
C46: AYUSH Treatments | D46: =SUBSTITUTE(C46," ","") -> AYUSHTreatments | E46: Hospitallization > 24 hours in Govt Approved Hospitals | G46: =INDEX('GHI DB'!$A$3:$BS$27,MATCH('GHI Features (Option 1)'!G$8,'GHI DB'!$A$3:$A$27,0),MATCH('GHI Features (Option 1)'!$E46,'GHI DB'!$A$3:$BS$3,0)) -> Not Covered | H46: =INDEX('GHI DB'!$A$3:$BS$27,MATCH('GHI Features (Option 1)'!H$8,'GHI DB'!$A$3:$A$27,0),MATCH('GHI Features (Option 1)'!$E46,'GHI DB'!$A$3:$BS$3,0)) -> Not Covered | I46: =INDEX('GHI DB'!$A$3:$BS$27,MATCH('GHI Features (Option 1)'!I$8,'GHI DB'!$A$3:$A$27,0),MATCH('GHI Features (Option 1)'!$E46,'GHI DB'!$A$3:$BS$3,0)) -> Not Covered | J46: =INDEX('GHI DB'!$A$3:$BS$27,MATCH('GHI Features (Option 1)'!J$8,'GHI DB'!$A$3:$A$27,0),MATCH('GHI Features (Option 1)'!$E46,'GHI DB'!$A$3:$BS$3,0)) -> Upto 25% of SI | K46: Change as per expiring policy for renewal cases
C47: Organ Donor Expenses | D47: =SUBSTITUTE(C47," ","") -> OrganDonorExpenses | E47: Covered upto 100% of SI | G47: =INDEX('GHI DB'!$A$3:$BS$27,MATCH('GHI Features (Option 1)'!G$8,'GHI DB'!$A$3:$A$27,0),MATCH('GHI Features (Option 1)'!$E47,'GHI DB'!$A$3:$BS$3,0)) -> Not Covered | H47: =INDEX('GHI DB'!$A$3:$BS$27,MATCH('GHI Features (Option 1)'!H$8,'GHI DB'!$A$3:$A$27,0),MATCH('GHI Features (Option 1)'!$E47,'GHI DB'!$A$3:$BS$3,0)) -> ✔ | I47: =INDEX('GHI DB'!$A$3:$BS$27,MATCH('GHI Features (Option 1)'!I$8,'GHI DB'!$A$3:$A$27,0),MATCH('GHI Features (Option 1)'!$E47,'GHI DB'!$A$3:$BS$3,0)) -> ✔ | J47: =INDEX('GHI DB'!$A$3:$BS$27,MATCH('GHI Features (Option 1)'!J$8,'GHI DB'!$A$3:$A$27,0),MATCH('GHI Features (Option 1)'!$E47,'GHI DB'!$A$3:$BS$3,0)) -> ✖ | K47: Change as per expiring policy for renewal cases
C48: Lasik Eye Surgery | D48: =SUBSTITUTE(C48," ","") -> LasikEyeSurgery | E48: Eye power correction | G48: =INDEX('GHI DB'!$A$3:$BS$27,MATCH('GHI Features (Option 1)'!G$8,'GHI DB'!$A$3:$A$27,0),MATCH('GHI Features (Option 1)'!$E48,'GHI DB'!$A$3:$BS$3,0)) -> ✖ | H48: =INDEX('GHI DB'!$A$3:$BS$27,MATCH('GHI Features (Option 1)'!H$8,'GHI DB'!$A$3:$A$27,0),MATCH('GHI Features (Option 1)'!$E48,'GHI DB'!$A$3:$BS$3,0)) -> If eye power +/- 6.5 | I48: =INDEX('GHI DB'!$A$3:$BS$27,MATCH('GHI Features (Option 1)'!I$8,'GHI DB'!$A$3:$A$27,0),MATCH('GHI Features (Option 1)'!$E48,'GHI DB'!$A$3:$BS$3,0)) -> If eye power +/- 6.5 | J48: =INDEX('GHI DB'!$A$3:$BS$27,MATCH('GHI Features (Option 1)'!J$8,'GHI DB'!$A$3:$A$27,0),MATCH('GHI Features (Option 1)'!$E48,'GHI DB'!$A$3:$BS$3,0)) -> If eye power +/- 5 | K48: Change as per expiring policy for renewal cases
C49: Terrorism | D49: =SUBSTITUTE(C49," ","") -> Terrorism | E49: Terrorism | G49: =INDEX('GHI DB'!$A$3:$BS$27,MATCH('GHI Features (Option 1)'!G$8,'GHI DB'!$A$3:$A$27,0),MATCH('GHI Features (Option 1)'!$E49,'GHI DB'!$A$3:$BS$3,0)) -> ✔ | H49: =INDEX('GHI DB'!$A$3:$BS$27,MATCH('GHI Features (Option 1)'!H$8,'GHI DB'!$A$3:$A$27,0),MATCH('GHI Features (Option 1)'!$E49,'GHI DB'!$A$3:$BS$3,0)) -> ✔ | I49: =INDEX('GHI DB'!$A$3:$BS$27,MATCH('GHI Features (Option 1)'!I$8,'GHI DB'!$A$3:$A$27,0),MATCH('GHI Features (Option 1)'!$E49,'GHI DB'!$A$3:$BS$3,0)) -> ✔ | J49: =INDEX('GHI DB'!$A$3:$BS$27,MATCH('GHI Features (Option 1)'!J$8,'GHI DB'!$A$3:$A$27,0),MATCH('GHI Features (Option 1)'!$E49,'GHI DB'!$A$3:$BS$3,0)) -> ✖ | K49: Change as per expiring policy for renewal cases
B51: Mid-Term Policy Changes | C51: Additions and Deletions | D51: =SUBSTITUTE(C51," ","") -> AdditionsandDeletions | E51: On pro-rata basis | G51: =INDEX('GHI DB'!$A$3:$BS$27,MATCH('GHI Features (Option 1)'!G$8,'GHI DB'!$A$3:$A$27,0),MATCH('GHI Features (Option 1)'!$E51,'GHI DB'!$A$3:$BS$3,0)) -> ✔ | H51: =INDEX('GHI DB'!$A$3:$BS$27,MATCH('GHI Features (Option 1)'!H$8,'GHI DB'!$A$3:$A$27,0),MATCH('GHI Features (Option 1)'!$E51,'GHI DB'!$A$3:$BS$3,0)) -> ✔ | I51: =INDEX('GHI DB'!$A$3:$BS$27,MATCH('GHI Features (Option 1)'!I$8,'GHI DB'!$A$3:$A$27,0),MATCH('GHI Features (Option 1)'!$E51,'GHI DB'!$A$3:$BS$3,0)) -> ✔ | J51: =INDEX('GHI DB'!$A$3:$BS$27,MATCH('GHI Features (Option 1)'!J$8,'GHI DB'!$A$3:$A$27,0),MATCH('GHI Features (Option 1)'!$E51,'GHI DB'!$A$3:$BS$3,0)) -> ✔
C52: Mid term Increase in Sum Insured | D52: =SUBSTITUTE(C52," ","") -> MidtermIncreaseinSumInsured | E52: Only for employee promotion (if graded SI) | G52: =INDEX('GHI DB'!$A$3:$BS$27,MATCH('GHI Features (Option 1)'!G$8,'GHI DB'!$A$3:$A$27,0),MATCH('GHI Features (Option 1)'!$E52,'GHI DB'!$A$3:$BS$3,0)) -> ✔ | H52: =INDEX('GHI DB'!$A$3:$BS$27,MATCH('GHI Features (Option 1)'!H$8,'GHI DB'!$A$3:$A$27,0),MATCH('GHI Features (Option 1)'!$E52,'GHI DB'!$A$3:$BS$3,0)) -> ✖ | I52: =INDEX('GHI DB'!$A$3:$BS$27,MATCH('GHI Features (Option 1)'!I$8,'GHI DB'!$A$3:$A$27,0),MATCH('GHI Features (Option 1)'!$E52,'GHI DB'!$A$3:$BS$3,0)) -> ✖ | J52: =INDEX('GHI DB'!$A$3:$BS$27,MATCH('GHI Features (Option 1)'!J$8,'GHI DB'!$A$3:$A$27,0),MATCH('GHI Features (Option 1)'!$E52,'GHI DB'!$A$3:$BS$3,0)) -> ✔
B54: The Healthysure Advantage | C54: Upgrade Option | D54: =SUBSTITUTE(C54," ","") -> UpgradeOption | E54: Flexi Top-up Insurance of Rs 30 Lacs with continuity option | G54: =INDEX('GHI DB'!$A$3:$BS$27,MATCH('GHI Features (Option 1)'!G$8,'GHI DB'!$A$3:$A$27,0),MATCH('GHI Features (Option 1)'!$E54,'GHI DB'!$A$3:$BS$3,0)) -> ✔ | H54: =INDEX('GHI DB'!$A$3:$BS$27,MATCH('GHI Features (Option 1)'!H$8,'GHI DB'!$A$3:$A$27,0),MATCH('GHI Features (Option 1)'!$E54,'GHI DB'!$A$3:$BS$3,0)) -> ✖ | I54: =INDEX('GHI DB'!$A$3:$BS$27,MATCH('GHI Features (Option 1)'!I$8,'GHI DB'!$A$3:$A$27,0),MATCH('GHI Features (Option 1)'!$E54,'GHI DB'!$A$3:$BS$3,0)) -> ✔ | J54: =INDEX('GHI DB'!$A$3:$BS$27,MATCH('GHI Features (Option 1)'!J$8,'GHI DB'!$A$3:$A$27,0),MATCH('GHI Features (Option 1)'!$E54,'GHI DB'!$A$3:$BS$3,0)) -> ✔
C55: Doctor Teleconsultations | D55: =SUBSTITUTE(C55," ","") -> DoctorTeleconsultations | E55: Unlimited with General Physicians | G55: =INDEX('GHI DB'!$A$3:$BS$27,MATCH('GHI Features (Option 1)'!G$8,'GHI DB'!$A$3:$A$27,0),MATCH('GHI Features (Option 1)'!$E55,'GHI DB'!$A$3:$BS$3,0)) -> ✔ | H55: =INDEX('GHI DB'!$A$3:$BS$27,MATCH('GHI Features (Option 1)'!H$8,'GHI DB'!$A$3:$A$27,0),MATCH('GHI Features (Option 1)'!$E55,'GHI DB'!$A$3:$BS$3,0)) -> ✖ | I55: =INDEX('GHI DB'!$A$3:$BS$27,MATCH('GHI Features (Option 1)'!I$8,'GHI DB'!$A$3:$A$27,0),MATCH('GHI Features (Option 1)'!$E55,'GHI DB'!$A$3:$BS$3,0)) -> ✔ | J55: =INDEX('GHI DB'!$A$3:$BS$27,MATCH('GHI Features (Option 1)'!J$8,'GHI DB'!$A$3:$A$27,0),MATCH('GHI Features (Option 1)'!$E55,'GHI DB'!$A$3:$BS$3,0)) -> ✔
C56: Personal AI Health Assistant | E56: Instant help on medical symptoms and book doctor appointments | G56: =INDEX('GHI DB'!$A$3:$BS$27,MATCH('GHI Features (Option 1)'!G$8,'GHI DB'!$A$3:$A$27,0),MATCH('GHI Features (Option 1)'!$E56,'GHI DB'!$A$3:$BS$3,0)) -> ✔ | H56: =INDEX('GHI DB'!$A$3:$BS$27,MATCH('GHI Features (Option 1)'!H$8,'GHI DB'!$A$3:$A$27,0),MATCH('GHI Features (Option 1)'!$E56,'GHI DB'!$A$3:$BS$3,0)) -> ✔ | I56: =INDEX('GHI DB'!$A$3:$BS$27,MATCH('GHI Features (Option 1)'!I$8,'GHI DB'!$A$3:$A$27,0),MATCH('GHI Features (Option 1)'!$E56,'GHI DB'!$A$3:$BS$3,0)) -> ✔ | J56: =INDEX('GHI DB'!$A$3:$BS$27,MATCH('GHI Features (Option 1)'!J$8,'GHI DB'!$A$3:$A$27,0),MATCH('GHI Features (Option 1)'!$E56,'GHI DB'!$A$3:$BS$3,0)) -> ✔
C57: Emergency Ambulance | E57: Within 25 min Pan-India | G57: =INDEX('GHI DB'!$A$3:$BS$27,MATCH('GHI Features (Option 1)'!G$8,'GHI DB'!$A$3:$A$27,0),MATCH('GHI Features (Option 1)'!$E57,'GHI DB'!$A$3:$BS$3,0)) -> ✔ | H57: =INDEX('GHI DB'!$A$3:$BS$27,MATCH('GHI Features (Option 1)'!H$8,'GHI DB'!$A$3:$A$27,0),MATCH('GHI Features (Option 1)'!$E57,'GHI DB'!$A$3:$BS$3,0)) -> ✔ | I57: =INDEX('GHI DB'!$A$3:$BS$27,MATCH('GHI Features (Option 1)'!I$8,'GHI DB'!$A$3:$A$27,0),MATCH('GHI Features (Option 1)'!$E57,'GHI DB'!$A$3:$BS$3,0)) -> ✔ | J57: =INDEX('GHI DB'!$A$3:$BS$27,MATCH('GHI Features (Option 1)'!J$8,'GHI DB'!$A$3:$A$27,0),MATCH('GHI Features (Option 1)'!$E57,'GHI DB'!$A$3:$BS$3,0)) -> ✔
C58: Health Checkups | D58: =SUBSTITUTE(C58," ","") -> HealthCheckups | E58: Full body checkup upto 70% off | G58: =INDEX('GHI DB'!$A$3:$BS$27,MATCH('GHI Features (Option 1)'!G$8,'GHI DB'!$A$3:$A$27,0),MATCH('GHI Features (Option 1)'!$E58,'GHI DB'!$A$3:$BS$3,0)) -> ✔ | H58: =INDEX('GHI DB'!$A$3:$BS$27,MATCH('GHI Features (Option 1)'!H$8,'GHI DB'!$A$3:$A$27,0),MATCH('GHI Features (Option 1)'!$E58,'GHI DB'!$A$3:$BS$3,0)) -> ✔ | I58: =INDEX('GHI DB'!$A$3:$BS$27,MATCH('GHI Features (Option 1)'!I$8,'GHI DB'!$A$3:$A$27,0),MATCH('GHI Features (Option 1)'!$E58,'GHI DB'!$A$3:$BS$3,0)) -> ✔ | J58: =INDEX('GHI DB'!$A$3:$BS$27,MATCH('GHI Features (Option 1)'!J$8,'GHI DB'!$A$3:$A$27,0),MATCH('GHI Features (Option 1)'!$E58,'GHI DB'!$A$3:$BS$3,0)) -> ✔
C59: Gym Memberships | E59: Gym Membership Discount upto 50% | G59: =INDEX('GHI DB'!$A$3:$BS$27,MATCH('GHI Features (Option 1)'!G$8,'GHI DB'!$A$3:$A$27,0),MATCH('GHI Features (Option 1)'!$E59,'GHI DB'!$A$3:$BS$3,0)) -> ✔ | H59: =INDEX('GHI DB'!$A$3:$BS$27,MATCH('GHI Features (Option 1)'!H$8,'GHI DB'!$A$3:$A$27,0),MATCH('GHI Features (Option 1)'!$E59,'GHI DB'!$A$3:$BS$3,0)) -> ✔ | I59: =INDEX('GHI DB'!$A$3:$BS$27,MATCH('GHI Features (Option 1)'!I$8,'GHI DB'!$A$3:$A$27,0),MATCH('GHI Features (Option 1)'!$E59,'GHI DB'!$A$3:$BS$3,0)) -> ✔ | J59: =INDEX('GHI DB'!$A$3:$BS$27,MATCH('GHI Features (Option 1)'!J$8,'GHI DB'!$A$3:$A$27,0),MATCH('GHI Features (Option 1)'!$E59,'GHI DB'!$A$3:$BS$3,0)) -> ✔
C60: Medicines Delivery | D60: =SUBSTITUTE(C60," ","") -> MedicinesDelivery | E60: Prescribed medicines upto 20% off | G60: =INDEX('GHI DB'!$A$3:$BS$27,MATCH('GHI Features (Option 1)'!G$8,'GHI DB'!$A$3:$A$27,0),MATCH('GHI Features (Option 1)'!$E60,'GHI DB'!$A$3:$BS$3,0)) -> ✔ | H60: =INDEX('GHI DB'!$A$3:$BS$27,MATCH('GHI Features (Option 1)'!H$8,'GHI DB'!$A$3:$A$27,0),MATCH('GHI Features (Option 1)'!$E60,'GHI DB'!$A$3:$BS$3,0)) -> ✔ | I60: =INDEX('GHI DB'!$A$3:$BS$27,MATCH('GHI Features (Option 1)'!I$8,'GHI DB'!$A$3:$A$27,0),MATCH('GHI Features (Option 1)'!$E60,'GHI DB'!$A$3:$BS$3,0)) -> ✔ | J60: =INDEX('GHI DB'!$A$3:$BS$27,MATCH('GHI Features (Option 1)'!J$8,'GHI DB'!$A$3:$A$27,0),MATCH('GHI Features (Option 1)'!$E60,'GHI DB'!$A$3:$BS$3,0)) -> ✔
B62: *Terms and conditions as per policy wordings apply
E143: STELLAPPS
E144: Vhire4u

Sheet GPA DB old
A1: Group Personal Accident & Disability Cover
A2: Features | B2: Go Digit ( Basic Plan) | C2: Go Digit ( Standard Plan) | D2: Go Digit (Pro Plan) | E2: IFFCO Tokio (Base Plan) | F2: IFFCO Tokio ( Pro Plan) | G2: Care Health (previously, Religare) | H2: Tata AIG | I2: GoDigit | J2: ICICI Lombard | K2: Manipal Cigna
A3: Sum Insured | B3: Rs.X Lacs (Max 50 lacs, 3x of CTC whichever is lower) | C3: Rs.X Lacs (Max 2 Cr, Max 3x of CTC whichever is lower) | D3: Rs.X Lacs (Max 2 Cr, Max 3x of CTC whichever is lower) | E3: Upto 20 lac | F3: Upto 20 lac | G3: Rs.X Lacs | H3: Rs.X Lacs | I3: Rs.X Lacs | J3: Rs. 10 Lacs
A4: Total Premium (excl. GST) | B4: ₹XXX | C4: ₹XXX | D4: ₹XXX | E4: ₹XXX | F4: ₹XXX | G4: ₹XXX | H4: ₹XXX | I4: ₹XXX | J4: 3938
A5: Premium per mille (excl. GST) | B5: Risk Class 1 - 0.15 per mile Risk Class 2 - 0.19 per mile (Fresh Cases only) | C5: Risk Class 1 - 0.25 per mille Risk Class 2 - 0.325 per mille (Fresh Cases only) | D5: Risk Class 1 - 0.32 per mile Risk Class 2 - 0.40 per mile (Fresh Cases only) | E5: 0.25 per mile | F5: 0.50 per mile | G5: ₹0.XX per mille | H5: ₹0.XX per mille | I5: ₹0.XX per mille | J5: ₹0.21 per mille
A6: Family Definition | B6: Self only | C6: Self only | D6: Self only | E6: Self only | F6: Self only | G6: Self only | H6: Self only | I6: Self only | J6: Self only
A7: No. of lives | B7: On-Roll: XX lives | C7: On-Roll: XX lives | D7: On-Roll: XX lives | E7: On-Roll: XX lives Off-Roll: XX lives | F7: On-Roll: XX lives Off-Roll: XX lives | G7: On-Roll: XX lives | H7: On-Roll: XX lives Off-Roll: XX lives | I7: On-Roll: XX lives Off-Roll: XX lives | J7: 19 lives
A8: Accidental Death | B8: 100% of SI | C8: 100% of SI | D8: 100% of SI | E8: 100% of SI | F8: 100% of SI | G8: 100% of SI | H8: 100% of SI | I8: 100% of SI | J8: 100% of SI
A9: Permanent Total Disablement | B9: 100% of SI | C9: 150% of SI | D9: 150% of SI | E9: Upto 100% of SI | F9: Upto 100% of SI | G9: 100% of SI | H9: 100% of SI | I9: 100% of SI | J9: 100% of SI
A10: Permanent Partial Disablement | B10: Up to 100% of SI based on extent of disability | C10: Up to 100% of SI based on extent of disability | D10: Up to 100% of SI based on extent of disability | E10: Upto 100% of SI | F10: Upto 100% of SI | G10: Upto 100% of SI | H10: Upto 100% of SI | I10: Upto 100% of SI | J10: Upto 100% of SI
A11: Temporary Total Disablement (if patient confined to bed due to temporary and total inability to engage in any occupation or any activity) | B11: 1% of SI or Rs. 5,000 per week or actual salary, whichever is lower for 104 weeks | C11: 1% of SI or Rs. 5,000 per week or actual salary, whichever is lower for 104 weeks | D11: 1% of SI or Rs. 10,000 per week or actual salary, whichever is lower for 104 weeks | E11: 1% of SI or Rs. 5000 or Actual salary per week upto 104 weeks whichever is lower | F11: 1% of SI or Rs. 5000 or Actual salary per week upto 104 weeks whichever is lower | G11: 1% of SI or Rs. 5000 or Actual salary per week upto 104 weeks whichever is lower | H11: 1% of SI or Rs. 5000 or Actual salary per week up to 52 weeks whichever is lower | I11: 1% of SI or Rs. 5000 or Actual salary per week upto 100 weeks whichever is lower | J11: 1% of SI or Rs. 5000 or Actual salary per week upto 100 weeks whichever is lower
A12: Accidental Hospitalization (IPD) (min. 24 hours hospitalization) | B12: Not Covered | C12: Reimb upto 50% of the SI or Rs. 1L whichever is less Other Benefits: Day Care Procedures - Covered Pre / Post Hospitalization - 60/90 days Road Ambulance Charges - Rs.5,000 Domiciliary Hospitalization - Covered Dental (due to accients) - 100% of SI Trauma Counselling - Covered Second Medical Opinion - Covered Transport of Imported Medicines - Covered | D12: Reimb upto 50% of the SI or Rs. 2L whichever is less Other Benefits: Day Care Procedures - Covered Pre / Post Hospitalization - 60/90 days Road Ambulance Charges - Rs.5,000 Domiciliary Hospitalization - Covered Dental (due to accients) - 100% of SI Trauma Counselling - Covered Second Medical Opinion - Covered Transport of Imported Medicines - Covered Daily Hospi Cash - Rs. 1,000 per day for 30 days (2x if ICU hospitalisation > 24 hours) | E12: Not Covered | F12: Reimb upto Rs. 2L or actuals whichever is less Other Benefits: Pre / Post Hospitalization - 60/90 days Road Ambulance Charges - Rs.5,000 Domiciliary Hospitalization - Covered Dental (due to accients) - 100% of SI upto 15,000 Trauma Counselling - Covered Second Medical Opinion - Covered Daily Hospi Cash - Rs. 1,000 per day for 30 days (2x if ICU hospitalisation > 24 hours) | G12: Reimb of 10% of SI or 40% of admissible PA claim or actual expense, whichever is lower if accidental death or disability | H12: Reimb of 10% of SI or 40% of admissible PA claim or actual expense, whichever is lower if accidental death or disability OR Reimb of Actuals upto Rs. 25,000 (no sub-limit) for any accidental injury | I12: Reimb of 10% of SI or 40% of admissible PA claim or actual expense, whichever is lower if accidental death or disability | J12: None
A13: Accidental Expenses (OPD) | B13: NA | C13: NA | D13: NA | E13: Not Covered | F13: Fracture Cover - Upto 10% SI or Rs. 50,000 whichever is lower Burns Cover - Upto 10% SI or Rs. 50,000 whichever is lower | G13: Medex Cover - Reimb of Actuals upto Rs. 25,000 (no sub-limit) for any accidental injury | H13: None | I13: None | J13: Reimb of Actuals upto Rs. 25,000 (no sub-limit) for any accidental injury
A14: Additional Benefits | B14: Children Education Benefit- 10% of SI upto Rs. 5000 per child (max 2 children) Compassionate Visit - 10% SI upto Rs. 25,000 Funeral Expenses - upto Rs. 2500 Transportation of Dead Body - upto Rs.2500 Medical Extension - 40% of death/disability claim amount or 10% of S.I or actual which ever is less triggered only when claim is admissible under benefit table A,B,C or D1 | C14: Children Education Benefit- 10% of SI upto Rs. 5000 per child Funeral Expenses - upto Rs. 5000 Transportation of Dead Body - upto Rs.5000 Burns Cover - Upto 10% SI Upto 10000 Compassionate Visit - 10% SI upto Rs. 25,000 | D14: Children Education Benefit- Upto Rs. 10,000 per child Funeral Expenses - upto Rs. 10,000 Transportation of Dead Body - upto Rs.10,000 Burns Cover - Upto 10% SI Upto 10000 Compassionate Visit - 10% SI upto Rs. 25,000 Lifestyle modification - 10% SI upto Rs. 25,000 | E14: Not Covered | F14: Children Education Benefit- 10% of SI upto Rs. 5000 per child (max 2 children) Funeral Expenses - upto Rs. 5,000 Transportation of Dead Body - upto Rs.5000 Compassionate Visit - 5% SI upto Rs. 10,000 | G14: Child Education Benefit Funeral Expenses Transportation Cost of Dead Body Ambulance Charges Burns Cover | H14: Child Education Benefit Funeral Expenses Transportation Cost of Dead Body Ambulance Charges Burns Cover | I14: Child Education Benefit Funeral Expenses Transportation Cost of Dead Body Ambulance Charges Burns Cover | J14: Child Education Welfare - Upto Rs. 10,000 per child (Restricted to 2 children) Transportation Cost of Dead Body - Upto Rs. 2,500/-
A15: Terrorism | B15: Covered | C15: Covered | D15: Covered | E15: Covered (Terrorism activity arising out of nuclear, biological and/or chemical means is not covered.) | F15: Covered (Terrorism activity arising out of nuclear, biological and/or chemical means is not covered.) | G15: Covered (except not covered arising out Nuclear/Biological or chemical means) | H15: Covered | I15: Covered (except not covered arising out Nuclear/Biological or chemical means) | J15: Covered (except not covered arising out Nuclear/Biological or chemical means)
A16: Geographical Limit | B16: Worldwide | C16: Worldwide | D16: Worldwide | E16: Worldwide | F16: Worldwide | G16: India Only | H16: Worldwide | I16: Worldwide | J16: India
A17: Coverage | B17: 24 x 7 Cover | C17: 24 x 7 Cover | D17: 24 x 7 Cover | E17: 24 x 7 Cover | F17: 24 x 7 Cover | G17: 24 x 7 Cover | H17: 24 x 7 Cover | I17: 24 x 7 Cover | J17: 24 x 7 Cover
A20: Indicative Risk Class
A21: Risk Class 1
A22: Risk Class 2
A23: Risk Class 3

Sheet GHI DB
A1: Features | B1: Logo | C1: Family Definition | G1: Type of Cover | I1: Room Rent Restriction | M1: Co Pay | S1: Corporate Buffer | U1: Upgrade Option | V1: Pan India Coverage | W1: Cashless Network | X1: Reimbursement Network | Y1: Claims Intermediary | Z1: Inpatient Hospitalization | AA1: Day Care Treatments | AB1: Disease Capping | AC1: COVID 19 Coverage | AD1: Domicillary Hospitalization | AE1: Pre and Post Hospitalization Coverage | AG1: Doctor Teleconsultations | AH1: Personal AI Health Assistant | AI1: Emergency Ambulance | AJ1: Health Checkups | AK1: Gym Memberships | AL1: Medicines Delivery | AM1: Dental Coverage | AN1: Maternity Cover | AP1: Maternity Waiting Period | AR1: Pre and Post Natal Expenses | AS1: Initial Waiting Period | AT1: Specific Diseases Waiting Period | AU1: PreExisting Diseases Waiting Period | AV1: Road Ambulance | AW1: Air Ambulance | AX1: Modern Treatments and Robotic Surgeries | AY1: Psychiatric Illness | BA1: AYUSH Treatments | BC1: Organ Donor Expenses | BE1: Lasik Eye Surgery | BF1: Terrorism | BG1: Additions and Deletions | BI1: Mid term Increase in Sum Insured | BK1: Mid term Addition of Dependents | BM1: Midterm addition of parents | BO1: Cashless Authorization TAT | BP1: Reimburement Claim Settlement TAT | BQ1: Reimbursement Claim filing | BR1: Reimbursement Claim Intimation | BS1: Reimbursement Claim Submission
B2: =SUBSTITUTE(B1," ","") -> Logo | C2: =SUBSTITUTE(C1," ","") -> FamilyDefinition | G2: =SUBSTITUTE(G1," ","") -> TypeofCover | I2: =SUBSTITUTE(I1," ","") -> RoomRentRestriction | M2: =SUBSTITUTE(M1," ","") -> CoPay | S2: =SUBSTITUTE(S1," ","") -> CorporateBuffer | V2: =SUBSTITUTE(V1," ","") -> PanIndiaCoverage | W2: =SUBSTITUTE(W1," ","") -> CashlessNetwork | X2: =SUBSTITUTE(X1," ","") -> ReimbursementNetwork | Y2: =SUBSTITUTE(Y1," ","") -> ClaimsIntermediary | Z2: =SUBSTITUTE(Z1," ","") -> InpatientHospitalization | AA2: =SUBSTITUTE(AA1," ","") -> DayCareTreatments | AB2: =SUBSTITUTE(AB1," ","") -> DiseaseCapping | AC2: =SUBSTITUTE(AC1," ","") -> COVID19Coverage | ... AE2: =SUBSTITUTE(AE1," ","") -> PreandPostHospitalizationCoverage | AG2: =SUBSTITUTE(AG1," ","") -> DoctorTeleconsultations | AH2: =SUBSTITUTE(AH1," ","") -> PersonalAIHealthAssistant | AI2: =SUBSTITUTE(AI1," ","") -> EmergencyAmbulance | AJ2: =SUBSTITUTE(AJ1," ","") -> HealthCheckups | AK2: Gym Memberships | AL2: =SUBSTITUTE(AL1," ","") -> MedicinesDelivery | AM2: =SUBSTITUTE(AM1," ","") -> DentalCoverage | AN2: =SUBSTITUTE(AN1," ","") -> MaternityCover | AP2: =SUBSTITUTE(AP1," ","") -> MaternityWaitingPeriod | AR2: =SUBSTITUTE(AR1," ","") -> PreandPostNatalExpenses | AS2: =SUBSTITUTE(AS1," ","") -> InitialWaitingPeriod | AT2: =SUBSTITUTE(AT1," ","") -> SpecificDiseasesWaitingPeriod | AU2: =SUBSTITUTE(AU1," ","") -> PreExistingDiseasesWaitingPeriod | AV2: =SUBSTITUTE(AV1," ","") -> RoadAmbulance | AW2: =SUBSTITUTE(AW1," ","") -> AirAmbulance | AX2: =SUBSTITUTE(AX1," ","") -> ModernTreatmentsandRoboticSurgeries | AY2: =SUBSTITUTE(AY1," ","") -> PsychiatricIllness | BA2: =SUBSTITUTE(BA1," ","") -> AYUSHTreatments | BC2: =SUBSTITUTE(BC1," ","") -> OrganDonorExpenses | BE2: =SUBSTITUTE(BE1," ","") -> LasikEyeSurgery | BF2: =SUBSTITUTE(BF1," ","") -> Terrorism | BG2: =SUBSTITUTE(BG1," ","") -> AdditionsandDeletions | BI2: =SUBSTITUTE(BI1," ","") -> MidtermIncreaseinSumInsured | BK2: =SUBSTITUTE(BK1," ","") -> MidtermAdditionofDependents | BM2: =SUBSTITUTE(BM1," ","") -> Midtermadditionofparents | BO2: =SUBSTITUTE(BO1," ","") -> CashlessAuthorizationTAT | BP2: =SUBSTITUTE(BP1," ","") -> ReimburementClaimSettlementTAT | BQ2: =SUBSTITUTE(BQ1," ","") -> ReimbursementClaimfiling | BR2: =SUBSTITUTE(BR1," ","") -> ReimbursementClaimIntimation | BS2: =SUBSTITUTE(BS1," ","") -> ReimbursementClaimSubmission
A3: Remarks | B3: Logo | C3: Self | D3: Spouse | E3: Children - upto 25 yrs of age | F3: 2 Parents/PIL - upto 80 yrs of age | G3: Family Floater | H3: Individual | I3: Normal - 1% of SI ICU - 2% of SI (per day) | J3: Normal - 2% of SI ICU - 4% of SI (per day) | K3: Normal - Single Pvt. AC ICU - No Capping (per day) | L3: Normal - No Capping ICU - No Capping | M3: 0% Co-Pay | N3: 5% Co-Pay | O3: 10% Co-Pay | P3: 15% Co-Pay | Q3: 20% Co-Pay | R3: 25% Co-Pay | S3: Rs. XXX restricted to Family Floater SI | T3: Not Covered | U3: Flexi Top-up Insurance of Rs 30 Lacs with continuity option | V3: Pan-India Coverage | W3: No. of Network Hospitals | X3: All Hospitals | Y3: TPA | Z3: Hospitalization > 24 hours | AA3: Hospitalization < 24 hours | AB3: No disease capping | AC3: Hospitalization > 24 hours | AD3: Home hospitalization > 3 days + Patient unable to move OR hospital bed not available | AE3: Covered | AF3: Not Covered | AG3: Unlimited with General Physicians | AH3: Instant help on medical symptoms and book doctor appointments | AI3: Within 25 min Pan-India | AJ3: Full body checkup upto 70% off | AK3: Gym Membership Discount upto 50% | AL3: Prescribed medicines upto 20% off | AM3: Upto Rs. XXX (no exclusions, Day 1 coverage) | AN3: Normal - Rs. 50k C Section - Rs. 50K | AO3: Not Covered | AP3: Waived Off | AQ3: Not Applicable | AR3: Covered within maternity limit | AS3: Waived Off | AT3: Waived Off | AU3: Waived Off | AV3: Coverage per event | AW3: Coverage per event | AX3: As per Regulatory Guidelines | AY3: Hospitalization > 24 hours | AZ3: Not Covered | BA3: Hospitallization > 24 hours in Govt Approved Hospitals | BB3: Not Covered | BC3: Covered upto 100% of SI | BD3: Not Covered | BE3: Eye power correction | BF3: Terrorism | BG3: On pro-rata basis | BH3: Not Allowed | BI3: Only for employee promotion (if graded SI) | BJ3: Not Allowed | BK3: Day 1 coverage of new borns and spouses of newly weds | BL3: Not Allowed | BM3: Only for new joinees | BN3: Not Allowed | BO3: Faster cashless authorisation | BP3: Within 30 days from date of document submission | BQ3: Paperless | BR3: Criteria for intimation within 7 days waived off | BS3: Criteria for document submission within 30 days from date of discharge waived off
A4: Acko | B4: =_xlfn.IMAGE("AZ4", "A4") -> #VALUE! | C4: ✔ | D4: ✔ | E4: 2 | F4: ✔ | G4: ✔ | H4: ✔ | I4: ✔ | J4: ✔ | K4: ✔ | L4: ✔ | M4: ✔ | N4: ✔ | O4: ✔ | P4: ✔ | Q4: ✔ | R4: ✔ | S4: ✔ | T4: Not Covered | U4: ✔ | V4: ✔ | W4: 6,500+ Hospitals | X4: ✔ | Y4: Cashless through Family Health & Reimbursement through Inhouse TPA | Z4: ✔ | AA4: ✔ (Listed Procedures Only) | AB4: ✔ | AC4: ✔ | AD4: ✖ | AE4: 30/60 days | AF4: Not Covered | AG4: ✔ | AH4: ✔ | AI4: ✔ | AJ4: ✔ | AK4: ✔ | AL4: ✔ | AM4: ✖ | AN4: ✔ | AO4: Not Covered | AP4: ✔ | AQ4: Not Applicable | AR4: Upto Rs. 2.5K | AS4: ✔ | AT4: ✔ | AU4: ✔ | AV4: Upto Rs. 1k | AW4: ✖ | AX4: 50% Co-Pay | AY4: ✖ | AZ4: Not Covered | BA4: ✖ | BB4: Not Covered | BC4: ✖ | BD4: Not Covered | BE4: With Conditions | BF4: With Conditions | BG4: ✔ | BH4: Not Allowed | BI4: ✔ | BJ4: Not Allowed | BK4: ✔ | BL4: Not Allowed | BM4: ✔ | BN4: Not Allowed | BO4: 2-4 Hrs | BP4: ✔ | BQ4: ✔ | BR4: ✔ | BS4: ✔
A5: Aditya Birla Health | B5: =_xlfn.IMAGE("AZ4", "A4") -> #VALUE! | C5: ✔ | D5: ✔ | E5: 2 | F5: Upto 90 Years | G5: ✔ | H5: ✔ | I5: ✔ | J5: ✔ | K5: ✔ | L5: ✔ | M5: ✔ | N5: ✔ | O5: ✔ | P5: ✔ | Q5: ✔ | R5: ✔ | S5: ✔ | T5: Not Covered | U5: ✔ | V5: ✔ | W5: 10,000+ Hospitals | X5: ✔ | Y5: Inhouse TPA / Medi Assist TPA/ Paramount TPA | Z5: ✔ | AA5: ✔ (Listed Procedures Only) | AB5: ✔ | AC5: ✔ | AD5: ✔ | AE5: 30/60 days | AF5: Not Covered | AG5: ✔ | AH5: ✔ | AI5: ✔ | AJ5: ✔ | AK5: ✔ | AL5: ✔ | AM5: ✖ | AN5: ✔ | AO5: Not Covered | AP5: ✔ | AQ5: Not Applicable | AR5: Upto Rs. 5K | AS5: ✔ | AT5: ✔ | AU5: ✔ | AV5: Upto Rs. 1k | AW5: ✖ | AX5: 50% Co-Pay | AY5: Upto Rs. 25k | AZ5: Not Covered | BA5: Upto Rs. 50k | BB5: Not Covered | BC5: ✖ | BD5: Not Covered | BE5: If eye power +/- 7.5 | BF5: ✔ | BG5: ✔ | BH5: Not Allowed | BI5: ✖ | BJ5: Not Allowed | BK5: ✔ | BL5: Not Allowed | BM5: ✔ | BN5: Not Allowed | BO5: 2-4 Hrs | BP5: ✔ | BQ5: ✔ | BR5: ✖ | BS5: ✔
A6: Bajaj General | B6: =_xlfn.IMAGE("AZ4", "A4") -> #VALUE! | C6: ✔ | D6: ✔ | E6: 2 | F6: 2 | G6: ✔ | H6: ✔ | I6: ✔ | J6: ✔ | K6: ✔ | L6: ✔ | M6: - | N6: - | O6: - | P6: - | Q6: - | R6: - | S6: ✔ | T6: Not Covered | U6: ✔ | V6: ✔ | W6: 6500+ Hospitals | X6: ✔ | Y6: Inhouse TPA | Z6: ✔ | AA6: ✔ (Listed Procedures Only) | AB6: ✔ | AC6: ✔ | AD6: ✖ | AE6: 30/60 days | AF6: Not Covered | AG6: ✔ | AH6: ✔ | AI6: ✔ | AJ6: ✔ | AK6: ✔ | AL6: ✔ | AM6: ✖ | AN6: ✔ | AO6: Not Covered | AP6: ✔ | AQ6: Not Applicable | AR6: ✔ | AS6: ✔ | AT6: ✔ | AU6: ✔ | AV6: Upto Rs. 2k | AW6: ✖ | AX6: 50% Co-Pay | AY6: ✖ | AZ6: Not Covered | BA6: ✔ | BB6: Not Covered | BC6: ✖ | BD6: Not Covered | BE6: If eye power +/- 7.0 | BF6: ✔ | BG6: ✔ | BH6: ✔ | BI6: ✖ | BJ6: Not Allowed | BK6: ✔ | BL6: Not Allowed | BM6: ✔ | BN6: Not Allowed | BO6: 2-4 Hrs | BP6: ✔ | BQ6: ✔ | BR6: ✖ | BS6: ✔
A7: Bajaj General (SME Exclusive) | C7: ✔ | D7: ✔ | E7: 4 | F7: ✖ | G7: ✔ | H7: ✔ | I7: Normal - For SI 1/2/3 lacs - 2% of SI upto 7,500; for SI 5 lacs - Single Pvt AC ICU - No Limit | J7: Normal - For SI 1/2/3 lacs - 2% of SI upto 7,500; for SI 5 lacs - Single Pvt AC ICU - No Limit | K7: Normal - For SI 1/2/3 lacs - 2% of SI upto 7,500; for SI 5 lacs - Single Pvt AC ICU - No Limit | L7: Normal - For SI 1/2/3 lacs - 2% of SI upto 7,500; for SI 5 lacs - Single Pvt AC ICU - No Limit | M7: ✔ | N7: - | O7: - | P7: - | Q7: - | R7: - | S7: ✖ | T7: Not Covered | U7: ✔ | V7: ✔ | W7: 6500+ Hospitals | X7: ✔ | Y7: Inhouse TPA | Z7: ✔ | AA7: ✔ (Listed Procedures Only) | AB7: ✔ | AC7: ✔ | AD7: ✖ | AE7: 30/60 days | AF7: Not Covered | AG7: ✔ | AH7: ✔ | AI7: ✔ | AJ7: ✔ | AK7: ✔ | AL7: ✔ | AM7: ✖ | AN7: ✔ | AO7: Not Covered | AP7: ✔ | AQ7: Not Applicable | AR7: ✔ | AS7: ✔ | AT7: ✔ | AU7: ✔ | AV7: Upto Rs. 2.5K | AW7: ✖ | AX7: Upto 50% of SI | AY7: Upto Rs. 50k | AZ7: Not Covered | BA7: ✔ | BB7: Not Covered | BC7: ✖ | BD7: Not Covered | BE7: If eye power +/- 6.5 | BF7: ✔ | BG7: ✔ | BH7: ✔ | BI7: ✖ | BJ7: Not Allowed | BK7: ✔ | BL7: Not Allowed | BM7: Not Covered | BN7: Not Covered | BO7: 2-4 Hrs
A8: Care Health | B8: =_xlfn.IMAGE("AZ4", "A4") -> #VALUE! | C8: ✔ | D8: ✔ | E8: 4 | F8: ✔ | G8: ✔ | H8: ✔ | I8: ✔ | J8: ✔ | K8: ✔ | L8: ✔ | M8: ✔ | N8: ✔ | O8: ✔ | P8: ✔ | Q8: ✔ | R8: ✔ | S8: ✔ | T8: Not Covered | U8: ✔ | V8: ✔ | W8: 8,350+ Hospitals | X8: ✔ | Y8: Inhouse TPA | Z8: ✔ | AA8: ✔ (Listed Procedures Only) | AB8: ✔ | AC8: ✔ | AD8: ✔ | AE8: 30/60 days | AF8: Not Covered | AG8: ✔ | AH8: ✔ | AI8: ✔ | AJ8: ✔ | AK8: ✔ | AL8: ✔ | AM8: ✖ | AN8: ✔ | AO8: Not Covered | AP8: ✔ | AQ8: Not Applicable | AR8: ✖ | AS8: ✔ | AT8: ✔ | AU8: ✔ | AV8: Upto Rs. 2k | AW8: ✖ | AX8: 50% Co-Pay | AY8: Upto 50% of SI | AZ8: Not Covered | BA8: Upto 25% of SI | BB8: Not Covered | BC8: ✖ | BD8: Not Covered | BE8: If eye power +/- 5 | BF8: ✖ | BG8: ✔ | BH8: ✔ | BI8: ✔ | BJ8: Not Allowed | BK8: ✔ | BL8: Not Allowed | BM8: ✔ | BN8: Not Allowed | BO8: 2-4 Hrs | BP8: ✔ | BQ8: ✔ | BR8: ✔ | BS8: ✔
A9: Future Generali | B9: =_xlfn.IMAGE("AZ4", "A4") -> #VALUE! | C9: ✔ | D9: ✔ | E9: - | F9: - | G9: ✔ | H9: ✔ | I9: ✔ | J9: ✔ | K9: ✔ | L9: ✔ | M9: ✔ | N9: ✔ | O9: ✔ | P9: ✔ | Q9: ✔ | R9: ✔ | S9: ✔ | T9: Not Covered | U9: ✔ | V9: ✔ | W9: 6,000+ Hospitals | X9: ✔ | Y9: Inhouse TPA | Z9: ✔ | AA9: ✔ (Listed Procedures Only) | AB9: ✔ | AC9: ✔ | AD9: ✖ | AE9: 30/60 days | AF9: Not Covered | AG9: ✔ | AH9: ✔ | AI9: ✔ | AJ9: ✔ | AK9: ✔ | AL9: ✔ | AM9: ✖ | AN9: ✔ | AO9: Not Covered | AP9: ✔ | AQ9: Not Applicable | AR9: Upto Rs. 5K | AS9: ✔ | AT9: ✔ | AU9: ✔ | AV9: Upto Rs. 2k | AW9: ✖ | AX9: 50% Co-Pay | AY9: ✖ | AZ9: Not Covered | BA9: ✖ | BB9: Not Covered | BC9: ✖ | BD9: Not Covered | BE9: ✖ | BF9: ✖ | BG9: ✔ | BH9: ✔ | BI9: ✖ | BJ9: Not Allowed | BK9: ✔ | BL9: Not Allowed | BM9: ✔ | BN9: Not Allowed | BO9: 2-4 Hrs | BP9: ✔ | BQ9: ✔ | BR9: Within 2 Days | BS9: ✔
A10: Go Digit | B10: =_xlfn.IMAGE("https://upload.wikimedia.org/wikipedia/commons/c/c4/Digit_Insurance.jpg", "Digit") -> #VALUE! | C10: ✔ | D10: ✔ | E10: 6 | F10: ✔ | G10: ✔ | H10: ✔ | I10: ✔ | J10: ✔ | K10: ✔ | L10: ✔ | M10: ✔ | N10: ✔ | O10: ✔ | P10: ✔ | Q10: ✔ | R10: ✔ | S10: ✔ | T10: Not Covered | U10: ✔ | V10: ✔ | W10: 8,500+ Hospitals | X10: ✔ | Y10: Medi Assist Insurance | Z10: ✔ | AA10: ✔ (Listed Procedures Only) | AB10: ✔ | AC10: ✔ | AD10: ✔ | AE10: 30/60 days | AF10: Not Covered | AG10: ✔ | AH10: ✔ | AI10: ✔ | AJ10: ✔ | AK10: ✔ | AL10: ✔ | AM10: ✖ | AN10: ✔ | AO10: Not Covered | AP10: ✔ | AQ10: Not Applicable | AR10: ✔ | AS10: ✔ | AT10: ✔ | AU10: ✔ | AV10: Upto Rs. 2k | AW10: Upto Rs. 1 lac | AX10: 50% Co-Pay | AY10: Upto Rs. 30k | AZ10: Not Covered | BA10: Upto 25% of SI | BB10: Not Covered | BC10: ✔ | BD10: Not Covered | BE10: ✖ | BF10: ✔ | BG10: ✔ | BH10: ✔ | BI10: ✔ | BJ10: Not Allowed | BK10: ✔ | BL10: Not Allowed | BM10: ✔ | BN10: Not Allowed | BO10: 2-4 Hrs | BP10: ✔ | BQ10: ✔ | BR10: ✔ | BS10: ✔
A11: HDFC Ergo | C11: ✔ | D11: ✔ | E11: 2 | F11: ✔ | G11: ✔ | H11: ✔ | I11: ✔ | J11: ✔ | K11: ✖ | L11: ✔ | M11: ✔ | N11: ✔ | O11: ✔ | P11: ✖ | Q11: ✖ | R11: ✖ | S11: ✔ | T11: Not Covered | U11: ✔ | V11: ✔ | X11: ✔ | Y11: Inhouse TPA | Z11: ✔ | AA11: ✔ (Listed Procedures Only) | AB11: ✔ | AC11: ✔ | AD11: ✖ | AE11: 30/60 days | AF11: Not Covered | AG11: ✔ | AH11: ✔ | AI11: ✔ | AJ11: ✔ | AK11: ✔ | AL11: ✔ | AM11: ✖ | AN11: ✔ | AO11: Not Covered | AP11: ✔ | AQ11: Not Applicable | AR11: ✖ | AS11: ✔ | AT11: ✔ | AU11: ✔ | AV11: Upto Actuals | AW11: Upto Rs. 100k | AX11: 50% Co-Pay | AY11: ✖ | AZ11: Not Covered | BA11: Not Covered | BB11: Not Covered | BC11: Not Covered | BD11: Not Covered | BE11: ✖ | BF11: ✔ | BG11: ✔ | BH11: ✔ | BI11: ✔ | BJ11: Not Allowed | BK11: ✔ | BL11: Not Allowed | BM11: ✔ | BN11: Not Allowed | BO11: 2-4 Hrs | BP11: ✔ | BQ11: ✔ | BR11: Within 24 Hrs | BS11: ✔
A12: ICICI Lombard | B12: =_xlfn.IMAGE("AZ4", "A4") -> #VALUE! | C12: ✔ | D12: ✔ | E12: 4 | F12: ✔ | G12: ✔ | H12: ✔ | I12: ✔ | J12: ✔ | K12: ✔ | L12: ✔ | M12: ✔ | N12: ✔ | O12: ✔ | P12: ✔ | Q12: ✔ | R12: ✔ | S12: ✔ | T12: Not Covered | U12: ✔ | V12: ✔ | W12: 6,500+ Hospitals | X12: ✔ | Y12: Inhouse TPA | Z12: ✔ | AA12: ✔ (Listed Procedures Only) | AB12: ✔ | AC12: ✔ | AD12: ✖ | AE12: 60/90 Days | AF12: Not Covered | AG12: ✔ | AH12: ✔ | AI12: ✔ | AJ12: ✔ | AK12: ✔ | AL12: ✔ | AM12: ✖ | AN12: ✔ | AO12: Not Covered | AP12: ✔ | AQ12: Not Applicable | AR12: Upto Rs. 5K | AS12: ✔ | AT12: ✔ | AU12: ✔ | AV12: Upto Rs. 2k | AW12: Upto Rs. 1 lac | AX12: 50% Co-Pay | AY12: Upto Rs. 30k | AZ12: Not Covered | BA12: ✖ | BB12: Not Covered | BC12: ✖ | BD12: Not Covered | BE12: If eye power +/- 6.5 | BF12: ✔ | BG12: ✔ | BH12: ✔ | BI12: ✔ | BJ12: Not Allowed | BK12: ✔ | BL12: Not Allowed | BM12: ✔ | BN12: Not Allowed | BO12: 2-4 Hrs | BP12: ✔ | BQ12: ✔ | BR12: ✔ | BS12: ✔
A13: ICICI Lombard (SME Exclusive) | C13: ✔ | D13: ✔ | E13: 4 | F13: ✔ | G13: ✔ | H13: ✔ | I13: ✔ | J13: ✔ | K13: X | L13: ✔ | M13: ✔ | O13: ✔ | Q13: ✔ | S13: ✔ | T13: Not Covered | U13: ✔ | V13: ✔ | X13: ✔ | Y13: Inhouse TPA | Z13: ✔ | AA13: ✔ (Listed Procedures Only) | AB13: ✔ | AC13: ✔ | AD13: ✔ | AE13: 30/60 days | AF13: Not Covered | AG13: ✔ | AH13: ✔ | AI13: ✔ | AJ13: ✔ | AK13: ✔ | AL13: ✔ | AM13: ✖ | AN13: ✔ | AO13: Not Covered | AP13: ✔ | AQ13: Not Applicable | AR13: Covered upto 10% of maternity within maternity limit | AS13: ✔ | AT13: ✔ | AU13: ✔ | AV13: Upto 1% of SI | AW13: Upto 25% of SI | AX13: Upto 50% of SI | AY13: Upto Rs. 100k | AZ13: Not Covered | BA13: Upto 50% of SI | BB13: Not Covered | BC13: ✔ | BD13: Not Covered | BE13: If eye power +/- 6.5 | BF13: ✔ | BG13: ✔ | BH13: ✔ | BI13: ✔ | BJ13: Not Allowed | BK13: ✔ | BL13: Not Allowed | BM13: ✔ | BN13: Not Allowed | BO13: 2-4 Hrs | BP13: ✔ | BQ13: ✔ | BR13: ✔ | BS13: ✔
A14: ICICI Lombard (HRMS Exclusive) | C14: ✔ | D14: ✔ | E14: 4 | F14: ✖ | G14: ✔ | H14: ✔ | I14: For SI 1/2/3 lac - Rs. 5,000 for Normal, Rs. 10,000 for ICU For SI 5 lac - Single Private AC, No Limit for ICU | J14: For SI 1/2/3 lac - Rs. 5,000 for Normal, Rs. 10,000 for ICU For SI 5 lac - Single Private AC, No Limit for ICU | K14: For SI 1/2/3 lac - Rs. 5,000 for Normal, Rs. 10,000 for ICU For SI 5 lac - Single Private AC, No Limit for ICU | L14: For SI 1/2/3 lac - Rs. 5,000 for Normal, Rs. 10,000 for ICU For SI 5 lac - Single Private AC, No Limit for ICU | M14: ✔ | N14: ✖ | O14: ✖ | P14: ✖ | Q14: ✖ | R14: ✖ | S14: ✖ | T14: Not Covered | U14: ✖ | V14: ✔ | X14: ✔ | Y14: Inhouse | Z14: ✔ | AA14: ✔ (Listed Procedures Only) | AB14: ✖ (Disease Capping Limits Apply) | AC14: Included (min. 24 hours in-patient hospitalisation) | AD14: ✖ | AE14: 30/60 days | AF14: Not Covered | AG14: ✖ | AH14: ✔ | AI14: ✔ | AJ14: ✔ | AK14: ✔ | AL14: ✔ | AM14: ✖ | AN14: Optional -50k (with extra loading) | AO14: Not Covered | AP14: ✔ | AQ14: Not Applicable | AR14: ✖ | AS14: NIL for accidental hospitalization 30 days for any other hospitalization | AT14: ✔ | AU14: ✔ | AV14: Upto Rs.2.5k | AW14: ✖ | AX14: 50% Co-Pay | AY14: ✖ | AZ14: Not Covered | BA14: Upto 25% of SI | BB14: Not Covered | BC14: ✔ | BD14: Not Covered | BE14: If eye power +/- 7.5 | BF14: ✔ | BG14: Rolling forward addition (Annual) Pro-rata deletion | BH14: Not Allowed | BI14: ✔ | BJ14: Not Allowed | BK14: ✖ | BL14: ✖ | BM14: ✖ | BN14: ✖ | BO14: 2-4 Hrs | BP14: ✔ | BQ14: ✔ | BR14: ✔ | BS14: ✔
A15: IFFCO Tokio | B15: =_xlfn.IMAGE("AZ4", "A4") -> #VALUE! | C15: ✔ | D15: ✔ | E15: 2 | F15: ✔ | G15: ✔ | H15: ✔ | I15: ✔ | J15: ✔ | K15: ✔ | L15: ✔ | M15: ✔ | N15: ✔ | O15: ✔ | P15: ✔ | Q15: ✔ | R15: ✔ | S15: ✔ | T15: Not Covered | U15: ✔ | V15: ✔ | W15: 7,500+ Hospitals | X15: ✔ | Y15: Paramount TPA/ Internal TPA | Z15: ✔ | AA15: ✔ (Listed Procedures Only) | AB15: ✔ | AC15: ✔ | AD15: ✔ | AE15: 30/60 days | AF15: Not Covered | AG15: ✔ | AH15: ✔ | AI15: ✔ | AJ15: ✔ | AK15: ✔ | AL15: ✔ | AM15: ✖ | AN15: ✔ | AO15: Not Covered | AP15: ✔ | AQ15: Not Applicable | AR15: Upto Rs. 2.5K | AS15: ✔ | AT15: ✔ | AU15: ✔ | AV15: Upto Rs. 1k | AW15: ✖ | AX15: 50% Co-Pay | AY15: ✔ | AZ15: Not Covered | BA15: ✔ | BB15: Not Covered | BC15: ✔ | BD15: Not Covered | BE15: ✖ | BF15: ✖ | BG15: ✔ | BH15: ✔ | BI15: ✔ | BJ15: Not Allowed | BK15: ✔ | BL15: Not Allowed | BM15: ✔ | BN15: Not Allowed | BO15: 2-4 Hrs | BP15: ✔ | BQ15: ✖ | BR15: ✔ | BS15: ✔
A16: Magma | B16: =_xlfn.IMAGE("AZ4", "A4") -> #VALUE! | C16: ✔ | D16: ✔ | E16: 2 | F16: ✔ | G16: ✔ | H16: ✔ | I16: ✔ | J16: ✔ | K16: ✔ | L16: ✔ | M16: ✔ | N16: ✔ | O16: ✔ | P16: ✔ | Q16: ✔ | R16: ✔ | S16: ✔ | T16: Not Covered | U16: ✔ | V16: ✔ | W16: 6,000+ Hospitals | X16: ✔ | Y16: Paramount TPA | Z16: ✔ | AA16: ✔ (Listed Procedures Only) | AB16: Only on CKD and Cancer Upto 3 Lacs | AC16: ✔ | AD16: ✖ | AE16: 30/60 days | AF16: Not Covered | AG16: ✔ | AH16: ✔ | AI16: ✔ | AJ16: ✔ | AK16: ✔ | AL16: ✔ | AM16: ✖ | AN16: ✔ | AO16: Not Covered | AP16: ✔ | AQ16: Not Applicable | AR16: Upto Rs. 5K | AS16: ✔ | AT16: ✔ | AU16: ✔ | AV16: Upto Rs. 3k | AW16: ✖ | AX16: 50% Co-Pay | AY16: Upto Rs. 30k | AZ16: Not Covered | BA16: Upto 25% of SI | BB16: Not Covered | BC16: ✖ | BD16: Not Covered | BE16: If eye power +/- 7.5 | BF16: ✔ | BG16: ✔ | BH16: ✔ | BI16: ✔ | BJ16: Not Allowed | BK16: ✔ | BL16: Not Allowed | BM16: ✔ | BN16: Not Allowed | BO16: 2-4 Hrs | BP16: ✔ | BQ16: ✔ | BR16: Within 15 Days | BS16: ✔
A17: Manipal Cigna | C17: ✔ | D17: ✔ | E17: 2 | F17: ✔ | G17: ✔ | H17: ✔ | I17: ✔ | J17: ✔ | K17: ✔ | L17: ✔ | M17: ✔ | N17: ✔ | O17: ✔ | P17: ✔ | Q17: ✔ | R17: ✔ | S17: ✔ | T17: Not Covered | U17: ✔ | V17: ✔ | W17: 6,500+ Hopsitals | X17: ✔ | Y17: Medi Assist Insurance | Z17: ✔ | AA17: ✔ (Listed Procedures Only) | AB17: ✔ | AC17: ✔ | AD17: ✖ | AE17: 60/90 Days | AF17: Not Covered | AG17: ✔ | AH17: ✔ | AI17: ✔ | AJ17: ✔ | AK17: ✔ | AL17: ✔ | AM17: ✖ | AN17: ✔ | AO17: Not Covered | AP17: ✔ | AQ17: Not Applicable | AR17: Upto Rs. 5K | AS17: ✔ | AT17: ✔ | AU17: ✔ | AV17: Upto Rs. 2.5k | AW17: ✖ | AX17: 50% Co-Pay | AY17: ✖ | AZ17: Not Covered | BA17: Not Covered | BB17: Not Covered | BC17: ✔ | BD17: Not Covered | BE17: If eye power +/- 6.5 | BF17: ✔ | BG17: ✔ | BH17: Not Allowed | BI17: ✔ | BJ17: Not Allowed | BK17: ✔ | BL17: Not Allowed | BM17: Not Allowed | BN17: Not Allowed | BO17: 2-4 Hrs | BP17: ✔ | BQ17: ✔ | BR17: ✔ | BS17: ✔
A18: Manipal Cigna (Gig Exclusive) | C18: ✔ | D18: ✔ | E18: 4 | F18: ✖ | G18: ✖ | H18: ✖ | I18: For SI 1 lac - Rs. 2,000 for Normal, Rs. 4,000 for ICU For SI 2/3 lac - Rs. 5,000 for Normal, Rs. 10,000 for ICU | J18: For SI 1 lac - Rs. 2,000 for Normal, Rs. 4,000 for ICU For SI 2/3 lac - Rs. 5,000 for Normal, Rs. 10,000 for ICU | K18: For SI 1 lac - Rs. 2,000 for Normal, Rs. 4,000 for ICU For SI 2/3 lac - Rs. 5,000 for Normal, Rs. 10,000 for ICU | L18: For SI 1 lac - Rs. 2,000 for Normal, Rs. 4,000 for ICU For SI 2/3 lac - Rs. 5,000 for Normal, Rs. 10,000 for ICU | M18: ✔ | N18: ✖ | O18: ✖ | P18: ✖ | Q18: ✖ | R18: ✖ | S18: ✖ | T18: Not Covered | U18: ✖ | V18: ✔ | X18: ✔ | Y18: Inhouse | Z18: ✔ | AA18: ✔ (Listed Procedures Only) | AB18: ✔ | AC18: Included (min. 24 hours in-patient hospitalisation) | AD18: ✖ | AE18: 60/90 Days | AF18: Not Covered | AG18: ✖ | AH18: ✔ | AI18: ✔ | AJ18: ✔ | AK18: ✔ | AL18: ✔ | AM18: ✖ | AN18: Optional -50k (with extra loading) | AO18: Not Covered | AP18: ✔ | AQ18: Not Applicable | AR18: ✖ | AS18: ✖ | AT18: Nil | AU18: Nil | AV18: Upto Rs. 2.5k | AW18: ✖ | AX18: 50% Co-Pay | AY18: ✖ | AZ18: Not Covered | BA18: Not Covered | BB18: Not Covered | BC18: ✔ | BD18: Not Covered | BE18: If eye power +/- 6.5 | BF18: ✔ | BG18: ✔ | BH18: Not Allowed | BI18: ✖ | BJ18: ✖ | BK18: ✖ | BL18: ✖ | BM18: ✖ | BN18: ✖ | BO18: ✖ | BP18: ✖ | BQ18: ✖ | BR18: ✖ | BS18: ✖
A19: Manipal Cigna (SME Exclusive) | C19: ✔ | D19: ✔ | E19: 4 | F19: ✖ | G19: ✔ | H19: ✔ | I19: For SI 1 lac - Rs. 2,000 for Normal, Rs. 4,000 for ICU For SI 2 lac/ 3 lac - Rs. 5,000 for Normal, Rs. 10,000 for ICU For SI 5 lac - Single Private AC, No Limit for ICU | J19: For SI 1 lac - Rs. 2,000 for Normal, Rs. 4,000 for ICU For SI 2 lac/ 3 lac - Rs. 5,000 for Normal, Rs. 10,000 for ICU For SI 5 lac - Single Private AC, No Limit for ICU | K19: For SI 1 lac - Rs. 2,000 for Normal, Rs. 4,000 for ICU For SI 2 lac/ 3 lac - Rs. 5,000 for Normal, Rs. 10,000 for ICU For SI 5 lac - Single Private AC, No Limit for ICU | L19: For SI 1 lac - Rs. 2,000 for Normal, Rs. 4,000 for ICU For SI 2 lac/ 3 lac - Rs. 5,000 for Normal, Rs. 10,000 for ICU For SI 5 lac - Single Private AC, No Limit for ICU | M19: ✔ | N19: ✔ | O19: ✔ | P19: ✔ | Q19: ✔ | R19: ✔ | S19: ✖ | T19: Not Covered | U19: ✔ | V19: ✔ | W19: 8300+ Hospitals | X19: ✔ | Y19: Inhouse | Z19: ✔ | AA19: ✔ (Listed Procedures Only) | AB19: ✔ | AC19: ✔ | AD19: ✖ | AE19: 60/90 Days | AF19: Not Covered | AG19: ✔ | AH19: ✔ | AI19: ✔ | AJ19: ✔ | AK19: ✔ | AL19: ✔ | AM19: ✖ | AN19: Optional - 35K, 50K, 75K (with extra loading) | AO19: Not Covered | AP19: ✔ | AQ19: Not Applicable | AR19: ✔ | AS19: ✔ | AT19: ✔ | AU19: ✔ | AV19: Upto Rs. 2.5k | AW19: ✖ | AX19: 50% Co-Pay | AY19: ✖ | AZ19: Not Covered | BA19: Not Covered | BB19: Not Covered | BC19: ✔ | BD19: Not Covered | BE19: If eye power +/- 6.5 | BF19: ✔ | BG19: ✔ | BH19: Not Allowed | BI19: ✖ | BJ19: Not Allowed | BK19: ✔ | BL19: Not Allowed | BM19: ✔ | BN19: Not Allowed | BO19: 2-4 Hrs | BP19: ✔ | BQ19: ✔ | BR19: ✔ | BS19: ✔
A20: New India | B20: =_xlfn.IMAGE("AZ4", "A4") -> #VALUE! | C20: =INDEX('BASE GHI 'BASE GHI TP'!A3TP'!$A$3:$BS$24,MATCH('GHI Policy Features (Option 1)'!F$9,'BASE GHI TP'!$A$3:$A$24,0),MATCH('GHI Policy Features (Option 1)'!$E31,'BASE GHI TP'!$A$3:$BS$3,0)) | D20: ✔ | E20: 2 | F20: ✔ | G20: ✔ | H20: ✔ | I20: ✔ | J20: ✔ | K20: ✔ | L20: ✔ | M20: ✔ | N20: ✔ | O20: ✔ | P20: ✔ | Q20: ✔ | R20: ✔ | S20: ✔ | T20: Not Covered | U20: ✔ | V20: ✔ | W20: 6,500+ Hospitals | X20: ✔ | Y20: Paramount TPA | Z20: ✔ | AA20: ✔ (Listed Procedures Only) | AB20: ✔ | AC20: ✔ | AD20: ✖ | AE20: 30/60 days | AF20: Not Covered | AG20: ✔ | AH20: ✔ | AI20: ✔ | AJ20: ✔ | AK20: ✔ | AL20: ✔ | AM20: ✖ | AN20: ✔ | AO20: Not Covered | AP20: ✔ | AQ20: Not Applicable | AR20: Upto Rs. 2.5K | AS20: ✔ | AT20: ✔ | AU20: ✔ | AV20: Upto Rs. 2k | AW20: ✖ | AX20: 50% Co-Pay | AY20: ✖ | AZ20: Not Covered | BA20: Upto 25% of SI | BB20: Not Covered | BC20: ✖ | BD20: Not Covered | BE20: If eye power +/- 7.5 | BF20: ✔ | BG20: ✔ | BH20: ✔ | BI20: ✔ | BJ20: Not Allowed | BK20: ✔ | BL20: Not Allowed | BM20: ✔ | BN20: Not Allowed | BO20: 2-4 Hrs | BP20: ✔ | BQ20: ✖ | BR20: ✖ | BS20: ✔
A21: Niva Bupa | B21: =_xlfn.IMAGE("AZ4", "A4") -> #VALUE! | C21: ✔ | D21: ✔ | E21: 3 | F21: ✔ | G21: ✔ | H21: ✔ | I21: ✔ | J21: ✔ | K21: ✔ | L21: ✔ | M21: ✔ | N21: ✔ | O21: ✔ | P21: ✔ | Q21: ✔ | R21: ✔ | S21: ✔ | T21: Not Covered | U21: ✔ | V21: ✔ | W21: 8,600+ Hospitals | X21: ✔ | Y21: Inhouse TPA | Z21: ✔ | AA21: ✔ (Listed Procedures Only) | AB21: ✔ | AC21: ✔ | AD21: ✔ | AE21: 30/60 days | AF21: Not Covered | AG21: ✔ | AH21: ✔ | AI21: ✔ | AJ21: ✔ | AK21: ✔ | AL21: ✔ | AM21: ✖ | AN21: ✔ | AO21: Not Covered | AP21: ✔ | AQ21: Not Applicable | AR21: Upto Rs. 2.5K | AS21: ✔ | AT21: ✔ | AU21: ✔ | AV21: Upto Rs. 2k | AW21: ✖ | AX21: 50% Co-Pay | AY21: ✖ | AZ21: Not Covered | BA21: Upto 20% of SI | BB21: Not Covered | BC21: ✖ | BD21: Not Covered | BE21: If eye power +/- 7.5 | BF21: ✔ | BG21: ✔ | BH21: ✔ | BI21: ✔ | BJ21: Not Allowed | BK21: ✔ | BL21: Not Allowed | BM21: ✔ | BN21: Not Allowed | BO21: 2-4 Hrs | BP21: ✔ | BQ21: ✔ | BR21: ✔ | BS21: ✔
A22: Oriental Insurance | B22: =_xlfn.IMAGE("AZ4", "A4") -> #VALUE! | C22: ✔ | D22: ✔ | E22: 2 | F22: ✔ | G22: ✔ | H22: ✔ | I22: ✔ | J22: ✔ | K22: ✔ | L22: ✔ | M22: ✔ | N22: ✔ | O22: ✔ | P22: ✔ | Q22: ✔ | R22: ✔ | S22: ✔ | T22: Not Covered | U22: ✔ | V22: ✔ | W22: 6,500+ Hospitals | X22: ✔ | Y22: Paramount TPA | Z22: ✔ | AA22: ✔ (Listed Procedures Only) | AB22: ✔ | AC22: ✔ | AD22: ✖ | AE22: 30/60 days | AF22: Not Covered | AG22: ✔ | AH22: ✔ | AI22: ✔ | AJ22: ✔ | AK22: ✔ | AL22: ✔ | AM22: ✖ | AN22: ✔ | AO22: Not Covered | AP22: ✔ | AQ22: Not Applicable | AR22: Upto Rs. 5K | AS22: ✔ | AT22: ✔ | AU22: ✔ | AV22: Upto Rs. 2k | AW22: ✖ | AX22: 50% Co-Pay | AY22: ✖ | AZ22: Not Covered | BA22: Upto 20% of SI | BB22: Not Covered | BC22: ✖ | BD22: Not Covered | BE22: If eye power +/- 7.5 | BF22: ✔ | BG22: ✔ | BH22: ✔ | BI22: ✔ | BJ22: Not Allowed | BK22: ✔ | BL22: Not Allowed | BM22: ✔ | BN22: Not Allowed | BO22: 2-4 Hrs | BP22: ✔ | BQ22: ✔ | BR22: ✔ | BS22: ✔
A23: Raheja QBE | B23: =_xlfn.IMAGE("AZ4", "A4") -> #VALUE! | C23: ✔ | D23: ✔ | E23: 2 | F23: Upto 90 Years | G23: ✔ | H23: ✔ | I23: ✔ | J23: ✔ | K23: ✔ | L23: ✔ | M23: ✔ | N23: ✔ | O23: ✔ | P23: ✔ | Q23: ✔ | R23: ✔ | S23: ✔ | T23: Not Covered | U23: ✔ | V23: ✔ | W23: 8,500+ Hospitals | X23: ✔ | Y23: Paramount TPA | Z23: ✔ | AA23: ✔ (Listed Procedures Only) | AB23: ✔ | AC23: ✔ | AD23: ✔ | AE23: 30/60 days | AF23: Not Covered | AG23: ✔ | AH23: ✔ | AI23: ✔ | AJ23: ✔ | AK23: ✔ | AL23: ✔ | AM23: ✖ | AN23: ✔ | AO23: Not Covered | AP23: ✔ | AQ23: Not Applicable | AR23: ✔ | AS23: ✔ | AT23: ✔ | AU23: ✔ | AV23: Upto Rs. 2k | AW23: ✖ | AX23: 50% Co-Pay | AY23: ✔ | AZ23: Not Covered | BA23: Upto 25% of SI | BB23: Not Covered | BC23: ✖ | BD23: Not Covered | BE23: ✖ | BF23: ✖ | BG23: ✔ | BH23: Not Allowed | BI23: ✖ | BJ23: Not Allowed | BK23: ✔ | BL23: Not Allowed | BM23: ✔ | BN23: Not Allowed | BO23: 2-4 Hrs | BP23: ✔ | BQ23: ✔ | BR23: ✖ | BS23: ✔
A24: Indusind General | C24: ✔ | D24: ✔ | E24: 2 | F24: Upto 90 Years | G24: ✔ | H24: ✔ | I24: ✔ | J24: ✔ | K24: ✔ | L24: ✔ | M24: ✔ | N24: ✔ | O24: ✔ | P24: ✔ | Q24: ✔ | R24: ✔ | S24: ✔ | T24: Not Covered | U24: ✔ | V24: ✔ | W24: 8,600+ Hospitals | X24: ✔ | Y24: Medi Assist Insurance | Z24: ✔ | AA24: ✔ (Listed Procedures Only) | AB24: ✔ | AC24: ✔ | AD24: ✖ | AE24: 30/60 days | AF24: Not Covered | AG24: ✔ | AH24: ✔ | AI24: ✔ | AJ24: ✔ | AK24: ✔ | AL24: ✔ | AM24: ✖ | AN24: ✔ | AO24: Not Covered | AP24: ✔ | AQ24: Not Applicable | AR24: Upto Rs. 5K | AS24: ✔ | AT24: ✔ | AU24: ✔ | AV24: Upto Rs. 2k | AW24: ✖ | AX24: 50% Co-Pay | AY24: ✔ | AZ24: Not Covered | BA24: Upto 25% of SI | BB24: Not Covered | BC24: ✔ | BD24: Not Covered | BE24: If eye power +/- 7.5 | BF24: ✔ | BG24: ✔ | BH24: Not Allowed | BI24: ✔ | BJ24: Not Allowed | BK24: ✔ | BL24: Not Allowed | BM24: ✔ | BN24: Not Allowed | BO24: 2-4 Hrs | BP24: ✔ | BQ24: ✔ | BR24: ✔ | BS24: ✔
A25: SBI General | C25: ✔ | D25: ✔ | E25: 2 | F25: Upto 90 Years | G25: ✔ | H25: ✔ | I25: ✔ | J25: ✔ | K25: ✔ | L25: ✔ | M25: ✔ | N25: ✔ | O25: ✔ | P25: ✔ | Q25: ✔ | R25: ✔ | S25: ✔ | T25: Not Covered | U25: ✔ | V25: ✔ | W25: 23,000+ Hospitals | X25: ✔ | Y25: Medi Assist Insurance | Z25: ✔ | AA25: ✔ (Listed Procedures Only) | AB25: ✔ | AC25: ✔ | AD25: ✖ | AE25: 60/90 days | AF25: Not Covered | AG25: ✔ | AH25: ✔ | AI25: ✔ | AJ25: ✔ | AK25: ✔ | AL25: ✔ | AM25: ✖ | AN25: ✔ | AO25: Not Covered | AP25: ✔ | AQ25: Not Applicable | AR25: Upto Rs. 5K | AS25: ✔ | AT25: ✔ | AU25: ✔ | AV25: 1% of SI or Rs. 1k | AW25: ✖ | AX25: 50% Co-Pay | AY25: ✔ | AZ25: Not Covered | BA25: Upto 25% of SI | BB25: Not Covered | BC25: ✔ | BD25: Not Covered | BE25: If eye power +/- 7.5 | BF25: ✔ | BG25: ✔ | BH25: Not Allowed | BI25: ✔ | BJ25: Not Allowed | BK25: ✔ | BL25: Not Allowed | BM25: ✔ | BN25: Not Allowed | BO25: 2-4 Hrs | BP25: ✔ | BQ25: ✔ | BR25: ✔ | BS25: ✔
A26: Star Health | B26: =_xlfn.IMAGE("AZ4", "A4") -> #VALUE! | C26: ✔ | D26: ✔ | E26: 2 | F26: ✔ | G26: ✔ | H26: ✔ | I26: ✔ | J26: ✔ | K26: ✔ | L26: ✔ | M26: ✔ | N26: ✔ | O26: ✔ | P26: ✔ | Q26: ✔ | R26: ✔ | S26: ✔ | T26: Not Covered | U26: ✔ | V26: ✔ | W26: 8,500+ Hospitals | X26: ✔ | Y26: Inhouse TPA | Z26: ✔ | AA26: ✔ (Listed Procedures Only) | AB26: ✔ | AC26: ✔ | AD26: ✖ | AE26: 30/60 days | AF26: Not Covered | AG26: ✔ | AH26: ✔ | AI26: ✔ | AJ26: ✔ | AK26: ✔ | AL26: ✔ | AM26: ✖ | AN26: ✔ | AO26: Not Covered | AP26: ✔ | AQ26: Not Applicable | AR26: Upto Rs. 5K | AS26: ✔ | AT26: ✔ | AU26: ✔ | AV26: Upto Rs. 2k | AW26: ✖ | AX26: ✖ | AY26: Upto 30% of SI | AZ26: Not Covered | BA26: Upto Rs. 25k | BB26: Not Covered | BC26: ✔ | BD26: Not Covered | BE26: If eye power +/- 7.5 | BF26: ✔ | BG26: ✔ | BH26: ✔ | BI26: ✖ | BJ26: Not Allowed | BK26: ✔ | BL26: Not Allowed | BM26: ✔ | BN26: Not Allowed | BO26: 2-4 Hrs | BP26: ✔ | BQ26: ✔ | BR26: Within 24 Hrs | BS26: ✔
A27: TATA AIG | B27: =_xlfn.IMAGE("AZ4", "A4") -> #VALUE! | C27: ✔ | D27: ✔ | E27: 3 | F27: ✔ | G27: ✔ | H27: ✔ | I27: ✔ | J27: ✔ | K27: ✔ | L27: ✔ | M27: ✔ | N27: ✔ | O27: ✔ | P27: ✔ | Q27: ✔ | R27: ✔ | S27: ✔ | T27: Not Covered | U27: ✔ | V27: ✔ | W27: 7,200+ Hospitals | X27: ✔ | Y27: Family Health Insurance TPA | Z27: ✔ | AA27: ✔ (Listed Procedures Only) | AB27: ✔ | AC27: ✔ | AD27: ✔ | AE27: 30/60 days | AF27: Not Covered | AG27: ✔ | AH27: ✔ | AI27: ✔ | AJ27: ✔ | AK27: ✔ | AL27: ✔ | AM27: ✖ | AN27: ✔ | AO27: Not Covered | AP27: ✔ | AQ27: Not Applicable | AR27: Upto Rs. 5K | AS27: ✔ | AT27: ✔ | AU27: ✔ | AV27: Upto Rs. 2.5k | AW27: Upto Rs. 50k | AX27: 50% Co-Pay | AY27: Upto Rs. 50k | AZ27: Not Covered | BA27: Upto 25% of SI | BB27: Not Covered | BC27: ✔ | BD27: Not Covered | BE27: If eye power +/- 6.5 | BF27: ✔ | BG27: ✔ | BH27: ✔ | BI27: ✔ | BJ27: Not Allowed | BK27: ✔ | BL27: Not Allowed | BM27: ✔ | BN27: Not Allowed | BO27: 2-4 Hrs | BP27: ✔ | BQ27: ✖ | BR27: ✖ | BS27: ✔

Sheet GPA Features (Option 1)
A1: =Inputs!B5 -> Bandana Gupta Class
A2: =Inputs!B2 -> 45177 | C2: Group Personal Accident Insurance
C3: Client Name | F3: ='Company Info'!B4 -> ABC
C4: Type of Policy | F4: Rollover | J4: Manual
C5: Policy Period | F5: 1-Apr-25 To 31-Mar-26 | J5: Manual
F7: PROPOSED INSURERS | I7: PREVIOUS INSURER
F8: Tata AIG (Basic Plan) | G8: Tata AIG (Standard Plan) | H8: Tata AIG (Pro Plan) | I8: Care Health
C9: Premium Details
C10: Sum Insured (Rs.) | F10: 10 Lacs | G10: 10 Lacs | H10: 10 Lacs | I10: 10 Lacs | J10: Manual
C11: Annual Premium (Excl. GST) | F11: 96700 | G11: 140000 | H11: 150000 | I11: 50000 | J11: Manual
C12: Total Number Of Lives | F12: 529 | G12: 450 | H12: 450 | I12: 300 | J12: Manual
C13: Avg. Premium Per Employee | F13: =F11/F12 -> 182.79773 | G13: =G11/G12 -> 311.11111 | H13: =H11/H12 -> 333.33333 | I13: =I11/I12 -> 166.66667
C14: Premium Per Mille | F14: 0.3 | G14: 0.3 | H14: 0.3 | I14: 0.4 | J14: Manual
C15: Policy Features - Group Personal Accident Insurance
B16: Members Covered | C16: Family Definition | D16: =SUBSTITUTE($C$16," ","") -> FamilyDefinition | F16: Self | G16: Self | H16: Self | I16: Self
B18: Key Benefits | C18: Accidental Death | D18: =SUBSTITUTE(C18," ","") -> AccidentalDeath | F18: =INDEX('GPA DB'!$A$3:$O$15,MATCH('GPA Features (Option 1)'!F$8,'GPA DB'!$A$3:$A$15,0),MATCH('GPA Features (Option 1)'!$C18,'GPA DB'!$A$3:$O$3,0)) -> 100% of SI | G18: =INDEX('GPA DB'!$A$3:$O$17,MATCH('GPA Features (Option 1)'!G$8,'GPA DB'!$A$3:$A$17,0),MATCH('GPA Features (Option 1)'!$C18,'GPA DB'!$A$3:$O$3,0)) -> 100% of SI | H18: =INDEX('GPA DB'!$A$3:$O$17,MATCH('GPA Features (Option 1)'!H$8,'GPA DB'!$A$3:$A$17,0),MATCH('GPA Features (Option 1)'!$C18,'GPA DB'!$A$3:$O$3,0)) -> 100% of SI | I18: =INDEX('GPA DB'!$A$3:$O$15,MATCH('GPA Features (Option 1)'!I$8,'GPA DB'!$A$3:$A$15,0),MATCH('GPA Features (Option 1)'!$C18,'GPA DB'!$A$3:$O$3,0)) -> 100% of SI
C19: Permanent Total Disablement | D19: =SUBSTITUTE(C19," ","") -> PermanentTotalDisablement | F19: =INDEX('GPA DB'!$A$3:$O$15,MATCH('GPA Features (Option 1)'!F$8,'GPA DB'!$A$3:$A$15,0),MATCH('GPA Features (Option 1)'!$C19,'GPA DB'!$A$3:$O$3,0)) -> 100% of SI | G19: =INDEX('GPA DB'!$A$3:$O$17,MATCH('GPA Features (Option 1)'!G$8,'GPA DB'!$A$3:$A$17,0),MATCH('GPA Features (Option 1)'!$C19,'GPA DB'!$A$3:$O$3,0)) -> 100% of SI | H19: =INDEX('GPA DB'!$A$3:$O$17,MATCH('GPA Features (Option 1)'!H$8,'GPA DB'!$A$3:$A$17,0),MATCH('GPA Features (Option 1)'!$C19,'GPA DB'!$A$3:$O$3,0)) -> 100% of SI | I19: =INDEX('GPA DB'!$A$3:$O$15,MATCH('GPA Features (Option 1)'!I$8,'GPA DB'!$A$3:$A$15,0),MATCH('GPA Features (Option 1)'!$C19,'GPA DB'!$A$3:$O$3,0)) -> 100% of SI
C20: Permanent Partial Disablement | D20: =SUBSTITUTE(C20," ","") -> PermanentPartialDisablement | F20: =INDEX('GPA DB'!$A$3:$O$15,MATCH('GPA Features (Option 1)'!F$8,'GPA DB'!$A$3:$A$15,0),MATCH('GPA Features (Option 1)'!$C20,'GPA DB'!$A$3:$O$3,0)) -> Up to 100% of SI based on extent of disability | G20: =INDEX('GPA DB'!$A$3:$O$17,MATCH('GPA Features (Option 1)'!G$8,'GPA DB'!$A$3:$A$17,0),MATCH('GPA Features (Option 1)'!$C20,'GPA DB'!$A$3:$O$3,0)) -> Up to 100% of SI based on extent of disability | H20: =INDEX('GPA DB'!$A$3:$O$17,MATCH('GPA Features (Option 1)'!H$8,'GPA DB'!$A$3:$A$17,0),MATCH('GPA Features (Option 1)'!$C20,'GPA DB'!$A$3:$O$3,0)) -> Up to 100% of SI based on extent of disability | I20: =INDEX('GPA DB'!$A$3:$O$15,MATCH('GPA Features (Option 1)'!I$8,'GPA DB'!$A$3:$A$15,0),MATCH('GPA Features (Option 1)'!$C20,'GPA DB'!$A$3:$O$3,0)) -> Up to 100% of SI based on extent of disability
C21: Temporary Total Disablement (if patient confined to bed due to temporary and total inability to engage in any occupation or any activity) | D21: =SUBSTITUTE(C21," ","") -> TemporaryTotalDisablement (ifpatientconfinedtobedduetotemporaryandtotalinabilitytoengageinanyoccupationoranyactivity) | F21: =INDEX('GPA DB'!$A$3:$O$15,MATCH('GPA Features (Option 1)'!F$8,'GPA DB'!$A$3:$A$15,0),MATCH('GPA Features (Option 1)'!$C21,'GPA DB'!$A$3:$O$3,0)) -> 1% of SI or Rs. 5000 or Actual salary per week upto 104 weeks whichever is lower | G21: =INDEX('GPA DB'!$A$3:$O$17,MATCH('GPA Features (Option 1)'!G$8,'GPA DB'!$A$3:$A$17,0),MATCH('GPA Features (Option 1)'!$C21,'GPA DB'!$A$3:$O$3,0)) -> 1% of SI or Rs. 5000 or Actual salary per week upto 104 weeks whichever is lower | H21: =INDEX('GPA DB'!$A$3:$O$17,MATCH('GPA Features (Option 1)'!H$8,'GPA DB'!$A$3:$A$17,0),MATCH('GPA Features (Option 1)'!$C21,'GPA DB'!$A$3:$O$3,0)) -> 1% of SI or Rs. 10,000 or Actual salary per week upto 104 weeks whichever is lower | I21: =INDEX('GPA DB'!$A$3:$O$15,MATCH('GPA Features (Option 1)'!I$8,'GPA DB'!$A$3:$A$15,0),MATCH('GPA Features (Option 1)'!$C21,'GPA DB'!$A$3:$O$3,0)) -> 1% of SI or Rs. 5000 or Actual salary per week upto 104 weeks whichever is lower
C22: Accidental Hospitalization (IPD) (min. 24 hours hospitalization) | F22: =INDEX('GPA DB'!$A$3:$O$15,MATCH('GPA Features (Option 1)'!F$8,'GPA DB'!$A$3:$A$15,0),MATCH('GPA Features (Option 1)'!$C22,'GPA DB'!$A$3:$O$3,0)) -> 10% of the CSI or 40% of the Admissible Claim or Actuals whichever is less (only if accidental death or disability - PTD/ PPD) | G22: =INDEX('GPA DB'!$A$3:$O$17,MATCH('GPA Features (Option 1)'!G$8,'GPA DB'!$A$3:$A$17,0),MATCH('GPA Features (Option 1)'!$C22,'GPA DB'!$A$3:$O$3,0)) -> Fixed INR 1,00,000 or Actuals whichever is lower. | H22: =INDEX('GPA DB'!$A$3:$O$17,MATCH('GPA Features (Option 1)'!H$8,'GPA DB'!$A$3:$A$17,0),MATCH('GPA Features (Option 1)'!$C22,'GPA DB'!$A$3:$O$3,0)) -> Fixed INR 1,00,000 or Actuals whichever is lower. | I22: =INDEX('GPA DB'!$A$3:$O$15,MATCH('GPA Features (Option 1)'!I$8,'GPA DB'!$A$3:$A$15,0),MATCH('GPA Features (Option 1)'!$C22,'GPA DB'!$A$3:$O$3,0)) -> Reimb of 10% of SI or 40% of admissible PA claim or actual expense, whichever is lower if accidental death or disability
C23: Accidental Expenses (OPD) | F23: =INDEX('GPA DB'!$A$3:$O$15,MATCH('GPA Features (Option 1)'!F$8,'GPA DB'!$A$3:$A$15,0),MATCH('GPA Features (Option 1)'!$C23,'GPA DB'!$A$3:$O$3,0)) -> NA | G23: =INDEX('GPA DB'!$A$3:$O$17,MATCH('GPA Features (Option 1)'!G$8,'GPA DB'!$A$3:$A$17,0),MATCH('GPA Features (Option 1)'!$C23,'GPA DB'!$A$3:$O$3,0)) -> NA | H23: =INDEX('GPA DB'!$A$3:$O$17,MATCH('GPA Features (Option 1)'!H$8,'GPA DB'!$A$3:$A$17,0),MATCH('GPA Features (Option 1)'!$C23,'GPA DB'!$A$3:$O$3,0)) -> NA | I23: =INDEX('GPA DB'!$A$3:$O$15,MATCH('GPA Features (Option 1)'!I$8,'GPA DB'!$A$3:$A$15,0),MATCH('GPA Features (Option 1)'!$C23,'GPA DB'!$A$3:$O$3,0)) -> NA
B25: Other Benefits | C25: Additional Benefits | F25: =INDEX('GPA DB'!$A$3:$O$15,MATCH('GPA Features (Option 1)'!F$8,'GPA DB'!$A$3:$A$15,0),MATCH('GPA Features (Option 1)'!$C25,'GPA DB'!$A$3:$O$3,0)) -> • Children Education Benefit- 10% of SI upto Rs. 5000 per child (max 2 children upto 25 years of age) • Compassionate Visit - 10% SI upto Rs. 25,000 • Funeral Expenses - 2.5% of SI upto Rs. 2500 • Transportation of Dead Body - 2.5% of SI upto Rs.2500 | G25: =INDEX('GPA DB'!$A$3:$O$17,MATCH('GPA Features (Option 1)'!G$8,'GPA DB'!$A$3:$A$17,0),MATCH('GPA Features (Option 1)'!$C25,'GPA DB'!$A$3:$O$3,0)) -> • Children Education Benefit- 10% of SI upto Rs. 5000 per child (max 2 children upto 25 years of age) • Compassionate Visit - 10% SI upto Rs. 25,000 • Funeral Expenses - 2.5% of SI upto Rs. 5000 • Transportation of Dead Body - 2.5% of SI upto Rs.5000 • Lifestyle modification - 10% SI upto Rs. 10,000 | H25: =INDEX('GPA DB'!$A$3:$O$17,MATCH('GPA Features (Option 1)'!H$8,'GPA DB'!$A$3:$A$17,0),MATCH('GPA Features (Option 1)'!$C25,'GPA DB'!$A$3:$O$3,0)) -> • Children Education Benefit- Upto Rs. 10,000 per child (max 2 children upto 25 years of age) • Compassionate Visit - 10% SI upto Rs. 25,000 • Funeral Expenses - 5% of SI upto Rs. 10,000 • Transportation of Dead Body - 5% of SI upto Rs.10,000 • Lifestyle modification - 10% SI upto Rs. 25,000 | I25: =INDEX('GPA DB'!$A$3:$O$15,MATCH('GPA Features (Option 1)'!I$8,'GPA DB'!$A$3:$A$15,0),MATCH('GPA Features (Option 1)'!$C25,'GPA DB'!$A$3:$O$3,0)) -> • Child Education Benefit • Funeral Expenses • Transportation Cost of Dead Body • Ambulance Charges • Burns Cover
C26: Terrorism | F26: =INDEX('GPA DB'!$A$3:$O$15,MATCH('GPA Features (Option 1)'!F$8,'GPA DB'!$A$3:$A$15,0),MATCH('GPA Features (Option 1)'!$C26,'GPA DB'!$A$3:$O$3,0)) -> Covered | G26: =INDEX('GPA DB'!$A$3:$O$17,MATCH('GPA Features (Option 1)'!G$8,'GPA DB'!$A$3:$A$17,0),MATCH('GPA Features (Option 1)'!$C26,'GPA DB'!$A$3:$O$3,0)) -> Covered | H26: =INDEX('GPA DB'!$A$3:$O$17,MATCH('GPA Features (Option 1)'!H$8,'GPA DB'!$A$3:$A$17,0),MATCH('GPA Features (Option 1)'!$C26,'GPA DB'!$A$3:$O$3,0)) -> Covered | I26: =INDEX('GPA DB'!$A$3:$O$15,MATCH('GPA Features (Option 1)'!I$8,'GPA DB'!$A$3:$A$15,0),MATCH('GPA Features (Option 1)'!$C26,'GPA DB'!$A$3:$O$3,0)) -> Covered (except not covered arising out Nuclear/Biological or chemical means)
B28: Coverage | C28: Geographical Limit | F28: =INDEX('GPA DB'!$A$3:$O$15,MATCH('GPA Features (Option 1)'!F$8,'GPA DB'!$A$3:$A$15,0),MATCH('GPA Features (Option 1)'!$C28,'GPA DB'!$A$3:$O$3,0)) -> Worldwide | G28: =INDEX('GPA DB'!$A$3:$O$17,MATCH('GPA Features (Option 1)'!G$8,'GPA DB'!$A$3:$A$17,0),MATCH('GPA Features (Option 1)'!$C28,'GPA DB'!$A$3:$O$3,0)) -> Worldwide | H28: =INDEX('GPA DB'!$A$3:$O$17,MATCH('GPA Features (Option 1)'!H$8,'GPA DB'!$A$3:$A$17,0),MATCH('GPA Features (Option 1)'!$C28,'GPA DB'!$A$3:$O$3,0)) -> Worldwide | I28: =INDEX('GPA DB'!$A$3:$O$15,MATCH('GPA Features (Option 1)'!I$8,'GPA DB'!$A$3:$A$15,0),MATCH('GPA Features (Option 1)'!$C28,'GPA DB'!$A$3:$O$3,0)) -> Worldwide
C29: Risk Inncidence | F29: =INDEX('GPA DB'!$A$3:$O$15,MATCH('GPA Features (Option 1)'!F$8,'GPA DB'!$A$3:$A$15,0),MATCH('GPA Features (Option 1)'!$C29,'GPA DB'!$A$3:$O$3,0)) -> 24 x 7 Cover | G29: =INDEX('GPA DB'!$A$3:$O$17,MATCH('GPA Features (Option 1)'!G$8,'GPA DB'!$A$3:$A$17,0),MATCH('GPA Features (Option 1)'!$C29,'GPA DB'!$A$3:$O$3,0)) -> 24 x 7 Cover | H29: =INDEX('GPA DB'!$A$3:$O$17,MATCH('GPA Features (Option 1)'!H$8,'GPA DB'!$A$3:$A$17,0),MATCH('GPA Features (Option 1)'!$C29,'GPA DB'!$A$3:$O$3,0)) -> 24 x 7 Cover | I29: =INDEX('GPA DB'!$A$3:$O$15,MATCH('GPA Features (Option 1)'!I$8,'GPA DB'!$A$3:$A$15,0),MATCH('GPA Features (Option 1)'!$C29,'GPA DB'!$A$3:$O$3,0)) -> 24 x 7 Cover
B31: Mid-Term Policy Changes | C31: Additions and Deletions | D31: Additions and Deletions | F31: =INDEX('GPA DB'!$A$3:$O$15,MATCH('GPA Features (Option 1)'!F$8,'GPA DB'!$A$3:$A$15,0),MATCH('GPA Features (Option 1)'!$C31,'GPA DB'!$A$3:$O$3,0)) -> On pro-rata basis | G31: =INDEX('GPA DB'!$A$3:$O$17,MATCH('GPA Features (Option 1)'!G$8,'GPA DB'!$A$3:$A$17,0),MATCH('GPA Features (Option 1)'!$C31,'GPA DB'!$A$3:$O$3,0)) -> On pro-rata basis | H31: =INDEX('GPA DB'!$A$3:$O$17,MATCH('GPA Features (Option 1)'!H$8,'GPA DB'!$A$3:$A$17,0),MATCH('GPA Features (Option 1)'!$C31,'GPA DB'!$A$3:$O$3,0)) -> On pro-rata basis | I31: =INDEX('GPA DB'!$A$3:$O$15,MATCH('GPA Features (Option 1)'!I$8,'GPA DB'!$A$3:$A$15,0),MATCH('GPA Features (Option 1)'!$C31,'GPA DB'!$A$3:$O$3,0)) -> On pro-rata basis
C32: Mid term Increase in Sum Insured | F32: =INDEX('GPA DB'!$A$3:$O$15,MATCH('GPA Features (Option 1)'!F$8,'GPA DB'!$A$3:$A$15,0),MATCH('GPA Features (Option 1)'!$C32,'GPA DB'!$A$3:$O$3,0)) -> Covered (In Case of Graded SI) | G32: =INDEX('GPA DB'!$A$3:$O$17,MATCH('GPA Features (Option 1)'!G$8,'GPA DB'!$A$3:$A$17,0),MATCH('GPA Features (Option 1)'!$C32,'GPA DB'!$A$3:$O$3,0)) -> Covered (In Case of Graded SI) | H32: =INDEX('GPA DB'!$A$3:$O$17,MATCH('GPA Features (Option 1)'!H$8,'GPA DB'!$A$3:$A$17,0),MATCH('GPA Features (Option 1)'!$C32,'GPA DB'!$A$3:$O$3,0)) -> Covered (In Case of Graded SI) | I32: =INDEX('GPA DB'!$A$3:$O$15,MATCH('GPA Features (Option 1)'!I$8,'GPA DB'!$A$3:$A$15,0),MATCH('GPA Features (Option 1)'!$C32,'GPA DB'!$A$3:$O$3,0)) -> Covered (In Case of Graded SI)
B34: *Terms and conditions as per policy wordings apply

Sheet GPA DB
A2: Group Personal Accident & Disability Cover
A3: Features | B3: Premium per mille (excl. GST) | C3: Family Definition | D3: Accidental Death | E3: Permanent Total Disablement | F3: Permanent Partial Disablement | G3: Temporary Total Disablement (if patient confined to bed due to temporary and total inability to engage in any occupation or any activity) | H3: Accidental Hospitalization (IPD) (min. 24 hours hospitalization) | I3: Accidental Expenses (OPD) | J3: Additions and Deletions | K3: Mid term Increase in Sum Insured | L3: Additional Benefits | M3: Terrorism | N3: Geographical Limit | O3: Risk Inncidence
A4: Aditya Birla Health | C4: Self only | D4: 100% of SI | E4: 100% of SI | F4: Up to 100% of SI based on extent of disability | G4: 1% of SI or Rs. 5000 or Actual salary per week upto 104 weeks whichever is lower | H4: Reimb of 10% of SI or 40% of admissible PA claim or actual expense, whichever is lower if accidental death or disability | I4: NA | J4: On pro-rata basis | K4: Covered (In Case of Graded SI) | L4: • Child Education Benefit • Funeral Expenses • Transportation Cost of Dead Body • Ambulance Charges • Burns Cover | M4: Covered (except not covered arising out Nuclear/Biological or chemical means) | N4: Worldwide | O4: 24 x 7 Cover
A5: Bajaj Allianz | C5: Self only | D5: 100% of SI | E5: 100% of SI | F5: Up to 100% of SI based on extent of disability | G5: 1% of SI or Rs. 5000 or Actual salary per week upto 104 weeks whichever is lower | H5: Reimb of 10% of SI or 40% of admissible PA claim or actual expense, whichever is lower if accidental death or disability | I5: NA | J5: On pro-rata basis | K5: Covered (In Case of Graded SI) | L5: • Child Education Benefit • Funeral Expenses • Transportation Cost of Dead Body • Ambulance Charges • Burns Cover | M5: Covered (except not covered arising out Nuclear/Biological or chemical means) | N5: Worldwide | O5: 24 x 7 Cover
A6: Care Health | C6: Self only | D6: 100% of SI | E6: 100% of SI | F6: Up to 100% of SI based on extent of disability | G6: 1% of SI or Rs. 5000 or Actual salary per week upto 104 weeks whichever is lower | H6: Reimb of 10% of SI or 40% of admissible PA claim or actual expense, whichever is lower if accidental death or disability | I6: NA | J6: On pro-rata basis | K6: Covered (In Case of Graded SI) | L6: • Child Education Benefit • Funeral Expenses • Transportation Cost of Dead Body • Ambulance Charges • Burns Cover | M6: Covered (except not covered arising out Nuclear/Biological or chemical means) | N6: Worldwide | O6: 24 x 7 Cover
A7: GoDigit | C7: Self only | D7: 100% of SI | E7: 100% of SI | F7: Up to 100% of SI based on extent of disability | G7: 1% of SI or Rs. 5000 or Actual salary per week upto 100 weeks whichever is lower | H7: Reimb of 10% of SI or 40% of admissible PA claim or actual expense, whichever is lower if accidental death or disability | I7: NA | J7: On pro-rata basis | K7: Covered (In Case of Graded SI) | L7: • Child Education Benefit • Funeral Expenses • Transportation Cost of Dead Body • Ambulance Charges • Burns Cover | M7: Covered (except not covered arising out Nuclear/Biological or chemical means) | N7: Worldwide | O7: 24 x 7 Cover
A8: ICICI Lombard | C8: Self only | D8: 100% of SI | E8: 100% of SI | F8: Up to 100% of SI based on extent of disability | G8: 1% of SI or Rs. 5000 or Actual salary per week upto 100 weeks whichever is lower | H8: Payable upto Rs.25000 or Less | I8: NA | J8: On pro-rata basis | K8: Covered (In Case of Graded SI) | L8: • Child Education Welfare - Upto Rs. 10,000 per child (Restricted to 2 children) • Transportation Cost of Dead Body - Upto Rs. 2,500/- | M8: Covered (except not covered arising out Nuclear/Biological or chemical means) | N8: Worldwide | O8: 24 x 7 Cover
A9: Magma (Basic Plan) | B9: Risk Class 1 - 0.15 per mile Risk Class 2 - 0.19 per mile (Fresh Cases only) | C9: Self only | D9: 100% of SI | E9: 100% of SI | F9: Up to 100% of SI based on extent of disability | G9: 1% of SI or Rs. 5,000 per week or actual salary, whichever is lower for 104 weeks | H9: 10% of SI or 40% of admissible claim amount or actuals whichever is lower | I9: NA | J9: On pro-rata basis | K9: Covered (In Case of Graded SI) | L9: • Children Education Benefit- 10% of SI upto Rs. 5000 per child (max 2 children) • Compassionate Visit - 10% SI upto Rs. 10,000 • Funeral Expenses - upto Rs. 2500 • Transportation of Dead Body - upto Rs.2500 | M9: Covered | N9: India | O9: 24 x 7 Cover
A10: Magma (Standard Plan) | B10: Risk Class 1 - 0.25 per mille Risk Class 2 - 0.325 per mille (Fresh Cases only) | C10: Self only | D10: 100% of SI | E10: 150% of SI | F10: Up to 100% of SI based on extent of disability | G10: 1% of SI or Rs. 5,000 per week or actual salary, whichever is lower for 104 weeks | H10: Reimb upto 50% of the SI or Rs. 1L whichever is less Other Benefits: • Day Care Procedures - Covered • Pre / Post Hospitalization - 60/90 days • Road Ambulance Charges - Rs.5,000 • Domiciliary Hospitalization - Covered • Dental (due to accients) - 100% of SI • Trauma Counselling - Covered • Second Medical Opinion - Covered • Transport of Imported Medicines - Covered | I10: NA | J10: On pro-rata basis | K10: Covered (In Case of Graded SI) | L10: • Children Education Benefit- 10% of SI upto Rs. 5000 per child • Funeral Expenses - upto Rs. 5000 Transportation of Dead Body - upto Rs.5000 • Burns Cover - Upto 10% SI Upto 10000 • Compassionate Visit - 10% SI upto Rs. 10,000 • Lifestyle modification - 10% SI upto Rs. 10,000 | M10: Covered | N10: India | O10: 24 x 7 Cover
A11: Magma (Pro Plan) | B11: Risk Class 1 - 0.32 per mile Risk Class 2 - 0.40 per mile (Fresh Cases only) | C11: Self only | D11: 100% of SI | E11: 150% of SI | F11: Up to 100% of SI based on extent of disability | G11: 1% of SI or Rs. 10,000 per week or actual salary, whichever is lower for 104 weeks | H11: Reimb upto 50% of the SI or Rs. 2L whichever is less Other Benefits: • Day Care Procedures - Covered • Pre / Post Hospitalization - 60/90 days • Road Ambulance Charges - Rs.5,000 • Domiciliary Hospitalization - Covered • Dental (due to accients) - 100% of SI • Trauma Counselling - Covered • Second Medical Opinion - Covered • Transport of Imported Medicines - Covered • Daily Hospi Cash - Rs. 1,000 per day for 30 days (2x if ICU hospitalisation > 24 hours) | I11: NA | J11: On pro-rata basis | K11: Covered (In Case of Graded SI) | L11: • Children Education Benefit- Upto Rs. 10,000 per child • Funeral Expenses - upto Rs. 10,000 • Transportation of Dead Body - upto Rs.10,000 • Burns Cover - Upto 10% SI Upto 10000 • Compassionate Visit - 10% SI upto Rs. 25,000 • Lifestyle modification - 10% SI upto Rs. 25,000 | M11: Covered | N11: India | O11: 24 x 7 Cover
A12: Magma (Basic Plan) - NEE Group | B12: Monthly: Risk Class 1 - 0.019 per mile Risk Class 2 - 0.021 per mile Annual: Risk Class 1 - 0.16 per mille Risk Class 2 - 0.18 per mille | C12: Self only | D12: 100% of SI | E12: 100% of SI | F12: Up to 100% of SI based on extent of disability | G12: Not covered | H12: NA | I12: NA | J12: Rolling forward addition No Deletion | K12: Covered (In Case of Graded SI) | L12: NA | M12: Covered | N12: India | O12: 24 x 7 Cover
A13: Magma (Pro Plan) - NEE Group | B13: Monthly: Risk Class 1 - 0.04 per mile Risk Class 2 - 0.05 per mile Annual: Risk Class 1 - 0.33 per mille Risk Class 2 - 0.36 per mille | C13: Self only | D13: 100% of SI | E13: 100% of SI | F13: Up to 100% of SI based on extent of disability | G13: Not covered | H13: Reimb upto 50% of the SI or 50% of admissable claims or upto Rs. 1L whichever is less Other Benefits: Road Ambulance Charges - Rs.3,000 or actuals, whichever is lower Daily Hospicash - Rs.1,000/- per day to the actual number of days or 30 days, whichever is lower subject to minimum of 1 day continous hospitalization (2X if ICU hospitalisation>24 hours) | I13: Fracture Indemnity Cover - Upto 10% of SI or Rs.25000, whichever is lower Burn Cover - Upto 10% of SI or Rs.25000, whichever is lower | J13: Rolling forward addition No Deletion | K13: Covered (In Case of Graded SI) | L13: Children Education Benefit- 10% of SI or upto Rs. 5000 per child (max 2 children) Compassionate Visit - 5% of SI upto Rs. 10,000, min. distance in excess of 500 kms Funeral Expenses - upto Rs. 5000 or actuals, whichever is lower Transportation of Dead Body - upto Rs. 5000 or actuals, whichever is lower. | M13: Covered | N13: India | O13: 24 x 7 Cover
A14: Niva Bupa | C14: Self only | D14: 100% of SI | E14: 100% of SI | F14: Up to 100% of SI based on extent of disability | G14: 1% of SI or Rs. 5000 or Actual salary per week upto 104 weeks whichever is lower | H14: Reimb of 10% of SI or 40% of admissible PA claim or actual expense, whichever is lower if accidental death or disability | I14: NA | J14: On pro-rata basis | K14: Covered (In Case of Graded SI) | L14: • Child Education Benefit • Funeral Expenses • Transportation Cost of Dead Body • Ambulance Charges • Burns Cover | M14: Covered (except not covered arising out Nuclear/Biological or chemical means) | N14: Worldwide | O14: 24 x 7 Cover
A15: Tata AIG (Basic Plan) | C15: Self only | D15: 100% of SI | E15: 100% of SI | F15: Up to 100% of SI based on extent of disability | G15: 1% of SI or Rs. 5000 or Actual salary per week upto 104 weeks whichever is lower | H15: 10% of the CSI or 40% of the Admissible Claim or Actuals whichever is less (only if accidental death or disability - PTD/ PPD) | I15: NA | J15: On pro-rata basis | K15: Covered (In Case of Graded SI) | L15: • Children Education Benefit- 10% of SI upto Rs. 5000 per child (max 2 children upto 25 years of age) • Compassionate Visit - 10% SI upto Rs. 25,000 • Funeral Expenses - 2.5% of SI upto Rs. 2500 • Transportation of Dead Body - 2.5% of SI upto Rs.2500 | M15: Covered | N15: Worldwide | O15: 24 x 7 Cover
A16: Tata AIG (Standard Plan) | C16: Self only | D16: 100% of SI | E16: 100% of SI | F16: Up to 100% of SI based on extent of disability | G16: 1% of SI or Rs. 5000 or Actual salary per week upto 104 weeks whichever is lower | H16: Fixed INR 1,00,000 or Actuals whichever is lower. | I16: NA | J16: On pro-rata basis | K16: Covered (In Case of Graded SI) | L16: • Children Education Benefit- 10% of SI upto Rs. 5000 per child (max 2 children upto 25 years of age) • Compassionate Visit - 10% SI upto Rs. 25,000 • Funeral Expenses - 2.5% of SI upto Rs. 5000 • Transportation of Dead Body - 2.5% of SI upto Rs.5000 • Lifestyle modification - 10% SI upto Rs. 10,000 | M16: Covered | N16: Worldwide | O16: 24 x 7 Cover
A17: Tata AIG (Pro Plan) | C17: Self only | D17: 100% of SI | E17: 100% of SI | F17: Up to 100% of SI based on extent of disability | G17: 1% of SI or Rs. 10,000 or Actual salary per week upto 104 weeks whichever is lower | H17: Fixed INR 1,00,000 or Actuals whichever is lower. | I17: NA | J17: On pro-rata basis | K17: Covered (In Case of Graded SI) | L17: • Children Education Benefit- Upto Rs. 10,000 per child (max 2 children upto 25 years of age) • Compassionate Visit - 10% SI upto Rs. 25,000 • Funeral Expenses - 5% of SI upto Rs. 10,000 • Transportation of Dead Body - 5% of SI upto Rs.10,000 • Lifestyle modification - 10% SI upto Rs. 25,000 | M17: Covered | N17: Worldwide | O17: 24 x 7 Cover

Sheet GTLI Features (Option 1)
A1: =Inputs!B5 -> Bandana Gupta Class
A2: =Inputs!B2 -> 45177 | C2: Group Term Life Insurance
C3: Client Name | F3: ='Company Info'!B4 -> ABC
C4: Type of Policy | F4: Rollover | J4: Manual
C5: Policy Period | F5: 1-Apr-25 To 31-Mar-26 | J5: Manual
F7: PROPOSED INSURERS | I7: PREVIOUS INSURER
F8: Credit Access Life (Exclusive) | G8: Kotak Life | H8: =Inputs!D53 -> HDFC Life | I8: =Inputs!E53 -> Pramerica Life
C9: Premium Details
C10: Sum Insured (Rs.) | F10: 10 Lacs | G10: 10 Lacs | H10: 10 Lacs | I10: 10 Lacs
C11: Annual Premium Excl. GST | F11: 500000 | G11: 600000 | H11: 700000 | I11: 320000 | J11: Manual
C12: Total Number Of Lives | F12: 300 (X members require medical examination > Free Cover Limit) | G12: 300 (X members require medical examination > Free Cover Limit) | H12: 300 (X members require medical examination > Free Cover Limit) | I12: =Inputs!F59 -> 150 | J12: Manual
C13: Avg. Premium Per Employee (in INR) | F13: =F11/300 -> 1666.6667 | G13: =G11/300 -> 2000 | H13: =H11/300 -> 2333.3333 | I13: =I11/150 -> 2133.3333
C14: Premium Per Mille (in INR) | F14: 2 | G14: 2.3 | H14: 2.7 | I14: 2 | J14: Manual
C15: Policy Features - Group Term Life Insurance
B16: Members Covered | C16: Family Definition | D16: =SUBSTITUTE($C$16," ","") -> FamilyDefinition | F16: Self | G16: Self | H16: Self | I16: Self
B18: Key Terms | C18: Age Band | D18: =SUBSTITUTE(C18," ","") -> AgeBand | F18: =INDEX('GTLI DB'!$A$7:$J$16,MATCH('GTLI Features (Option 1)'!F$8,'GTLI DB'!$A$7:$A$16,0),MATCH('GTLI Features (Option 1)'!$C18,'GTLI DB'!$A$7:$J$7,0)) -> 18-70 years | G18: =INDEX('GTLI DB'!$A$7:$J$16,MATCH('GTLI Features (Option 1)'!G$8,'GTLI DB'!$A$7:$A$16,0),MATCH('GTLI Features (Option 1)'!$C18,'GTLI DB'!$A$7:$J$7,0)) -> 18-60 years | H18: =INDEX('GTLI DB'!$A$7:$J$16,MATCH('GTLI Features (Option 1)'!H$8,'GTLI DB'!$A$7:$A$16,0),MATCH('GTLI Features (Option 1)'!$C18,'GTLI DB'!$A$7:$J$7,0)) -> 18-60 years | I18: =INDEX('GTLI DB'!$A$7:$J$15,MATCH('GTLI Features (Option 1)'!I$8,'GTLI DB'!$A$7:$A$15,0),MATCH('GTLI Features (Option 1)'!$C18,'GTLI DB'!$A$7:$J$7,0)) -> 18-60 years
C19: Lumpsum Fixed benefits | D19: =SUBSTITUTE(C19," ","") -> LumpsumFixedbenefits | F19: =INDEX('GTLI DB'!$A$7:$J$16,MATCH('GTLI Features (Option 1)'!F$8,'GTLI DB'!$A$7:$A$16,0),MATCH('GTLI Features (Option 1)'!$C19,'GTLI DB'!$A$7:$J$7,0)) -> 100% of Sum assured death benefit | G19: =INDEX('GTLI DB'!$A$7:$J$16,MATCH('GTLI Features (Option 1)'!G$8,'GTLI DB'!$A$7:$A$16,0),MATCH('GTLI Features (Option 1)'!$C19,'GTLI DB'!$A$7:$J$7,0)) -> 100% of Sum Assured | H19: =INDEX('GTLI DB'!$A$7:$J$16,MATCH('GTLI Features (Option 1)'!H$8,'GTLI DB'!$A$7:$A$16,0),MATCH('GTLI Features (Option 1)'!$C19,'GTLI DB'!$A$7:$J$7,0)) -> 100% of Sum Assured | I19: =INDEX('GTLI DB'!$A$7:$J$15,MATCH('GTLI Features (Option 1)'!I$8,'GTLI DB'!$A$7:$A$15,0),MATCH('GTLI Features (Option 1)'!$C19,'GTLI DB'!$A$7:$J$7,0)) -> 100% of Sum Assured
C20: Terminal Illness Benefit (Life expectancy < 12 months) | F20: =INDEX('GTLI DB'!$A$7:$J$16,MATCH('GTLI Features (Option 1)'!F$8,'GTLI DB'!$A$7:$A$16,0),MATCH('GTLI Features (Option 1)'!$C20,'GTLI DB'!$A$7:$J$7,0)) -> Not Covered | G20: =INDEX('GTLI DB'!$A$7:$J$16,MATCH('GTLI Features (Option 1)'!G$8,'GTLI DB'!$A$7:$A$16,0),MATCH('GTLI Features (Option 1)'!$C20,'GTLI DB'!$A$7:$J$7,0)) -> Not Covered | H20: =INDEX('GTLI DB'!$A$7:$J$16,MATCH('GTLI Features (Option 1)'!H$8,'GTLI DB'!$A$7:$A$16,0),MATCH('GTLI Features (Option 1)'!$C20,'GTLI DB'!$A$7:$J$7,0)) -> Not Covered | I20: =INDEX('GTLI DB'!$A$7:$J$15,MATCH('GTLI Features (Option 1)'!I$8,'GTLI DB'!$A$7:$A$15,0),MATCH('GTLI Features (Option 1)'!$C20,'GTLI DB'!$A$7:$J$7,0)) -> Not Covered
C21: Critical Illness Benefit (Severe but not terminal) | F21: =INDEX('GTLI DB'!$A$7:$J$16,MATCH('GTLI Features (Option 1)'!F$8,'GTLI DB'!$A$7:$A$16,0),MATCH('GTLI Features (Option 1)'!$C21,'GTLI DB'!$A$7:$J$7,0)) -> Not Covered | G21: =INDEX('GTLI DB'!$A$7:$J$16,MATCH('GTLI Features (Option 1)'!G$8,'GTLI DB'!$A$7:$A$16,0),MATCH('GTLI Features (Option 1)'!$C21,'GTLI DB'!$A$7:$J$7,0)) -> Not Covered | H21: =INDEX('GTLI DB'!$A$7:$J$16,MATCH('GTLI Features (Option 1)'!H$8,'GTLI DB'!$A$7:$A$16,0),MATCH('GTLI Features (Option 1)'!$C21,'GTLI DB'!$A$7:$J$7,0)) -> Not Covered | I21: =INDEX('GTLI DB'!$A$7:$J$15,MATCH('GTLI Features (Option 1)'!I$8,'GTLI DB'!$A$7:$A$15,0),MATCH('GTLI Features (Option 1)'!$C21,'GTLI DB'!$A$7:$J$7,0)) -> Not Covered
C22: Pre-requisites for claim | F22: =INDEX('GTLI DB'!$A$7:$J$16,MATCH('GTLI Features (Option 1)'!F$8,'GTLI DB'!$A$7:$A$16,0),MATCH('GTLI Features (Option 1)'!$C22,'GTLI DB'!$A$7:$J$7,0)) -> a. Death due to natural or unnatural reasons (incl. any accident, COVID-19, natural disaster or suicide) b. Death certificate issued by the local authority in case of death claim | G22: =INDEX('GTLI DB'!$A$7:$J$16,MATCH('GTLI Features (Option 1)'!G$8,'GTLI DB'!$A$7:$A$16,0),MATCH('GTLI Features (Option 1)'!$C22,'GTLI DB'!$A$7:$J$7,0)) -> a. Death due to natural or unnatural reasons (incl. any accident, COVID-19, natural disaster or suicide) b. Death certificate issued by the local authority in case of death claim | H22: =INDEX('GTLI DB'!$A$7:$J$16,MATCH('GTLI Features (Option 1)'!H$8,'GTLI DB'!$A$7:$A$16,0),MATCH('GTLI Features (Option 1)'!$C22,'GTLI DB'!$A$7:$J$7,0)) -> a. Death due to natural or unnatural reasons (incl. any accident, COVID-19, natural disaster or suicide) b. Death certificate issued by the local authority in case of death claim | I22: =INDEX('GTLI DB'!$A$7:$J$15,MATCH('GTLI Features (Option 1)'!I$8,'GTLI DB'!$A$7:$A$15,0),MATCH('GTLI Features (Option 1)'!$C22,'GTLI DB'!$A$7:$J$7,0)) -> a. Death due to natural or unnatural reasons (incl. any accident, COVID-19, natural disaster or suicide) b. Death certificate issued by the local authority in case of death claim
C23: Other Conditions | F23: =INDEX('GTLI DB'!$A$7:$J$16,MATCH('GTLI Features (Option 1)'!F$8,'GTLI DB'!$A$7:$A$16,0),MATCH('GTLI Features (Option 1)'!$C23,'GTLI DB'!$A$7:$J$7,0)) -> 1. Coverage is provided to all full time and permenant employees of the company residing in India. 2. Coverage should not exceed 10 times annual CTC for any member 3. All employees have to be actively at work at the coverage commencement for the employee i.e. employee has not availed a sick leave (other than COVID-19) for a continuous period > 7 days in the preceding year. Else, the person has to be submit a medical questionnaire 4. Moral hazard events such as driving under influence of alcohol/narcotics, participation in hazardous/adventurous activities not covered 5. Members travelling to/ residing in attached negative country list will not be covered, and for other countries if member’s residency period (continuous) > 180 days then we reserve right to review and amend the quoted rate. | G23: =INDEX('GTLI DB'!$A$7:$J$16,MATCH('GTLI Features (Option 1)'!G$8,'GTLI DB'!$A$7:$A$16,0),MATCH('GTLI Features (Option 1)'!$C23,'GTLI DB'!$A$7:$J$7,0)) -> 1. Coverage is provided to all full time and permenant employees of the company residing in India. 2. Coverage should not exceed 10 times annual CTC for any member 3. All employees have to be actively at work at the coverage commencement for the employee i.e. employee has not availed a sick leave (other than COVID-19) for a continuous period > 7 days in the preceding year. Else, the person has to be submit a medical questionnaire 4. Moral hazard events such as driving under influence of alcohol/narcotics, participation in hazardous/adventurous activities not covered 5. Members travelling to/ residing in attached negative country list will not be covered, and for other countries if member’s residency period (continuous) > 180 days then we reserve right to review and amend the quoted rate. | H23: =INDEX('GTLI DB'!$A$7:$J$16,MATCH('GTLI Features (Option 1)'!H$8,'GTLI DB'!$A$7:$A$16,0),MATCH('GTLI Features (Option 1)'!$C23,'GTLI DB'!$A$7:$J$7,0)) -> 1. Coverage is provided to all full time and permenant employees of the company residing in India. 2. Coverage should not exceed 10 times annual CTC for any member 3. All employees have to be actively at work at the coverage commencement for the employee i.e. employee has not availed a sick leave (other than COVID-19) for a continuous period > 7 days in the preceding year. Else, the person has to be submit a medical questionnaire 4. Moral hazard events such as driving under influence of alcohol/narcotics, participation in hazardous/adventurous activities not covered 5. Members travelling to/ residing in attached negative country list will not be covered, and for other countries if member’s residency period (continuous) > 180 days then we reserve right to review and amend the quoted rate. | I23: =INDEX('GTLI DB'!$A$7:$J$15,MATCH('GTLI Features (Option 1)'!I$8,'GTLI DB'!$A$7:$A$15,0),MATCH('GTLI Features (Option 1)'!$C23,'GTLI DB'!$A$7:$J$7,0)) -> 1. Coverage is provided to all full time and permenant employees of the company residing in India. 2. Coverage should not exceed 10 times annual CTC for any member 3. All employees have to be actively at work at the coverage commencement for the employee i.e. employee has not availed a sick leave (other than COVID-19) for a continuous period > 7 days in the preceding year. Else, the person has to be submit a medical questionnaire 4. Moral hazard events such as driving under influence of alcohol/narcotics, participation in hazardous/adventurous activities not covered 5. Members travelling to/ residing in attached negative country list will not be covered, and for other countries if member’s residency period (continuous) > 180 days then we reserve right to review and amend the quoted rate.
C24: Quote Validity | F24: =INDEX('GTLI DB'!$A$7:$N$16,MATCH('GTLI Features (Option 1)'!F$8,'GTLI DB'!$A$7:$A$16,0),MATCH('GTLI Features (Option 1)'!$C24,'GTLI DB'!$A$7:$N$7,0)) -> 10 Days | G24: =INDEX('GTLI DB'!$A$7:$N$16,MATCH('GTLI Features (Option 1)'!G$8,'GTLI DB'!$A$7:$A$16,0),MATCH('GTLI Features (Option 1)'!$C24,'GTLI DB'!$A$7:$N$7,0)) -> 10 Days | H24: =INDEX('GTLI DB'!$A$7:$N$16,MATCH('GTLI Features (Option 1)'!H$8,'GTLI DB'!$A$7:$A$16,0),MATCH('GTLI Features (Option 1)'!$C24,'GTLI DB'!$A$7:$N$7,0)) -> 10 Days | I24: =INDEX('GTLI DB'!$A$7:$N$16,MATCH('GTLI Features (Option 1)'!I$8,'GTLI DB'!$A$7:$A$16,0),MATCH('GTLI Features (Option 1)'!$C24,'GTLI DB'!$A$7:$N$7,0)) -> 10 Days
B26: Coverage | C26: Geographical Limit | F26: =INDEX('GTLI DB'!$A$7:$N$16,MATCH('GTLI Features (Option 1)'!F$8,'GTLI DB'!$A$7:$A$16,0),MATCH('GTLI Features (Option 1)'!$C26,'GTLI DB'!$A$7:$N$7,0)) -> Worldwide (Except Declined Countries) | G26: =INDEX('GTLI DB'!$A$7:$N$16,MATCH('GTLI Features (Option 1)'!G$8,'GTLI DB'!$A$7:$A$16,0),MATCH('GTLI Features (Option 1)'!$C26,'GTLI DB'!$A$7:$N$7,0)) -> Worldwide (Except Declined Countries) | H26: =INDEX('GTLI DB'!$A$7:$N$16,MATCH('GTLI Features (Option 1)'!H$8,'GTLI DB'!$A$7:$A$16,0),MATCH('GTLI Features (Option 1)'!$C26,'GTLI DB'!$A$7:$N$7,0)) -> Worldwide (Except Declined Countries) | I26: =INDEX('GTLI DB'!$A$7:$N$16,MATCH('GTLI Features (Option 1)'!I$8,'GTLI DB'!$A$7:$A$16,0),MATCH('GTLI Features (Option 1)'!$C26,'GTLI DB'!$A$7:$N$7,0)) -> Worldwide (Except Declined Countries)
C27: Risk Incidence | F27: =INDEX('GTLI DB'!$A$7:$N$16,MATCH('GTLI Features (Option 1)'!F$8,'GTLI DB'!$A$7:$A$16,0),MATCH('GTLI Features (Option 1)'!$C27,'GTLI DB'!$A$7:$N$7,0)) -> 24 x 7 Cover | G27: =INDEX('GTLI DB'!$A$7:$N$16,MATCH('GTLI Features (Option 1)'!G$8,'GTLI DB'!$A$7:$A$16,0),MATCH('GTLI Features (Option 1)'!$C27,'GTLI DB'!$A$7:$N$7,0)) -> 24 x 7 Cover | H27: =INDEX('GTLI DB'!$A$7:$N$16,MATCH('GTLI Features (Option 1)'!H$8,'GTLI DB'!$A$7:$A$16,0),MATCH('GTLI Features (Option 1)'!$C27,'GTLI DB'!$A$7:$N$7,0)) -> 24 x 7 Cover | I27: =INDEX('GTLI DB'!$A$7:$N$16,MATCH('GTLI Features (Option 1)'!I$8,'GTLI DB'!$A$7:$A$16,0),MATCH('GTLI Features (Option 1)'!$C27,'GTLI DB'!$A$7:$N$7,0)) -> 24 x 7 Cover
B29: Mid-Term Policy Changes | C29: Additions & Deletions | D29: Additions & Deletions | F29: =INDEX('GTLI DB'!$A$7:$N$16,MATCH('GTLI Features (Option 1)'!F$8,'GTLI DB'!$A$7:$A$16,0),MATCH('GTLI Features (Option 1)'!$C29,'GTLI DB'!$A$7:$N$7,0)) -> On Pro-rata Basis | G29: =INDEX('GTLI DB'!$A$7:$N$16,MATCH('GTLI Features (Option 1)'!G$8,'GTLI DB'!$A$7:$A$16,0),MATCH('GTLI Features (Option 1)'!$C29,'GTLI DB'!$A$7:$N$7,0)) -> Additions - Pro-rata Basis Deletions - Quarterly | H29: =INDEX('GTLI DB'!$A$7:$N$16,MATCH('GTLI Features (Option 1)'!H$8,'GTLI DB'!$A$7:$A$16,0),MATCH('GTLI Features (Option 1)'!$C29,'GTLI DB'!$A$7:$N$7,0)) -> On Pro-rata Basis | I29: =INDEX('GTLI DB'!$A$7:$N$16,MATCH('GTLI Features (Option 1)'!I$8,'GTLI DB'!$A$7:$A$16,0),MATCH('GTLI Features (Option 1)'!$C29,'GTLI DB'!$A$7:$N$7,0)) -> On Pro-rata Basis
C30: Mid term Increase in Sum Insured | F30: =INDEX('GTLI DB'!$A$7:$N$16,MATCH('GTLI Features (Option 1)'!F$8,'GTLI DB'!$A$7:$A$16,0),MATCH('GTLI Features (Option 1)'!$C30,'GTLI DB'!$A$7:$N$7,0)) -> Not Covered | G30: =INDEX('GTLI DB'!$A$7:$N$16,MATCH('GTLI Features (Option 1)'!G$8,'GTLI DB'!$A$7:$A$16,0),MATCH('GTLI Features (Option 1)'!$C30,'GTLI DB'!$A$7:$N$7,0)) -> Covered (In Case of Graded SI) | H30: =INDEX('GTLI DB'!$A$7:$N$16,MATCH('GTLI Features (Option 1)'!H$8,'GTLI DB'!$A$7:$A$16,0),MATCH('GTLI Features (Option 1)'!$C30,'GTLI DB'!$A$7:$N$7,0)) -> Covered (In Case of Graded SI) | I30: =INDEX('GTLI DB'!$A$7:$N$16,MATCH('GTLI Features (Option 1)'!I$8,'GTLI DB'!$A$7:$A$16,0),MATCH('GTLI Features (Option 1)'!$C30,'GTLI DB'!$A$7:$N$7,0)) -> Covered (In Case of Graded SI)
B32: *Terms and conditions as per policy wordings apply

Sheet OPD Policy Features (Option 1)
C2: Healthysure x Even OPD
C3: Client Name | E3: ='Company Info'!B4 -> ABC
C4: Type of Policy | E4: Rollover
C5: Policy Period | E5: 1-Apr-25 To 31-Mar-26
E7: Plan Type
F8: Silver | G8: Gold | H8: Platinum | I8: Previous Year
C9: Premium Details
C10: Sum Insured | E10: In INR | F10: 3k | G10: 15k | H10: 30k | I10: -
C11: Annual Premium Excl. GST | E11: In INR | F11: =F12*F13 -> 99900 | G11: =G12*G13 -> 299900 | H11: =H12*H13 -> 799900 | I11: -
C12: Total No. of Employees | E12: Count | F12: 100 | G12: 100 | H12: 100 | I12: -
C13: Premium per Employee (excl GST) | E13: In INR | F13: 999 | G13: 2999 | H13: 7999 | I13: -
C14: Policy Features - OPD Insurance
B15: General | C15: Family Definition | E15: - | F15: Employee, Spouse & 2 Children | G15: Employee, Spouse & 2 Children | H15: Employee, Spouse & 2 Children | I15: -
C16: Waiting Periods | E16: Corporate Plan | F16: Day 1 | G16: Day 1 | H16: Day 1 | I16: -
C17: Cashless | E17: Pay Anywhere in India | F17: ✔ | G17: ✔ | H17: ✔ | I17: -
C18: Reimbursement | E18: Settled Within 24 hours | F18: ✔ | G18: ✔ | H18: ✔ | I18: -
B20: Coverage | C20: Doctor Consultations (Online) | E20: General Physicians | F20: Unlimited | G20: Unlimited | H20: Unlimited | I20: -
E21: Specialists | F21: Upto Sum Insured | G21: Upto Sum Insured | H21: Upto Sum Insured | I21: -
C23: Doctor Consultations (Offline) | E23: GP & Specialists | F23: 3k | G23: 7.5k | H23: 10k | I23: -
C24: Prescribed Diagnostics | E24: Pathology & Radiology
C26: Prescribed Medicines | E26: Allopathic | F26: ✖ | G26: 7.5k | H26: 10k | I26: -
C28: Vision | E28: Prescription Glasses | F28: ✖ | G28: ✖ | H28: 10k | I28: -
C29: Dental | E29: All Procedures (excl. cosmetic)
C30: Vaccines | E30: WHO Prescribed
B32: Mid-term Policy Changes | C32: Additions | E32: - | F32: Pro-rata | G32: Pro-rata | H32: Pro-rata | I32: -
C33: Deletions | E33: - | F33: Pro-rata (whether or not claimed) | G33: Pro-rata (whether or not claimed) | H33: Pro-rata (whether or not claimed) | I33: -
B35: Note
B36: 1) Only corporates with min. 10 employees are eligible
B37: 2) For voluntary subscription, we need participation of 30% employees or 30 employees whichever is higher
B38: 3) For detailed terms and conditions, click here to see the document

Sheet GHI Insurers
A1: =Inputs!B5 -> Bandana Gupta Class
A2: =Inputs!B2 -> 45177 | C2: Group Health Insurance
C3: Client Name | F3: ='GHI Features (Option 1)'!G3 -> ABC
C4: Type of Policy | F4: ='GHI Features (Option 1)'!G4 -> Rollover
C5: Policy Period | F5: ='GHI Features (Option 1)'!G5 -> 1-Apr-25 To 31-Mar-26
F7: PROPOSED INSURERS | I7: PREVIOUS INSURER
F8: Bajaj General | G8: ICICI Lombard | H8: =Inputs!D14 -> Manipal Cigna | I8: =Inputs!E14 -> IFFCO Tokio
C9: Know Your Insurer - Credentials
B10: Background | C10: Founding Year | F10: =INDEX('Technical DB (Health)'!$C$3:$Q$21,MATCH(F$8,'Technical DB (Health)'!$A$3:$A$21,0),MATCH($C10,'Technical DB (Health)'!$C$2:$Q$2,0)) -> 2001 | G10: =INDEX('Technical DB (Health)'!$C$3:$Q$21,MATCH(G$8,'Technical DB (Health)'!$A$3:$A$21,0),MATCH($C10,'Technical DB (Health)'!$C$2:$Q$2,0)) -> 2001 | H10: =INDEX('Technical DB (Health)'!$C$3:$Q$21,MATCH(H$8,'Technical DB (Health)'!$A$3:$A$21,0),MATCH($C10,'Technical DB (Health)'!$C$2:$Q$2,0)) -> 2014 | I10: =INDEX('Technical DB (Health)'!$C$3:$Q$21,MATCH(I$8,'Technical DB (Health)'!$A$3:$A$21,0),MATCH($C10,'Technical DB (Health)'!$C$2:$Q$2,0)) -> 2000
C11: Backed by | F11: =INDEX('Technical DB (Health)'!$C$3:$Q$21,MATCH(F$8,'Technical DB (Health)'!$A$3:$A$21,0),MATCH($C11,'Technical DB (Health)'!$C$2:$Q$2,0)) -> Bajaj Finserv and Allianz SE | G11: =INDEX('Technical DB (Health)'!$C$3:$Q$21,MATCH(G$8,'Technical DB (Health)'!$A$3:$A$21,0),MATCH($C11,'Technical DB (Health)'!$C$2:$Q$2,0)) -> ICICI Bank | H11: =INDEX('Technical DB (Health)'!$C$3:$Q$21,MATCH(H$8,'Technical DB (Health)'!$A$3:$A$21,0),MATCH($C11,'Technical DB (Health)'!$C$2:$Q$2,0)) -> Manipal Group, Cigna Holdings | I11: =INDEX('Technical DB (Health)'!$C$3:$Q$21,MATCH(I$8,'Technical DB (Health)'!$A$3:$A$21,0),MATCH($C11,'Technical DB (Health)'!$C$2:$Q$2,0)) -> IFFCO India, Tokio Marine Insurance (Japan)
B13: Credibility | C13: GHI Book size (FY25) | F13: =INDEX('Technical DB (Health)'!$C$3:$Q$21,MATCH(F$8,'Technical DB (Health)'!$A$3:$A$21,0),MATCH($C13,'Technical DB (Health)'!$C$2:$Q$2,0)) -> ₹ 3,260 Cr | G13: =INDEX('Technical DB (Health)'!$C$3:$Q$21,MATCH(G$8,'Technical DB (Health)'!$A$3:$A$21,0),MATCH($C13,'Technical DB (Health)'!$C$2:$Q$2,0)) -> ₹ 5,394 Cr | H13: =INDEX('Technical DB (Health)'!$C$3:$Q$21,MATCH(H$8,'Technical DB (Health)'!$A$3:$A$21,0),MATCH($C13,'Technical DB (Health)'!$C$2:$Q$2,0)) -> ₹ 924 Cr | I13: =INDEX('Technical DB (Health)'!$C$3:$Q$21,MATCH(I$8,'Technical DB (Health)'!$A$3:$A$21,0),MATCH($C13,'Technical DB (Health)'!$C$2:$Q$2,0)) -> ₹ 531 Cr
C14: GHI Growth Rate (FY25) | F14: =INDEX('Technical DB (Health)'!$C$3:$Q$21,MATCH(F$8,'Technical DB (Health)'!$A$3:$A$21,0),MATCH($C14,'Technical DB (Health)'!$C$2:$Q$2,0)) -> 0.1795 | G14: =INDEX('Technical DB (Health)'!$C$3:$Q$21,MATCH(G$8,'Technical DB (Health)'!$A$3:$A$21,0),MATCH($C14,'Technical DB (Health)'!$C$2:$Q$2,0)) -> 0.0948 | H14: =INDEX('Technical DB (Health)'!$C$3:$Q$21,MATCH(H$8,'Technical DB (Health)'!$A$3:$A$21,0),MATCH($C14,'Technical DB (Health)'!$C$2:$Q$2,0)) -> 0.0151 | I14: =INDEX('Technical DB (Health)'!$C$3:$Q$21,MATCH(I$8,'Technical DB (Health)'!$A$3:$A$21,0),MATCH($C14,'Technical DB (Health)'!$C$2:$Q$2,0)) -> -0.3608 | O14: `
C15: Solvency Ratio (Mar-25) (IRDAI recommended: >1.5) | F15: =INDEX('Technical DB (Health)'!$C$3:$Q$21,MATCH(F$8,'Technical DB (Health)'!$A$3:$A$21,0),MATCH($C15,'Technical DB (Health)'!$C$2:$Q$2,0)) -> 3.52 | G15: =INDEX('Technical DB (Health)'!$C$3:$Q$21,MATCH(G$8,'Technical DB (Health)'!$A$3:$A$21,0),MATCH($C15,'Technical DB (Health)'!$C$2:$Q$2,0)) -> 2.70 | H15: =INDEX('Technical DB (Health)'!$C$3:$Q$21,MATCH(H$8,'Technical DB (Health)'!$A$3:$A$21,0),MATCH($C15,'Technical DB (Health)'!$C$2:$Q$2,0)) -> 1.91 | I15: =INDEX('Technical DB (Health)'!$C$3:$Q$21,MATCH(I$8,'Technical DB (Health)'!$A$3:$A$21,0),MATCH($C15,'Technical DB (Health)'!$C$2:$Q$2,0)) -> 1.86
B17: Policy Administration | C17: Policy Issuance TAT | F17: =INDEX('Technical DB (Health)'!$C$3:$Q$21,MATCH(F$8,'Technical DB (Health)'!$A$3:$A$21,0),MATCH($C17,'Technical DB (Health)'!$C$2:$Q$2,0)) -> 10 to 20 days | G17: =INDEX('Technical DB (Health)'!$C$3:$Q$21,MATCH(G$8,'Technical DB (Health)'!$A$3:$A$21,0),MATCH($C17,'Technical DB (Health)'!$C$2:$Q$2,0)) -> 10 to 20 days | H17: =INDEX('Technical DB (Health)'!$C$3:$Q$21,MATCH(H$8,'Technical DB (Health)'!$A$3:$A$21,0),MATCH($C17,'Technical DB (Health)'!$C$2:$Q$2,0)) -> 10 to 20 days | I17: =INDEX('Technical DB (Health)'!$C$3:$Q$21,MATCH(I$8,'Technical DB (Health)'!$A$3:$A$21,0),MATCH($C17,'Technical DB (Health)'!$C$2:$Q$2,0)) -> 10 to 20 days
C18: Endorsement TAT | F18: =INDEX('Technical DB (Health)'!$C$3:$Q$21,MATCH(F$8,'Technical DB (Health)'!$A$3:$A$21,0),MATCH($C18,'Technical DB (Health)'!$C$2:$Q$2,0)) -> 1 to 3 days | G18: =INDEX('Technical DB (Health)'!$C$3:$Q$21,MATCH(G$8,'Technical DB (Health)'!$A$3:$A$21,0),MATCH($C18,'Technical DB (Health)'!$C$2:$Q$2,0)) -> 1 to 3 days | H18: =INDEX('Technical DB (Health)'!$C$3:$Q$21,MATCH(H$8,'Technical DB (Health)'!$A$3:$A$21,0),MATCH($C18,'Technical DB (Health)'!$C$2:$Q$2,0)) -> 3 to 5 days | I18: =INDEX('Technical DB (Health)'!$C$3:$Q$21,MATCH(I$8,'Technical DB (Health)'!$A$3:$A$21,0),MATCH($C18,'Technical DB (Health)'!$C$2:$Q$2,0)) -> 5 to 10 days
B20: Claims | C20: Cashless Network | F20: =INDEX('Technical DB (Health)'!$C$3:$Q$21,MATCH(F$8,'Technical DB (Health)'!$A$3:$A$21,0),MATCH($C20,'Technical DB (Health)'!$C$2:$Q$2,0)) -> 12000+ | G20: =INDEX('Technical DB (Health)'!$C$3:$Q$21,MATCH(G$8,'Technical DB (Health)'!$A$3:$A$21,0),MATCH($C20,'Technical DB (Health)'!$C$2:$Q$2,0)) -> 10,200+ | H20: =INDEX('Technical DB (Health)'!$C$3:$Q$21,MATCH(H$8,'Technical DB (Health)'!$A$3:$A$21,0),MATCH($C20,'Technical DB (Health)'!$C$2:$Q$2,0)) -> 8,500+ | I20: =INDEX('Technical DB (Health)'!$C$3:$Q$21,MATCH(I$8,'Technical DB (Health)'!$A$3:$A$21,0),MATCH($C20,'Technical DB (Health)'!$C$2:$Q$2,0)) -> 7,000+
C21: Claim Settlement Ratio | F21: =INDEX('Technical DB (Health)'!$C$3:$Q$21,MATCH(F$8,'Technical DB (Health)'!$A$3:$A$21,0),MATCH($C21,'Technical DB (Health)'!$C$2:$Q$2,0)) -> 0.98 | G21: =INDEX('Technical DB (Health)'!$C$3:$Q$21,MATCH(G$8,'Technical DB (Health)'!$A$3:$A$21,0),MATCH($C21,'Technical DB (Health)'!$C$2:$Q$2,0)) -> 0.98 | H21: =INDEX('Technical DB (Health)'!$C$3:$Q$21,MATCH(H$8,'Technical DB (Health)'!$A$3:$A$21,0),MATCH($C21,'Technical DB (Health)'!$C$2:$Q$2,0)) -> 0.98 | I21: =INDEX('Technical DB (Health)'!$C$3:$Q$21,MATCH(I$8,'Technical DB (Health)'!$A$3:$A$21,0),MATCH($C21,'Technical DB (Health)'!$C$2:$Q$2,0)) -> 0.98
C22: Cashless TAT | F22: =INDEX('Technical DB (Health)'!$C$3:$Q$21,MATCH(F$8,'Technical DB (Health)'!$A$3:$A$21,0),MATCH($C22,'Technical DB (Health)'!$C$2:$Q$2,0)) -> 1 to 3 hours | G22: =INDEX('Technical DB (Health)'!$C$3:$Q$21,MATCH(G$8,'Technical DB (Health)'!$A$3:$A$21,0),MATCH($C22,'Technical DB (Health)'!$C$2:$Q$2,0)) -> 1 to 3 hours | H22: =INDEX('Technical DB (Health)'!$C$3:$Q$21,MATCH(H$8,'Technical DB (Health)'!$A$3:$A$21,0),MATCH($C22,'Technical DB (Health)'!$C$2:$Q$2,0)) -> 2 to 4 hours | I22: =INDEX('Technical DB (Health)'!$C$3:$Q$21,MATCH(I$8,'Technical DB (Health)'!$A$3:$A$21,0),MATCH($C22,'Technical DB (Health)'!$C$2:$Q$2,0)) -> 2 to 4 hours
C23: Reimbursement TAT | F23: =INDEX('Technical DB (Health)'!$C$3:$Q$21,MATCH(F$8,'Technical DB (Health)'!$A$3:$A$21,0),MATCH($C23,'Technical DB (Health)'!$C$2:$Q$2,0)) -> 15 to 30 days | G23: =INDEX('Technical DB (Health)'!$C$3:$Q$21,MATCH(G$8,'Technical DB (Health)'!$A$3:$A$21,0),MATCH($C23,'Technical DB (Health)'!$C$2:$Q$2,0)) -> 7 to 15 days | H23: =INDEX('Technical DB (Health)'!$C$3:$Q$21,MATCH(H$8,'Technical DB (Health)'!$A$3:$A$21,0),MATCH($C23,'Technical DB (Health)'!$C$2:$Q$2,0)) -> 15 to 30 days | I23: =INDEX('Technical DB (Health)'!$C$3:$Q$21,MATCH(I$8,'Technical DB (Health)'!$A$3:$A$21,0),MATCH($C23,'Technical DB (Health)'!$C$2:$Q$2,0)) -> 15 to 30 days
C24: % of claims settled in 3 months | F24: =INDEX('Technical DB (Health)'!$C$3:$Q$21,MATCH(F$8,'Technical DB (Health)'!$A$3:$A$21,0),MATCH($C24,'Technical DB (Health)'!$C$2:$Q$2,0)) -> 0.996 | G24: =INDEX('Technical DB (Health)'!$C$3:$Q$21,MATCH(G$8,'Technical DB (Health)'!$A$3:$A$21,0),MATCH($C24,'Technical DB (Health)'!$C$2:$Q$2,0)) -> 1 | H24: =INDEX('Technical DB (Health)'!$C$3:$Q$21,MATCH(H$8,'Technical DB (Health)'!$A$3:$A$21,0),MATCH($C24,'Technical DB (Health)'!$C$2:$Q$2,0)) -> 0.999 | I24: =INDEX('Technical DB (Health)'!$C$3:$Q$21,MATCH(I$8,'Technical DB (Health)'!$A$3:$A$21,0),MATCH($C24,'Technical DB (Health)'!$C$2:$Q$2,0)) -> 0.8989
C25: Reimbursement Mode (Paperless/Paper) | F25: =INDEX('Technical DB (Health)'!$C$3:$Q$21,MATCH(F$8,'Technical DB (Health)'!$A$3:$A$21,0),MATCH($C25,'Technical DB (Health)'!$C$2:$Q$2,0)) -> Paperless | G25: =INDEX('Technical DB (Health)'!$C$3:$Q$21,MATCH(G$8,'Technical DB (Health)'!$A$3:$A$21,0),MATCH($C25,'Technical DB (Health)'!$C$2:$Q$2,0)) -> Paperless | H25: =INDEX('Technical DB (Health)'!$C$3:$Q$21,MATCH(H$8,'Technical DB (Health)'!$A$3:$A$21,0),MATCH($C25,'Technical DB (Health)'!$C$2:$Q$2,0)) -> Paperless | I25: =INDEX('Technical DB (Health)'!$C$3:$Q$21,MATCH(I$8,'Technical DB (Health)'!$A$3:$A$21,0),MATCH($C25,'Technical DB (Health)'!$C$2:$Q$2,0)) -> Paper-based
C26: TPA (in-house or External) | F26: =INDEX('Technical DB (Health)'!$C$3:$Q$21,MATCH(F$8,'Technical DB (Health)'!$A$3:$A$21,0),MATCH($C26,'Technical DB (Health)'!$C$2:$Q$2,0)) -> In-house | G26: =INDEX('Technical DB (Health)'!$C$3:$Q$21,MATCH(G$8,'Technical DB (Health)'!$A$3:$A$21,0),MATCH($C26,'Technical DB (Health)'!$C$2:$Q$2,0)) -> In-house | H26: =INDEX('Technical DB (Health)'!$C$3:$Q$21,MATCH(H$8,'Technical DB (Health)'!$A$3:$A$21,0),MATCH($C26,'Technical DB (Health)'!$C$2:$Q$2,0)) -> In-house External Option available | I26: =INDEX('Technical DB (Health)'!$C$3:$Q$21,MATCH(I$8,'Technical DB (Health)'!$A$3:$A$21,0),MATCH($C26,'Technical DB (Health)'!$C$2:$Q$2,0)) -> In-house External Option available
D109: STELLAPPS
D110: Vhire4u

Sheet GTLI Insurers
A1: =Inputs!B5 -> Bandana Gupta Class
A2: =Inputs!B2 -> 45177 | C2: Group Health Insurance
C3: Client Name | F3: ='GTLI Features (Option 1)'!F3 -> ABC
C4: Type of Policy | F4: ='GTLI Features (Option 1)'!F4 -> Rollover
C5: Policy Period | F5: ='GTLI Features (Option 1)'!F5 -> 1-Apr-25 To 31-Mar-26
F7: PROPOSED INSURERS | I7: PREVIOUS INSURER
F8: ICICI Prudential | G8: Pramerica Life | H8: Go Digit Life | I8: ICICI Prudential
C9: Know Your Insurer - Credentials
B10: Background | C10: Founding Year | F10: =INDEX('Technical DB (Life)'!$B$3:$J$38,MATCH(F$8,'Technical DB (Life)'!$A$3:$A$38,0),MATCH($C10,'Technical DB (Life)'!$B$2:$J$2,0)) -> 2000 | G10: =INDEX('Technical DB (Life)'!$B$3:$J$38,MATCH(G$8,'Technical DB (Life)'!$A$3:$A$38,0),MATCH($C10,'Technical DB (Life)'!$B$2:$J$2,0)) -> 2007 | H10: =INDEX('Technical DB (Life)'!$B$3:$J$38,MATCH(H$8,'Technical DB (Life)'!$A$3:$A$38,0),MATCH($C10,'Technical DB (Life)'!$B$2:$J$2,0)) -> 2021 | I10: =INDEX('Technical DB (Life)'!$B$3:$J$38,MATCH(I$8,'Technical DB (Life)'!$A$3:$A$38,0),MATCH($C10,'Technical DB (Life)'!$B$2:$J$2,0)) -> 2000
C11: Backed by | F11: =INDEX('Technical DB (Life)'!$B$3:$J$38,MATCH(F$8,'Technical DB (Life)'!$A$3:$A$38,0),MATCH($C11,'Technical DB (Life)'!$B$2:$J$2,0)) -> ICICI Bank, Prudential Corporation Group | G11: =INDEX('Technical DB (Life)'!$B$3:$J$38,MATCH(G$8,'Technical DB (Life)'!$A$3:$A$38,0),MATCH($C11,'Technical DB (Life)'!$B$2:$J$2,0)) -> Piramal Group, Prudential International Group | H11: =INDEX('Technical DB (Life)'!$B$3:$J$38,MATCH(H$8,'Technical DB (Life)'!$A$3:$A$38,0),MATCH($C11,'Technical DB (Life)'!$B$2:$J$2,0)) -> Fairfax Group | I11: =INDEX('Technical DB (Life)'!$B$3:$J$38,MATCH(I$8,'Technical DB (Life)'!$A$3:$A$38,0),MATCH($C11,'Technical DB (Life)'!$B$2:$J$2,0)) -> ICICI Bank, Prudential Corporation Group
B13: Credibility | C13: GTLI Book size (FY25) | F13: =INDEX('Technical DB (Life)'!$B$3:$J$38,MATCH(F$8,'Technical DB (Life)'!$A$3:$A$38,0),MATCH($C13,'Technical DB (Life)'!$B$2:$J$2,0)) -> ₹ 6,815 Cr | G13: =INDEX('Technical DB (Life)'!$B$3:$J$38,MATCH(G$8,'Technical DB (Life)'!$A$3:$A$38,0),MATCH($C13,'Technical DB (Life)'!$B$2:$J$2,0)) -> ₹ 134 Cr | H13: =INDEX('Technical DB (Life)'!$B$3:$J$38,MATCH(H$8,'Technical DB (Life)'!$A$3:$A$38,0),MATCH($C13,'Technical DB (Life)'!$B$2:$J$2,0)) -> ₹ 331 Cr | I13: =INDEX('Technical DB (Life)'!$B$3:$J$38,MATCH(I$8,'Technical DB (Life)'!$A$3:$A$38,0),MATCH($C13,'Technical DB (Life)'!$B$2:$J$2,0)) -> ₹ 6,815 Cr
C14: GTLI Growth Rate (FY25) | F14: =INDEX('Technical DB (Life)'!$B$3:$J$38,MATCH(F$8,'Technical DB (Life)'!$A$3:$A$38,0),MATCH($C14,'Technical DB (Life)'!$B$2:$J$2,0)) -> 0.9641 | G14: =INDEX('Technical DB (Life)'!$B$3:$J$38,MATCH(F$8,'Technical DB (Life)'!$A$3:$A$38,0),MATCH($C14,'Technical DB (Life)'!$B$2:$J$2,0)) -> 0.9641 | H14: =INDEX('Technical DB (Life)'!$B$3:$J$38,MATCH(G$8,'Technical DB (Life)'!$A$3:$A$38,0),MATCH($C14,'Technical DB (Life)'!$B$2:$J$2,0)) -> 1.0354 | I14: =INDEX('Technical DB (Life)'!$B$3:$J$38,MATCH(I$8,'Technical DB (Life)'!$A$3:$A$38,0),MATCH($C14,'Technical DB (Life)'!$B$2:$J$2,0)) -> 0.9641 | O14: `
C15: Solvency Ratio (Mar-25) (IRDAI recommended: >1.5) | F15: =INDEX('Technical DB (Life)'!$B$3:$J$38,MATCH(F$8,'Technical DB (Life)'!$A$3:$A$38,0),MATCH($C15,'Technical DB (Life)'!$B$2:$J$2,0)) -> 1.92 | G15: =INDEX('Technical DB (Life)'!$B$3:$J$38,MATCH(F$8,'Technical DB (Life)'!$A$3:$A$38,0),MATCH($C15,'Technical DB (Life)'!$B$2:$J$2,0)) -> 1.92 | H15: =INDEX('Technical DB (Life)'!$B$3:$J$38,MATCH(G$8,'Technical DB (Life)'!$A$3:$A$38,0),MATCH($C15,'Technical DB (Life)'!$B$2:$J$2,0)) -> 2.62 | I15: =INDEX('Technical DB (Life)'!$B$3:$J$38,MATCH(I$8,'Technical DB (Life)'!$A$3:$A$38,0),MATCH($C15,'Technical DB (Life)'!$B$2:$J$2,0)) -> 1.92
B17: Policy Administration | C17: Policy Issuance TAT | F17: =INDEX('Technical DB (Life)'!$B$3:$J$38,MATCH(F$8,'Technical DB (Life)'!$A$3:$A$38,0),MATCH($C17,'Technical DB (Life)'!$B$2:$J$2,0)) -> 15 to 30 Days | G17: =INDEX('Technical DB (Life)'!$B$3:$J$38,MATCH(G$8,'Technical DB (Life)'!$A$3:$A$38,0),MATCH($C17,'Technical DB (Life)'!$B$2:$J$2,0)) -> 7 to 15 Days | H17: =INDEX('Technical DB (Life)'!$B$3:$J$38,MATCH(H$8,'Technical DB (Life)'!$A$3:$A$38,0),MATCH($C17,'Technical DB (Life)'!$B$2:$J$2,0)) -> 15 to 30 Days | I17: =INDEX('Technical DB (Life)'!$B$3:$J$38,MATCH(I$8,'Technical DB (Life)'!$A$3:$A$38,0),MATCH($C17,'Technical DB (Life)'!$B$2:$J$2,0)) -> 15 to 30 Days
C18: Endorsement TAT | F18: =INDEX('Technical DB (Life)'!$B$3:$J$38,MATCH(F$8,'Technical DB (Life)'!$A$3:$A$38,0),MATCH($C18,'Technical DB (Life)'!$B$2:$J$2,0)) -> 1 to 3 Days | G18: =INDEX('Technical DB (Life)'!$B$3:$J$38,MATCH(G$8,'Technical DB (Life)'!$A$3:$A$38,0),MATCH($C18,'Technical DB (Life)'!$B$2:$J$2,0)) -> 3 to 5 Days | H18: =INDEX('Technical DB (Life)'!$B$3:$J$38,MATCH(G$8,'Technical DB (Life)'!$A$3:$A$38,0),MATCH($C18,'Technical DB (Life)'!$B$2:$J$2,0)) -> 3 to 5 Days | I18: =INDEX('Technical DB (Life)'!$B$3:$J$38,MATCH(I$8,'Technical DB (Life)'!$A$3:$A$38,0),MATCH($C18,'Technical DB (Life)'!$B$2:$J$2,0)) -> 1 to 3 Days
B20: Claims | C20: Claim Settlement Ratio | F20: =INDEX('Technical DB (Life)'!$B$3:$J$38,MATCH(F$8,'Technical DB (Life)'!$A$3:$A$38,0),MATCH($C20,'Technical DB (Life)'!$B$2:$J$2,0)) -> 0.9685 | G20: =INDEX('Technical DB (Life)'!$B$3:$J$38,MATCH(G$8,'Technical DB (Life)'!$A$3:$A$38,0),MATCH($C20,'Technical DB (Life)'!$B$2:$J$2,0)) -> 0.9275 | H20: =INDEX('Technical DB (Life)'!$B$3:$J$38,MATCH(H$8,'Technical DB (Life)'!$A$3:$A$38,0),MATCH($C20,'Technical DB (Life)'!$B$2:$J$2,0)) -> 0.5754 | I20: =INDEX('Technical DB (Life)'!$B$3:$J$38,MATCH(I$8,'Technical DB (Life)'!$A$3:$A$38,0),MATCH($C20,'Technical DB (Life)'!$B$2:$J$2,0)) -> 0.9685
C21: % of claims settled within 30 days of intimation | F21: =INDEX('Technical DB (Life)'!$B$3:$J$38,MATCH(F$8,'Technical DB (Life)'!$A$3:$A$38,0),MATCH($C21,'Technical DB (Life)'!$B$2:$J$2,0)) -> 0.989 | G21: =INDEX('Technical DB (Life)'!$B$3:$J$38,MATCH(G$8,'Technical DB (Life)'!$A$3:$A$38,0),MATCH($C21,'Technical DB (Life)'!$B$2:$J$2,0)) -> 0.9795 | H21: =INDEX('Technical DB (Life)'!$B$3:$J$38,MATCH(G$8,'Technical DB (Life)'!$A$3:$A$38,0),MATCH($C21,'Technical DB (Life)'!$B$2:$J$2,0)) -> 0.9795 | I21: =INDEX('Technical DB (Life)'!$B$3:$J$38,MATCH(I$8,'Technical DB (Life)'!$A$3:$A$38,0),MATCH($C21,'Technical DB (Life)'!$B$2:$J$2,0)) -> 0.989
D100: STELLAPPS
D101: Vhire4u

Sheet GTLI DB
A1: Client Name
A2: HealthySure Quotes: | B2: 44372
A4: No. of lives | B4: XX Employees
A6: Group Term Life Cover
A7: Features | B7: Sum Assured | C7: Family Definition | D7: Age Band | E7: Lumpsum Fixed benefits | F7: Terminal Illness Benefit (Life expectancy < 12 months) | G7: Critical Illness Benefit (Severe but not terminal) | H7: Pre-requisites for claim | I7: Other Conditions | J7: Additions & Deletions | K7: Mid term Increase in Sum Insured | L7: Risk Incidence | M7: Geographical Limit | N7: Quote Validity
A8: Aditya Birla Sun Life | C8: Self | D8: 18-60 years | E8: 100% of Sum Assured | F8: Not Covered | G8: Not Covered | H8: a. Death due to natural or unnatural reasons (incl. any accident, COVID-19, natural disaster or suicide) b. Death certificate issued by the local authority in case of death claim | I8: 1. Coverage is provided to all full time and permenant employees of the company residing in India. 2. Coverage should not exceed 10 times annual CTC for any member 3. All employees have to be actively at work at the coverage commencement for the employee i.e. employee has not availed a sick leave (other than COVID-19) for a continuous period > 7 days in the preceding year. Else, the person has to be submit a medical questionnaire 4. Moral hazard events such as driving under influence of alcohol/narcotics, participation in hazardous/adventurous activities not covered 5. Members travelling to/ residing in attached negative country list will not be covered, and for other countries if member’s residency period (continuous) > 180 days then we reserve right to review and amend the quoted rate. | J8: On Pro-rata Basis | K8: Covered (In Case of Graded SI) | L8: 24 x 7 Cover | M8: Worldwide (Except Declined Countries) | N8: 10 Days
